Workbook
Name Print_Titles: Ввод!$4:$5
Name БазоваяПапка: Справочники!$N$1

Sheet Ввод
A2: Дата отчёта: | C2: 46280
E4: ПОРТФЕЛЬ | G4: ПРОСРОЧКА | K4: ДОЗВОНИЛИСЬ / ОБЕЩАЛИ | Q4: НЕ ДОЗВОНИЛИСЬ / ОБЪЕЗД | Y4: ОПЛАЧЕНО ОБЩЕЕ ЗА ДЕНЬ | AA4: ЭФФЕКТИВНОСТЬ И НАГРУЗКА
A5: № | B5: Область | C5: Ответственный | D5: Сотруд- ников | E5: Портфель, сум | F5: Портфель, шт | G5: Просрочка, сум | H5: Просрочка, шт | I5: % к портфелю | J5: % к кол-ву | K5: Дозвон, сум | L5: Дозвон, шт | M5: Обещали, сум | N5: Обещали, шт | O5: Оплатил, сум | P5: Оплатил, шт | Q5: Не дозв., сум | R5: Не дозв., шт | S5: Объезд: обещал, сум | T5: Объезд: обещал, шт | U5: Объезд: оплатил, сум | V5: Объезд: оплатил, шт | W5: Оплатил, сум | X5: Оплатил, шт | Y5: Оплачено, сум | Z5: Оплачено, шт | AA5: % дозвона (шт) | AB5: % обещаний (от дозвона) | AC5: Просрочка на 1 сотр. | AD5: Дозвон на 1 сотр. | AG5: служ. (для сортировки)
A6: 1 | B6: АНДИЖОН ВИЛОЯТИ | C6: =IFERROR(INDEX(Справочники!$D$4:$D$21,MATCH($B6,Справочники!$B$4:$B$21,0)),"") | D6: =SUMIF(Справочники!$H$4:$H$21,$B6,Справочники!$E$4:$E$21) -> 0 | E6: 2.1670184e+10 | F6: 445 | G6: =$K6+$Q6 -> 2.1699731e+08 | H6: =$L6+$R6 -> 32 | I6: =IFERROR($G6/$E6,"") -> 0.010013635 | J6: =IFERROR($H6/$F6,"") -> 0.071910112 | K6: 0 | L6: 0 | M6: 0 | N6: 0 | O6: 0 | P6: 0 | Q6: 5.4204674e+08 | R6: 126 | S6: 0 | T6: 0 | U6: 0 | V6: 0 | W6: 0 | X6: 0 | Y6: 0 | Z6: 0 | AA6: =IFERROR($L6/$H6,"") -> 0 | AB6: =IFERROR($N6/$L6,"") | AC6: =IFERROR($H6/$D6,"") | AD6: =IFERROR($L6/$D6,"") | AG6: =IFERROR($AA6,0)+ROW()/1000000 -> 6e-06
A7: 2 | B7: БУХОРО ВИЛОЯТИ | C7: =IFERROR(INDEX(Справочники!$D$4:$D$21,MATCH($B7,Справочники!$B$4:$B$21,0)),"") | D7: =SUMIF(Справочники!$H$4:$H$21,$B7,Справочники!$E$4:$E$21) -> 0 | E7: 5.1231734e+09 | F7: 167 | G7: =$K7+$Q7 -> 2.0266951e+08 | H7: =$L7+$R7 -> 18 | I7: =IFERROR($G7/$E7,"") -> 0.03955937 | J7: =IFERROR($H7/$F7,"") -> 0.10778443 | K7: 95285619 | L7: 39 | M7: 70433470 | N7: 31 | O7: 24852149 | P7: 8 | Q7: 1.7555188e+08 | R7: 13 | S7: 5579415.3 | T7: 3 | U7: 2968080.1 | V7: 1 | W7: 0 | X7: 0 | Y7: 27820230 | Z7: 9 | AA7: =IFERROR($L7/$H7,"") -> 0 | AB7: =IFERROR($N7/$L7,"") | AC7: =IFERROR($H7/$D7,"") | AD7: =IFERROR($L7/$D7,"") | AG7: =IFERROR($AA7,0)+ROW()/1000000 -> 7e-06
A8: 3 | B8: ЖИЗЗАХ ВИЛОЯТИ | C8: =IFERROR(INDEX(Справочники!$D$4:$D$21,MATCH($B8,Справочники!$B$4:$B$21,0)),"") | D8: =SUMIF(Справочники!$H$4:$H$21,$B8,Справочники!$E$4:$E$21) -> 0 | E8: 1.3904205e+10 | F8: 493 | G8: =$K8+$Q8 -> 2.498528e+08 | H8: =$L8+$R8 -> 51 | I8: =IFERROR($G8/$E8,"") -> 0.017969585 | J8: =IFERROR($H8/$F8,"") -> 0.10344828 | K8: 1.7985286e+08 | L8: 54 | M8: 1.4792243e+08 | N8: 39 | O8: 31930431 | P8: 15 | Q8: 1.8132605e+08 | R8: 44 | S8: 38493366 | T8: 7 | U8: 6829564.9 | V8: 1 | W8: 0 | X8: 0 | Y8: 38759996 | Z8: 16 | AA8: =IFERROR($L8/$H8,"") -> 0.39215686 | AB8: =IFERROR($N8/$L8,"") -> 0.95 | AC8: =IFERROR($H8/$D8,"") | AD8: =IFERROR($L8/$D8,"") | AG8: =IFERROR($AA8,0)+ROW()/1000000 -> 0.39216486
A9: 4 | B9: КАШКАДАРЁ ВИЛОЯТИ | C9: =IFERROR(INDEX(Справочники!$D$4:$D$21,MATCH($B9,Справочники!$B$4:$B$21,0)),"") | D9: =SUMIF(Справочники!$H$4:$H$21,$B9,Справочники!$E$4:$E$21) -> 0 | E9: 1.2186569e+10 | F9: 418 | G9: =$K9+$Q9 -> 2.0555796e+08 | H9: =$L9+$R9 -> 33 | I9: =IFERROR($G9/$E9,"") -> 0.016867583 | J9: =IFERROR($H9/$F9,"") -> 0.078947368 | K9: 1.1066281e+08 | L9: 30 | M9: 99913911 | N9: 25 | O9: 4598852.4 | P9: 4 | Q9: 3.1010541e+08 | R9: 91 | S9: 43293472 | T9: 13 | U9: 8357865.7 | V9: 4 | W9: 0 | X9: 0 | Y9: 12956718 | Z9: 8 | AA9: =IFERROR($L9/$H9,"") -> 0.87878788 | AB9: =IFERROR($N9/$L9,"") -> 0.62068966 | AC9: =IFERROR($H9/$D9,"") | AD9: =IFERROR($L9/$D9,"") | AG9: =IFERROR($AA9,0)+ROW()/1000000 -> 0.87879688
A10: 5 | B10: КОРАКАЛПОГИСТОН РЕСПУБЛИКАСИ | C10: =IFERROR(INDEX(Справочники!$D$4:$D$21,MATCH($B10,Справочники!$B$4:$B$21,0)),"") | D10: =SUMIF(Справочники!$H$4:$H$21,$B10,Справочники!$E$4:$E$21) -> 0 | E10: 1.1119545e+10 | F10: 269 | G10: =$K10+$Q10 -> 2.5963958e+08 | H10: =$L10+$R10 -> 26 | I10: =IFERROR($G10/$E10,"") -> 0.023349839 | J10: =IFERROR($H10/$F10,"") -> 0.096654275 | K10: 1.6080593e+08 | L10: 41 | M10: 1.0925662e+08 | N10: 27 | O10: 12226022 | P10: 4 | Q10: 1.4325956e+08 | R10: 25 | S10: 98869394 | T10: 14 | U10: 0 | V10: 0 | W10: 0 | X10: 0 | Y10: 12226022 | Z10: 4 | AA10: =IFERROR($L10/$H10,"") -> 0.76923077 | AB10: =IFERROR($N10/$L10,"") -> 0.2 | AC10: =IFERROR($H10/$D10,"") | AD10: =IFERROR($L10/$D10,"") | AG10: =IFERROR($AA10,0)+ROW()/1000000 -> 0.76924077
A11: 6 | B11: НАВОИЙ ВИЛОЯТИ | C11: =IFERROR(INDEX(Справочники!$D$4:$D$21,MATCH($B11,Справочники!$B$4:$B$21,0)),"") | D11: =SUMIF(Справочники!$H$4:$H$21,$B11,Справочники!$E$4:$E$21) -> 0 | E11: 6.476845e+09 | F11: 209 | G11: =$K11+$Q11 -> 1.0708535e+08 | H11: =$L11+$R11 -> 18 | I11: =IFERROR($G11/$E11,"") -> 0.016533567 | J11: =IFERROR($H11/$F11,"") -> 0.086124402 | K11: 56491064 | L11: 14 | M11: 18594377 | N11: 4 | O11: 21230024 | P11: 6 | Q11: 1.8946783e+08 | R11: 54 | S11: 0 | T11: 0 | U11: 0 | V11: 0 | W11: 0 | X11: 0 | Y11: 21230024 | Z11: 6 | AA11: =IFERROR($L11/$H11,"") -> 0.055555556 | AB11: =IFERROR($N11/$L11,"") -> 1 | AC11: =IFERROR($H11/$D11,"") | AD11: =IFERROR($L11/$D11,"") | AG11: =IFERROR($AA11,0)+ROW()/1000000 -> 0.055566556
A12: 7 | B12: НАМАНГАН ВИЛОЯТИ | C12: =IFERROR(INDEX(Справочники!$D$4:$D$21,MATCH($B12,Справочники!$B$4:$B$21,0)),"") | D12: =SUMIF(Справочники!$H$4:$H$21,$B12,Справочники!$E$4:$E$21) -> 0 | E12: 1.4729616e+10 | F12: 438 | G12: =$K12+$Q12 -> 5.9799851e+08 | H12: =$L12+$R12 -> 62 | I12: =IFERROR($G12/$E12,"") -> 0.040598377 | J12: =IFERROR($H12/$F12,"") -> 0.14155251 | K12: 3.3091676e+08 | L12: 57 | M12: 19229763 | N12: 9 | O12: 1832838.7 | P12: 1 | Q12: 6.2396477e+08 | R12: 104 | S12: 22291379 | T12: 7 | U12: 0 | V12: 0 | W12: 0 | X12: 0 | Y12: 1832838.7 | Z12: 1 | AA12: =IFERROR($L12/$H12,"") -> 0.48387097 | AB12: =IFERROR($N12/$L12,"") -> 1 | AC12: =IFERROR($H12/$D12,"") | AD12: =IFERROR($L12/$D12,"") | AG12: =IFERROR($AA12,0)+ROW()/1000000 -> 0.48388297
A13: 8 | B13: САМАРКАНД ВИЛОЯТИ | C13: =IFERROR(INDEX(Справочники!$D$4:$D$21,MATCH($B13,Справочники!$B$4:$B$21,0)),"") | D13: =SUMIF(Справочники!$H$4:$H$21,$B13,Справочники!$E$4:$E$21) -> 0 | E13: 1.6007859e+10 | F13: 549 | G13: =$K13+$Q13 -> 2.6721243e+08 | H13: =$L13+$R13 -> 61 | I13: =IFERROR($G13/$E13,"") -> 0.016692577 | J13: =IFERROR($H13/$F13,"") -> 0.11111111 | K13: 75847567 | L13: 26 | M13: 66850720 | N13: 20 | O13: 5817515.7 | P13: 5 | Q13: 5.2037017e+08 | R13: 134 | S13: 28936132 | T13: 12 | U13: 18691648 | V13: 7 | W13: 0 | X13: 0 | Y13: 24509164 | Z13: 12 | AA13: =IFERROR($L13/$H13,"") -> 0.24590164 | AB13: =IFERROR($N13/$L13,"") -> 1 | AC13: =IFERROR($H13/$D13,"") | AD13: =IFERROR($L13/$D13,"") | AG13: =IFERROR($AA13,0)+ROW()/1000000 -> 0.24591464
A14: 9 | B14: СИРДАРЁ ВИЛОЯТИ | C14: =IFERROR(INDEX(Справочники!$D$4:$D$21,MATCH($B14,Справочники!$B$4:$B$21,0)),"") | D14: =SUMIF(Справочники!$H$4:$H$21,$B14,Справочники!$E$4:$E$21) -> 0 | E14: 7.1897605e+09 | F14: 151 | G14: =$K14+$Q14 -> 97690450 | H14: =$L14+$R14 -> 17 | I14: =IFERROR($G14/$E14,"") -> 0.013587441 | J14: =IFERROR($H14/$F14,"") -> 0.11258278 | K14: 0 | L14: 0 | M14: 0 | N14: 0 | O14: 0 | P14: 0 | Q14: 2.0944622e+08 | R14: 51 | S14: 0 | T14: 0 | U14: 0 | V14: 0 | W14: 0 | X14: 0 | Y14: 0 | Z14: 0 | AA14: =IFERROR($L14/$H14,"") -> 0.58823529 | AB14: =IFERROR($N14/$L14,"") -> 0.1 | AC14: =IFERROR($H14/$D14,"") | AD14: =IFERROR($L14/$D14,"") | AG14: =IFERROR($AA14,0)+ROW()/1000000 -> 0.58824929
A15: 10 | B15: СУРХОНДАРЁ ВИЛОЯТИ | C15: =IFERROR(INDEX(Справочники!$D$4:$D$21,MATCH($B15,Справочники!$B$4:$B$21,0)),"") | D15: =SUMIF(Справочники!$H$4:$H$21,$B15,Справочники!$E$4:$E$21) -> 0 | E15: 1.6585229e+10 | F15: 558 | G15: =$K15+$Q15 -> 1.0837511e+09 | H15: =$L15+$R15 -> 97 | I15: =IFERROR($G15/$E15,"") -> 0.065344354 | J15: =IFERROR($H15/$F15,"") -> 0.17383513 | K15: 1.3909364e+08 | L15: 44 | M15: 1.3907186e+08 | N15: 43 | O15: 21786.19 | P15: 1 | Q15: 1.3763867e+09 | R15: 187 | S15: 14102688 | T15: 8 | U15: 6495805.8 | V15: 3 | W15: 0 | X15: 0 | Y15: 6517592 | Z15: 4 | AA15: =IFERROR($L15/$H15,"") -> 0.18556701 | AB15: =IFERROR($N15/$L15,"") -> 0.11111111 | AC15: =IFERROR($H15/$D15,"") | AD15: =IFERROR($L15/$D15,"") | AG15: =IFERROR($AA15,0)+ROW()/1000000 -> 0.18558201
A16: 11 | B16: ТОШКЕНТ ВИЛОЯТИ | C16: =IFERROR(INDEX(Справочники!$D$4:$D$21,MATCH($B16,Справочники!$B$4:$B$21,0)),"") | D16: =SUMIF(Справочники!$H$4:$H$21,$B16,Справочники!$E$4:$E$21) -> 0 | E16: 3.6871387e+10 | F16: 842 | G16: =$K16+$Q16 -> 8.8698663e+08 | H16: =$L16+$R16 -> 93 | I16: =IFERROR($G16/$E16,"") -> 0.024056232 | J16: =IFERROR($H16/$F16,"") -> 0.11045131 | K16: 0 | L16: 0 | M16: 0 | N16: 0 | O16: 0 | P16: 0 | Q16: 1.3924235e+09 | R16: 245 | S16: 0 | T16: 0 | U16: 0 | V16: 0 | W16: 0 | X16: 0 | Y16: 0 | Z16: 0 | AA16: =IFERROR($L16/$H16,"") -> 0 | AB16: =IFERROR($N16/$L16,"") | AC16: =IFERROR($H16/$D16,"") | AD16: =IFERROR($L16/$D16,"") | AG16: =IFERROR($AA16,0)+ROW()/1000000 -> 1.6e-05
A17: 12 | B17: ТОШКЕНТ ШАХРИ | C17: =IFERROR(INDEX(Справочники!$D$4:$D$21,MATCH($B17,Справочники!$B$4:$B$21,0)),"") | D17: =SUMIF(Справочники!$H$4:$H$21,$B17,Справочники!$E$4:$E$21) -> 0 | E17: 4.3531855e+10 | F17: 908 | G17: =$K17+$Q17 -> 1.6257267e+09 | H17: =$L17+$R17 -> 115 | I17: =IFERROR($G17/$E17,"") -> 0.037345679 | J17: =IFERROR($H17/$F17,"") -> 0.12665198 | K17: 58642688 | L17: 14 | M17: 56137552 | N17: 13 | O17: 2505136.5 | P17: 1 | Q17: 1.7336808e+09 | R17: 214 | S17: 97012424 | T17: 10 | U17: 14652137 | V17: 5 | W17: 0 | X17: 0 | Y17: 17157273 | Z17: 6 | AA17: =IFERROR($L17/$H17,"") -> 0 | AB17: =IFERROR($N17/$L17,"") | AC17: =IFERROR($H17/$D17,"") | AD17: =IFERROR($L17/$D17,"") | AG17: =IFERROR($AA17,0)+ROW()/1000000 -> 1.7e-05
... A19: 14 | B19: ХОРАЗМ ВИЛОЯТИ | C19: =IFERROR(INDEX(Справочники!$D$4:$D$21,MATCH($B19,Справочники!$B$4:$B$21,0)),"") | D19: =SUMIF(Справочники!$H$4:$H$21,$B19,Справочники!$E$4:$E$21) -> 0 | E19: 2.0499096e+10 | F19: 504 | G19: =$K19+$Q19 -> 2.9345986e+08 | H19: =$L19+$R19 -> 49 | I19: =IFERROR($G19/$E19,"") -> 0.014315746 | J19: =IFERROR($H19/$F19,"") -> 0.097222222 | K19: 1.6805918e+08 | L19: 50 | M19: 1.4938058e+08 | N19: 44 | O19: 17082325 | P19: 5 | Q19: 4.6508188e+08 | R19: 95 | S19: 27724170 | T19: 7 | U19: 0 | V19: 0 | W19: 0 | X19: 0 | Y19: 17082325 | Z19: 5 | AA19: =IFERROR($L19/$H19,"") -> 0.46938776 | AB19: =IFERROR($N19/$L19,"") -> 0.26086957 | AC19: =IFERROR($H19/$D19,"") | AD19: =IFERROR($L19/$D19,"") | AG19: =IFERROR($AA19,0)+ROW()/1000000 -> 0.46940676
B20: ИТОГО | D20: =SUM(D6:D19) -> 0 | E20: =SUM(E6:E19) -> 2.4329876e+11 | F20: =SUM(F6:F19) -> 6312 | G20: =SUM(G6:G19) -> 6.9014395e+09 | H20: =SUM(H6:H19) -> 725 | I20: =IFERROR($G20/$E20,"") -> 0.02836611 | J20: =IFERROR($H20/$F20,"") -> 0.11486058 | K20: =SUM(K6:K19) -> 1.1882477e+09 | L20: =SUM(L6:L19) -> 166 | M20: =SUM(M6:M19) -> 7.4828599e+08 | N20: =SUM(N6:N19) -> 96 | O20: =SUM(O6:O19) -> 0 | P20: =SUM(P6:P19) -> 0 | Q20: =SUM(Q6:Q19) -> 5.7131919e+09 | R20: =SUM(R6:R19) -> 559 | ... Z20: =SUM(Z6:Z19) -> 28 | AA20: =IFERROR($L20/$H20,"") -> 0.22896552 | AB20: =IFERROR($N20/$L20,"") -> 0.57831325 | AC20: =IFERROR($H20/$D20,"") | AD20: =IFERROR($L20/$D20,"")
B23: ОТКРЫТЬ СПИСОК КЛИЕНТОВ
B24: Область | C24: Дозв. | D24: Обещ. | E24: Опл. | F24: Не дозв. | G24: Объезд | H24: Опл. без разг. | I24: Всего
B25: АНДИЖОН ВИЛОЯТИ | F25: ▸
B26: БУХОРО ВИЛОЯТИ | C26: ▸ | D26: ▸ | E26: ▸ | F26: ▸ | G26: ▸ | I26: ▸
B27: ЖИЗЗАХ ВИЛОЯТИ | C27: ▸ | D27: ▸ | E27: ▸ | F27: ▸ | G27: ▸ | I27: ▸
B28: КАШКАДАРЁ ВИЛОЯТИ | C28: ▸ | D28: ▸ | E28: ▸ | F28: ▸ | G28: ▸ | I28: ▸
B29: КОРАКАЛПОГИСТОН РЕСПУБЛИКАСИ | C29: ▸ | D29: ▸ | E29: ▸ | F29: ▸ | G29: ▸ | I29: ▸
B30: НАВОИЙ ВИЛОЯТИ | C30: ▸ | D30: ▸ | E30: ▸ | F30: ▸ | I30: ▸
B31: НАМАНГАН ВИЛОЯТИ | C31: ▸ | D31: ▸ | E31: ▸ | F31: ▸ | G31: ▸ | I31: ▸
B32: САМАРКАНД ВИЛОЯТИ | C32: ▸ | D32: ▸ | E32: ▸ | F32: ▸ | G32: ▸ | I32: ▸
B33: СИРДАРЁ ВИЛОЯТИ | F33: ▸
B34: СУРХОНДАРЁ ВИЛОЯТИ | C34: ▸ | D34: ▸ | E34: ▸ | F34: ▸ | G34: ▸ | I34: ▸
B35: ТОШКЕНТ ВИЛОЯТИ | F35: ▸
B36: ТОШКЕНТ ШАХРИ | C36: ▸ | D36: ▸ | E36: ▸ | F36: ▸ | G36: ▸ | I36: ▸
B37: ФАРГОНА ВИЛОЯТИ | C37: ▸ | D37: ▸ | E37: ▸ | F37: ▸ | G37: ▸ | I37: ▸
B38: ХОРАЗМ ВИЛОЯТИ | C38: ▸ | D38: ▸ | E38: ▸ | F38: ▸ | G38: ▸ | I38: ▸

Sheet Отчёт_дня
A3: Дата отчёта: | C3: =Ввод!$C$2 -> 46272
A6: 1. ПОКАЗАТЕЛИ ДНЯ
A7: Портфель, сум | D7: =Ввод!$E$20 -> 2.4329876e+11
A8: Просрочка, сум | D8: =Ввод!$G$20 -> 6.9014395e+09
A9: % просрочки к портфелю | D9: =Ввод!$I$20 -> 0.02836611
A10: Просрочка, шт | D10: =Ввод!$H$20 -> 725
A11: Дозвонились, шт | D11: =Ввод!$L$20 -> 166
A12: % дозвона | D12: =Ввод!$AA$20 -> 0.22896552
A13: Обещали оплату, шт | D13: =Ввод!$N$20 -> 96
A14: Не дозвонились, шт | D14: =Ввод!$R$20 -> 559
A15: Объезд, шт | D15: =Ввод!$T$20 -> 2
A16: Оплачено за день, сум | D16: =Ввод!$Y$20 -> 0
A19: 2. ДЕТАЛИЗАЦИЯ ПО ОБЛАСТЯМ
A21: Область | B21: Ответственный | C21: Сотруд- ников | D21: % дозвона | E21: Просрочка на 1 сотр. | F21: Оплачено, сум | G21: Оценка
A22: =Ввод!$B$6 -> АНДИЖОН ВИЛОЯТИ | B22: =Ввод!$C$6 | C22: =Ввод!$D$6 -> 0 | D22: =IFERROR(Ввод!$AA$6,0) -> 0 | E22: =IFERROR(Ввод!$AC$6,0) | F22: =Ввод!$Y$6 -> 0 | G22: =IF(Ввод!$H$6=0,"Нет данных",IF($D22>=0.8,"Отлично",IF($D22>=0.5,"Хорошо","Требует внимания"))) -> Требует внимания
A23: =Ввод!$B$7 -> БУХОРО ВИЛОЯТИ | B23: =Ввод!$C$7 | C23: =Ввод!$D$7 -> 0 | D23: =IFERROR(Ввод!$AA$7,0) -> 0 | E23: =IFERROR(Ввод!$AC$7,0) | F23: =Ввод!$Y$7 -> 0 | G23: =IF(Ввод!$H$7=0,"Нет данных",IF($D23>=0.8,"Отлично",IF($D23>=0.5,"Хорошо","Требует внимания"))) -> Требует внимания
A24: =Ввод!$B$8 -> ЖИЗЗАХ ВИЛОЯТИ | B24: =Ввод!$C$8 | C24: =Ввод!$D$8 -> 0 | D24: =IFERROR(Ввод!$AA$8,0) -> 0.39215686 | E24: =IFERROR(Ввод!$AC$8,0) | F24: =Ввод!$Y$8 -> 0 | G24: =IF(Ввод!$H$8=0,"Нет данных",IF($D24>=0.8,"Отлично",IF($D24>=0.5,"Хорошо","Требует внимания"))) -> Требует внимания
A25: =Ввод!$B$9 -> КАШКАДАРЁ ВИЛОЯТИ | B25: =Ввод!$C$9 | C25: =Ввод!$D$9 -> 0 | D25: =IFERROR(Ввод!$AA$9,0) -> 0.87878788 | E25: =IFERROR(Ввод!$AC$9,0) | F25: =Ввод!$Y$9 -> 0 | G25: =IF(Ввод!$H$9=0,"Нет данных",IF($D25>=0.8,"Отлично",IF($D25>=0.5,"Хорошо","Требует внимания"))) -> Отлично
A26: =Ввод!$B$10 -> КОРАКАЛПОГИСТОН РЕСПУБЛИКАСИ | B26: =Ввод!$C$10 | C26: =Ввод!$D$10 -> 0 | D26: =IFERROR(Ввод!$AA$10,0) -> 0.76923077 | E26: =IFERROR(Ввод!$AC$10,0) | F26: =Ввод!$Y$10 -> 0 | G26: =IF(Ввод!$H$10=0,"Нет данных",IF($D26>=0.8,"Отлично",IF($D26>=0.5,"Хорошо","Требует внимания"))) -> Хорошо
A27: =Ввод!$B$11 -> НАВОИЙ ВИЛОЯТИ | B27: =Ввод!$C$11 | C27: =Ввод!$D$11 -> 0 | D27: =IFERROR(Ввод!$AA$11,0) -> 0.055555556 | E27: =IFERROR(Ввод!$AC$11,0) | F27: =Ввод!$Y$11 -> 0 | G27: =IF(Ввод!$H$11=0,"Нет данных",IF($D27>=0.8,"Отлично",IF($D27>=0.5,"Хорошо","Требует внимания"))) -> Требует внимания
A28: =Ввод!$B$12 -> НАМАНГАН ВИЛОЯТИ | B28: =Ввод!$C$12 | C28: =Ввод!$D$12 -> 0 | D28: =IFERROR(Ввод!$AA$12,0) -> 0.48387097 | E28: =IFERROR(Ввод!$AC$12,0) | F28: =Ввод!$Y$12 -> 0 | G28: =IF(Ввод!$H$12=0,"Нет данных",IF($D28>=0.8,"Отлично",IF($D28>=0.5,"Хорошо","Требует внимания"))) -> Требует внимания
A29: =Ввод!$B$13 -> САМАРКАНД ВИЛОЯТИ | B29: =Ввод!$C$13 | C29: =Ввод!$D$13 -> 0 | D29: =IFERROR(Ввод!$AA$13,0) -> 0.24590164 | E29: =IFERROR(Ввод!$AC$13,0) | F29: =Ввод!$Y$13 -> 0 | G29: =IF(Ввод!$H$13=0,"Нет данных",IF($D29>=0.8,"Отлично",IF($D29>=0.5,"Хорошо","Требует внимания"))) -> Требует внимания
A30: =Ввод!$B$14 -> СИРДАРЁ ВИЛОЯТИ | B30: =Ввод!$C$14 | C30: =Ввод!$D$14 -> 0 | D30: =IFERROR(Ввод!$AA$14,0) -> 0.58823529 | E30: =IFERROR(Ввод!$AC$14,0) | F30: =Ввод!$Y$14 -> 0 | G30: =IF(Ввод!$H$14=0,"Нет данных",IF($D30>=0.8,"Отлично",IF($D30>=0.5,"Хорошо","Требует внимания"))) -> Хорошо
A31: =Ввод!$B$15 -> СУРХОНДАРЁ ВИЛОЯТИ | B31: =Ввод!$C$15 | C31: =Ввод!$D$15 -> 0 | D31: =IFERROR(Ввод!$AA$15,0) -> 0.18556701 | E31: =IFERROR(Ввод!$AC$15,0) | F31: =Ввод!$Y$15 -> 0 | G31: =IF(Ввод!$H$15=0,"Нет данных",IF($D31>=0.8,"Отлично",IF($D31>=0.5,"Хорошо","Требует внимания"))) -> Требует внимания
A32: =Ввод!$B$16 -> ТОШКЕНТ ВИЛОЯТИ | B32: =Ввод!$C$16 | C32: =Ввод!$D$16 -> 0 | D32: =IFERROR(Ввод!$AA$16,0) -> 0 | E32: =IFERROR(Ввод!$AC$16,0) | F32: =Ввод!$Y$16 -> 0 | G32: =IF(Ввод!$H$16=0,"Нет данных",IF($D32>=0.8,"Отлично",IF($D32>=0.5,"Хорошо","Требует внимания"))) -> Требует внимания
A33: =Ввод!$B$17 -> ТОШКЕНТ ШАХРИ | B33: =Ввод!$C$17 | C33: =Ввод!$D$17 -> 0 | D33: =IFERROR(Ввод!$AA$17,0) -> 0 | E33: =IFERROR(Ввод!$AC$17,0) | F33: =Ввод!$Y$17 -> 0 | G33: =IF(Ввод!$H$17=0,"Нет данных",IF($D33>=0.8,"Отлично",IF($D33>=0.5,"Хорошо","Требует внимания"))) -> Требует внимания
A34: =Ввод!$B$18 -> ФАРГОНА ВИЛОЯТИ | B34: =Ввод!$C$18 | C34: =Ввод!$D$18 -> 0 | D34: =IFERROR(Ввод!$AA$18,0) -> 0 | E34: =IFERROR(Ввод!$AC$18,0) | F34: =Ввод!$Y$18 -> 0 | G34: =IF(Ввод!$H$18=0,"Нет данных",IF($D34>=0.8,"Отлично",IF($D34>=0.5,"Хорошо","Требует внимания"))) -> Требует внимания
A35: =Ввод!$B$19 -> ХОРАЗМ ВИЛОЯТИ | B35: =Ввод!$C$19 | C35: =Ввод!$D$19 -> 0 | D35: =IFERROR(Ввод!$AA$19,0) -> 0.46938776 | E35: =IFERROR(Ввод!$AC$19,0) | F35: =Ввод!$Y$19 -> 0 | G35: =IF(Ввод!$H$19=0,"Нет данных",IF($D35>=0.8,"Отлично",IF($D35>=0.5,"Хорошо","Требует внимания"))) -> Требует внимания
A41: 6. ЛИДЕРЫ И ОТСТАЮЩИЕ ПО % ДОЗВОНА (по областям)
A42: Лидеры | C42: % дозвона | E42: Требуют внимания | H42: % дозвона
A43: =IFERROR(INDEX(Ввод!$B$6:$B$19,MATCH(LARGE(Ввод!$AG$6:$AG$19,1),Ввод!$AG$6:$AG$19,0)),"") -> КАШКАДАРЁ ВИЛОЯТИ | C43: =IFERROR(INDEX(Ввод!$AA$6:$AA$19,MATCH(LARGE(Ввод!$AG$6:$AG$19,1),Ввод!$AG$6:$AG$19,0)),"") -> 0.87878788 | E43: =IFERROR(INDEX(Ввод!$B$6:$B$19,MATCH(SMALL(Ввод!$AG$6:$AG$19,1),Ввод!$AG$6:$AG$19,0)),"") -> АНДИЖОН ВИЛОЯТИ | H43: =IFERROR(INDEX(Ввод!$AA$6:$AA$19,MATCH(SMALL(Ввод!$AG$6:$AG$19,1),Ввод!$AG$6:$AG$19,0)),"") -> 0
A44: =IFERROR(INDEX(Ввод!$B$6:$B$19,MATCH(LARGE(Ввод!$AG$6:$AG$19,2),Ввод!$AG$6:$AG$19,0)),"") -> КОРАКАЛПОГИСТОН РЕСПУБЛИКАСИ | C44: =IFERROR(INDEX(Ввод!$AA$6:$AA$19,MATCH(LARGE(Ввод!$AG$6:$AG$19,2),Ввод!$AG$6:$AG$19,0)),"") -> 0.76923077 | E44: =IFERROR(INDEX(Ввод!$B$6:$B$19,MATCH(SMALL(Ввод!$AG$6:$AG$19,2),Ввод!$AG$6:$AG$19,0)),"") -> БУХОРО ВИЛОЯТИ | H44: =IFERROR(INDEX(Ввод!$AA$6:$AA$19,MATCH(SMALL(Ввод!$AG$6:$AG$19,2),Ввод!$AG$6:$AG$19,0)),"") -> 0
A45: =IFERROR(INDEX(Ввод!$B$6:$B$19,MATCH(LARGE(Ввод!$AG$6:$AG$19,3),Ввод!$AG$6:$AG$19,0)),"") -> СИРДАРЁ ВИЛОЯТИ | C45: =IFERROR(INDEX(Ввод!$AA$6:$AA$19,MATCH(LARGE(Ввод!$AG$6:$AG$19,3),Ввод!$AG$6:$AG$19,0)),"") -> 0.58823529 | E45: =IFERROR(INDEX(Ввод!$B$6:$B$19,MATCH(SMALL(Ввод!$AG$6:$AG$19,3),Ввод!$AG$6:$AG$19,0)),"") -> ТОШКЕНТ ВИЛОЯТИ | H45: =IFERROR(INDEX(Ввод!$AA$6:$AA$19,MATCH(SMALL(Ввод!$AG$6:$AG$19,3),Ввод!$AG$6:$AG$19,0)),"") -> 0

Sheet Дашборд
A3: Дата отчёта: | C3: =Ввод!$C$2 -> 46272 | E3: Просрочка, сум | H3: =Ввод!$G$20 -> 6.9014395e+09
E4: Оплачено за день, сум | H4: =Ввод!$Y$20 -> 0
E5: Просрочка на 1 сотрудника, шт | H5: =IFERROR(Ввод!$H$20/Ввод!$D$20,0) -> 0
A7: СВОД ПО ОБЛАСТЯМ
A8: Область | B8: Тип | C8: Сотруд- ников | D8: Портфель, сум | E8: Просрочка, сум | F8: % просрочки | G8: Просрочка, шт | H8: Дозвон, шт | I8: % дозвона | J8: Просрочка на 1 сотр. | K8: Обещали, шт | L8: Оплачено, сум | M8: Оценка | N8: Область
A9: =Ввод!$B$6 -> АНДИЖОН ВИЛОЯТИ | C9: =Ввод!$D$6 -> 0 | D9: =Ввод!$E$6 -> 2.1670184e+10 | E9: =Ввод!$G$6 -> 2.1699731e+08 | F9: =IFERROR($E9/$D9,0) -> 0.010013635 | G9: =Ввод!$H$6 -> 32 | H9: =Ввод!$L$6 -> 0 | I9: =IFERROR($H9/$G9,0) -> 0 | J9: =IFERROR($G9/$C9,0) -> 0 | K9: =Ввод!$N$6 -> 0 | L9: =Ввод!$Y$6 -> 0 | M9: =IF($G9=0,"Нет данных",IF($I9>=0.8,"Отлично",IF($I9>=0.5,"Хорошо","Требует внимания"))) -> Требует внимания | N9: =IFERROR(INDEX(Справочники!$H$4:$H$21,MATCH($A9,Справочники!$B$4:$B$21,0)),"")
A10: =Ввод!$B$7 -> БУХОРО ВИЛОЯТИ | C10: =Ввод!$D$7 -> 0 | D10: =Ввод!$E$7 -> 5.1231734e+09 | E10: =Ввод!$G$7 -> 2.0266951e+08 | F10: =IFERROR($E10/$D10,0) -> 0.03955937 | G10: =Ввод!$H$7 -> 18 | H10: =Ввод!$L$7 -> 0 | I10: =IFERROR($H10/$G10,0) -> 0 | J10: =IFERROR($G10/$C10,0) -> 0 | K10: =Ввод!$N$7 -> 0 | L10: =Ввод!$Y$7 -> 0 | M10: =IF($G10=0,"Нет данных",IF($I10>=0.8,"Отлично",IF($I10>=0.5,"Хорошо","Требует внимания"))) -> Требует внимания | N10: =IFERROR(INDEX(Справочники!$H$4:$H$21,MATCH($A10,Справочники!$B$4:$B$21,0)),"")
A11: =Ввод!$B$8 -> ЖИЗЗАХ ВИЛОЯТИ | C11: =Ввод!$D$8 -> 0 | D11: =Ввод!$E$8 -> 1.3904205e+10 | E11: =Ввод!$G$8 -> 2.498528e+08 | F11: =IFERROR($E11/$D11,0) -> 0.017969585 | G11: =Ввод!$H$8 -> 51 | H11: =Ввод!$L$8 -> 20 | I11: =IFERROR($H11/$G11,0) -> 0.39215686 | J11: =IFERROR($G11/$C11,0) -> 0 | K11: =Ввод!$N$8 -> 19 | L11: =Ввод!$Y$8 -> 0 | M11: =IF($G11=0,"Нет данных",IF($I11>=0.8,"Отлично",IF($I11>=0.5,"Хорошо","Требует внимания"))) -> Требует внимания | N11: =IFERROR(INDEX(Справочники!$H$4:$H$21,MATCH($A11,Справочники!$B$4:$B$21,0)),"")
A12: =Ввод!$B$9 -> КАШКАДАРЁ ВИЛОЯТИ | C12: =Ввод!$D$9 -> 0 | D12: =Ввод!$E$9 -> 1.2186569e+10 | E12: =Ввод!$G$9 -> 2.0555796e+08 | F12: =IFERROR($E12/$D12,0) -> 0.016867583 | G12: =Ввод!$H$9 -> 33 | H12: =Ввод!$L$9 -> 29 | I12: =IFERROR($H12/$G12,0) -> 0.87878788 | J12: =IFERROR($G12/$C12,0) -> 0 | K12: =Ввод!$N$9 -> 18 | L12: =Ввод!$Y$9 -> 0 | M12: =IF($G12=0,"Нет данных",IF($I12>=0.8,"Отлично",IF($I12>=0.5,"Хорошо","Требует внимания"))) -> Отлично | N12: =IFERROR(INDEX(Справочники!$H$4:$H$21,MATCH($A12,Справочники!$B$4:$B$21,0)),"")
A13: =Ввод!$B$10 -> КОРАКАЛПОГИСТОН РЕСПУБЛИКАСИ | C13: =Ввод!$D$10 -> 0 | D13: =Ввод!$E$10 -> 1.1119545e+10 | E13: =Ввод!$G$10 -> 2.5963958e+08 | F13: =IFERROR($E13/$D13,0) -> 0.023349839 | G13: =Ввод!$H$10 -> 26 | H13: =Ввод!$L$10 -> 20 | I13: =IFERROR($H13/$G13,0) -> 0.76923077 | J13: =IFERROR($G13/$C13,0) -> 0 | K13: =Ввод!$N$10 -> 4 | L13: =Ввод!$Y$10 -> 0 | M13: =IF($G13=0,"Нет данных",IF($I13>=0.8,"Отлично",IF($I13>=0.5,"Хорошо","Требует внимания"))) -> Хорошо | N13: =IFERROR(INDEX(Справочники!$H$4:$H$21,MATCH($A13,Справочники!$B$4:$B$21,0)),"")
A14: =Ввод!$B$11 -> НАВОИЙ ВИЛОЯТИ | C14: =Ввод!$D$11 -> 0 | D14: =Ввод!$E$11 -> 6.476845e+09 | E14: =Ввод!$G$11 -> 1.0708535e+08 | F14: =IFERROR($E14/$D14,0) -> 0.016533567 | G14: =Ввод!$H$11 -> 18 | H14: =Ввод!$L$11 -> 1 | I14: =IFERROR($H14/$G14,0) -> 0.055555556 | J14: =IFERROR($G14/$C14,0) -> 0 | K14: =Ввод!$N$11 -> 1 | L14: =Ввод!$Y$11 -> 0 | M14: =IF($G14=0,"Нет данных",IF($I14>=0.8,"Отлично",IF($I14>=0.5,"Хорошо","Требует внимания"))) -> Требует внимания | N14: =IFERROR(INDEX(Справочники!$H$4:$H$21,MATCH($A14,Справочники!$B$4:$B$21,0)),"")
A15: =Ввод!$B$12 -> НАМАНГАН ВИЛОЯТИ | C15: =Ввод!$D$12 -> 0 | D15: =Ввод!$E$12 -> 1.4729616e+10 | E15: =Ввод!$G$12 -> 5.9799851e+08 | F15: =IFERROR($E15/$D15,0) -> 0.040598377 | G15: =Ввод!$H$12 -> 62 | H15: =Ввод!$L$12 -> 30 | I15: =IFERROR($H15/$G15,0) -> 0.48387097 | J15: =IFERROR($G15/$C15,0) -> 0 | K15: =Ввод!$N$12 -> 30 | L15: =Ввод!$Y$12 -> 0 | M15: =IF($G15=0,"Нет данных",IF($I15>=0.8,"Отлично",IF($I15>=0.5,"Хорошо","Требует внимания"))) -> Требует внимания | N15: =IFERROR(INDEX(Справочники!$H$4:$H$21,MATCH($A15,Справочники!$B$4:$B$21,0)),"")
A16: =Ввод!$B$13 -> САМАРКАНД ВИЛОЯТИ | C16: =Ввод!$D$13 -> 0 | D16: =Ввод!$E$13 -> 1.6007859e+10 | E16: =Ввод!$G$13 -> 2.6721243e+08 | F16: =IFERROR($E16/$D16,0) -> 0.016692577 | G16: =Ввод!$H$13 -> 61 | H16: =Ввод!$L$13 -> 15 | I16: =IFERROR($H16/$G16,0) -> 0.24590164 | J16: =IFERROR($G16/$C16,0) -> 0 | K16: =Ввод!$N$13 -> 15 | L16: =Ввод!$Y$13 -> 0 | M16: =IF($G16=0,"Нет данных",IF($I16>=0.8,"Отлично",IF($I16>=0.5,"Хорошо","Требует внимания"))) -> Требует внимания | N16: =IFERROR(INDEX(Справочники!$H$4:$H$21,MATCH($A16,Справочники!$B$4:$B$21,0)),"")
A17: =Ввод!$B$14 -> СИРДАРЁ ВИЛОЯТИ | C17: =Ввод!$D$14 -> 0 | D17: =Ввод!$E$14 -> 7.1897605e+09 | E17: =Ввод!$G$14 -> 97690450 | F17: =IFERROR($E17/$D17,0) -> 0.013587441 | G17: =Ввод!$H$14 -> 17 | H17: =Ввод!$L$14 -> 10 | I17: =IFERROR($H17/$G17,0) -> 0.58823529 | J17: =IFERROR($G17/$C17,0) -> 0 | K17: =Ввод!$N$14 -> 1 | L17: =Ввод!$Y$14 -> 0 | M17: =IF($G17=0,"Нет данных",IF($I17>=0.8,"Отлично",IF($I17>=0.5,"Хорошо","Требует внимания"))) -> Хорошо | N17: =IFERROR(INDEX(Справочники!$H$4:$H$21,MATCH($A17,Справочники!$B$4:$B$21,0)),"")
A18: =Ввод!$B$15 -> СУРХОНДАРЁ ВИЛОЯТИ | C18: =Ввод!$D$15 -> 0 | D18: =Ввод!$E$15 -> 1.6585229e+10 | E18: =Ввод!$G$15 -> 1.0837511e+09 | F18: =IFERROR($E18/$D18,0) -> 0.065344354 | G18: =Ввод!$H$15 -> 97 | H18: =Ввод!$L$15 -> 18 | I18: =IFERROR($H18/$G18,0) -> 0.18556701 | J18: =IFERROR($G18/$C18,0) -> 0 | K18: =Ввод!$N$15 -> 2 | L18: =Ввод!$Y$15 -> 0 | M18: =IF($G18=0,"Нет данных",IF($I18>=0.8,"Отлично",IF($I18>=0.5,"Хорошо","Требует внимания"))) -> Требует внимания | N18: =IFERROR(INDEX(Справочники!$H$4:$H$21,MATCH($A18,Справочники!$B$4:$B$21,0)),"")
A19: =Ввод!$B$16 -> ТОШКЕНТ ВИЛОЯТИ | C19: =Ввод!$D$16 -> 0 | D19: =Ввод!$E$16 -> 3.6871387e+10 | E19: =Ввод!$G$16 -> 8.8698663e+08 | F19: =IFERROR($E19/$D19,0) -> 0.024056232 | G19: =Ввод!$H$16 -> 93 | H19: =Ввод!$L$16 -> 0 | I19: =IFERROR($H19/$G19,0) -> 0 | J19: =IFERROR($G19/$C19,0) -> 0 | K19: =Ввод!$N$16 -> 0 | L19: =Ввод!$Y$16 -> 0 | M19: =IF($G19=0,"Нет данных",IF($I19>=0.8,"Отлично",IF($I19>=0.5,"Хорошо","Требует внимания"))) -> Требует внимания | N19: =IFERROR(INDEX(Справочники!$H$4:$H$21,MATCH($A19,Справочники!$B$4:$B$21,0)),"")
A20: =Ввод!$B$17 -> ТОШКЕНТ ШАХРИ | C20: =Ввод!$D$17 -> 0 | D20: =Ввод!$E$17 -> 4.3531855e+10 | E20: =Ввод!$G$17 -> 1.6257267e+09 | F20: =IFERROR($E20/$D20,0) -> 0.037345679 | G20: =Ввод!$H$17 -> 115 | H20: =Ввод!$L$17 -> 0 | I20: =IFERROR($H20/$G20,0) -> 0 | J20: =IFERROR($G20/$C20,0) -> 0 | K20: =Ввод!$N$17 -> 0 | L20: =Ввод!$Y$17 -> 0 | M20: =IF($G20=0,"Нет данных",IF($I20>=0.8,"Отлично",IF($I20>=0.5,"Хорошо","Требует внимания"))) -> Требует внимания | N20: =IFERROR(INDEX(Справочники!$H$4:$H$21,MATCH($A20,Справочники!$B$4:$B$21,0)),"")
A21: =Ввод!$B$18 -> ФАРГОНА ВИЛОЯТИ | C21: =Ввод!$D$18 -> 0 | D21: =Ввод!$E$18 -> 1.7403439e+10 | E21: =Ввод!$G$18 -> 806811380 | F21: =IFERROR($E21/$D21,0) -> 0.046359308 | G21: =Ввод!$H$18 -> 53 | H21: =Ввод!$L$18 -> 0 | I21: =IFERROR($H21/$G21,0) -> 0 | J21: =IFERROR($G21/$C21,0) -> 0 | K21: =Ввод!$N$18 -> 0 | L21: =Ввод!$Y$18 -> 0 | M21: =IF($G21=0,"Нет данных",IF($I21>=0.8,"Отлично",IF($I21>=0.5,"Хорошо","Требует внимания"))) -> Требует внимания | N21: =IFERROR(INDEX(Справочники!$H$4:$H$21,MATCH($A21,Справочники!$B$4:$B$21,0)),"")
A22: =Ввод!$B$19 -> ХОРАЗМ ВИЛОЯТИ | C22: =Ввод!$D$19 -> 0 | D22: =Ввод!$E$19 -> 2.0499096e+10 | E22: =Ввод!$G$19 -> 2.9345986e+08 | F22: =IFERROR($E22/$D22,0) -> 0.014315746 | G22: =Ввод!$H$19 -> 49 | H22: =Ввод!$L$19 -> 23 | I22: =IFERROR($H22/$G22,0) -> 0.46938776 | J22: =IFERROR($G22/$C22,0) -> 0 | K22: =Ввод!$N$19 -> 6 | L22: =Ввод!$Y$19 -> 0 | M22: =IF($G22=0,"Нет данных",IF($I22>=0.8,"Отлично",IF($I22>=0.5,"Хорошо","Требует внимания"))) -> Требует внимания | N22: =IFERROR(INDEX(Справочники!$H$4:$H$21,MATCH($A22,Справочники!$B$4:$B$21,0)),"")
A27: ИТОГО | C27: =SUM(C9:C26) -> 0 | D27: =SUM(D9:D26) -> 2.4329876e+11 | E27: =SUM(E9:E26) -> 6.9014395e+09 | F27: =IFERROR($E27/$D27,0) -> 0.02836611 | G27: =SUM(G9:G26) -> 725 | H27: =SUM(H9:H26) -> 166 | I27: =IFERROR($H27/$G27,0) -> 0.22896552 | J27: =IFERROR($G27/$C27,0) -> 0 | K27: =SUM(K9:K26) -> 96 | L27: =SUM(L9:L26) -> 0 | M27: =IF($I27>=0.8,"Отлично",IF($I27>=0.5,"Хорошо","Требует внимания")) -> Требует внимания

Sheet Справочники
A3: № | B3: Филиал (точно как в файлах) | C3: Тип | D3: Ответственный (Ф.И.О.) | E3: Кол-во сотрудников | F3: Телефон | G3: Норматив % просрочки | H3: Область | K3: Оценка эффективности | N3: Статус проверки
A4: 1 | B4: Урганч филиали | C4: Регион | D4: — впишите — | E4: 0 | F4: +998 __ ___ __ __ | G4: 0.05 | H4: ХОРАЗМ ВИЛОЯТИ | K4: Отлично (≥80% дозвона) | N4: Не проверено
A5: 2 | B5: Самарқанд филиали | C5: Регион | D5: — впишите — | E5: 0 | F5: +998 __ ___ __ __ | G5: 0.05 | H5: САМАРКАНД ВИЛОЯТИ | K5: Хорошо (50–79%) | N5: Проверено куратором
A6: 3 | B6: Денов филиали | C6: Регион | D6: — впишите — | E6: 0 | F6: +998 __ ___ __ __ | G6: 0.05 | H6: СУРХОНДАРЁ ВИЛОЯТИ | K6: Требует внимания (<50%)
A7: 4 | B7: Жиззах филиали | C7: Регион | D7: — впишите — | E7: 0 | F7: +998 __ ___ __ __ | G7: 0.05 | H7: ЖИЗЗАХ ВИЛОЯТИ | K7: Нет данных
A8: 5 | B8: Андижон филиали | C8: Регион | D8: — впишите — | E8: 0 | F8: +998 __ ___ __ __ | G8: 0.05 | H8: АНДИЖОН ВИЛОЯТИ
A9: 6 | B9: Наманган филиали | C9: Регион | D9: — впишите — | E9: 0 | F9: +998 __ ___ __ __ | G9: 0.05 | H9: НАМАНГАН ВИЛОЯТИ
A10: 7 | B10: Фарғона филиали | C10: Регион | D10: — впишите — | E10: 0 | F10: +998 __ ___ __ __ | G10: 0.05 | H10: ФАРГОНА ВИЛОЯТИ
A11: 8 | B11: Қарши филиали | C11: Регион | D11: — впишите — | E11: 0 | F11: +998 __ ___ __ __ | G11: 0.05 | H11: КАШКАДАРЁ ВИЛОЯТИ
A12: 9 | B12: Нукус филиали | C12: Регион | D12: — впишите — | E12: 0 | F12: +998 __ ___ __ __ | G12: 0.05 | H12: КОРАКАЛПОГИСТОН РЕСПУБЛИКАСИ
A13: 10 | B13: Навоий филиали | C13: Регион | D13: — впишите — | E13: 0 | F13: +998 __ ___ __ __ | G13: 0.05 | H13: НАВОИЙ ВИЛОЯТИ
A14: 11 | B14: Бухоро филиали | C14: Регион | D14: — впишите — | E14: 0 | F14: +998 __ ___ __ __ | G14: 0.05 | H14: БУХОРО ВИЛОЯТИ
A15: 12 | B15: Термиз филиали | C15: Регион | D15: — впишите — | E15: 0 | F15: +998 __ ___ __ __ | G15: 0.05 | H15: СУРХОНДАРЁ ВИЛОЯТИ
A16: 13 | B16: Гулистон филиали | C16: Регион | D16: — впишите — | E16: 0 | F16: +998 __ ___ __ __ | G16: 0.05 | H16: СИРДАРЁ ВИЛОЯТИ
A17: 14 | B17: Олмалиқ филиали | C17: Регион | D17: — впишите — | E17: 0 | F17: +998 __ ___ __ __ | G17: 0.05 | H17: ТОШКЕНТ ВИЛОЯТИ
A18: 15 | B18: Чирчик филиали | C18: Регион | D18: — впишите — | E18: 0 | F18: +998 __ ___ __ __ | G18: 0.05 | H18: ТОШКЕНТ ВИЛОЯТИ
A19: 16 | B19: Янги Йул филиали | C19: Регион | D19: — впишите — | E19: 0 | F19: +998 __ ___ __ __ | G19: 0.05 | H19: ТОШКЕНТ ВИЛОЯТИ
... A21: 18 | B21: BOSH OFIS | C21: Центральное | D21: — впишите — | E21: 0 | F21: +998 __ ___ __ __ | G21: 0.05 | H21: ТОШКЕНТ ШАХРИ
B22: ИТОГО | E22: =SUM(E4:E21) -> 0

Sheet Дозвонились
A1: ← Вернуться в отчёт
A2: Область | B2: Филиал | C2: Группа | D2: Код клиента | E2: Клиент | F2: Номер телефона | G2: Адрес | H2: Кол-во просроченных дней | I2: Итого просрочка | J2: Оплата | K2: Izoh
A3: БУХОРО ВИЛОЯТИ | C3: Дозвон | D3: Кр-99063147-1 | E3: YUSUPOV TALGAT RAVILEVICH | F3: +998934589950 SMS O’ZI, 998504052350 SMS AYOLI, 998936202480 SMS QIZI, 998936560151 SMS ONASI, | G3: 5-СОН ГАФУР ГУЛОМ НОМЛИ МФЙ, ИФТИХОР КУЧАСИ, 32-UY | H3: 8 | I3: 8437576.4 | J3: 8437576.4 | K3: To'ladi
A4: БУХОРО ВИЛОЯТИ | C4: Дозвон | D4: Кр-99038186-1 | E4: SA’DULLAYEVA ROXILLA SADULLO QIZI | F4: 998933094290 SMS OZI, 998993803457 SMS QUDASI, 998990943457 SMS SINGLISI, | G4: BUXORO VILOYATI BUXORO TUMANI, QALQO QISHLOG'I, 4-MUYILISH, 8-UY | H4: 1 | I4: 7600197.6 | J4: 7600197.6 | K4: To'ladi
A5: БУХОРО ВИЛОЯТИ | C5: Обещал | D5: Кр-99036711-1 | E5: ERGASHOV ALISHER NARZULLAYEVICH | F5: 998934784464 SMS O’ZI, 998939569626 SMS OTASI, 998931571911 SMS ONASI, 998930052290 SMS SINGLISI , | G5: BUXORO VILOYATI, QORAKO'L TUMANI, ISTIQLOL MFY, YANGI QISHLOQ KO'CHASI, 15-UY | H5: 1 | I5: 5020948.3 | K5: Va'da berdi | ertaga anq tulaydi
A6: БУХОРО ВИЛОЯТИ | C6: Обещал | D6: Кр-99028153-4 | E6: GOIPOV EL’BRUS RAXMADOVICH | F6: 94-120-61-31 SMS OZI, 94-219-60-83 SMS AYOLI, 94-782-03-28 OGLI (бегана), 94-382-28-11 SMS QIZI, | G6: BUXORO VILOYATI OLOT TUMANI XIDREYLI MFY 141-UY | H6: 8 | I6: 4961647.2 | K6: Va'da berdi
A7: БУХОРО ВИЛОЯТИ | C7: Обещал | D7: Кр-99034426-1 | E7: AZIZOV ILXOM BAXTIYAROVICH | F7: 998905146560 SMS OZI, 998907121044 SMS AYOLI, 998938741010 SMS OTASI, 998936421010 SMS ONASI, 998936421010 толовчичи шодиёр, | G7: BUXORO VILOYATI BUXORO SHAHAR TOJIQARAYEV MFY 61-UY | H7: 1 | I7: 4692523.7 | K7: Va'da berdi | ertaga
A8: БУХОРО ВИЛОЯТИ | C8: Обещал | D8: Кр-99062677-2 | E8: POCHCHOYEVA ZULAYXO TOLIBJONOVNA | F8: +998932594485 SMS O’ZI, 998952224447 SMS ERI, 998992304600 SMS QAYNONASI, 998995554600 SMS QAYNOTA, 998939564485 узи 2, | G8: BUXORO VILOYAT JONDOR TUMAN IBN SINO MFY ASBOBSOZ KO’CHA 130-UY | H8: 8 | I8: 4269476.9 | K8: Va'da berdi | JUMA KUNI TOLOV QLAMN OYLI TUWADI DEDI
A9: БУХОРО ВИЛОЯТИ | C9: Обещал | D9: Кр-99018891-5 | E9: FAXILLOYEVA MOXINUR FOZILOVNA | F9: 97-306-16-10 SMS OZI, 90-513-05-03 SMS ERI, 97-854-75-48 SMS QAYNONA, 91-411-91-88 SMS QAYNOTA, 50-578-16-10 SMS UZI2, | G9: BUXORO VILOYATI BUXORO TUMANI NOVMETAN QFY | H9: 8 | I9: 4132073.3 | K9: Va'da berdi | bugun tolov qladi 5 gaca filialga borb
A10: БУХОРО ВИЛОЯТИ | C10: Обещал | D10: Кр-99033022-1 | E10: ASKAROV SHOHBOZ ULUG’BEKOVICH | F10: 998944219181 SMS OIZ, 998796441812 SMS OZI 2, 998931971731 SMS AYOLI, | G10: TOSHKENT SHAHAR, YANGIHAYOT TUMANI, YANGI DARXON MFY, NAVRO'Z KOCHASI 16-UY | H10: 8 | I10: 3155149.2 | K10: Va'da berdi | JUMA KUNI TOLOV QLAMN OYLI TUWADI DEDI
A11: БУХОРО ВИЛОЯТИ | C11: Дозвон | D11: Кр-99040789-2 | E11: DJURAYEVA SHAXINABONU ERKIN QIZI | F11: +998882100226 SMS O’ZI, 998772011384 SMS ONASI, 998991035070 SMS OTASI, 998997982977 SMS ZALAGADATEL, | G11: Уртачул МФЙ, Урта-Чул қишлоғи, 26-уй | H11: 8 | I11: 3150032.5 | J11: 3150032.5 | K11: To'ladi
A12: БУХОРО ВИЛОЯТИ | C12: Обещал | D12: Кр-99038162-1 | E12: DJAMOLOV BOBIR BAHRIDDINOVICH | F12: 998914174488 SMS OZI, 998914182244 SMS OZI, 998934225600 SMS O’G’LI Бехруз шу номерга қилинсин, 998930807508 SMS O’G’LI, | G12: BUXORO VILOYATI, VOBKENT TUMANI, ROZMOZ MFY, ELACH KO'CHASI, 4-UY | H12: 1 | I12: 2825554.5 | K12: Va'da berdi | bugun tulaydi
A13: БУХОРО ВИЛОЯТИ | C13: Обещал | D13: Кр-99037180-2 | E13: YULDASHEVA DILNOZA FAXRIDINOVNA | F13: 998914076943 SMS OZI, 998907441349 SMS ERI , 998941250707 SMS JIYANI, 998507056161 SMS AMAKISI, +998914076943 SMS O’ZI, | G13: ИСТИКБОЛ МФЙ, ШУРОБОД, 67-УЙ | H13: 8 | I13: 2736915.4 | K13: Va'da berdi | bugun tulaydi
A14: БУХОРО ВИЛОЯТИ | C14: Обещал | D14: Кр-99033611-1 | E14: ELMURODOVA ZEBINISO ODILOVNA | F14: 998939904907 SMS O’ZI, 998939983008 SMS ERI, 998943754907 SMS OTASI, 998931374907 SMS O’G’LI, 998501888730 SMS ERI 2, 998501204758 to'lovchi, | G14: BUXORO VILOYATI SHOFIRKON TUMANI PATTAXON MFY, YANGIOBOD q-q, 18-UY | H14: 1 | I14: 2701930.7 | K14: Va'da berdi | 18 sida tolaydi
A15: БУХОРО ВИЛОЯТИ | C15: Обещал | D15: Кр-99048166-1 | E15: KURBANOV DILMUROD TUYMURADOVICH | F15: +998936859009 SMS O’ZI, 998505100034 SMS QIZI, 998931361133 SMS O’G’LI, 998956001133 SMS AYOLI, | G15: BUXORO VILOYATI, BUXORO SHAHAR, IBN SINO MFY, BAHOUDDIN NAQSH BAND KO’CHASI,197-UY, 91-XONADON | H15: 8 | I15: 2505488 | K15: Va'da berdi
A16: БУХОРО ВИЛОЯТИ | C16: Обещал | D16: Кр-99039939-1 | E16: TUXTAYEVA NARGIZA JURAYEVNA | F16: 998918365488 SMS OZI, 998903407973 SMS ONASI, 998331951802 SMS ERI, 998994452534 SMS UY, | G16: BUXORO VILOYATI BUXORO SHAHAR FOSHUN MFY ALPOMISH KO'CHASI, 17/3 UY, 10-XONADON | H16: 8 | I16: 2408716.9 | K16: Va'da berdi
A17: БУХОРО ВИЛОЯТИ | C17: Обещал | D17: Кр-99033006-2 | E17: AMIRQULOV AZIZBEK FARXOD O’G’LI | F17: 998943206655 SMS O’ZI , 998930065166 SMS AKASI, 998940514494 SMS UKASI, | G17: BUXORO VILOYATI KORAKO’L TUMANI DARG’ALI MFY OQG’UN QISHLOG’I 22-UY | H17: 13 | I17: 2230158.7 | K17: Va'da berdi | ozi kotarmadi akasi ozm toliman 2 kunda dedi
A18: БУХОРО ВИЛОЯТИ | C18: Обещал | D18: Кр-99062595-1 | E18: NORQULOV HAYOT XODJIYEVICH | F18: 998907109550 SMS OZI, 998907119550 SMS AYOLI, 998902980454 SMS DOSTI, 998919369550 SMS UY, | G18: BUXORO VILOYATI BUXORO SHAHAR 19-SONLI FAYZULLA XO'JAYEV NOMLI MFY, SHODLIK KO'CHASI | H18: 8 | I18: 2213446.4 | K18: Va'da berdi | ertaga anq tolov qladi filialga borb
A19: БУХОРО ВИЛОЯТИ | C19: Обещал | D19: Кр-99019690-5 | E19: HAYDAROV FURQAT RAXMATILLOYEVICH | F19: 97-488-07-66 SMS O'ZI, 88-301-90-93 SMS AKASI, 97-296-06-93 SMS UY, 93-841-53-50 SMS AYOLI, 998505999203 SMS O'ZI2, | G19: BUXORO VILOYAT BUXORO SHAHRI BESHKAPPA KO'CHASI 106 UY | H19: 8 | I19: 2186873.8 | K19: Va'da berdi | OZI KOTARMADI UYDIGILANI TELI UCHGAN TGDAN YOZDM BUGUN TOLOV QLAMAN FILIALDAGI NMIRON BN GAPLAWGANMAN DEDI
A20: БУХОРО ВИЛОЯТИ | C20: Дозвон | D20: Кр-99062944-1 | E20: SAMIYEV DOSTONBEK TAVAKKALZODA | F20: +998882814800 SMS O’ZI, 998505068777 SMS UKASI, 998883064800 SMS UKASI, 998883440311 SMS ONASI, | G20: BUXORO VILOYATI SHOFIRKON TUMANI G’ULOMTE MFY G’ULOMTE QISHLOG’I | H20: 8 | I20: 2105616.6 | J20: 2105616.6 | K20: To'ladi | filialga naxt tolangan
A21: БУХОРО ВИЛОЯТИ | C21: Обещал | D21: Кр-99041320-3 | E21: SHODIYEV ULUG’BEK SALIMOVICH | F21: +998914431901 sms o’zi, 998907119935 sms onasi, 998912408206 sms ayoli, 998914471901 sms o’zi 2, | G21: Бухарская область, Гиждуванский район, Соктари МСГ, Соктари, дом 239 | H21: 8 | I21: 2084856 | K21: Va'da berdi | avans tuwadi 2kunda toliman dedi
A22: БУХОРО ВИЛОЯТИ | C22: Обещал | D22: Кр-99063975-1 | E22: QUZIYEV MAQSUD HIKMATULLOYEVICH | F22: 998912463904 SINGLISI, 998933147491 AYOLI, 998996229992 O’ZI, | G22: SDFC | H22: 8 | I22: 2059464.5 | K22: Va'da berdi
A23: БУХОРО ВИЛОЯТИ | C23: Обещал | D23: Кр-99040399-1 | E23: FATULLOYEV RIXSILLO SAYFULLA O’G’LI | F23: +998933163138 SMS O’ZI, 998933019922 SMS AKASI, 998934553785 SMS OTASI, 998943129933 SMS YANGASI, | G23: Бухарская область, Жондоpский район, Жамият МСГ, Шамширгарон, дом 309/1 | H23: 8 | I23: 1856810.5 | K23: Va'da berdi
A24: БУХОРО ВИЛОЯТИ | C24: Обещал | D24: Кр-99057620-1 | E24: SADRIDDINOV SAVRIDDIN HUSNIDDIN O’G’LI | F24: 998997027515 SMS UZI, 998906367515 SMS OTASI, 998997077515 SMS ONASI, 998918087515 SMS AKASI, | G24: BUXORO VILOYATI VOBKENT TUMANI KO'LXATIB MFY, NAVOIY KO'CHASI, 4-UY | H24: 8 | I24: 1845061.8 | K24: Va'da berdi | 16 SIDA OYLI TUWAD
A25: БУХОРО ВИЛОЯТИ | C25: Обещал | D25: Кр-99047434-2 | E25: UMRZOQOV FAXRIDDIN AXMEDJONOVICH | F25: 998959754272 O`ZI, 998941220757 AYOLI, 998945457562 DO`STI, 998959754272 uzi, 998941220757 ayoli, 998945457562 dosti, | G25: Бухоро шахар коракул тумани Мустакиллик 50 уй | H25: 8 | I25: 1815275.3 | K25: Va'da berdi
A26: БУХОРО ВИЛОЯТИ | C26: Обещал | D26: Кр-99038109-1 | E26: QO’YLIYEV SARDOR SATTOR O’G’LI | F26: 998885546677 SMS OZI, 998954741616 SMS AKASI, 998990748047 SMS OPASI, 998883041232 SMS UYI, | G26: BUXORO VILOYATI KOGON TUMANI, NIYOZ HOJI MFY, VADAN QISHLOG'I 88-UY | H26: 1 | I26: 1763754.3 | K26: Va'da berdi | sewanba kun oylik tuwadi tolov qlaman dedi
A27: БУХОРО ВИЛОЯТИ | C27: Обещал | D27: Кр-99041716-1 | E27: ODINAYEV ASLON AZIMOVICH | F27: +998872504057 SMS O’ZI, 998905122625 SMS DO’STI, 998912479697 SMS O’G’LI, 998978588778 SMS O’G’LI 2, 998882802662 yangi nomer o'zi, | G27: Убачули МФЙ, Мевазор кучаси, 96-уй | H27: 8 | I27: 1724153.7 | K27: Va'da berdi
A28: БУХОРО ВИЛОЯТИ | C28: Обещал | D28: Кр-99031584-1 | E28: NOROVA IRODA NE’MATOVNA | F28: 90-809-45-45 SMS O'ZI, 93-372-19-81 SMS QIZI MAFTUNA, 50-758-04-06 SMS QIZI MAHSUDA tanimidi, 91-016-68-42 SMS ONASI, 950378185 opchasi, 998774080081 узи , | G28: BUXORO VILOYATI QORAKO’L TUMANI TASHABBUS MFY ADXAM / YUNUSOBOD TUMANI 2-MAVZE 31-UY 45-XONADON | H28: 8 | I28: 1670536.4 | K28: Va'da berdi
A29: БУХОРО ВИЛОЯТИ | C29: Обещал | D29: Кр-99063280-1 | E29: QURBONOV XUSHVAQT G’ULOMOVICH | F29: +998914177518 SMS O’ZI, 998990454555 SMS AYOLI, 998993454441 SMS DO’STI, | G29: OLOT TUMANI | H29: 8 | I29: 1535825 | K29: Va'da berdi | BUGUN TOLAYDI
A30: БУХОРО ВИЛОЯТИ | C30: Обещал | D30: Кр-99062864-1 | E30: MAXMUDOV ALIAKBAR SAIDJONOVICH | F30: +998900650514 SMS, 998507103377 SMS UY, 998905128669 SMS AYOLI, | G30: BUXORO VILOYATI BUXORO SHAHAR AVSHORMAHALLA MFY 77-UY | H30: 8 | I30: 1516902 | K30: Va'da berdi | BUGUN TOLAYDI
A31: БУХОРО ВИЛОЯТИ | C31: Дозвон | D31: Кр-99040456-1 | E31: TEMIROV NODIRBEK G’OLIBJON OG’LI | F31: 998902981307 SMS OZI, 998995556077 SMS AMAKISI, 998918381398 SMS OTASI, 998906110811 SMS ONASI, | G31: BUXORO VILOYATI G'IJDUVON TUMANI ZARANGARI MFY, BO'LAKIYON QISHLOG'I 36-UY | H31: 8 | I31: 1432784.8 | J31: 1432784.8 | K31: To'ladi | filialga
A32: БУХОРО ВИЛОЯТИ | C32: Обещал | D32: Кр-99032591-1 | E32: BOZOROV DILSHOD OLIM O’G’LI | F32: 998995853782 SMS O’G’LI, 998940186667 SMS AYOLI(BEGONA), 998938997077 SMS ONASI, 998930831515 SMS HAMKASBI бегона , | G32: BUXORO VILOYATI ROMITAN TUMANI O'TABEK MFY, PITMON q-q, 6-uy | I32: 1298935.7 | K32: Va'da berdi | erta tolov qladi
A33: БУХОРО ВИЛОЯТИ | C33: Обещал | D33: Кр-99019690-4 | E33: HAYDAROV FURQAT RAXMATILLOYEVICH | F33: 97-488-07-66 SMS O'ZI, 88-301-90-93 SMS AKASI, 97-296-06-93 SMS UY, 93-841-53-50 SMS AYOLI, 998505999203 SMS O'ZI2, | G33: BUXORO VILOYAT BUXORO SHAHRI BESHKAPPA KO'CHASI 106 UY | H33: 11 | I33: 1212298.9 | K33: Va'da berdi | OZI KOTARMADI UYDIGILANI TELI UCHGAN TGDAN YOZDM BUGUN TOLOV QLAMAN FILIALDAGI NMIRON BN GAPLAWGANMAN DEDI
A34: БУХОРО ВИЛОЯТИ | C34: Обещал | D34: Кр-99019690-6 | E34: HAYDAROV FURQAT RAXMATILLOYEVICH | F34: 97-488-07-66 SMS O'ZI, 88-301-90-93 SMS AKASI, 97-296-06-93 SMS UY, 93-841-53-50 SMS AYOLI, 998505999203 SMS O'ZI2, | G34: BUXORO VILOYAT BUXORO SHAHRI BESHKAPPA KO'CHASI 106 UY | H34: 8 | I34: 1137499.2 | K34: Va'da berdi | OZI KOTARMADI UYDIGILANI TELI UCHGAN TGDAN YOZDM BUGUN TOLOV QLAMAN FILIALDAGI NMIRON BN GAPLAWGANMAN DEDI
A35: БУХОРО ВИЛОЯТИ | C35: Дозвон | D35: Кр-99049403-1 | E35: NAVRO’ZOV AZIZBEK HAYDAROVICH | F35: +998882827877 SMS O’ZI, 998914030464 SMS ONASI, 998936515100 SMS AKASI, 998973056003 SMS AKASI, | G35: BUXORO VILOYATI BUXORO TUMANI RABOTAK MFY YANGIOBOD KO’CHASI 118-UY | H35: 8 | I35: 1118758.3 | J35: 1118758.3 | K35: To'ladi
A36: БУХОРО ВИЛОЯТИ | C36: Обещал | D36: Кр-99036367-2 | E36: BEHBUDOV ASLBEK RIZAMATOVICH | F36: +998947812907 SMS O’ZI, 998914462869 SMS OTASI, 998948795777 SMS JIYANI, 998997034797 SMS ONASI, | G36: BUXORO VILOYATI QORAKO’L TUMANI KUYI JANPAR 101-UY | H36: 8 | I36: 1113123.3 | K36: Va'da berdi | 20 09 CIDA TOLIDI
A37: БУХОРО ВИЛОЯТИ | C37: Дозвон | D37: Кр-99057614-1 | E37: RASULOV XAKIM RO’ZIYEVICH | F37: 998914413241 SMS UZI, 998943434898 SMS UGLI, 998914158714 SMS TURMUSH O'RTOG'I, 998919256826 ozi2, | G37: NAVOIY VILOYATI,KOMNIMEX TUMANI,YUKSALISH MFY,CHORDARA QISHLOG'I,37 UY | H37: 8 | I37: 1007128.8 | J37: 1007128.8 | K37: To'ladi
A38: БУХОРО ВИЛОЯТИ | C38: Обещал | D38: Кр-99049211-1 | E38: ADIZOV AZAMAT SHOYIMOVICH | F38: 998940642993 SMS JIYANI, 998942218131 SMS O’ZI, 998978055824 SMS UKASI, 998999767786 SMS AYOLI, | G38: GULISTON, DOM 56 | H38: 8 | I38: 721276.55 | K38: Va'da berdi | filial bilan gaplawdim dedi
A39: БУХОРО ВИЛОЯТИ | C39: Обещал | D39: Кр-99044175-1 | E39: MURODOV MUROD UMAR O’G’LI | F39: +998995624067 SMS O’ZI, 998914450878 SMS DO’STI, 998918384026 SMS ONASI, 998948893111 SMS DO’STI, | G39: Паноб МФЙ, Янги ҳаёт қишлоғи, 138-уй | I39: 559713.31 | K39: Va'da berdi | bugun
A40: БУХОРО ВИЛОЯТИ | C40: Обещал | D40: Кр-99062840-2 | E40: DAVRONOV SOBIR KAMOLOVICH | F40: 998934608944 UKASI, 998936850790 AYOLI, 998945177590 O’ZI 2 NOMERI, 998935690790 uzi new SMS, | G40: G’IJDUVON TUMANI | H40: 8 | I40: 477080.45 | K40: Va'da berdi | bu navoiy viloyati
A41: БУХОРО ВИЛОЯТИ | C41: Дозвон | D41: Кр-99035271-1 | E41: ERGASHEV MADAT MAXMUDOVICH | F41: 998951410082 SMS O’ZI begona, 998883078283 SMS AYOLI, 998939756160 SMS ONASI, 998880830140 SMS UY, 998882854888 узи, 998879650920 кизи, | G41: BUXORO VILOYATI SHOFIRKON TUMANI, XO'JA ORIF MFY, XO'JA ORIF KO'CHASI, 201-UY | H41: 1 | I41: 54.48 | J41: 54.48 | K41: To'ladi
A42: ЖИЗЗАХ ВИЛОЯТИ | C42: Обещал | D42: Кр-99047637-1 | E42: AZIMOV ASADBEK OTABEK O’G’LI | F42: +998905382222 SMS NOMER, 998971120007 SMS O’ZI, 998991937773 begonA EKAN, | G42: JIZZAX VILOYATI JIZZAX SHAHRI TURON MFY SAYILJOYI KUCHASI 21-UY | H42: 71 | I42: 19927076 | K42: Va'da berdi | ertaga yopadi
A43: ЖИЗЗАХ ВИЛОЯТИ | C43: Обещал | D43: Кр-99060448-1 | E43: MAMIROVA ZEBO ZOIROVNA | F43: 998779762227 SMS OZI, 998938244230 SMS AYOLI, 998906432211 SMS UKASI, | G43: JIZZAX VILOYATI SHAROF RASHIDOV TUMANI YAXTANLIK MFY GUZAL KOCHASI 52-UY | H43: 11 | I43: 11697427 | K43: Va'da berdi | wu hafta tolaydi
A44: ЖИЗЗАХ ВИЛОЯТИ | C44: Обещал | D44: Кр-99027165-3 | E44: DJABBAROVA PULATOY SAYFIDDINNOVNA | F44: 91-941-83-83 SMS UZI , 93-393-79-09 SMS UZI 2, 94-977-84-58 SMS QAYNONASI , 93-449-77-15 SMS OGLI, 99-079-20-10 SMS UZI new, | G44: JIZZAX VILOYATI JIZZAX TUMANI QANGLI MFY CHAVANDOZLAR KUCHASI 13-UY | H44: 11 | I44: 8369851.8 | K44: Va'da berdi | kecgaca tolaydi
A45: ЖИЗЗАХ ВИЛОЯТИ | C45: Обещал | D45: Кр-99056937-2 | E45: RASHIDOVA NASIBA YAKUBOVNA | F45: 998889541771 SMS OZI, 998843817712 SMS OZI2, 998974390219 SMS KELINI, | G45: JIZZAX VILOYATI JIZZAX SHAHAR MIRZO ULUG'BEK MAHALLASI 2-UY 10-XONADON | H45: 11 | I45: 8235139.5 | K45: Va'da berdi | bugun tulaydi
A46: ЖИЗЗАХ ВИЛОЯТИ | C46: Обещал | D46: Кр-99028729-1 | E46: AMANOV BUNYOD MUMIN O’G’LI | F46: 998991791177 SMS OZI, 998902642879 SMS OPASI, 998509979579 SMS TOLOVCHISI, 998996790117 SMS AYOLI, 998881591177 AYOLI, 998944449556 ONASI, | G46: МУЗБУЛОК МФЙ, МУЗБУЛОК МФЙ, ЛОЙИХАДАГИ, uy:Р.С | H46: 4 | I46: 6850779.4 | K46: Va'da berdi | kecgaca tolaydi
A47: ЖИЗЗАХ ВИЛОЯТИ | C47: Обещал | D47: Кр-99062344-1 | E47: ALIMOV BAXROM YETMISHOVICH | F47: 998959098681 O`ZI, 998959108681 AYOLI, 998956261810 QIZI, | G47: JIZZAX VILOYATI ZARBDOR TUMANI RAVOT MFY PILLAKOR KUCHASI 1-UYI | H47: 8 | I47: 6616631.7 | K47: Va'da berdi | 2kunda tolimn filyaldagilar blan gaplawdm dedi
A48: ЖИЗЗАХ ВИЛОЯТИ | C48: Дозвон | D48: Кр-99028616-4 | E48: MALLAYEV SHUXRAT BOSIMOVICH | F48: 93-301-00-66 SMS O'ZI, 93-301-07-54 SMS AYOLI, 93-301-06-96 SMS SIN, 99-245-90-99 SMS SIN 2, 998945450550 Eldor ogli , 998992169079 tulovchi, 998997563446 tulovchi, | G48: JIZZAX VILOYATI JIZZAX TUMANI QANGLI MFY TARAQLI KUCHASI 13-UY | H48: 8 | I48: 6576640.7 | J48: 6576640.7 | K48: To'ladi
A49: ЖИЗЗАХ ВИЛОЯТИ | C49: Обещал | D49: Кр-99028038-1 | E49: XAZRATKULOVA RAYXON TURSUNBAYEVNA | F49: 998772725500 SMS OZI, 998951307770 SMS UKASI, 998904928594 SMS ZOLOGATEL, | G49: JIZZAX VILOYATI JIZZAX SHAHRI OBOD MFY XALQLAR DUSTLIGI KUCHASI 101-A UY 23-XONADON | H49: 6 | I49: 5897133.6 | K49: Va'da berdi | ukasi temur bilan gaplawganman dedi
A50: ЖИЗЗАХ ВИЛОЯТИ | C50: Обещал | D50: Кр-99021925-1 | E50: ISMOILOVA NARGIZA ABDUSALIYEVNA | F50: 998938567000 SMS O’ZI, 998501040408 SMS ERI, 998943437777 SMS ERI , 998905160057 SMS ERINI UKASI, 998931070408 tolovchi eri , 998971299092 sms tulovchi, 998508043200 FARUX TULOVCHISI, | G50: JIZZAX VILOYATI SHAROF RASHIDOV TUMANI QANG'LI QFY ARISHLI MAHALLASI ZIYOKOR KUCHASI 4-UY | H50: 1 | I50: 5112052.5 | K50: Va'da berdi | ertaga tulaydi
A51: ЖИЗЗАХ ВИЛОЯТИ | C51: Дозвон | D51: Кр-99033288-1 | E51: KENJAYEVA MUHABBAT XOLQUZIYEVNA | F51: 998995277527 SMS O’ZI, 998932993392 SMS QIZI, 990982993399 SMS KUYOVI, | G51: JIZZAX VILOYATI SH RASHIDOV TUMANI QAHRAMON MFY TURKISTON KUCHASI 42-UY | H51: 11 | I51: 4835015.5 | J51: 4835015.5 | K51: To'ladi
A52: ЖИЗЗАХ ВИЛОЯТИ | C52: Обещал | D52: Кр-99042115-1 | E52: MIRZAYEV OYBEK SUNATILLAYEVICH | F52: +998902659695 SMS, 998915909006 SMS, 998974559695 SMS, | G52: JIZZAX VILOYATI SH.RASHIDOV TUMANI TOKCHILIK MFY ZARGARLIK KUCHASI 2-UY | H52: 8 | I52: 4443964.3 | K52: Va'da berdi | bugun kecgaca yopadi
A53: ЖИЗЗАХ ВИЛОЯТИ | C53: Обещал | D53: Кр-99063504-1 | E53: MIRZAYEVA LOBARXON ERGASHEVNA | F53: 998933556974 UZI, 998934026974 ERI, 998958832266 TO’LOVCHI, | G53: ТОШКЕСГАН КФЙ, ЛОЙИХАДАГИ КЎЧА, uy:РАКАМСИЗ | H53: 8 | I53: 4415942.1 | K53: Va'da berdi | ertaga tolaydi
A54: ЖИЗЗАХ ВИЛОЯТИ | C54: Дозвон | D54: Кр-99040359-1 | E54: KOMOLJONOV IXTIYOR BAXTIYOROVICH | F54: 998999434941 SMS OZI, 998194149412 SMS OZI2, 998901828688 SMS AYOLI, | G54: JIZZAX VILOYATI JIZZAX TUMANI ZIYOKOR MFY ABDUQAHHOR KUCHASI 42-UY | H54: 8 | I54: 4215460.2 | J54: 4215460.2 | K54: To'ladi
A55: ЖИЗЗАХ ВИЛОЯТИ | C55: Обещал | D55: Кр-99062963-2 | E55: RAJABOV BAXODIR BOZARBOYEVICH | F55: 998941996644 AYOLI, | G55: Саройлик МФЙ, Эркинлик кучаси, 45-уй | H55: 8 | I55: 4084124.4 | K55: Va'da berdi | erta abetgaca tolaydi
A56: ЖИЗЗАХ ВИЛОЯТИ | C56: Обещал | D56: Кр-99031840-1 | E56: UKTAMOV KOMILJON G’ULOMJON O’G’LI | F56: 998947060276 SMS O’ZI, 998996837171 SMS Uzi, 998883472121 SMS AKASI, 998941621146 SMS ONASI, | G56: JIZZAX VILOYATI SH.RASHIDOV TUMANI BUSTON MFY YOSHLIK KUCHASI 3-UY | H56: 1 | I56: 3851979.2 | K56: Va'da berdi | kecgaca tolaydi
A57: ЖИЗЗАХ ВИЛОЯТИ | C57: Обещал | D57: Кр-99057340-1 | E57: SUYUNOVA UMIDA ILHOM QIZI | F57: 998995542023 SMS ERI, 998930913798 SMS UZI, 998943461045 SMS UY, 998901020807 SMS Akasi, | G57: JIZZAX VILOYATI MIRZACHO'L TUMANI IPAK YULI QFY YANGI XAYOT KUCHASI 29-UY | H57: 8 | I57: 3789341.3 | K57: Va'da berdi | soat 4da tel qiliw kerak
A58: ЖИЗЗАХ ВИЛОЯТИ | C58: Обещал | D58: Кр-99003082-6 | E58: TO’XTAYEV RASHID RAXMONQULOVICH | F58: 998881535010 SMS O’ZI, 998912352020 SMS BEGONA, 998979809700 SMS UKASI, 998915964295 SMS ozi shunga qilinsin , | G58: JIZZAX VILOYATI SHAROF RASHIDOV TUMANI ZIYOKOR MFY ZIYOKOR KO'CHASI 96-UY | H58: 1 | I58: 3507616 | K58: Va'da berdi | ertaga tulaydi
A59: ЖИЗЗАХ ВИЛОЯТИ | C59: Обещал | D59: Кр-99052135-1 | E59: TURAKULOV SIROJIDDIN SUNNAT O’G’LI | F59: 998919421111 UY, 998993447700 sms new uz, | G59: ЗИЛОЛ, ЗИЛОЛ, ЯНГИОБОД, uy:30 | H59: 12 | I59: 3447004.6 | K59: Va'da berdi
A60: ЖИЗЗАХ ВИЛОЯТИ | C60: Обещал | D60: Кр-99034257-1 | E60: MURADOV SHOKIRJON ABDULLAYEVICH | F60: 998950381202 SMS OZI, 998957986998 SMS SINI, 998933680979 SMS AYOLI, 998991677998 SMS KELINI, 998950240408 SMS O’G’LI TO’LOVCHI, | G60: JIZZAX VILOYATI G’ALLAOROL TUMANI MADANIYAT MFY QANGLIOBOD SHAXARCHASI 265-UY | H60: 8 | I60: 3441012.5 | K60: Va'da berdi | 2kunda toliman dedi
A61: ЖИЗЗАХ ВИЛОЯТИ | C61: Обещал | D61: Кр-99035229-1 | E61: XOJAMBERDIYEVA GULNOZA SHAVKATOVNA | F61: 998884843344 SMS ERI , 998992335888 SMS O’ZI, 998883566521 SMS DO’STI, 998932103564 SMS UY, 998933007076 SMS ERI GULNOZANI, 998884814433 tulovchi, | G61: JIZZAX VILOYATI ZARBDOR TUMANI SHODLIK MFY NIHOL KUCHASI 19-UY | H61: 4 | I61: 3418638.3 | K61: Va'da berdi | kecgaca tolaydi
A62: ЖИЗЗАХ ВИЛОЯТИ | C62: Обещал | D62: Кр-99063773-1 | E62: MUHAMADIYEVA GULNORA QIZILOVNA | F62: 998911950663 UZI, 998977947748 O’G’LI, 998995406039 O’G’LI, | G62: Жиззахлик МФЙ, ул.Ш.Рашидов , 24-уй | H62: 8 | I62: 3386877.7 | K62: Va'da berdi | abetgaca tulaydi
A63: ЖИЗЗАХ ВИЛОЯТИ | C63: Обещал | D63: Кр-99045797-1 | E63: QARSHIBAYEV RUSLAN QAXRAMON O’G’LI | F63: +998900251515 SMS, 998902978487 SMS, 998992408778 SMS, | G63: JIZZAX VILOYATI SH.RASHIDOV TUMANI TOSHKENTLIK MFY QATORTOL KUCHASI 7-UY | H63: 12 | I63: 3182278.2 | K63: Va'da berdi | 2kunda tolaydi bowqa viloyatda edi kesin ertaga tolaydi dedi
A64: ЖИЗЗАХ ВИЛОЯТИ | C64: Обещал | D64: Кр-99039288-1 | E64: YAKUBOV BUNYOD NEMATILLAYEVICH | F64: 998904878684 SMS OZI, 998886441986 SMS AYOLI, 998932988684 SMS OZI, 998773450986 SMS SINGLISI, | G64: JIZZAX VILOYATI DUSTLIK TUMANI MEVAZOR QFY LOLAZOR KUCHASI 35-UY | H64: 13 | I64: 3181468 | K64: Va'da berdi | kecgaca tolaydi
A65: ЖИЗЗАХ ВИЛОЯТИ | C65: Обещал | D65: Кр-99052894-1 | E65: SUVONQULOV SHAXRIYOR MIRZABEK O’G’LI | F65: 998943079900 SMS OZI, 998932800094 SMS AKASI, 998938265665 SMS AKASI 2, 999839712506 SMS UKASI, | G65: JIZZAX VILOYATI SHAROF RASHIDOV TUMANI QANG'LI QFY NURAFSHON MFY OBOD KUCHASI 9-UY | H65: 8 | I65: 3034487.5 | K65: Va'da berdi | ertaga abetgaca tolaydi
A66: ЖИЗЗАХ ВИЛОЯТИ | C66: Обещал | D66: Кр-99055031-1 | E66: PARDAYEVA XAFIZA AKRAMOVNA | F66: 998995900655 SMS OZI, 998997473110 SMS OZI, 998958160926 SMS O'G'LI, | G66: JIZZAX VILOYATI G'ALLAOROL TUMANI MIRZABULOQ QFY NAYMAN KUCHASI 36-UY | H66: 8 | I66: 3018725.1 | K66: Va'da berdi | kecgaca tolaydi
A67: ЖИЗЗАХ ВИЛОЯТИ | C67: Обещал | D67: Кр-99036491-1 | E67: XAYDAROVA KOMILA ZAYNIDDINOVNA | F67: 998973462688 SMS OZI , 998936507904 SMS AYOLI , 998944740513 SMS QIZI, 998338990215 SMS SINGLISI , 998943462688 SMS NEW, | G67: JIZZAX VILOYATI SH.RASHIDOV TUMANI SOVUNGARLIK MFY 11-UY | H67: 12 | I67: 2908627.9 | K67: Va'da berdi | 16gaca tolaydi temur aka bilan gaplawdm dedi
A68: ЖИЗЗАХ ВИЛОЯТИ | C68: Дозвон | D68: Кр-99039305-1 | E68: G’ANIYEV LAZIZ G’ULOM O’G’LI | F68: 998952401313 SMS OZI, 998975682026 SMS ONASI, 998915682026 SMS DADASI, 998950895353 SMS UKASI, | G68: JIZZAX VILOYATI SH.RASHIDOV TUMANI SOVUNGARLIK MFY MAROQAND KUCHASI 52-UY | H68: 13 | I68: 2861348.7 | J68: 2861348.7 | K68: To'ladi
A69: ЖИЗЗАХ ВИЛОЯТИ | C69: Обещал | D69: Кр-99039896-1 | E69: UMMATOV JAVLON MAVLONOVICH | F69: 998959172024 SMS OZI, 998957701676 SMS UKASI, 998957741676 SMS SINGLIASI, 998911956219 SMS DADASI, 998995247977 sms uzi mew, 998995247977 sms uzi new, | G69: JIZZAX VILOYATI SH.RASHIDOV TUMANI UCH TEPA MFY GUNCHA KUCHASI 97-UY | H69: 8 | I69: 2809934.1 | K69: Va'da berdi | tel qiliw kerak
A70: ЖИЗЗАХ ВИЛОЯТИ | C70: Обещал | D70: Кр-99035971-1 | E70: SHAROPOV JASUR SALAXIDDINOVICH | F70: 998995618200 SMS O’ZI, 998885248200 SMS AYOLI, 998905380123 SMS ONASI , | G70: JIZZAX VILOYATI SH.RASHIDOV TUMANI TOSHKENTLIK MAHALLASI BINOKOR KUCHASI 28-UY | H70: 1 | I70: 2493532.3 | K70: Va'da berdi | bugun kecga ulgurmasam ertaga tawiman dei
A71: ЖИЗЗАХ ВИЛОЯТИ | C71: Обещал | D71: Кр-99046098-1 | E71: RAMAZANOV IXTIYOR BAXTIYOR O’G’LI | F71: 998915983004 SMS, 998945960080 SMS, 998950800277 SMS, | G71: JIZZAX VILOYATI, JIZZAX SHAHRI, TINCHLIK MFY, S.KARIMOV KO’CHASI, 5/17-UY | H71: 11 | I71: 2244914.6 | K71: Va'da berdi | erta yo indin aniq tolaydi
A72: ЖИЗЗАХ ВИЛОЯТИ | C72: Дозвон | D72: Кр-99033588-1 | E72: ESHQULOV ANVAR AXMATOVICH | F72: 998915647757 SMS O’ZI, 999830732622 SMS O’ZI 2, 998933028868 SMS AYOLI, 998991682525 SMS SINGLI, | G72: JIZZAX VILOYATI JIZZAX SHAHRI ZARGARLIK MFY 12-UY 5 XONADON | H72: 1 | I72: 2141957.4 | J72: 2141957.4 | K72: To'ladi
A73: ЖИЗЗАХ ВИЛОЯТИ | C73: Дозвон | D73: Кр-99023067-3 | E73: XURSANOV ODIL OLIM O’G’LI | F73: 88-025-41-14 SMS O’ZI, 94-567-66-44 SMS UKASI, 97-648-97-07 SMS UY, 99-046-56-79 SMS AKASI, 998934385777 SMS UKASI, 998773344114 New ozi, | G73: JIZZZAX VILOYATI ZAFAROBOD TUMANI LOLAZOR QFY X.OLIMJON KUCHASI 1/2-XONADON | H73: 13 | I73: 1985508.2 | J73: 1985508.2 | K73: To'ladi
A74: ЖИЗЗАХ ВИЛОЯТИ | C74: Обещал | D74: Кр-99057414-1 | E74: KARSHIBAYEV SHUXRAT URALOVICH | F74: 998991231880 SMS UZI, 998958914146 SMS UZI 2, 998938265151 SMS AKASI, | G74: JIZZAX VILOYATI ARNASOY TUMANI BO'STON MFY A.QARSHIYEV KUCHASI 30/2-UY | H74: 8 | I74: 1778665 | K74: Va'da berdi | bugun tulaydi
A75: ЖИЗЗАХ ВИЛОЯТИ | C75: Обещал | D75: Кр-99039329-1 | E75: TURSUNMATOV ABDULAZIZ ALIAKBAR O’G’LI | F75: +998947200340 SMS OZI, 998772942607 SMS DADASI, 998990231125 SMS AKASI, 998999992897 SMS UKASI, | G75: МУГОЛ КФЙ, МУГОЛ КФЙ, ЛОЙИХАДАГИ, uy:Р.С | H75: 8 | I75: 1765774.1 | K75: Va'da berdi | ertaga tulaydi
A76: ЖИЗЗАХ ВИЛОЯТИ | C76: Дозвон | D76: Кр-99062952-1 | E76: OCHILOVA DILFUZA URALBOYEVNA | F76: 998931755565 O’G’LI, 998942217575 ERI, | G76: Дустлик МФЙ, Сарой кучаси, 24-уй | H76: 8 | I76: 1753023.2 | J76: 1753023.2 | K76: To'ladi
A77: ЖИЗЗАХ ВИЛОЯТИ | C77: Дозвон | D77: Кр-99013156-3 | E77: XOLDAROV BAXTIYOR ALIM O’G’LI | F77: 998933552200 SMS UZI, 998937015455 SMS AYOLI, 998952810022 SMS UZI 2, 998993272200 SMS BEGONA, 998773652200 SMS BAXTIYOR NEW, | G77: JIZZAX VILOYATI PAXTAKOR TUMANI MINGCHINOR QFY PANG’AT QISHLOG’I MANAVIYAT KUCHASI 1-UY | H77: 5 | I77: 1732593.7 | J77: 1732593.7 | K77: To'ladi
A78: ЖИЗЗАХ ВИЛОЯТИ | C78: Обещал | D78: Кр-99041856-2 | E78: ERDASHEV RUSTAM JALILOVICH | F78: +998932916225 OZI, 998946894222 SMS OZI, 998952852325 SMS OZI 3, | G78: JIZZAX VILOYATI ARNASOY TUMANI G.GULOM MFY BOGIDILKUSHOD KUCHASI 6-UY | H78: 8 | I78: 1531566.7 | K78: Va'da berdi | ertaga tulaydi
A79: ЖИЗЗАХ ВИЛОЯТИ | C79: Обещал | D79: Кр-99036491-2 | E79: XAYDAROVA KOMILA ZAYNIDDINOVNA | F79: 998973462688 SMS OZI , 998936507904 SMS AYOLI , 998944740513 SMS QIZI, 998338990215 SMS SINGLISI , 998943462688 SMS NEW, | G79: JIZZAX VILOYATI SH.RASHIDOV TUMANI SOVUNGARLIK MFY 11-UY | H79: 8 | I79: 1470244.2 | K79: Va'da berdi | 16gaca tolaydi temur aka bilan gaplawdm dedi
A80: ЖИЗЗАХ ВИЛОЯТИ | C80: Дозвон | D80: Кр-99046629-4 | E80: UMAROV VAXOB VALIYEVICH | F80: +998904908890 SMS, 998940358890 SMS, 998999968799 SMS, 998993662364 SMS, | G80: Джизакская область, Джизак г., Хамзаобод, Ойбек, дом 23 | H80: 8 | I80: 1437771 | J80: 1437771 | K80: To'ladi
A81: ЖИЗЗАХ ВИЛОЯТИ | C81: Дозвон | D81: Кр-99013156-2 | E81: XOLDAROV BAXTIYOR ALIM O’G’LI | F81: 998933552200 SMS UZI, 998937015455 SMS AYOLI, 998952810022 SMS UZI 2, 998993272200 SMS BEGONA, 998773652200 SMS BAXTIYOR NEW, | G81: JIZZAX VILOYATI PAXTAKOR TUMANI MINGCHINOR QFY PANG’AT QISHLOG’I MANAVIYAT KUCHASI 1-UY | H81: 6 | I81: 1330322.9 | J81: 1330322.9 | K81: To'ladi
A82: ЖИЗЗАХ ВИЛОЯТИ | C82: Обещал | D82: Кр-99046548-1 | E82: BOYMURZAYEV HASAN NAZAR O’G’LI | F82: 998996766010 узи, 998954330009 укаси, 998919446010 уй, | G82: JIZZAX VILOYATI SHAROF RASHIDOV TUMANI PAXTOBOD QFY YAXTANLIK MAHALLASI | H82: 8 | I82: 1248009.3 | K82: Va'da berdi | kecgaca tolaydi
A83: ЖИЗЗАХ ВИЛОЯТИ | C83: Обещал | D83: Кр-99034257-2 | E83: MURADOV SHOKIRJON ABDULLAYEVICH | F83: 998950381202 SMS OZI, 998957986998 SMS SINI, 998933680979 SMS AYOLI, 998991677998 SMS KELINI, 998950240408 SMS O’G’LI TO’LOVCHI, | G83: JIZZAX VILOYATI G’ALLAOROL TUMANI MADANIYAT MFY QANGLIOBOD SHAXARCHASI 265-UY | H83: 8 | I83: 1154455.6 | K83: Va'da berdi | kecgaca tolaydi
A84: ЖИЗЗАХ ВИЛОЯТИ | C84: Обещал | D84: Кр-99045797-2 | E84: QARSHIBAYEV RUSLAN QAXRAMON O’G’LI | F84: +998900251515 SMS, 998902978487 SMS, 998992408778 SMS, | G84: JIZZAX VILOYATI SH.RASHIDOV TUMANI TOSHKENTLIK MFY QATORTOL KUCHASI 7-UY | H84: 8 | I84: 1152143.1 | K84: Va'da berdi | 2kunda tolaydi bowqa viloyatda edi kesin ertaga tolaydi dedi
A85: ЖИЗЗАХ ВИЛОЯТИ | C85: Обещал | D85: Кр-99048922-1 | E85: XOLMURODOV SHERBEK MARDON O‘G‘LI | F85: +998770010109 SMS OZI, 998944841200 SMS UYI, 998973311213 SMS OPASI, 998976410109 SMS OZI 2, 998770010109 Primary phone from road24, | G85: БАХМАЛ КФЙ, БАХМАЛ КФЙ, ЛОЙИХАДАГИ, uy:Р.С | H85: 1 | I85: 1122689.2 | K85: Va'da berdi | ertaga tulaydi
A86: ЖИЗЗАХ ВИЛОЯТИ | C86: Обещал | D86: Кр-99063395-2 | E86: SOXIBOV DILSHOD YUSUPALIYEVICH | F86: 998501038581 SMS QIZI, 998882488581 SMS AYOLI, 998990661191 SMS OZI, | G86: DEXQONOBOD 2 UY 7 XONADON | H86: 8 | I86: 1117596.9 | K86: Va'da berdi | uzogi paywanbagaca tolaydi rasiyadan pulni kutyapti
A87: ЖИЗЗАХ ВИЛОЯТИ | C87: Дозвон | D87: Кр-99040359-2 | E87: KOMOLJONOV IXTIYOR BAXTIYOROVICH | F87: 998999434941 SMS OZI, 998194149412 SMS OZI2, 998901828688 SMS AYOLI, | G87: JIZZAX VILOYATI JIZZAX TUMANI ZIYOKOR MFY ABDUQAHHOR KUCHASI 42-UY | H87: 8 | I87: 1117075.3 | J87: 1117075.3 | K87: To'ladi
A88: ЖИЗЗАХ ВИЛОЯТИ | C88: Обещал | D88: Кр-99033516-1 | E88: MIRZAMAXMUDOV ODILJON ALLAYOR O’G’LI | F88: 998997449700 SMS O’ZI, 998912084455 SMS O’ZI, 998338382297 SMS DO’STI, 998991332871 SMS ONASI, 998950702444 SMS AKASI, 998336669700 SMS OZI YANGI, 998932947066 SMS ABDUNABI ORTOGI, | G88: JIZZAX VILOYATI BAXMAL TUMANI UDAMALI QISHLOG’I 63-UY | H88: 1 | I88: 1079691.8 | K88: Va'da berdi | ertaga abetgaca tolaydi
A89: ЖИЗЗАХ ВИЛОЯТИ | C89: Дозвон | D89: Кр-99046629-1 | E89: UMAROV VAXOB VALIYEVICH | F89: +998904908890 SMS, 998940358890 SMS, 998999968799 SMS, 998993662364 SMS, | G89: Джизакская область, Джизак г., Хамзаобод, Ойбек, дом 23 | H89: 8 | I89: 1009358.8 | J89: 1009358.8 | K89: To'ladi
A90: ЖИЗЗАХ ВИЛОЯТИ | C90: Дозвон | D90: Кр-99028616-3 | E90: MALLAYEV SHUXRAT BOSIMOVICH | F90: 93-301-00-66 SMS O'ZI, 93-301-07-54 SMS AYOLI, 93-301-06-96 SMS SIN, 99-245-90-99 SMS SIN 2, 998945450550 Eldor ogli , 998992169079 tulovchi, 998997563446 tulovchi, | G90: JIZZAX VILOYATI JIZZAX TUMANI QANGLI MFY TARAQLI KUCHASI 13-UY | I90: 574655.15 | J90: 574655.15 | K90: To'ladi
A91: ЖИЗЗАХ ВИЛОЯТИ | C91: Обещал | D91: Кр-99045121-1 | E91: ISLAMOVA GO’ZAL ZOIR QIZI | F91: 998774512156 SMS, 998950414100 SMS, 998958824000 SMS, | G91: ОСМОНСОЙ ҚФЙ, ОСМОНСОЙ ҚФЙ, УРТАКИШЛОК КИШЛОГИ, uy:РАКАМСИЗ | I91: 452412.95 | K91: Va'da berdi | bugun kecgaca yopadi
A92: ЖИЗЗАХ ВИЛОЯТИ | C92: Обещал | D92: Кр-99034148-3 | E92: SAYFUTDINOVA GAVXAR SHUXRATOVNA | F92: 998903111016 SMS OZI, 998976480208 SMS ERI TOLOVCHI, 998912093311 SMS HAMKASBI, 998712267815 SMS UY, | G92: JIZZAX VILOYATI SH.RASHIDOV TUMANI ZIYOKOR QFY M.ESHONQULOV KUCHASI 125-UY | H92: 8 | I92: 397223.7 | K92: Va'da berdi | bugun tulaydi
A93: ЖИЗЗАХ ВИЛОЯТИ | C93: Дозвон | D93: Кр-99045776-1 | E93: USMONOV ZUXRIDDIN MUXTOROVICH | F93: 998943454563 SMS, 998976411165 SMS, 998979951965 SMS, | G93: JIZZAX VILOYATI DUSTLIK TUMANI QAXRAMON MFY GOLIBLAR KUCHASI 18-UY | I93: 302318.5 | J93: 302318.5 | K93: To'ladi
A94: ЖИЗЗАХ ВИЛОЯТИ | C94: Обещал | D94: Кр-99025940-2 | E94: XAYRULLAYEV MUXAMMAD FAYZULLAYEVICH | F94: 97-129-10-83 SMS UZI, 99-566-22-10 SMS UZI 2, 98-561-10-12 SMS TULOVCHI, 998995610220 SMS O’ZI SHUNGA QILINSIN, | G94: КУЛАМА ҚФЙ, МУЛКАНЛИК МФЙ, ЛОЙИХАДАГИ КЎЧА, uy:60 | I94: 285394.68 | K94: Va'da berdi | 7gaca yopadi
A95: ЖИЗЗАХ ВИЛОЯТИ | C95: Дозвон | D95: Кр-99033705-2 | E95: ABDIYEV IBRAIM RAXMONOVICH | F95: 998937753867 SMS O’ZI, 998937723867 SMS AYOLI, 998931210076 SMS UKASI, 998948762276 SMS OVSINI, | G95: JIZZAX VILOYATI ZAFAROBOD TUMANI UZUN QFY MUSTAQILLIK KUCHASI 24-UY | H95: 8 | I95: 57382.22 | J95: 57382.22 | K95: To'ladi
A96: КАШКАДАРЁ ВИЛОЯТИ | B96: SUPER BRANCH | C96: Обещал | D96: Кр-99036435-3 | E96: JO’RAQULOV MANSUR QULMUROT O’G’LI | F96: 998997330311 SMS O’ZI, 998333400311 SMS AYOLI, 998942976783 SMS O’ZI 2, 998881365522 SMS UKASI , | G96: ЧИРОКЧИ МФЙ, ЧИРОКЧИ, uy:Р/С | H96: 11 | I96: 17370593 | K96: Va'da berdi | 20 da to'lov qiladi
A97: КАШКАДАРЁ ВИЛОЯТИ | B97: SUPER BRANCH | C97: Обещал | D97: Кр-99060317-1 | E97: NAFASOV ASADBEK VALIJON O’G’LI | F97: 998973852277 SMS OZI, 998886191100 SMS AYOLI, 998770994440 SMS DADASI, 998886195000 SMS ONASI, | G97: QASHQADARYO VILOYATI YAKKABOG’ TUMANI ISTIQLOL MFY OLAQARG’A QISHLOG’I | H97: 11 | I97: 11559193 | K97: Va'da berdi | payshanba kuni
A98: КАШКАДАРЁ ВИЛОЯТИ | B98: SUPER BRANCH | C98: Обещал | D98: Кр-99059908-1 | E98: MURODOV BEGZOD ZOIDOVICH | F98: 998500721265 SMS OZI, 998509098588 SMS ONASI (BEGONA), 998976194411 SMS OTASI, 998977088588 SMS ASKASI, 998509098525 SMS UZI NEW, | G98: QASHQADARYO VILOYATI KITOB TUMANI CHARMGAR MFY SAYILGOH KO’CHASI 3-UY | H98: 11 | I98: 7888733.5 | K98: Va'da berdi | bugun
A99: КАШКАДАРЁ ВИЛОЯТИ | B99: SUPER BRANCH | C99: Дозвон | D99: Кр-99012796-5 | E99: SATTOROV JOBIR JAMOL O’G’LI | F99: 91-959-12-51 SMS, 90-615-02-67 SMS AYOLI, 99-113-18-42 SMS UKASI, 91-466-71-07 SMS AYASI, 998900702002 SMS , 998973106292 SMS XOLAVACHCHASI, 998991131842 SMS garov egasi, 998919531115 SMS uzi ZALOG EGASI, 998886220020 SMS TO'LOVCHI, | G99: QASHQADARYO VILOYATI KOSON TUMANI PAXTAZOR MFY X TEMIROV KO’CHASI 22-UY | H99: 8 | I99: 6150050.3 | K99: Telefon ko'tardi | 10 kunda to'liman dedi uyiga xodim jo'natamn
A100: КАШКАДАРЁ ВИЛОЯТИ | B100: SUPER BRANCH | C100: Обещал | D100: Кр-99034170-3 | E100: YUSUPOV OBID XOMETOVICH | F100: 998883831111 SMS O’ZI, 998973871111 SMS O’G’LI, 998973801991 SMS UKASI, 998912621111 SMS AKASI, | G100: QASHQADARYO VILOYATI SHAXRISABZ TUMANI XONTEPA MFY SHUKRONA 32 UY | H100: 8 | I100: 5852440.9 | K100: Va'da berdi | oylik tushadi xozir to'liman deb
...

Sheet Обещали
A1: ← Вернуться в отчёт
A2: Область | B2: Филиал | C2: Группа | D2: Код клиента | E2: Клиент | F2: Номер телефона | G2: Адрес | H2: Кол-во просроченных дней | I2: Итого просрочка | J2: Оплата | K2: Izoh
A3: БУХОРО ВИЛОЯТИ | C3: Обещал | D3: Кр-99036711-1 | E3: ERGASHOV ALISHER NARZULLAYEVICH | F3: 998934784464 SMS O’ZI, 998939569626 SMS OTASI, 998931571911 SMS ONASI, 998930052290 SMS SINGLISI , | G3: BUXORO VILOYATI, QORAKO'L TUMANI, ISTIQLOL MFY, YANGI QISHLOQ KO'CHASI, 15-UY | H3: 1 | I3: 5020948.3 | K3: Va'da berdi | ertaga anq tulaydi
A4: БУХОРО ВИЛОЯТИ | C4: Обещал | D4: Кр-99028153-4 | E4: GOIPOV EL’BRUS RAXMADOVICH | F4: 94-120-61-31 SMS OZI, 94-219-60-83 SMS AYOLI, 94-782-03-28 OGLI (бегана), 94-382-28-11 SMS QIZI, | G4: BUXORO VILOYATI OLOT TUMANI XIDREYLI MFY 141-UY | H4: 8 | I4: 4961647.2 | K4: Va'da berdi
A5: БУХОРО ВИЛОЯТИ | C5: Обещал | D5: Кр-99034426-1 | E5: AZIZOV ILXOM BAXTIYAROVICH | F5: 998905146560 SMS OZI, 998907121044 SMS AYOLI, 998938741010 SMS OTASI, 998936421010 SMS ONASI, 998936421010 толовчичи шодиёр, | G5: BUXORO VILOYATI BUXORO SHAHAR TOJIQARAYEV MFY 61-UY | H5: 1 | I5: 4692523.7 | K5: Va'da berdi | ertaga
A6: БУХОРО ВИЛОЯТИ | C6: Обещал | D6: Кр-99062677-2 | E6: POCHCHOYEVA ZULAYXO TOLIBJONOVNA | F6: +998932594485 SMS O’ZI, 998952224447 SMS ERI, 998992304600 SMS QAYNONASI, 998995554600 SMS QAYNOTA, 998939564485 узи 2, | G6: BUXORO VILOYAT JONDOR TUMAN IBN SINO MFY ASBOBSOZ KO’CHA 130-UY | H6: 8 | I6: 4269476.9 | K6: Va'da berdi | JUMA KUNI TOLOV QLAMN OYLI TUWADI DEDI
A7: БУХОРО ВИЛОЯТИ | C7: Обещал | D7: Кр-99018891-5 | E7: FAXILLOYEVA MOXINUR FOZILOVNA | F7: 97-306-16-10 SMS OZI, 90-513-05-03 SMS ERI, 97-854-75-48 SMS QAYNONA, 91-411-91-88 SMS QAYNOTA, 50-578-16-10 SMS UZI2, | G7: BUXORO VILOYATI BUXORO TUMANI NOVMETAN QFY | H7: 8 | I7: 4132073.3 | K7: Va'da berdi | bugun tolov qladi 5 gaca filialga borb
A8: БУХОРО ВИЛОЯТИ | C8: Обещал | D8: Кр-99033022-1 | E8: ASKAROV SHOHBOZ ULUG’BEKOVICH | F8: 998944219181 SMS OIZ, 998796441812 SMS OZI 2, 998931971731 SMS AYOLI, | G8: TOSHKENT SHAHAR, YANGIHAYOT TUMANI, YANGI DARXON MFY, NAVRO'Z KOCHASI 16-UY | H8: 8 | I8: 3155149.2 | K8: Va'da berdi | JUMA KUNI TOLOV QLAMN OYLI TUWADI DEDI
A9: БУХОРО ВИЛОЯТИ | C9: Обещал | D9: Кр-99038162-1 | E9: DJAMOLOV BOBIR BAHRIDDINOVICH | F9: 998914174488 SMS OZI, 998914182244 SMS OZI, 998934225600 SMS O’G’LI Бехруз шу номерга қилинсин, 998930807508 SMS O’G’LI, | G9: BUXORO VILOYATI, VOBKENT TUMANI, ROZMOZ MFY, ELACH KO'CHASI, 4-UY | H9: 1 | I9: 2825554.5 | K9: Va'da berdi | bugun tulaydi
A10: БУХОРО ВИЛОЯТИ | C10: Обещал | D10: Кр-99037180-2 | E10: YULDASHEVA DILNOZA FAXRIDINOVNA | F10: 998914076943 SMS OZI, 998907441349 SMS ERI , 998941250707 SMS JIYANI, 998507056161 SMS AMAKISI, +998914076943 SMS O’ZI, | G10: ИСТИКБОЛ МФЙ, ШУРОБОД, 67-УЙ | H10: 8 | I10: 2736915.4 | K10: Va'da berdi | bugun tulaydi
A11: БУХОРО ВИЛОЯТИ | C11: Обещал | D11: Кр-99033611-1 | E11: ELMURODOVA ZEBINISO ODILOVNA | F11: 998939904907 SMS O’ZI, 998939983008 SMS ERI, 998943754907 SMS OTASI, 998931374907 SMS O’G’LI, 998501888730 SMS ERI 2, 998501204758 to'lovchi, | G11: BUXORO VILOYATI SHOFIRKON TUMANI PATTAXON MFY, YANGIOBOD q-q, 18-UY | H11: 1 | I11: 2701930.7 | K11: Va'da berdi | 18 sida tolaydi
A12: БУХОРО ВИЛОЯТИ | C12: Обещал | D12: Кр-99048166-1 | E12: KURBANOV DILMUROD TUYMURADOVICH | F12: +998936859009 SMS O’ZI, 998505100034 SMS QIZI, 998931361133 SMS O’G’LI, 998956001133 SMS AYOLI, | G12: BUXORO VILOYATI, BUXORO SHAHAR, IBN SINO MFY, BAHOUDDIN NAQSH BAND KO’CHASI,197-UY, 91-XONADON | H12: 8 | I12: 2505488 | K12: Va'da berdi
A13: БУХОРО ВИЛОЯТИ | C13: Обещал | D13: Кр-99039939-1 | E13: TUXTAYEVA NARGIZA JURAYEVNA | F13: 998918365488 SMS OZI, 998903407973 SMS ONASI, 998331951802 SMS ERI, 998994452534 SMS UY, | G13: BUXORO VILOYATI BUXORO SHAHAR FOSHUN MFY ALPOMISH KO'CHASI, 17/3 UY, 10-XONADON | H13: 8 | I13: 2408716.9 | K13: Va'da berdi
A14: БУХОРО ВИЛОЯТИ | C14: Обещал | D14: Кр-99033006-2 | E14: AMIRQULOV AZIZBEK FARXOD O’G’LI | F14: 998943206655 SMS O’ZI , 998930065166 SMS AKASI, 998940514494 SMS UKASI, | G14: BUXORO VILOYATI KORAKO’L TUMANI DARG’ALI MFY OQG’UN QISHLOG’I 22-UY | H14: 13 | I14: 2230158.7 | K14: Va'da berdi | ozi kotarmadi akasi ozm toliman 2 kunda dedi
... A26: БУХОРО ВИЛОЯТИ | C26: Обещал | D26: Кр-99062864-1 | E26: MAXMUDOV ALIAKBAR SAIDJONOVICH | F26: +998900650514 SMS, 998507103377 SMS UY, 998905128669 SMS AYOLI, | G26: BUXORO VILOYATI BUXORO SHAHAR AVSHORMAHALLA MFY 77-UY | H26: 8 | I26: 1516902 | K26: Va'da berdi | BUGUN TOLAYDI
A27: БУХОРО ВИЛОЯТИ | C27: Обещал | D27: Кр-99032591-1 | E27: BOZOROV DILSHOD OLIM O’G’LI | F27: 998995853782 SMS O’G’LI, 998940186667 SMS AYOLI(BEGONA), 998938997077 SMS ONASI, 998930831515 SMS HAMKASBI бегона , | G27: BUXORO VILOYATI ROMITAN TUMANI O'TABEK MFY, PITMON q-q, 6-uy | I27: 1298935.7 | K27: Va'da berdi | erta tolov qladi
A28: БУХОРО ВИЛОЯТИ | C28: Обещал | D28: Кр-99019690-4 | E28: HAYDAROV FURQAT RAXMATILLOYEVICH | F28: 97-488-07-66 SMS O'ZI, 88-301-90-93 SMS AKASI, 97-296-06-93 SMS UY, 93-841-53-50 SMS AYOLI, 998505999203 SMS O'ZI2, | G28: BUXORO VILOYAT BUXORO SHAHRI BESHKAPPA KO'CHASI 106 UY | H28: 11 | I28: 1212298.9 | K28: Va'da berdi | OZI KOTARMADI UYDIGILANI TELI UCHGAN TGDAN YOZDM BUGUN TOLOV QLAMAN FILIALDAGI NMIRON BN GAPLAWGANMAN DEDI
A29: БУХОРО ВИЛОЯТИ | C29: Обещал | D29: Кр-99019690-6 | E29: HAYDAROV FURQAT RAXMATILLOYEVICH | F29: 97-488-07-66 SMS O'ZI, 88-301-90-93 SMS AKASI, 97-296-06-93 SMS UY, 93-841-53-50 SMS AYOLI, 998505999203 SMS O'ZI2, | G29: BUXORO VILOYAT BUXORO SHAHRI BESHKAPPA KO'CHASI 106 UY | H29: 8 | I29: 1137499.2 | K29: Va'da berdi | OZI KOTARMADI UYDIGILANI TELI UCHGAN TGDAN YOZDM BUGUN TOLOV QLAMAN FILIALDAGI NMIRON BN GAPLAWGANMAN DEDI
A30: БУХОРО ВИЛОЯТИ | C30: Обещал | D30: Кр-99036367-2 | E30: BEHBUDOV ASLBEK RIZAMATOVICH | F30: +998947812907 SMS O’ZI, 998914462869 SMS OTASI, 998948795777 SMS JIYANI, 998997034797 SMS ONASI, | G30: BUXORO VILOYATI QORAKO’L TUMANI KUYI JANPAR 101-UY | H30: 8 | I30: 1113123.3 | K30: Va'da berdi | 20 09 CIDA TOLIDI
A31: БУХОРО ВИЛОЯТИ | C31: Обещал | D31: Кр-99049211-1 | E31: ADIZOV AZAMAT SHOYIMOVICH | F31: 998940642993 SMS JIYANI, 998942218131 SMS O’ZI, 998978055824 SMS UKASI, 998999767786 SMS AYOLI, | G31: GULISTON, DOM 56 | H31: 8 | I31: 721276.55 | K31: Va'da berdi | filial bilan gaplawdim dedi
A32: БУХОРО ВИЛОЯТИ | C32: Обещал | D32: Кр-99044175-1 | E32: MURODOV MUROD UMAR O’G’LI | F32: +998995624067 SMS O’ZI, 998914450878 SMS DO’STI, 998918384026 SMS ONASI, 998948893111 SMS DO’STI, | G32: Паноб МФЙ, Янги ҳаёт қишлоғи, 138-уй | I32: 559713.31 | K32: Va'da berdi | bugun
A33: БУХОРО ВИЛОЯТИ | C33: Обещал | D33: Кр-99062840-2 | E33: DAVRONOV SOBIR KAMOLOVICH | F33: 998934608944 UKASI, 998936850790 AYOLI, 998945177590 O’ZI 2 NOMERI, 998935690790 uzi new SMS, | G33: G’IJDUVON TUMANI | H33: 8 | I33: 477080.45 | K33: Va'da berdi | bu navoiy viloyati
A34: ЖИЗЗАХ ВИЛОЯТИ | C34: Обещал | D34: Кр-99047637-1 | E34: AZIMOV ASADBEK OTABEK O’G’LI | F34: +998905382222 SMS NOMER, 998971120007 SMS O’ZI, 998991937773 begonA EKAN, | G34: JIZZAX VILOYATI JIZZAX SHAHRI TURON MFY SAYILJOYI KUCHASI 21-UY | H34: 71 | I34: 19927076 | K34: Va'da berdi | ertaga yopadi
A35: ЖИЗЗАХ ВИЛОЯТИ | C35: Обещал | D35: Кр-99060448-1 | E35: MAMIROVA ZEBO ZOIROVNA | F35: 998779762227 SMS OZI, 998938244230 SMS AYOLI, 998906432211 SMS UKASI, | G35: JIZZAX VILOYATI SHAROF RASHIDOV TUMANI YAXTANLIK MFY GUZAL KOCHASI 52-UY | H35: 11 | I35: 11697427 | K35: Va'da berdi | wu hafta tolaydi
A36: ЖИЗЗАХ ВИЛОЯТИ | C36: Обещал | D36: Кр-99027165-3 | E36: DJABBAROVA PULATOY SAYFIDDINNOVNA | F36: 91-941-83-83 SMS UZI , 93-393-79-09 SMS UZI 2, 94-977-84-58 SMS QAYNONASI , 93-449-77-15 SMS OGLI, 99-079-20-10 SMS UZI new, | G36: JIZZAX VILOYATI JIZZAX TUMANI QANGLI MFY CHAVANDOZLAR KUCHASI 13-UY | H36: 11 | I36: 8369851.8 | K36: Va'da berdi | kecgaca tolaydi
A37: ЖИЗЗАХ ВИЛОЯТИ | C37: Обещал | D37: Кр-99056937-2 | E37: RASHIDOVA NASIBA YAKUBOVNA | F37: 998889541771 SMS OZI, 998843817712 SMS OZI2, 998974390219 SMS KELINI, | G37: JIZZAX VILOYATI JIZZAX SHAHAR MIRZO ULUG'BEK MAHALLASI 2-UY 10-XONADON | H37: 11 | I37: 8235139.5 | K37: Va'da berdi | bugun tulaydi
A38: ЖИЗЗАХ ВИЛОЯТИ | C38: Обещал | D38: Кр-99028729-1 | E38: AMANOV BUNYOD MUMIN O’G’LI | F38: 998991791177 SMS OZI, 998902642879 SMS OPASI, 998509979579 SMS TOLOVCHISI, 998996790117 SMS AYOLI, 998881591177 AYOLI, 998944449556 ONASI, | G38: МУЗБУЛОК МФЙ, МУЗБУЛОК МФЙ, ЛОЙИХАДАГИ, uy:Р.С | H38: 4 | I38: 6850779.4 | K38: Va'da berdi | kecgaca tolaydi
A39: ЖИЗЗАХ ВИЛОЯТИ | C39: Обещал | D39: Кр-99062344-1 | E39: ALIMOV BAXROM YETMISHOVICH | F39: 998959098681 O`ZI, 998959108681 AYOLI, 998956261810 QIZI, | G39: JIZZAX VILOYATI ZARBDOR TUMANI RAVOT MFY PILLAKOR KUCHASI 1-UYI | H39: 8 | I39: 6616631.7 | K39: Va'da berdi | 2kunda tolimn filyaldagilar blan gaplawdm dedi
A40: ЖИЗЗАХ ВИЛОЯТИ | C40: Обещал | D40: Кр-99028038-1 | E40: XAZRATKULOVA RAYXON TURSUNBAYEVNA | F40: 998772725500 SMS OZI, 998951307770 SMS UKASI, 998904928594 SMS ZOLOGATEL, | G40: JIZZAX VILOYATI JIZZAX SHAHRI OBOD MFY XALQLAR DUSTLIGI KUCHASI 101-A UY 23-XONADON | H40: 6 | I40: 5897133.6 | K40: Va'da berdi | ukasi temur bilan gaplawganman dedi
A41: ЖИЗЗАХ ВИЛОЯТИ | C41: Обещал | D41: Кр-99021925-1 | E41: ISMOILOVA NARGIZA ABDUSALIYEVNA | F41: 998938567000 SMS O’ZI, 998501040408 SMS ERI, 998943437777 SMS ERI , 998905160057 SMS ERINI UKASI, 998931070408 tolovchi eri , 998971299092 sms tulovchi, 998508043200 FARUX TULOVCHISI, | G41: JIZZAX VILOYATI SHAROF RASHIDOV TUMANI QANG'LI QFY ARISHLI MAHALLASI ZIYOKOR KUCHASI 4-UY | H41: 1 | I41: 5112052.5 | K41: Va'da berdi | ertaga tulaydi
A42: ЖИЗЗАХ ВИЛОЯТИ | C42: Обещал | D42: Кр-99042115-1 | E42: MIRZAYEV OYBEK SUNATILLAYEVICH | F42: +998902659695 SMS, 998915909006 SMS, 998974559695 SMS, | G42: JIZZAX VILOYATI SH.RASHIDOV TUMANI TOKCHILIK MFY ZARGARLIK KUCHASI 2-UY | H42: 8 | I42: 4443964.3 | K42: Va'da berdi | bugun kecgaca yopadi
A43: ЖИЗЗАХ ВИЛОЯТИ | C43: Обещал | D43: Кр-99063504-1 | E43: MIRZAYEVA LOBARXON ERGASHEVNA | F43: 998933556974 UZI, 998934026974 ERI, 998958832266 TO’LOVCHI, | G43: ТОШКЕСГАН КФЙ, ЛОЙИХАДАГИ КЎЧА, uy:РАКАМСИЗ | H43: 8 | I43: 4415942.1 | K43: Va'da berdi | ertaga tolaydi
A44: ЖИЗЗАХ ВИЛОЯТИ | C44: Обещал | D44: Кр-99062963-2 | E44: RAJABOV BAXODIR BOZARBOYEVICH | F44: 998941996644 AYOLI, | G44: Саройлик МФЙ, Эркинлик кучаси, 45-уй | H44: 8 | I44: 4084124.4 | K44: Va'da berdi | erta abetgaca tolaydi
... A69: ЖИЗЗАХ ВИЛОЯТИ | C69: Обещал | D69: Кр-99033516-1 | E69: MIRZAMAXMUDOV ODILJON ALLAYOR O’G’LI | F69: 998997449700 SMS O’ZI, 998912084455 SMS O’ZI, 998338382297 SMS DO’STI, 998991332871 SMS ONASI, 998950702444 SMS AKASI, 998336669700 SMS OZI YANGI, 998932947066 SMS ABDUNABI ORTOGI, | G69: JIZZAX VILOYATI BAXMAL TUMANI UDAMALI QISHLOG’I 63-UY | H69: 1 | I69: 1079691.8 | K69: Va'da berdi | ertaga abetgaca tolaydi
A70: ЖИЗЗАХ ВИЛОЯТИ | C70: Обещал | D70: Кр-99045121-1 | E70: ISLAMOVA GO’ZAL ZOIR QIZI | F70: 998774512156 SMS, 998950414100 SMS, 998958824000 SMS, | G70: ОСМОНСОЙ ҚФЙ, ОСМОНСОЙ ҚФЙ, УРТАКИШЛОК КИШЛОГИ, uy:РАКАМСИЗ | I70: 452412.95 | K70: Va'da berdi | bugun kecgaca yopadi
A71: ЖИЗЗАХ ВИЛОЯТИ | C71: Обещал | D71: Кр-99034148-3 | E71: SAYFUTDINOVA GAVXAR SHUXRATOVNA | F71: 998903111016 SMS OZI, 998976480208 SMS ERI TOLOVCHI, 998912093311 SMS HAMKASBI, 998712267815 SMS UY, | G71: JIZZAX VILOYATI SH.RASHIDOV TUMANI ZIYOKOR QFY M.ESHONQULOV KUCHASI 125-UY | H71: 8 | I71: 397223.7 | K71: Va'da berdi | bugun tulaydi
A72: ЖИЗЗАХ ВИЛОЯТИ | C72: Обещал | D72: Кр-99025940-2 | E72: XAYRULLAYEV MUXAMMAD FAYZULLAYEVICH | F72: 97-129-10-83 SMS UZI, 99-566-22-10 SMS UZI 2, 98-561-10-12 SMS TULOVCHI, 998995610220 SMS O’ZI SHUNGA QILINSIN, | G72: КУЛАМА ҚФЙ, МУЛКАНЛИК МФЙ, ЛОЙИХАДАГИ КЎЧА, uy:60 | I72: 285394.68 | K72: Va'da berdi | 7gaca yopadi
A73: КАШКАДАРЁ ВИЛОЯТИ | B73: SUPER BRANCH | C73: Обещал | D73: Кр-99036435-3 | E73: JO’RAQULOV MANSUR QULMUROT O’G’LI | F73: 998997330311 SMS O’ZI, 998333400311 SMS AYOLI, 998942976783 SMS O’ZI 2, 998881365522 SMS UKASI , | G73: ЧИРОКЧИ МФЙ, ЧИРОКЧИ, uy:Р/С | H73: 11 | I73: 17370593 | K73: Va'da berdi | 20 da to'lov qiladi
A74: КАШКАДАРЁ ВИЛОЯТИ | B74: SUPER BRANCH | C74: Обещал | D74: Кр-99060317-1 | E74: NAFASOV ASADBEK VALIJON O’G’LI | F74: 998973852277 SMS OZI, 998886191100 SMS AYOLI, 998770994440 SMS DADASI, 998886195000 SMS ONASI, | G74: QASHQADARYO VILOYATI YAKKABOG’ TUMANI ISTIQLOL MFY OLAQARG’A QISHLOG’I | H74: 11 | I74: 11559193 | K74: Va'da berdi | payshanba kuni
A75: КАШКАДАРЁ ВИЛОЯТИ | B75: SUPER BRANCH | C75: Обещал | D75: Кр-99059908-1 | E75: MURODOV BEGZOD ZOIDOVICH | F75: 998500721265 SMS OZI, 998509098588 SMS ONASI (BEGONA), 998976194411 SMS OTASI, 998977088588 SMS ASKASI, 998509098525 SMS UZI NEW, | G75: QASHQADARYO VILOYATI KITOB TUMANI CHARMGAR MFY SAYILGOH KO’CHASI 3-UY | H75: 11 | I75: 7888733.5 | K75: Va'da berdi | bugun
A76: КАШКАДАРЁ ВИЛОЯТИ | B76: SUPER BRANCH | C76: Обещал | D76: Кр-99034170-3 | E76: YUSUPOV OBID XOMETOVICH | F76: 998883831111 SMS O’ZI, 998973871111 SMS O’G’LI, 998973801991 SMS UKASI, 998912621111 SMS AKASI, | G76: QASHQADARYO VILOYATI SHAXRISABZ TUMANI XONTEPA MFY SHUKRONA 32 UY | H76: 8 | I76: 5852440.9 | K76: Va'da berdi | oylik tushadi xozir to'liman deb
A77: КАШКАДАРЁ ВИЛОЯТИ | B77: SUPER BRANCH | C77: Обещал | D77: Кр-99062658-1 | E77: AVAZOV SHOXRUX ASADULLOYEVICH | F77: 998918871711 OZI QAYNI UKASI, 998945240302 ONASI, 998507181711 UKASI, 998942911001 O'ZI TO'LOVCHI, | G77: QASHQADARYO VILOYATI KASBI TUMANI XO’JAKASBI MFY 3-G’ALLAKORLAR KO’CHASI 2-UY | H77: 8 | I77: 5841569.5 | K77: Va'da berdi | payshanba kuni
A78: КАШКАДАРЁ ВИЛОЯТИ | B78: SUPER BRANCH | C78: Обещал | D78: Кр-99063528-1 | E78: SHODMONOV SHERZOD O’KTAM O’G’LI | F78: 998970660077 sms uzi, 998973890077 sms uzi2, 998981001601 sms uzi3, | G78: ЗАРБДОР МФЙ, РОВОТ, uy:Р/С, | H78: 8 | I78: 4733988.8 | K78: Va'da berdi | 15:00 tolov ammalga oshiriladi
A79: КАШКАДАРЁ ВИЛОЯТИ | B79: SUPER BRANCH | C79: Обещал | D79: Кр-99062537-1 | E79: RAXMONOV AZIZJON AZIMJON O’G’LI | F79: 998881270813 ozi, 998773201114 ayoli, 998993820813 dadasi, | G79: QASHQADARYO VILOYATI KASBI TUMANI TALLIYULG’UN MFY TALLIYULG’UN QISHLOG’I | H79: 8 | I79: 3449858.2 | K79: Va'da berdi | ertaga to'lom ammalga oshadi
A80: КАШКАДАРЁ ВИЛОЯТИ | B80: SUPER BRANCH | C80: Обещал | D80: Кр-99054733-1 | E80: OCHILOV DUSTMUROD FAXRIDINOVICH | F80: 998913976071 SMSOZ, 998999442521 SMS AYOLI, 998996848798 SMS DADASI, 998916333232 SMS TO'LOVCHI , | G80: QASHQADARYO VILOYATI KOSON TUMANI MASHAL MFY FUSUNKOR KUCHASI 1-1 UY 5-XONADON | H80: 8 | I80: 3324027.4 | K80: Va'da berdi | ERTAGA FILYALGA KELADI
A81: КАШКАДАРЁ ВИЛОЯТИ | B81: SUPER BRANCH | C81: Обещал | D81: Кр-99022781-4 | E81: SHARAPOV ABDULLO ZIYODULLO O’G’LI | F81: 90-505-02-07 SMS UZI, 91-553-02-07 SMS UZI 2, 91-522-09-87 SMS AKASI, 90-877-79-67 SMS AYOLI, 90-114-03-26 SMS ortog'i shunga tel qlila , 998978080207 UZI NEWW, | G81: QASHQADARYO VILOYATI KITOB TUMANI KATLOS MFY TUL QISHLOG’I 36-UY | H81: 8 | I81: 2438718.1 | K81: Va'da berdi | bugun to'liman dedi
A82: КАШКАДАРЁ ВИЛОЯТИ | B82: SUPER BRANCH | C82: Обещал | D82: Кр-99033686-1 | E82: CHORIYEVA SHOHNOZA ABDURASHIDOVNA | F82: 998957777748 узи, 998932222234 аели, 998991289300 дадаси, 998990405493 онаси, | G82: QASHQADARYO VILOYATI DEHQONOBOD TUMANI QURG’ONTOSH MFY GALA KUCHASI 100-UY | H82: 8 | I82: 2202881.2 | K82: Va'da berdi | ertaga akasi keladi yopvorad navoiyda kamndrofkada akasi
A83: КАШКАДАРЁ ВИЛОЯТИ | B83: SUPER BRANCH | C83: Обещал | D83: Кр-99035132-1 | E83: OCHILOV OYBEK ISROIL O’G’LI | F83: 998995008899 SMS O’ZI , 998507575193 SMS UKASI , 998500011995 SMS OILASI , 998507575293 SMS UKASI 2, 998972230068 SMS DADASI, | G83: QASHQADARYO VILOYATI KOSON TUMANI USHOKTEPA MFY USHOKTEPA KUCHASI 21 UY | H83: 6 | I83: 2196036.8 | K83: Va'da berdi | payshanba kuni to'liman dedi
A84: КАШКАДАРЁ ВИЛОЯТИ | B84: SUPER BRANCH | C84: Обещал | D84: Кр-99031215-3 | E84: SULTONOV XASAN ORIF O’G’LI | F84: 88-360-05-05 SMS O’ZI, 99-587-55-51 SMS UY, 91-216-71-34 SMS ONASI, 90-899-71-68 SMS DADASI, | G84: QASHQADARYO VILOYATI QAMASHI TUMANI BERDOLI MFY BERDOLI KO’CHASI 198-UY | H84: 8 | I84: 1801308.8 | K84: Va'da berdi | qisman to'lov qildi
... A97: КАШКАДАРЁ ВИЛОЯТИ | B97: Қарши филиали | C97: Обещал | D97: Кр-99041346-1 | E97: RAVSHANOV FARHOD CHORIYOROVICH | F97: 998952510007 sms ozi, 998953156767 sms, 998974348787 sms, | G97: Кашкадарьинская область, Камашинский район, Туқбой МСГ, ул. Сарой, дом 54 | H97: 8 | I97: 1340493.4 | K97: Va'da berdi | 2 kun ichda tolov qiladi
A98: КОРАКАЛПОГИСТОН РЕСПУБЛИКАСИ | C98: Обещал | D98: Кр-99062886-3 | E98: AYTMURATOV BAXIT DJANABAYEVICH | F98: +998933067303 OZI, 998932023938 OGLI, 998996823509 OYALI, 998939677376 OZII NEWWW, | G98: QORAQALPOGISTON RES SHUMBOY TUMANI ORJAP MFY AQ ALTIN KUSHASI 8 UY | H98: 71 | I98: 13465118 | K98: ALMATIDA AYOLI TO;LAYDI OY OXIRI | 1650 | Va'da berdi
A99: КОРАКАЛПОГИСТОН РЕСПУБЛИКАСИ | C99: Обещал | D99: Кр-99056260-1 | E99: ABDIKALIKOV DASTAN BOSTANOVICH | F99: 998887079454 SMS OZI, 998970010096 SMS AKASI, 998888018881 SMS UKASI, | G99: QARAQALPOGISTON RES NUKUS SHAHAR SHIMBAY SHAYXANA MFY KOKLEMZAR KUSHASI 113 UY 38 KVARTIRA | H99: 11 | I99: 9679134 | K99: OYLIKDAN QACHONLIGINI AYTMADI | 1401 | Va'da berdi
A100: КОРАКАЛПОГИСТОН РЕСПУБЛИКАСИ | C100: Обещал | D100: Кр-99032661-1 | E100: TLEUMBETOVA DILARAM DUYSENBAYEVNA | F100: 998937093732 SMS TO’LOVCHI, 998905951051 SMS TOLOVCHI 2, 998337402818 SMS AKASI, 998932095775 SMS AKASI 2, 998919282212 SMS Ikrom akasi tolovchi , 998919288148 SMS akasi , 998919382212 SMS ozi new , 998933645639 SMS MAHALLA SHUNGA CHIQILSIN , 998921950595 ERI TULOVCHI, | G100: NUKUS SHAHAR MATEN SIYTNIYZOZ KUSHASI 152A UY | H100: 63 | I100: 8278329.2 | K100: BUGUNGA TO'LOV QILAMAN DEDILA ERINI AVANSIDAN 7 MILLION | 408 | Uyiga borildi - to'ladi
A101: КОРАКАЛПОГИСТОН РЕСПУБЛИКАСИ | C101: Обещал | D101: Кр-99061501-1 | E101: JOLDIBAEV NARTAY TABINBAEVICH | F101: 998991188928 узи, 998995849029 аели, 998932002889 кизи, 998997028990 угли, | G101: QORAQALPOGISTON RES KEGIYLI TUMANI JANA BAZAR MFY BAXITLI EL KUSHASI 15 UY | H101: 8 | I101: 7372185.3 | K101: BUGUN ERTAGA VRACH QILISH SHARTMAS | 1546 | Va'da berdi
A102: КОРАКАЛПОГИСТОН РЕСПУБЛИКАСИ | C102: Обещал | D102: Кр-99046605-1 | E102: BALTAYEV SADULLA MAKSUDOVICH | F102: 998907147737 SMS UZI, 998947020528 SMS UGLI, 998945640304 SMS QIZI, 998997147737 o'zi newww, | G102: QORAQALPOGISTON RES XOJAYLI TUMANI TUTZAR MFY XALKABAD KUSHASI 8 UY | H102: 11 | I102: 6949519.2 | K102: G'ISHT ZAVODDA ISHLAYDI OYLIGIMI OLISHIM BN TASHAYMAN DEDILA AJDANIYA | 1244 | Va'da berdi
A103: КОРАКАЛПОГИСТОН РЕСПУБЛИКАСИ | C103: Обещал | D103: Кр-99026306-2 | E103: ABDURAXMANOV SANJAR SADULLAYEVICH | F103: 99-775-55-05 SMS O'ZI, 91-436-90-03 SMS UKASI begona, 99-348-90-03 SMS tulovchi , 998990247010 SMS ukasi tulovchi, | G103: QORAQALPOG’ISTON RESPUBLIKASI BERUNIY TUMANI BUNYODKOR MAXALLASI N.KUBRO KUCHASI 10 UY | H103: 6 | I103: 5707198 | K103: BU 3KUNDA TASHAB BERAMAN OYLIKDAN DDILA QAYERDA ISHLASHLARINI AYTMADILA | 178 | Va'da berdi
A104: КОРАКАЛПОГИСТОН РЕСПУБЛИКАСИ | C104: Обещал | D104: Кр-99057450-1 | E104: BEKIMOV GULIMBAY YERKABAYEVICH | F104: 998996622374 SMS O'ZI, 998912711974 SMS O'ZI 2, 998977965585 SMS AYOLI, | G104: BERUNIY TUMANI | H104: 8 | I104: 5236088.2 | K104: 20-25 OYLIKDAN O'G'LI TO'LAYDI | 1451 | Va'da berdi
A105: КОРАКАЛПОГИСТОН РЕСПУБЛИКАСИ | C105: Обещал | D105: Кр-99044140-3 | E105: BAEKEEV BERIK MUXAMBETKARIMOVICH | F105: 998884871988 OZI, 998970008892 OYALI, 998978889288 UKASI, | G105: ХАКИМ-АТА МФЙ, МСГ ХАКИМ-АТА, С,АЛЛАНИЯЗОВ, uy:Р/З | H105: 8 | I105: 5171582.4 | K105: 28DA BANESADA ISHLEDI | 1199 | Va'da berdi
A106: КОРАКАЛПОГИСТОН РЕСПУБЛИКАСИ | C106: Обещал | D106: Кр-99063426-1 | E106: YULDASHEVA ZULAYXA TURSUNBOYEVNA | F106: 998500178083 OZI, 998995680099 KELINI, 998997450099 OGLI, | G106: QORAQALPOGISTON RES AMUDARYO TUMANI SHAYKOL OFY 7- SHAQSHA 3 UY | H106: 8 | I106: 4755571.6 | K106: 20 KUNIGA UKASI ROSSIYADA ISHLEDI OWA YERDAN TASHAB BERADI | 1769 | Va'da berdi
A107: КОРАКАЛПОГИСТОН РЕСПУБЛИКАСИ | C107: Обещал | D107: Кр-99042828-1 | E107: KALANDAROV MANSUR MAXMUDOVICH | F107: +998912558828 SMS UZI, 998551028828 SMS UYI, 998992628828 SMS UKASI, | G107: КОРАКАЛПОГИСТОН РЕСПУБЛИКАСИ БЕРУНИЙ ТУМАНИ ШИМАМ ҚФЙ, КУК-КУЗ АХОЛИ ПУНКТИ, uy:Р/С | H107: 8 | I107: 4690275.9 | K107: 18KUNI ONASI TO'LOV QILIB BERADILA | 1179 | Va'da berdi
A108: КОРАКАЛПОГИСТОН РЕСПУБЛИКАСИ | C108: Обещал | D108: Кр-99019952-6 | E108: URAZIMBETOVA SHOHISTA GULIMBAYEVNA | F108: 99-186-59-19 SMS UZI, 998995033939 SMS ERI, 998940910907 SMS UZI, 998771152010 OGLI, | G108: QORAQALPOG’ISTON RESPUBLIKASI BERUNIY TUMANI BERUNIY OFY GULZOR KO’CHA | H108: 13 | I108: 4455521.9 | K108: MOSHINASINI SOTIB TO'LOV QILIB BERAMAN DEYABDILA | 97 | Va'da berdi
A109: КОРАКАЛПОГИСТОН РЕСПУБЛИКАСИ | C109: Обещал | D109: Кр-99041208-1 | E109: ZARIEVA ZUXIRA NASIROVNA | F109: 998905926568 OZI SMS, 998913755131 KELINI, 998991559339 OGLI, | G109: НАВРУЗ МФЙ, НАУРЫЗ МФЙ, МИЗДАКХАН КЎЧАСИ, uy:56 | H109: 8 | I109: 4176956.7 | K109: 20KUNI O'G'LI OYLIGIDAN | 1072 | Va'da berdi
... A133: НАМАНГАН ВИЛОЯТИ | C133: Обещал | D133: Кр-99035142-1 | E133: USMONALIYEV ABRORJON BAHROMJON O’G’LI | F133: 998950871314 SMS O’ZI , 998990811515 SMS AKASI , 998770037797 SMS AKASI begona, 998999040673 SMS ONASI , | G133: NAMANGAN VILOYATI YANGIQO’RG’ON TUMANI QANDIYON MFY YANGI QANDIYON KO’CHA 87 UY | H133: 6 | I133: 1396253.5 | K133: Va'da berdi | yopildi
A134: НАМАНГАН ВИЛОЯТИ | C134: Обещал | D134: Кр-99062024-1 | E134: DADABAYEVA RA’NO INAMJONOVNA | F134: 998935721472 SMS OZI, 998944938585 SMS ERI, 998934721472 SMS DADSI, 998974938585 SMS ERI, | G134: NAMANGAN VILOYATI CHUST TUMANI OLMOS MFY MUSTAQILLIK KO’CHASI 9-UY | I134: 1284540.2 | K134: Va'da berdi | yopildi
A135: НАМАНГАН ВИЛОЯТИ | C135: Обещал | D135: Кр-99032402-1 | E135: XUJAYEV GULOMJON ATAVALIYEVICH | F135: 998936750549 SMS O’ZI, 998935683707 SMS O’G’LI, 998935930302 SMS O’G’LI 2 begona, 998938813707 SMS KELINI, | G135: NAMANGAN VILOYATI UCHQO’RG’ON TUMANI YANGIYER MFY YANGIYER KO’CHASI 68 UY | H135: 8 | I135: 1040796.6 | K135: Va'da berdi | yopildi
A136: НАМАНГАН ВИЛОЯТИ | C136: Обещал | D136: Кр-99010690-2 | E136: ANVAROV XUSANBOY MALIKJON O’G’LI | F136: 93-423-99-69 SMS OZI, 998993940008 SMS DADASI, 94-905-55-69 SMS OPASI, 93-408-15-04 SMS ONASI, 998937196777 UZI NEWW, | G136: NAMANGAN VILOYATI UYCHI TUMANI YORQO’RGON MFY NURLIK KOCHASI 100-UY | H136: 8 | I136: 314876.99 | K136: Va'da berdi | yopildi
A137: НАМАНГАН ВИЛОЯТИ | C137: Обещал | D137: Кр-99031370-1 | E137: TOJIBOYEV XURSHIDBEK XURSANOVICH | F137: 94-509-59-83 SMS O’ZI watsab ishlidi, 998943460500 SMS BEGONA, 50-551-59-83 SMS O’ZI 2, 99-514-22-29 SMS AKASI, 998945954433 sms ozin new nomeri, 998943021414 tolovchi ukasi , | G137: NAMANGAN VILOYATI UCHQO’RG’ON TUMANI BAXT MFY HUVAYDO KO’CHASI 14 UY | H137: 13 | I137: 250875.97 | K137: Va'da berdi | yopildi cartaga tashadi
A138: САМАРКАНД ВИЛОЯТИ | C138: Обещал | D138: Кр-99024819-8 | E138: GULYAMOV IMRON BAXODIROVICH | F138: 90-503-44-22 SMS AKASI SHU HAL QILADI, 91-520-43-44 SMS UZI, 66-234-44-63 SMS UYI, 97-927-25-11 SMS UKASI, | G138: SAMARQAND VILOYATI SAMARQAND SHAHRI BOG’I SHIFO MFY MASKOVSKIY KUCHASI 12-UY | H138: 8 | I138: 10679970 | K138: Va'da berdi
A139: САМАРКАНД ВИЛОЯТИ | C139: Обещал | D139: Кр-99064082-1 | E139: XODJIQULOVA MAVLYUDA XXX | F139: 998871355366 SMS UYI, 998882338080 SMS OZI, 998933535366 SMS ERI, 998940039953 SMS O’G’LI, | G139: SAMARQAND VILOYATI SAMARQAND SHAHAR BOG’BONLAR MFY SIPITAMINSHOX KUCHASI 266-UY 29-XONODON | H139: 8 | I139: 8354433 | K139: Va'da berdi | ertaga tolid
A140: САМАРКАНД ВИЛОЯТИ | C140: Обещал | D140: Кр-99057416-1 | E140: BASHMONOVA DILFUZA ALIMOVNA | F140: 998937298058 SMS ERI, 998933480095 SMS OZI, 998330870702 SMS UYI, 998930508058 SMS UZI 2, | G140: SAMARQAND VILOYATI PAYARIQ TUMANI TOMOYROT MFY SHON-SHUHRAT KO'CHASI 113-UY | H140: 11 | I140: 7678655.1 | K140: Va'da berdi
A141: САМАРКАНД ВИЛОЯТИ | C141: Обещал | D141: Кр-99063322-2 | E141: UTABAYEV JONIBEK ILXOMOVICH | F141: 998901922133 SMS OPASI, 998910394407 SMS, 998915214468 SMM UYI, 998995267774 SMS OZI, | G141: SAMARQAND VILOYATI KATTAQO’RG’ON SHAHAR YERMSCHIT MFY BUNYODKOR KUCHASI 6 A DOM 1 KORPUS 1 KVARTERA | H141: 8 | I141: 4214418 | K141: Va'da berdi | ertaga tolid
A142: САМАРКАНД ВИЛОЯТИ | C142: Обещал | D142: Кр-99019784-3 | E142: AXATOVA NARGIZA ILXOMOVNA | F142: 99-771-09-30 SMS UZI , 99-599-69-66 SMS ERI, 93-353-56-07 SMS QIZI, 99-350-56-07 SMS UYI, +998997710930 SMS OZI, | G142: SAMARQAND VILOYATI SAMARQAND SHAHRI XO’JA QISHLOQ MFY LOCHIN KO’CHASI 2 YULAK 22-UY | H142: 8 | I142: 4097262.5 | K142: Va'da berdi
A143: САМАРКАНД ВИЛОЯТИ | C143: Обещал | D143: Кр-99063884-1 | E143: ABDURASHIDOV AKOBIR VASLIDDIN O’G’LI | F143: 998777162444 SMS DOSTI, 998943414303 SMS UZI, 998993961270 SMS TOLOVCHI, | G143: ДУРБЕШ ҚФЙ, ЯНГИРАВОТ МФЙ, ДУРБЕШ ҚИШЛОҒИ, uy:Р/С | H143: 8 | I143: 4062717.3 | K143: Va'da berdi | 28-29 tolov qiladi
A144: САМАРКАНД ВИЛОЯТИ | C144: Обещал | D144: Кр-99062920-1 | E144: BOBOYEV SHERXON RUZIMURODOVICH | F144: +998992957374 SMS OZI, 998904757374 SMS OZI 2, 998956738444 SMS UKASI, | G144: SAMARQAND VILOYATI NUROBOD TUMANI OQSOY MFY | H144: 8 | I144: 3435601 | K144: Va'da berdi | 5 laga tolid
A145: САМАРКАНД ВИЛОЯТИ | C145: Обещал | D145: Кр-99016634-3 | E145: YAZDONOV QAHRAMON BOTIR O’G’LI | F145: 97-930-70-09 SMS UZI, 99-417-18-37 SMS ZALOGADATEL, 77-076-93-94 SMS UKASI, 99-718-02-74 SMS AYASI, +998917012747 SMS OZI, 998770345939 SMS AKASI, 998959290482 SMS OPASI tulovchi shu, | G145: SAMARQAND VILOYATI URGUT TUMANI QAYROQLI MFY QAYROQLI QISHLOG’I 444-UY | H145: 8 | I145: 3156177.3 | K145: Va'da berdi | ertaga 3 gacha tolov qiladi
A146: САМАРКАНД ВИЛОЯТИ | C146: Обещал | D146: Кр-99027786-1 | E146: TEMIROV OLIMSHER JAXONGIR O’G’LI | F146: 998947420451 SMS OZI кариндоши, 998905021015 SMS AYOLI, 998901951510 SMS O'ZI 2, 998907420451 SMS ISHXONASI, 998949977497 узи , | G146: SAMARQAND VILOYATI PASTDARG’OM TUMANI PULATCHI QFY OLMAZOR MFY XALOVAT KO’CHASI 80-UY | H146: 6 | I146: 3047606.8 | K146: Va'da berdi | ertadan kin tyolov qiladi
... A187: СУРХОНДАРЁ ВИЛОЯТИ | C187: Обещал | D187: Кр-99043043-1 | E187: BOYQULOV FIRDAVS ABDUVOXID O’G’LI | F187: 998944361003 SMS O’ZI, 998991351177 SMS UY, 998996660094 SMS AKASI, | G187: Сурхандарьинская область, Денауский район, Хазарбоғ СИУ, Чим МСГ, ул. Гулистон, дом 6 | H187: 8 | I187: 2017063.7 | K187: Va'da berdi | kyng xaftalar tolo qllad | 1186
A188: СУРХОНДАРЁ ВИЛОЯТИ | C188: Обещал | D188: Кр-99040374-1 | E188: KARSHIYEV TAJIMURAT PRIMOVICH | F188: 998993876160 SMS OZI, 998997284700 SMS OGLI, 998991496886 SMS OGLI, | G188: SURXONDARYO VILOYATI QUMQO'RG'ON TUMANI DAVLATSOY MAXALLASI USTALAR KO'CHASI 26-UY | I188: 1996808.6 | K188: Va'da berdi | 1-2 kunda borb tolo qb kelad | 973
A189: СУРХОНДАРЁ ВИЛОЯТИ | C189: Обещал | D189: Кр-99034974-1 | E189: XUSHBAQOV MANSURBEK XUDAYBERDI O’G’LI | F189: 998972427172 SMS OZI, 998500532519 SMS UY, 998884231373 SMS OILASI, 998903750890 SMS OZI, | G189: SURXONDARYO VILOYATI OLTINSOY TUMANI DUG’OBA QFY OLMAZOR MFY MARJON BULOQ KO’CHASI 59-UY | H189: 12 | I189: 1703401.1 | K189: Va'da berdi | 20 cilariga tolov qlaman dd | 537
A190: СУРХОНДАРЁ ВИЛОЯТИ | C190: Обещал | D190: Кр-99037942-1 | E190: YODGOROV XAMRO ESHONQULOVICH | F190: 998919696012 SMS OZI, 998901201798 SMS UYI, 998991828111 SMS TULOVCHI UG`LI MUHRIDDIN, 998952435111 SMS ONASI, | G190: SURXONDARYO VILOYATI SARIOSIYO TUMANI SHAXRIOBOD MFY SOADATMAN 2-UY | I190: 1674909.8 | K190: Va'da berdi | 2-3 kunda tolo qlad | 734
A191: СУРХОНДАРЁ ВИЛОЯТИ | C191: Обещал | D191: Кр-99040161-1 | E191: JOVLIYEV ZOXID XURSANQUL O’G’LI | F191: 998951578486 SMS OZI, 998942078486 SMS AYOLI, 998942000757 SMS ONASI, | G191: StJttХoNDARYO vlLoYAT IvlUZRABoT TUMAN oRlYAT MF'Y | H191: 8 | I191: 1599135.1 | K191: Va'da berdi | bugundan qomedi kecasi bosayam tawed | 947
A192: СУРХОНДАРЁ ВИЛОЯТИ | C192: Обещал | D192: Кр-99035581-3 | E192: SAYDALIYEV BAXTINUR BAXRIDDIN O’G’LI | F192: 998919090044 SMS OZI, 998945824941 SMS UY, 998931229717 SMS AYOLI, 998885510044 SMS UKASI, 998880940070 SMS uzi new, 998917240044 SMS O’ZI, 998952236442 SMS AYOLI, 998917240044 NEW OZI, | G192: Сурхондарё вилояти Кизирик Тумани Работак МФЙ, Абдулла Қаххор 1 кучаси, 21...-уй | H192: 8 | I192: 1419181.6 | K192: Va'da berdi | bugun tolo qlad | 578
A193: СУРХОНДАРЁ ВИЛОЯТИ | C193: Обещал | D193: Кр-99041909-2 | E193: XURSANDOV IKROM NEMATULLO O’G’LI | F193: 998885991414 SMS O’ZI, 998887642002 SMS SHERIGI, 998972424999 SMS UY, | G193: Сурхандарьинская область, Денауский район, Тасмасой МСГ, ул. Лимонзор-2 берк, дом 6 | H193: 8 | I193: 1188955.3 | K193: Va'da berdi | bugun qisman tolo qlad erte oy indin qoganin qlad | 1142
A194: СУРХОНДАРЁ ВИЛОЯТИ | C194: Обещал | D194: Кр-99035156-1 | E194: ABDUYEV XODJAAKBAR KARIMOVICH | F194: 998952371191 SMS O’ZI nonvoylik qiladi, 998976237477 SMS UY, 998337202515 SMS SHERIGI, 998991085695 SMS ISHXONA, | G194: SURXONDARYO VILOYATI DENOV TUMANI SINA QFY FAYZAOBOD MFY NAFIS 52-UY | H194: 5 | I194: 1078690.8 | K194: Va'da berdi | bugun qisman tolo qlad qoganin 3-4 kunda mayda mayda qb yopb qoyad | 553
A195: СУРХОНДАРЁ ВИЛОЯТИ | C195: Обещал | D195: Кр-99041744-1 | E195: KARIMOVA MADINA SOTTOR QIZI | F195: 998975527101 SMS OZI, 998881927101 SMS UY, 999872010159 SMS OILASI, 998785510044 SMS UKASI, 998957737555 SMS ERI, | G195: SURXONDARYO VILOYATI DENOV TUMANI BUYUKIPAK YULI MFY I.KARIMOV 70-UY | H195: 8 | I195: 1018191.8 | K195: Va'da berdi | 2-3 kunda yopad | 1125
A196: СУРХОНДАРЁ ВИЛОЯТИ | C196: Обещал | D196: Кр-99035839-2 | E196: NAZAROV SOATMUROT BOBONAZAROVICH | F196: 998904112878 SMS tulovchi quruvchi, 998915861956 SMS OZI, 998915103380 SMS UY, 998952790593 SMS OGLI, | G196: SURXONDARYO VILOYATI DENOV TUMANI XAYRABOD QFY PAXTAKURASH MFY SURXONDARYO KO'CHASI 22-UY | H196: 8 | I196: 679595.62 | K196: Va'da berdi | soatmurot aka bn gaplawdm oglm tolid wu xaftalarda dd | 601
A197: СУРХОНДАРЁ ВИЛОЯТИ | C197: Обещал | D197: Кр-99041293-2 | E197: MUZRAPOV OTABEK SAYDAXMAT O’G’LI | F197: 998904944044 SMS O’ZI, 998915174919 SMS UKASI, 998958852122 SMS UY, | G197: ҚОРЛИҚ ҚФЙ, ҚОРЛИҚ ҚФЙ, ҚОРЛИҚ-1, uy:34 | H197: 8 | I197: 543388.92 | K197: Va'da berdi | erte uzogi indn tolo qlad | 1082
A198: СУРХОНДАРЁ ВИЛОЯТИ | C198: Обещал | D198: Кр-99041744-2 | E198: KARIMOVA MADINA SOTTOR QIZI | F198: 998975527101 SMS OZI, 998881927101 SMS UY, 999872010159 SMS OILASI, 998785510044 SMS UKASI, 998957737555 SMS ERI, | G198: SURXONDARYO VILOYATI DENOV TUMANI BUYUKIPAK YULI MFY I.KARIMOV 70-UY | H198: 8 | I198: 528418.84 | K198: Va'da berdi | bugun yopilad | 1126
A199: СУРХОНДАРЁ ВИЛОЯТИ | C199: Обещал | D199: Кр-99064054-1 | E199: TILAKOV YASHNARBEK BEGALIYEVICH | F199: 998770425002 TOG’ASI, 998954949000 O’ZI, 998957669000 AYOLI, | G199: RAYHON KO’CHASI 36-UY | H199: 8 | I199: 412804.58 | K199: Va'da berdi | 2 kunda | 1869
A200: СУРХОНДАРЁ ВИЛОЯТИ | C200: Обещал | D200: Кр-99035122-4 | E200: METTIYEVA MAYRAMXON QURBONOVNA | F200: 998507288828 SMS O’ZI, 998881929086 SMS UY, 998919101784 SMS ERI, 998887289693 SMS QIZI, | G200: SURXONDARYO VILOYATI SHORCHI TUMANI GO’ZALLIK MFY BOSTON KO’CHASI 17-UY | H200: 8 | I200: 214812.8 | K200: Va'da berdi | yopildi | 548
A201: ТОШКЕНТ ШАХРИ | C201: Обещал | D201: Кр-99063240-1 | E201: BOZOROV FAZLIDDIN JUMAYEVICH | F201: 998777923003 SMS DADASI (ISHXONASI), 998908073003 SMS ISHXONMASI, 998936998569 SMS ONASI, 998999162111 SMS OZI, | G201: TOSHKENT SHAHAR YANGIHAYOT TUMANI BINOKOR MFY SANGZOR KOCHASI 24-UY 19-XONADON | H201: 13 | I201: 11051842 | K201: Va'da berdi | 25chigacha
A202: ТОШКЕНТ ШАХРИ | C202: Обещал | D202: Кр-99062773-2 | E202: SADIKOV BAXROM FAXRIDDINOVICH | F202: 998909379991 OZI, 998774447753 AYOLI, 998956856668 ONASI, | G202: TOSHKENT SHAHAR SIRG’ALI TUMANI ESKI JALOYIR MFY ILG’OR KO’CHASI 5-TOR,22-UY | H202: 11 | I202: 9274968.3 | K202: Va'da berdi | 1-2kunda to'lidi
... A247: ФАРГОНА ВИЛОЯТИ | C247: Обещал | D247: Кр-99036269-2 | E247: TASHPULATOV AVAZJON AKRAMOVICH | F247: 998911256909 SMS OZI, 998916797220 SMS OTASI, 998901792328 SMS AYOLI TOLOVCHI , 998911296260 SMS ONASI, +998911256909 Primary phone from road24, | G247: FARG’ONA VILOYATI TOSHLOQ TUMANI FURKAT MFY HUNARMANTLAR KO’CHASI 26-XONADON | H247: 8 | I247: 2152613.9 | K247: Va'da berdi | ERI RASIYADA PUL JONATISHI KERAK EKAN BUGUN ISHINI BOLIB BUGUN YOKI ERTAGA PUL CHIQARADI EKAN CHIQARISHI BILAN TOLAB QOYAMAN DEDI | 837717.91
A248: ФАРГОНА ВИЛОЯТИ | C248: Обещал | D248: Кр-99036269-1 | E248: TASHPULATOV AVAZJON AKRAMOVICH | F248: 998911256909 SMS OZI, 998916797220 SMS OTASI, 998901792328 SMS AYOLI TOLOVCHI , 998911296260 SMS ONASI, +998911256909 Primary phone from road24, | G248: FARG’ONA VILOYATI TOSHLOQ TUMANI FURKAT MFY HUNARMANTLAR KO’CHASI 26-XONADON | I248: 2140681.1 | K248: Va'da berdi | ERI RASIYADA PUL JONATISHI KERAK EKAN BUGUN ISHINI BOLIB BUGUN YOKI ERTAGA PUL CHIQARADI EKAN CHIQARISHI BILAN TOLAB QOYAMAN DEDI | 0
A249: ФАРГОНА ВИЛОЯТИ | C249: Обещал | D249: Кр-99034447-1 | E249: NO’MONOV NIZOMBEK NE’MATULLO O’G’LI | F249: 998916665626 SMS O’ZI, 998772805626 SMS AKASI, 998916765958 SMS UKASI, 998939763939 SMS SHERIGI, 998999855218 SMS new ozi , 998911274848 SMS OZI YENGI NOMERI , | G249: FARG’ONA VILOYATI MARG’ILON SHAXAR NAVRUZ MFY ILXOM KO’CHASI 14-XONADON | H249: 1 | I249: 2033683.4 | K249: Va'da berdi | HARAMI USBET QILSAM BUGUN BOMASA ERTAGA TOLAB QOYAMAN DEYABDI | 1212000
A250: ФАРГОНА ВИЛОЯТИ | C250: Обещал | D250: Кр-99049204-2 | E250: ISROILOVA NABIRAXON YUSUPJON QIZI | F250: 998913970794 uzi, 998904068676 opasi, 998332042003 eri, 998903630794 ozi new, | G250: FARG’ONA VILOYATI QUVA TUMANI DEXQONOBOD MFY SHO’RMAXALLA KO’CHASI 268-UY | H250: 8 | I250: 1992991.2 | K250: Va'da berdi | 20CHIGA PULIM KELADI EKAN KELISHI BILAN TOLAB QOYAMAN DEDI | 757575.56
A251: ФАРГОНА ВИЛОЯТИ | C251: Обещал | D251: Кр-99042708-1 | E251: ABDIRAXMANOV ABDIRAXIM XO’JAMOVICH | F251: +998911401560 SMS O’ZI, 998903615861 O’G’LI, 998930451331 KELINI, 998949710065 AYOLI, | G251: FARG’ONA VILOYATI BUVAYDA TUMANI OQQO’RG’N MFY ARCHAZOR KO’CHASI 7-UY | H251: 8 | I251: 1869282.3 | K251: Va'da berdi | ERTAGA EBETLARGA QAYTA ALOQA TOLOV QILADI | 786437.67
A252: ФАРГОНА ВИЛОЯТИ | C252: Обещал | D252: Кр-99063815-1 | E252: O’RINXO’JAYEV SHERXON URAYIMJON O’G’LI | G252: BERUNIY MFY | H252: 8 | I252: 1861628.4 | K252: Va'da berdi | AYOLI BILAN GAPLASHILDI OZLARI QIRGIZISTONDA EKAN TELAGRAMDAN CHIQILADI | 756083.61
A253: ФАРГОНА ВИЛОЯТИ | C253: Обещал | D253: Кр-99032078-3 | E253: ABDULLAJONOV XOJIAKBAR OBIDJON O’G’LI | F253: 998949997060 SMS O’ZI axrana bolib ishlid , 998947097060 SMS AYOLI, 998948129222 SMS AKASI, 998959709293 SMS KELINI, 998507138440 OZI NEW , | G253: FARG’ONA VILOYATI FARG’ONA TUMANI MINDONOBOD MFY MADADKOR KO’CHASI 13-XONADON | H253: 8 | I253: 1797817.8 | K253: Va'da berdi | KUNI 170MIGA ISHLAYDI HARKUNI TOPKANINI TOLAYDI KILIKDAN | 1296416.31
A254: ФАРГОНА ВИЛОЯТИ | C254: Обещал | D254: Кр-99035151-1 | E254: NORMATOV ASILBEK SHUXRAT O’G’LI | F254: 998507746919 SMS O’ZI, 998941682299 SMS ZALOGADETOL, 998991074040 SMS SHERIGI, 998972442020 SMS UKASI, | G254: FARG’ONA VILOYATI QUVA TUMANI O’ROQVOSHI MFY XAMDUSTLIK KO’CHASI 59-XONADON | H254: 6 | I254: 1665613.1 | K254: Va'da berdi | CHORSHANBA KUNI KECHGACHA POLI YOPADI EKAN PULI KELMAY QOLIBDI | 1510770.58
...

Sheet Оплатили
A1: ← Вернуться в отчёт
A2: Область | B2: Филиал | C2: Группа | D2: Код клиента | E2: Клиент | F2: Номер телефона | G2: Адрес | H2: Кол-во просроченных дней | I2: Итого просрочка | J2: Оплата | K2: Izoh
A3: БУХОРО ВИЛОЯТИ | C3: Дозвон | D3: Кр-99063147-1 | E3: YUSUPOV TALGAT RAVILEVICH | F3: +998934589950 SMS O’ZI, 998504052350 SMS AYOLI, 998936202480 SMS QIZI, 998936560151 SMS ONASI, | G3: 5-СОН ГАФУР ГУЛОМ НОМЛИ МФЙ, ИФТИХОР КУЧАСИ, 32-UY | H3: 8 | I3: 8437576.4 | J3: 8437576.4 | K3: To'ladi
A4: БУХОРО ВИЛОЯТИ | C4: Дозвон | D4: Кр-99038186-1 | E4: SA’DULLAYEVA ROXILLA SADULLO QIZI | F4: 998933094290 SMS OZI, 998993803457 SMS QUDASI, 998990943457 SMS SINGLISI, | G4: BUXORO VILOYATI BUXORO TUMANI, QALQO QISHLOG'I, 4-MUYILISH, 8-UY | H4: 1 | I4: 7600197.6 | J4: 7600197.6 | K4: To'ladi
A5: БУХОРО ВИЛОЯТИ | C5: Дозвон | D5: Кр-99040789-2 | E5: DJURAYEVA SHAXINABONU ERKIN QIZI | F5: +998882100226 SMS O’ZI, 998772011384 SMS ONASI, 998991035070 SMS OTASI, 998997982977 SMS ZALAGADATEL, | G5: Уртачул МФЙ, Урта-Чул қишлоғи, 26-уй | H5: 8 | I5: 3150032.5 | J5: 3150032.5 | K5: To'ladi
A6: БУХОРО ВИЛОЯТИ | C6: Объезд | D6: Кр-99027688-2 | E6: HUSENOV BARNO HASANOVICH | F6: 94-003-53-53 sms O'ZI begana, 93-211-44-49 sms AYOLI, 93-558-53-33 sms O'G'LI, 50-720-12-44 sms QIZI, +998949965353 SMS O’ZI, 998507201244 SMS QIZI, 998932114449 SMS AYOLI, | G6: АРАБХОНА МФЙ, АРАБХОНА, | H6: 8 | I6: 2968080.1 | J6: 2968080.1 | K6: Uyiga borildi - to'ladi
A7: БУХОРО ВИЛОЯТИ | C7: Дозвон | D7: Кр-99062944-1 | E7: SAMIYEV DOSTONBEK TAVAKKALZODA | F7: +998882814800 SMS O’ZI, 998505068777 SMS UKASI, 998883064800 SMS UKASI, 998883440311 SMS ONASI, | G7: BUXORO VILOYATI SHOFIRKON TUMANI G’ULOMTE MFY G’ULOMTE QISHLOG’I | H7: 8 | I7: 2105616.6 | J7: 2105616.6 | K7: To'ladi | filialga naxt tolangan
A8: БУХОРО ВИЛОЯТИ | C8: Дозвон | D8: Кр-99040456-1 | E8: TEMIROV NODIRBEK G’OLIBJON OG’LI | F8: 998902981307 SMS OZI, 998995556077 SMS AMAKISI, 998918381398 SMS OTASI, 998906110811 SMS ONASI, | G8: BUXORO VILOYATI G'IJDUVON TUMANI ZARANGARI MFY, BO'LAKIYON QISHLOG'I 36-UY | H8: 8 | I8: 1432784.8 | J8: 1432784.8 | K8: To'ladi | filialga
A9: БУХОРО ВИЛОЯТИ | C9: Дозвон | D9: Кр-99049403-1 | E9: NAVRO’ZOV AZIZBEK HAYDAROVICH | F9: +998882827877 SMS O’ZI, 998914030464 SMS ONASI, 998936515100 SMS AKASI, 998973056003 SMS AKASI, | G9: BUXORO VILOYATI BUXORO TUMANI RABOTAK MFY YANGIOBOD KO’CHASI 118-UY | H9: 8 | I9: 1118758.3 | J9: 1118758.3 | K9: To'ladi
A10: БУХОРО ВИЛОЯТИ | C10: Дозвон | D10: Кр-99057614-1 | E10: RASULOV XAKIM RO’ZIYEVICH | F10: 998914413241 SMS UZI, 998943434898 SMS UGLI, 998914158714 SMS TURMUSH O'RTOG'I, 998919256826 ozi2, | G10: NAVOIY VILOYATI,KOMNIMEX TUMANI,YUKSALISH MFY,CHORDARA QISHLOG'I,37 UY | H10: 8 | I10: 1007128.8 | J10: 1007128.8 | K10: To'ladi
A11: БУХОРО ВИЛОЯТИ | C11: Дозвон | D11: Кр-99035271-1 | E11: ERGASHEV MADAT MAXMUDOVICH | F11: 998951410082 SMS O’ZI begona, 998883078283 SMS AYOLI, 998939756160 SMS ONASI, 998880830140 SMS UY, 998882854888 узи, 998879650920 кизи, | G11: BUXORO VILOYATI SHOFIRKON TUMANI, XO'JA ORIF MFY, XO'JA ORIF KO'CHASI, 201-UY | H11: 1 | I11: 54.48 | J11: 54.48 | K11: To'ladi
A12: ЖИЗЗАХ ВИЛОЯТИ | C12: Объезд | D12: Кр-99036112-1 | E12: O’TASHEV RAVSHAN BOXTIYOR O’G’LI | F12: 998991037766 SMS OZI, 998946525295 SMS AKA TOLOVCHI, 998946738436 SMS AYOLI TOLOVCHI, 998944973835 SMS AYOLI, 998958735995 SMS TOLOVCHI, | G12: JIZZAX VILOYATI MIRZACHUL TUMANI PAXTAZOR SHFY BUNYODKOR KUCHASI 38-UY 2-XONADON | H12: 42 | I12: 6829564.9 | J12: 6829564.9 | K12: Uyiga borildi - to'ladi | mowin olingan
A13: ЖИЗЗАХ ВИЛОЯТИ | C13: Дозвон | D13: Кр-99028616-4 | E13: MALLAYEV SHUXRAT BOSIMOVICH | F13: 93-301-00-66 SMS O'ZI, 93-301-07-54 SMS AYOLI, 93-301-06-96 SMS SIN, 99-245-90-99 SMS SIN 2, 998945450550 Eldor ogli , 998992169079 tulovchi, 998997563446 tulovchi, | G13: JIZZAX VILOYATI JIZZAX TUMANI QANGLI MFY TARAQLI KUCHASI 13-UY | H13: 8 | I13: 6576640.7 | J13: 6576640.7 | K13: To'ladi
A14: ЖИЗЗАХ ВИЛОЯТИ | C14: Дозвон | D14: Кр-99033288-1 | E14: KENJAYEVA MUHABBAT XOLQUZIYEVNA | F14: 998995277527 SMS O’ZI, 998932993392 SMS QIZI, 990982993399 SMS KUYOVI, | G14: JIZZAX VILOYATI SH RASHIDOV TUMANI QAHRAMON MFY TURKISTON KUCHASI 42-UY | H14: 11 | I14: 4835015.5 | J14: 4835015.5 | K14: To'ladi
... A24: ЖИЗЗАХ ВИЛОЯТИ | C24: Дозвон | D24: Кр-99046629-1 | E24: UMAROV VAXOB VALIYEVICH | F24: +998904908890 SMS, 998940358890 SMS, 998999968799 SMS, 998993662364 SMS, | G24: Джизакская область, Джизак г., Хамзаобод, Ойбек, дом 23 | H24: 8 | I24: 1009358.8 | J24: 1009358.8 | K24: To'ladi
A25: ЖИЗЗАХ ВИЛОЯТИ | C25: Дозвон | D25: Кр-99028616-3 | E25: MALLAYEV SHUXRAT BOSIMOVICH | F25: 93-301-00-66 SMS O'ZI, 93-301-07-54 SMS AYOLI, 93-301-06-96 SMS SIN, 99-245-90-99 SMS SIN 2, 998945450550 Eldor ogli , 998992169079 tulovchi, 998997563446 tulovchi, | G25: JIZZAX VILOYATI JIZZAX TUMANI QANGLI MFY TARAQLI KUCHASI 13-UY | I25: 574655.15 | J25: 574655.15 | K25: To'ladi
A26: ЖИЗЗАХ ВИЛОЯТИ | C26: Дозвон | D26: Кр-99045776-1 | E26: USMONOV ZUXRIDDIN MUXTOROVICH | F26: 998943454563 SMS, 998976411165 SMS, 998979951965 SMS, | G26: JIZZAX VILOYATI DUSTLIK TUMANI QAXRAMON MFY GOLIBLAR KUCHASI 18-UY | I26: 302318.5 | J26: 302318.5 | K26: To'ladi
A27: ЖИЗЗАХ ВИЛОЯТИ | C27: Дозвон | D27: Кр-99033705-2 | E27: ABDIYEV IBRAIM RAXMONOVICH | F27: 998937753867 SMS O’ZI, 998937723867 SMS AYOLI, 998931210076 SMS UKASI, 998948762276 SMS OVSINI, | G27: JIZZAX VILOYATI ZAFAROBOD TUMANI UZUN QFY MUSTAQILLIK KUCHASI 24-UY | H27: 8 | I27: 57382.22 | J27: 57382.22 | K27: To'ladi
A28: КАШКАДАРЁ ВИЛОЯТИ | B28: SUPER BRANCH | C28: Объезд | D28: Кр-99041785-1 | E28: ABDIRAXMONOV USMON FARMON O’G’LI | F28: 998997194818 SMS OZI, 998919101910 SMS DOSTI, 998930724818 SMS UYI, | G28: QASHQADARYO VILOYATI QARSHI TUMANI ROVOT MFY S.NASAFIY KO’CHASI 85-UY | H28: 8 | I28: 4260208.2 | J28: 4260208.2 | K28: Uyiga borildi - to'ladi
A29: КАШКАДАРЁ ВИЛОЯТИ | B29: SUPER BRANCH | C29: Объезд | D29: Кр-99062619-1 | E29: QURBANOV BAXODIR JURAYEVICH | F29: 998940074848 узи, 998908819989 аели, 998913206851 дадаси, 998919624032 онаси, | G29: QASHQADARYO VILOYATI MUBORAK TUMANI BOBUR MFY BOBUR KUCHASI 1-UY 27-XONADON | H29: 8 | I29: 2852315.9 | J29: 2852315.9 | K29: Uyiga borildi - to'ladi
A30: КАШКАДАРЁ ВИЛОЯТИ | B30: SUPER BRANCH | C30: Дозвон | D30: Кр-99036546-1 | E30: YULDASHEV RUSTAM QURBONAZAR O’G’LI | F30: 998976711771 SMS OZI, 998987770193 SMS OZI 2, 998904252808 SMS OILASI , 998880062055 SMS AKASI , | G30: QASHQADARYO VILOYATI G’UZOR TUMANI ERKIN KUCHASI 27-UY | I30: 971135.03 | J30: 971135.03 | K30: To'ladi
A31: КАШКАДАРЁ ВИЛОЯТИ | B31: SUPER BRANCH | C31: Дозвон | D31: Кр-99060392-1 | E31: RO’ZIYEV JASURBEK ABDURASULOVICH | F31: 998881132930 узи, 998990742930 онаси, 998990762930 отаси, 998995652930 акаси, | G31: QASHQADARYO VILOYATI KASBI TUMANI NAZARTEPA MFY NAZARTEPA KUCHASI 12-UY 42-MAKTAB | H31: 8 | I31: 60492.42 | J31: 60492.42 | K31: To'ladi
A32: КАШКАДАРЁ ВИЛОЯТИ | B32: SUPER BRANCH | C32: Объезд | D32: Кр-99034450-3 | E32: MAHMATQOBILOV ELBEK PULAT O’G’LI | F32: 998957714245 SMS O’ZI, 998505882555 SMS DO’STI, 998934943260 SMS AYOLI, 998958830199 SMS OTASI, | G32: ЧАМБИЛ МФЙ, ОКЧОВА, uy:83. | H32: 8 | I32: 21815.95 | J32: 21815.95 | K32: Uyiga borildi - to'ladi
A33: КАШКАДАРЁ ВИЛОЯТИ | B33: Қарши филиали | C33: Дозвон | D33: Кр-99036280-4 | E33: DJURAYEV URAL NORTULAYEVICH | F33: 998973133705 SMS OZI, 998886389305 SMS AYOLI, 998882214343 SMS AKASI, 998970706311 SMS UKASI, | G33: КАШКАДАРЁ ВИЛОЯТИ КОСОН ТУМАНИ Эсабой МФЙ Эсабой кучаси 11 уй | H33: 8 | I33: 3169494.4 | J33: 3169494.4 | K33: To'ladi
A34: КАШКАДАРЁ ВИЛОЯТИ | B34: Қарши филиали | C34: Объезд | D34: Кр-99029105-1 | E34: MAHMUDOV OLIM OTAQULOVICH | F34: 95-178-02-25 SMS OZI TULOVCHISI, 99-152-62-55 SMS ONASI, 97-803-97-77 SMS AYOLI, 97-743-33-66 SMS ZALOGADATEL, 98-366-82-72 SMS ZALOGADATEL, 998777420100 UZI NEWW, | G34: QASHQADARYO VILOYATI QARSHI TUMANI CHAROG'ON QFY 33-UY | H34: 12 | I34: 1223525.7 | J34: 1223525.7 | K34: Uyiga borildi - to'ladi
A35: КАШКАДАРЁ ВИЛОЯТИ | B35: Қарши филиали | C35: Дозвон | D35: Кр-99063664-1 | E35: SULTONOV BAHRIDDIN MURODILLOYEVICH | F35: +998872130901 SMS O'GLI, 998952201072 SMS, 998992596974 SMS, | G35: КАШКАДАРЁ ВИЛОЯТИ МИРИШКОР ТУМАНИ ЯНГИ МИРИШКОР МФЙ УЗБЕКИСТОН КУЧАСИ 149 УЙ | H35: 8 | I35: 397730.59 | J35: 397730.59 | K35: To'ladi
A36: КОРАКАЛПОГИСТОН РЕСПУБЛИКАСИ | C36: Дозвон | D36: Кр-99041972-1 | E36: TORENIYAZOV IKLASBAY PISHENOVICH | F36: +998907017280 OZI, 998904201880 OYALI, 998992005100 OGLI, | G36: Республика Каракалпакстан, Ходжейлийский район, Бунёдкор МФЙ, ул. Касип-ауыл, дом 34 | H36: 8 | I36: 4267388.8 | J36: 4267388.8 | K36: 20KUNI OYLIGIMDAN TO'LEMAN DEDI QISMAN TO'LADILA XOTINI BN GAPLASHDIM JUDA QO'POL EKAN MOLDE GAPIRDI O'ZIYAM BEZNESMEN EKAN | 1149 | Uyiga borildi - va'da berdi
A37: КОРАКАЛПОГИСТОН РЕСПУБЛИКАСИ | C37: Дозвон | D37: Кр-99042377-1 | E37: DJEKSENBAEVA IRINA DJANBIRAEVNA | F37: 998882145959 OZI, 998904244011 OGLI, 998919332729 QIZI, | G37: QARAQALPOGISTON RESPUBLIKASI NUKUS SHAHAR Nauriz MFY, Minar ko’chasi, 8-uy | H37: 8 | I37: 4211268.3 | J37: 4211268.3 | K37: QISMAN TO'LADI 2-3 KUNDA YANA TASHLAYDI AJDANIYA TUSHDIM | 1163 | Va'da berdi
A38: КОРАКАЛПОГИСТОН РЕСПУБЛИКАСИ | C38: Дозвон | D38: Кр-99039490-1 | E38: SAFARBAYEV SUROJ ROZUMBAYEVICH | F38: 998970834467 SMS OZI, 998770929111 SMS AYOLI, 998335387575 SMS DOSTI, 998919911936 SMS OZI 2, 998991193691 SMS OZI NEWW, | G38: QORAQALPOG’ISTON RESPUBLIKASI AMUDARYO TUMANI QIZILCHOLI MFY,YOSHLAR HIYOBONI 31-UY,32-XONADON | H38: 6 | I38: 2508202.8 | J38: 2508202.8 | K38: BU BUGUN QISMAN TO'LADILA | 877 | To'ladi
A39: КОРАКАЛПОГИСТОН РЕСПУБЛИКАСИ | C39: Дозвон | D39: Кр-99060322-1 | E39: SABUROV SAYLAUBAY KIPSHAKBAEVICH | F39: 998912685577 SMS OZI, 998907017858 SMS AYOLI, 998994765545 SMS OGLI, 998935660520 SMS OGLI, | G39: QARAQALPOGISTON RES NUKUS TUMANI KIRANTOV OFY NURANIY KUSHASI 35 UY | H39: 8 | I39: 1239161.9 | J39: 1239161.9 | K39: to'ladi | 1517 | To'ladi
A40: НАВОИЙ ВИЛОЯТИ | C40: Дозвон | D40: Кр-99063882-2 | E40: TESHAYEV HOJIKURBON TO’XTAMURODOVICH | F40: 998912525911 O’G’LI, 998914314545 O’ZI, 998991304500 UKASI,913314545 | G40: RABOT QISHLOG’I 203 UY | H40: 8 | I40: 9516019 | J40: 9516019 | K40: To'ladi
A41: НАВОИЙ ВИЛОЯТИ | C41: Дозвон | D41: Кр-99063878-2 | E41: SANOQULOV JASUR SUVON O’G’LI | F41: 998777612272 O’ZI, 998991642772 AYOLI, 998993753426 O’G’LI, | G41: NAVOIY VILOYATI NAVBAHOR TUMANI ARABXONA MFY ARABXONA SHOX KO’CHASI 200 UY | H41: 8 | I41: 5452116.2 | J41: 5452116.2 | K41: To'ladi | bugun tolidi
A42: НАВОИЙ ВИЛОЯТИ | C42: Дозвон | D42: Кр-99040301-1 | E42: SHARIPOV SHERZOD NABIYEVICH | F42: 998913302929 SMS OZI, 998912510707 SMS AKASI, 998901253625 SMS OTASI, 998121007702 SMS OZI 2, | G42: NAVOIY VILOYATI,QIZILTEPA TUMANI,RABOT MFY, MANZILOBOD KO’CHASI, 127 UY | H42: 8 | I42: 5026680.1 | J42: 5026680.1 | K42: To'ladi | tolandi
A43: НАВОИЙ ВИЛОЯТИ | C43: Дозвон | D43: Кр-99064038-1 | E43: SANAKULOVA MALOXAT ISOMITDINOVNA | F43: 998937590414 O’ZI, 998937771430 O’G’LI, | G43: ZARGAR KO’CHASI 32 UY | H43: 8 | I43: 1089191.7 | J43: 1089191.7 | K43: To'ladi | qisman ertaga qoganini tolidi
A44: НАВОИЙ ВИЛОЯТИ | C44: Дозвон | D44: Кр-99063138-1 | E44: KARIMOV ILHOMJON IKRAMOVICH | F44: 998931482717 AYOLI, 998934389278 OG’LI, | G44: Кармана кучаси 117 уй | H44: 8 | I44: 117592.87 | J44: 117592.87 | K44: To'ladi
A45: НАВОИЙ ВИЛОЯТИ | C45: Дозвон | D45: Кр-99036692-1 | E45: SHODIYEVA FERUZA G’AFFOROVNA | F45: 998919901871 SMS OZI, 998931793787 SMS JIYANI faqat shunga qilinsin shu xal qiladi, | G45: NAVOIY VILOYATI QIZILTEPA TUMANI A.NAVOIY MFY O'ZBEKISTON SHOX KO'CHASI 13-UY 14-XONADON | H45: 1 | I45: 28423.81 | J45: 28423.81 | K45: To'ladi | ozim yoptirdim\
A46: НАМАНГАН ВИЛОЯТИ | C46: Дозвон | D46: Кр-99063910-1 | E46: QOZAQOVA AZIZAXON SOBITXANOVNA | F46: +998990775453 SMS O’ZI, 998934053116 SMS O’G’LI, 998934075455 SMS O’G’LI, | G46: НАМАНГАН ВИЛОЯТИ УЧҚЎРҒОН ТУМАНИ ТУРКИСТОН МФЙ ПАРВОЗ КЎЧАСИ 104 УЙ 1 КОРПУС 43 ХОНАДОН | H46: 8 | I46: 1832838.7 | J46: 1832838.7 | K46: To'ladi | yopildi
A47: САМАРКАНД ВИЛОЯТИ | C47: Объезд | D47: Кр-99026954-6 | E47: AXROROV MEXROJ MASHRAFOVICH | F47: 99-783-00-20 SMS OZI tolovchi, 33-799-20-20 SMS UKASI, 91-702-64-03 SMS AYASI, 97-958-70-11 SMS AKASI, +998992719999 Primary phone from road24( БЕГОНА), 998992719999 Primary phone from road24( БЕГОНА), | G47: SAMARQAND VILOYATI SAMARQAND TUMANI QO’SHTAMG’ALI QFY JO’YISOY MFY | H47: 8 | I47: 5150210.4 | J47: 5150210.4 | K47: Uyiga borildi - to'ladi | yopildi
... A53: САМАРКАНД ВИЛОЯТИ | C53: Объезд | D53: Кр-99044880-1 | E53: SHAMSUTDINOV ALIBEK AMRITDIN O’G’LI | F53: +998775030831 SMS OZI, 998889181101 SMS AKASI, 998915294327 SMS UYI, 998990840360 SMS APASI, | G53: SAMARQAND VILOYATI PASTDARG’OM TUMANI JAG’OLBOYLI MFY JAG’OLBOYLI KUCHASI 16-UY | H53: 8 | I53: 1401165.1 | J53: 1401165.1 | K53: Uyiga borildi - to'ladi | yopildui
A54: САМАРКАНД ВИЛОЯТИ | C54: Дозвон | D54: Кр-99007936-13 | E54: MAMASHARIPOV UTKIR MAMARZAYEVICH | F54: 99-344-03-45 SMS, 99-459-49-27 SMS AYOLI, 99-250-69-06 SMS ozi , 99-161-65-45 SMS UYI , 99-150-69-06 SMS ayoli , 77-080-89-01 SMS FARANGIZ SHU TOLOVCHI, +998957710587 SMS OZI, 998991198901 SMS UKASI, 998995398901 SMS UYI, 998990827644 tulovchi, 998500281120 SMS UYI, 998959584111 SMS AKASI, | G54: SAMARQAND VILOYATI OQDARYO TUMANI A.TEMUR MFY KALLAR QISHLOG’I | I54: 549955.94 | J54: 549955.94 | K54: To'ladi | yopildi
A55: САМАРКАНД ВИЛОЯТИ | C55: Объезд | D55: Кр-99038439-2 | E55: RAXMATOV ASILBEK OTABEK O’G’LI | F55: 998931744999 SMS OZI, 998934977010 SMS UKASI, 998939111879 SMS DADASI, 998775171404 SMS UYI, | G55: SAMARQAND VILOYATI PAYARIQ TUMANI MADANIYAT MFY BAXMALSOY KUCHASI 171-UY | H55: 13 | I55: 342959.3 | J55: 342959.3 | K55: Uyiga borildi - to'ladi | yopildi
A56: САМАРКАНД ВИЛОЯТИ | C56: Дозвон | D56: Кр-99062999-2 | E56: KUDRATOV SODIKJON RIZAKULOVICH | F56: +998919757615 SMS OZI, 998774818491 SMS OZI 2, 998881117615 SMS AYOLI, | G56: SAMARQAND VILOYATI KATTAQO’RG’ON SHAHRI YAKKABOG’ MFY BOG’I DILKUSHOR KUCHASI 25-UY | H56: 8 | I56: 253449.63 | J56: 253449.63 | K56: To'ladi | yopildi
A57: САМАРКАНД ВИЛОЯТИ | C57: Дозвон | D57: Кр-99062738-1 | E57: RUZIYEV SUNATULLA SAFARALIYEVICH | F57: +998991126907 SMS OZI, 998993756907 SMS UYI, 998994228307 SMS SINGLISI, | G57: SAMARQAND VILOYATI NUROBOD TUMANI URTABUZ MFY TINCHLIK QISHLOG’I | H57: 13 | I57: 136542.15 | J57: 136542.15 | K57: To'ladi | yopildi
A58: САМАРКАНД ВИЛОЯТИ | C58: Дозвон | D58: Кр-99063278-2 | E58: ABDIQAYUMOV IBROHIM ZAYNIDDIN O’G’LI | F58: +998937202873 SMS OZI, 998500202086 SMS DADASI, 998915379123 SMS AYASI, 998915393006 SMS OZI 2, | G58: SAMARQAND VILOYATI PASTDARG’OM TUMANI KAMOLOT MAHALLASI | H58: 8 | I58: 76359.2 | J58: 76359.2 | K58: To'ladi | yopildi
A59: СУРХОНДАРЁ ВИЛОЯТИ | C59: Объезд | D59: Кр-99027939-1 | E59: TURAYEVA ADOLAT TOSHBOYEVNA | F59: 91-078-04-96 SMS, 91-233-33-57 SMS UY, 91-575-71-70 SMS OILASI, 91-588-17-69 SMS O’ZI, 97-261-88-46 javlon aka javob degan, 998992184093 SMS O'ZI 2, | G59: SURXONDARYO VILOYATI UZUNSHO’RCHI TUMANI DO’STLIK MFY HAMKOR KUCHASI 104-UY | H59: 1 | I59: 4226143.1 | J59: 4226143.1 | K59: Uyiga borildi - to'ladi | filialga tolad | 223
A60: СУРХОНДАРЁ ВИЛОЯТИ | C60: Объезд | D60: Кр-99032593-1 | E60: DAVLATOV FARXOD RAJABALIYEVICH | F60: 998995882144 SMS O’ZI, 998954747270 SMS O’G’LI, 998995737252 SMS ONASI, 998990169073 SMS UY, | G60: SURXONDARYO VILOYATI DENOV TUMANI SEBZOR MFY MAKTAB KO’CHASI 15-UY | H60: 1 | I60: 1299053.2 | J60: 1299053.2 | K60: Uyiga borildi - to'ladi | toladi filialga | 404
A61: СУРХОНДАРЁ ВИЛОЯТИ | C61: Объезд | D61: Кр-99057140-1 | E61: XUSHBAQOVA ZEBINISO ABDUMALIK QIZI | F61: 998932372417 OZI, 998937930462 ONASI, 998917259222 OGLI, | G61: SURXONDARYO VILOYAT TERMIZ SHAXAR BOG’ZOR MFY ZAVQIY KO’CHASI 24A-UY | H61: 8 | I61: 970609.56 | J61: 970609.56 | K61: Uyiga borildi - to'ladi | filialga toladi | 1416
A62: СУРХОНДАРЁ ВИЛОЯТИ | C62: Дозвон | D62: Кр-99035855-1 | E62: NAZAROVA SHOIRA BOZOR QIZI | F62: 998936365511 SMS OZI, 998944168997 SMS UY, 998888505511 SMS OILASI, 998930454064 SMS OTASI, | G62: SURXONDARYO VILOYATI BOYSUN TUMANI DASHTIG’OZ MFY SURXONDARYO KO’CHASI 22-UY | H62: 8 | I62: 21786.19 | J62: 21786.19 | K62: To'ladi | yopildi | 603
A63: ТОШКЕНТ ШАХРИ | C63: Объезд | D63: Кр-99017842-6 | E63: YAKUBJANOV ASADJON AXMADJANOVICH | F63: 99-482-80-45 sms OZI, 97-715-15-83 sms AYOLI, 91-008-35-35 sms O'G'LI, 99-482-80-45 sms OZI, | G63: TOSHKENT SHAHRI SERGELI TUMANI | H63: 5 | I63: 4757650.3 | J63: 4757650.3 | K63: Uyiga borildi - to'ladi
A64: ТОШКЕНТ ШАХРИ | C64: Объезд | D64: Кр-99063244-1 | E64: QUDRATXODJAYEV BEHZOD SHUXRATOVICH | F64: 998200001426 SMS OZI, 998997012006 SMS JIYANI, 998998604005 SMS OANSI, | G64: TOSHKENT SHAHAR YUNUSOBOD TUMANI O’LKAOBOD KOCHASI 4-UY | H64: 13 | I64: 3189339.2 | J64: 3189339.2 | K64: Uyiga borildi - to'ladi
A65: ТОШКЕНТ ШАХРИ | C65: Объезд | D65: Кр-99044138-2 | E65: ABDURASHIDOV ABDULAZIZ ABDULATIF O’G’LI | F65: 998946236666 SMS OZI 2, 998946638777 SMS OZI, 998983664777 SMS UKASI, | G65: Oltin vodiy MFY, Samo 1-berk ko’chasi, 18-uy | H65: 8 | I65: 2828306.4 | J65: 2828306.4 | K65: Uyiga borildi - to'ladi
A66: ТОШКЕНТ ШАХРИ | C66: Объезд | D66: Кр-99037634-2 | E66: XUDOYBERGANOV DONIYOR TUYG’UN O’G’LI | F66: 998946895455 SMS O’ZI, 998950051505 SMS DO’STI, 998900543915 SMS O’ZI, 998331775455 SMS UKASI, | G66: Бободехкон МФЙ, Хусайни, туп. 2 кучаси, 9-уй | H66: 8 | I66: 2516559.5 | J66: 2516559.5 | K66: Uyiga borildi - to'ladi
... A73: ФАРГОНА ВИЛОЯТИ | C73: Объезд | D73: Кр-99025845-2 | E73: TO’YCHIYEV IKROMJON UMAROVICH | F73: 99-796-56-34 SMS , 93-607-41-00 SMS AYOLI, 99-051-29-35 SMS OGLI DILYORBEK, 98-107-07-19 SMS OGLI, | G73: FARG’ONA VILOYATI BUVAYDA TUMANI SHO'R QISHLOQ | H73: 13 | I73: 1159484.8 | J73: 567996 | K73: Uyiga borildi - to'ladi | OGLI TOLASHI KERAK EKAN BUGUN TOLAYDI DEYABDI | 567996.06
A74: ФАРГОНА ВИЛОЯТИ | C74: Дозвон | D74: Кр-99028520-1 | E74: TO’RAKELDIYEV SODIQJON NORALI O’G’LI | F74: 94-833-02-02 SMS O'ZI, 50-881-13-13 SMS AKASI, 95-489-33-36 SMS DADASI, 91-670-67-69 SMS O'ROG'I, | G74: FARG’ONA VILOYATI FARGO’ONA SHAHAR SHODIYONA MFY TINIQSOY KO’CHASI 168-UY. | I74: 882630.38 | J74: 882630.38 | K74: To'ladi | 7 LARGA QAYTA ALOQA TOLOV QILADI EKAN AKASI | 0
A75: ФАРГОНА ВИЛОЯТИ | C75: Дозвон | D75: Кр-99028581-4 | E75: RUSTAMOVA CHINARA ABDRAXMANOVNA | F75: 93-443-38-30 SMS O'ZI, 91-396-85-25 SMS ERI , 95-110-82-02 SMS OPASI , 50-772-85-87 SMS SINGLISI , | G75: FARG’ONA VILOYATI FARG’ONA SHAHAR KIMYOGARLAR MFY, SO’LIM KO’CHASI 11/4-UY 18-XONADON | H75: 8 | I75: 777276.46 | J75: 358385 | K75: To'ladi | TOLAGAN FILAL ADASIB BOSHQA AYDIGA URGAN | 358385.15
A76: ФАРГОНА ВИЛОЯТИ | C76: Объезд | D76: Кр-99041883-1 | E76: UZAKOV ANVARJON MAKSIMOVICH | F76: +998993036357 SMS O’ZI, 998906326357 AYOLI, 998990097733 O’G’LI 2, 998991406357 O’G’LI, | G76: FARG’ONA VILOYATI OLTIARIQ TUMANI TINCHILIK MFY TADBIRKOR KO’CHASI 19-XONADON | H76: 8 | I76: 511789.26 | J76: 158652 | K76: Uyiga borildi - to'ladi | ERTAGA OGLI OZBEKISTONGA KIRADI EKAN ERTAGA KECHGACHA YOPIB QOYAMAN DEDI | 158652.49
A77: ХОРАЗМ ВИЛОЯТИ | B77: SUPER BRANCH | C77: Дозвон | D77: Кр-99057449-1 | E77: PALVANOV BAXRAM ATANAZAROVICH | F77: 998914344383 SMS UZI, 998941030433 SMS UGLI, 998906497173 SMS KELINI, 998954264383 SMS ozi new, | G77: XORAZM VILOYATI XIVA TUMANI KALTAMINOR MFY DESHONKALA KO’CHASI 89A-UY | H77: 8 | I77: 1961175.5 | J77: 1961175.5 | K77: To'ladi | abetgacha yopad | 1450
A78: ХОРАЗМ ВИЛОЯТИ | B78: Урганч филиали | C78: Дозвон | D78: Кр-99063321-2 | E78: RAXIMOVA GUZAL ALISHEROVNA | F78: +998975275555 SMS UZI, 998975165555 SMS ERI, | G78: ХОРАЗМ ВИЛОЯТИ УРГАНЧ Ш., ГУЛЗОР МФЙ, УРГАНЧ ШАХАР, ГУЛЗОР МФЙ, АЛ-БЕРУНИЙ, uy:60А | H78: 8 | I78: 10737405 | J78: 10737405 | K78: To'ladi | eri bugun abetgacha yopad | 1747
A79: ХОРАЗМ ВИЛОЯТИ | B79: Урганч филиали | C79: Дозвон | D79: Кр-99032959-2 | E79: ATADJANOVA MALIKA ABDULLAYEVNA | F79: 998914208844 SMS O’ZI, 998771625158 SMS JIYANI, 998918667040 SMS SINGLISI, +998914208844 SMS UZI, | G79: ХОРАЗМ ВИЛОЯТИ УРГАНЧ ШАХРИ Янгихаёт МФЙ, Фирдавсий,4 тор кўчаси, 131-уй | H79: 8 | I79: 2802027.6 | J79: 2802027.6 | K79: To'ladi | Abetdan kegin yopad | 416
A80: ХОРАЗМ ВИЛОЯТИ | B80: Урганч филиали | C80: Дозвон | D80: Кр-99045798-1 | E80: TAJIMURATOV FARXOD ISMOYILOVICH | F80: +998948952627 SMS UZI, 998914292627 SMS AYOLI, 998955512040 SMS UKASI, | G80: Тандирчи МФЙ, Олмазор кучаси, 26/1-уй | H80: 8 | I80: 1206858.4 | J80: 1206858.4 | K80: To'ladi | filialga ketvotti tolov qilgani | 1231
A81: ХОРАЗМ ВИЛОЯТИ | B81: Урганч филиали | C81: Дозвон | D81: Кр-99027378-2 | E81: RUZMETOVA DILNOZA OTANAZAROVNA | F81: 97-792-65-55 SMS TULOVCHI, 97-458-65-12 SMS ONASI, 97-221-52-99 SMS, | G81: ХОРАЗМ ВИЛОЯТИ УРГАНЧ ТУМАНИ ҒАЛАБА ҚФЙ, ОБОД МФЙ, ЧЕВАРЛАР КЎЧАСИ, uy:31 | H81: 8 | I81: 374858.49 | J81: 374858.49 | K81: To'ladi | ogli abetgacha tolid | 198

Sheet Не дозвонились
A1: ← Вернуться в отчёт
A2: Область | B2: Филиал | C2: Группа | D2: Код клиента | E2: Клиент | F2: Номер телефона | G2: Адрес | H2: Кол-во просроченных дней | I2: Итого просрочка | J2: Оплата | K2: Izoh
A3: АНДИЖОН ВИЛОЯТИ | C3: Недозвон | D3: Кр-99050899-1 | E3: ERGASHOV ELYORBEK NE’MATJONOVICH | F3: 998774544221 SMS OZI, 998902062924 SMS AYOLI, 998022181812 SMS OZI, 998902533553 SMS AKASI, | G3: ANDIJON VILOYATI BO’Z TUMANI GUZAR MFY, O’ZBEKISTON KO’CHASI 489-UY | H3: 102 | I3: 28770099
A4: АНДИЖОН ВИЛОЯТИ | C4: Недозвон | D4: Кр-99059626-1 | E4: ABDURAXMONOVA MANZURAXON IBRAGIMDJONOVNA | F4: 998972041812 SMS OZI, 998910530105 SMS OGLI, 998502108587 SMS QIZI, 998883838387 SMS KELINI, | G4: ANDIJON VILOYATI ASAKA TUMANI CHEK MFY XAMDO’STLIK KO’CHASI 157-UY | H4: 41 | I4: 17366846
A5: АНДИЖОН ВИЛОЯТИ | C5: Недозвон | D5: Кр-99062885-1 | E5: KASIMXODJAYEV ABDUXALIL ABDUMAJITOVICH | F5: +998916208060 SMS O’ZI, 998914781293 SMS AYOLI, 998916028060 SMS UY, 998976208060 SMS O’ZI2, | G5: ANDIJON VILOYATI ANDIJON SHAHAR MAYDONBOZOR MFY YAXSHI KO’CHASI 61/59-UY | H5: 8 | I5: 10101384
A6: АНДИЖОН ВИЛОЯТИ | C6: Недозвон | D6: Кр-99057085-1 | E6: YULDASHEVA NILUFAR KAMILOVNA | F6: 998872557757 SMS OZI, 998982700122 SMS OGLI, 998772581112 SMS QIZI, 998882331807 SMS JIYANI, | G6: ANDIJON VILOYATI ANDIJON TUMANI ZANGIBOBO MFY PORLOQ KO’CHASI 306-UY | H6: 11 | I6: 9656867.5
A7: АНДИЖОН ВИЛОЯТИ | C7: Недозвон | D7: Кр-99062881-1 | E7: DJALILOVA SAXIBAXON XAMIDJANOVNA | F7: +998945131961 SMS O’ZI, 998933171152 SMS KELINI, 998934373105 SMS XO’JAYNI, 998998439222 SMS O’G’LI, | G7: ANDIJON VILOYATI OLTINKO’L TUMANI ITTIFOQ MFY QO’RG’ONCHA KO’CH ASI 32-UY | H7: 8 | I7: 9190772.3
A8: АНДИЖОН ВИЛОЯТИ | C8: Недозвон | D8: Кр-99060389-1 | E8: SULTANOVA XAMIDA ULJABEKOVNA | F8: +998934141584 SMS O’ZI, 998973243443 SMS KELINI, 998979753443 SMS O’G’LI, 998993200858 SMS XO’JAYNI, | G8: Andijon viloyati Andijon shahar Sadoqat MFY Fuzuliy ko’chasi 49-uy | H8: 8 | I8: 8869357.7
A9: АНДИЖОН ВИЛОЯТИ | C9: Недозвон | D9: Кр-99050886-1 | E9: SULAYMANOV DILMUROD ABDUMALIKOVICH | F9: +998940074404 SMS O’ZI, 998773277467 SMS QIZI, 998934143383 SMS AYOLI, | G9: ANDIJON VILOYATI IZBOSKAN TUMANI OBOD MFY UZUN KO’CHA 275-UY | H9: 8 | I9: 8838174.3
A10: АНДИЖОН ВИЛОЯТИ | C10: Недозвон | D10: Кр-99058759-1 | E10: RAXMANOV DILSHODBEK TO’XTASINOVICH | F10: 998889930005 SMS OZI, 998955173700 SMS AYOLI, 998979970184 SMS UKASI, 998949300052 SMS OZI 2, | G10: ANDIJON VILOYATI QO’RG’ONTEPA TUMANI DEXQONCHEK MFY ERKIN IJOD KO’CHASI 74-UY | H10: 11 | I10: 8397917.9
A11: АНДИЖОН ВИЛОЯТИ | C11: Недозвон | D11: Кр-99033455-2 | E11: ABDULAZIZOV NOZIMJON NASIBJONOVICH | F11: 998934104844 SMS O’ZI, 998000048002 SMS O’ZI 2, 998932544648 SMS AYOLI, 998936913859 SMS XAMKASBI, 998948770475 SMS otasi new , | G11: ANDIJON VILOYATI PAXTAOBOD TUMANI MA’RIFAT MFY,MA’RIFAT KO’CHASI 47-UY | H11: 4 | I11: 8231629.9
A12: АНДИЖОН ВИЛОЯТИ | C12: Недозвон | D12: Кр-99047889-1 | E12: SHIRMATOV MUXAMMADOZOD QODIRALI O’G’LI | F12: +998911715500 SMS O’ZI, 998772495500 SMS OG’LI, 998972225500 SMS UY, 998998173300 SMS NEVARASI, | G12: ANDIJON VILOYATI ANDIJON SHAHAR ISTIQLOL MFY OBOD 1-TOR KO’CHASI 5-UY | H12: 11 | I12: 8200041.2
A13: АНДИЖОН ВИЛОЯТИ | C13: Недозвон | D13: Кр-99063424-2 | E13: TURSUNOV RAXMATILLO IKRAMJANOVICH | F13: 998702250075 SMS OZI, 998886020075 SMS UKASI2, 998889248080 SMS AYOLI, 998970711009 SMS UKASI, | G13: ANDIJON VILOYATI QO’RG’ONTEPA TUMANI | H13: 8 | I13: 7746590.8
A14: АНДИЖОН ВИЛОЯТИ | C14: Недозвон | D14: Кр-99058489-1 | E14: UZOQOVA IRODA IBROYIMJONOVNA | F14: 998976388885 SMS OZI, 998882215555 SMS XOJAYINI, 998366944492 SMS OZI 2, | G14: ANDIJON VILOYATI ANDIJON TUMANI CHEM MFY ZARQAYNAR KO’CHASI 18-UY | H14: 11 | I14: 7667856.7
... A103: АНДИЖОН ВИЛОЯТИ | C103: Недозвон | D103: Кр-99040647-1 | E103: AKBAROV RAVSHANBEK XXX | F103: 998996161058 SMS OZI, 998935511517 SMS AYOLI, 998942157201 SMS QIZI, 998992306087 SMS OGLI, +998996161058 SMS O’ZI, | G103: ANDIJON VILOYATI OLTINKO’L TUMANI AYRONCHI MFY, AYRONCHI KO’CHASI 856-UY | H103: 8 | I103: 1956751.3
A104: АНДИЖОН ВИЛОЯТИ | C104: Недозвон | D104: Кр-99049616-2 | E104: DAVIDOV MAMIRJON NEMATJONOVICH | F104: 998883672747 OZI, | G104: IIV3411 | I104: 1896080.3
A105: АНДИЖОН ВИЛОЯТИ | C105: Недозвон | D105: Кр-99044378-2 | E105: SHOKIROV NURULLO AXMADULLAYEVICH | F105: +998914912216 SMS O’ZI, 998770387887 SMS QIZI tel qilinmasin, 998779630238 SMS AYOLI , 998931144480 SMS O’G’LI, | G105: АНДИЖОН ВИЛОЯТИ АНДИЖОН ШАХРИ МАДАНИЯТ МФЙ, Т.КЕЛДИЕВ, uy:102 | H105: 8 | I105: 1887081.1
A106: АНДИЖОН ВИЛОЯТИ | C106: Недозвон | D106: Кр-99063106-1 | E106: SOTVOLDIYEVA MAXMUDAXON QOSIMOVNA | F106: 998770492346 OZI, 998931092588 OGLI, 998937212671 OPASI, 998942592770 DUGONASI, | G106: ANDIJON VILOYATI QO’RG’ONTEPA TUMANI UCHQUN MFY ISTIQBOL KO’CHASI 16 UY | H106: 8 | I106: 1868195.4
A107: АНДИЖОН ВИЛОЯТИ | C107: Недозвон | D107: Кр-99004621-4 | E107: NADIROV MURODJON BAXRAMJON O’G’LI | F107: 90-543-11-01 SMS, 99-327-66-67 sms танимийди, 90-528-19-14 SMS TANIMASAKAN , 91-175-12-12 SMS ortogi, +998905431101 SMS O’ZI, 998887838780 SMS AKASI, 998946398780 SMS JIYANI ASADBEK, 998977268780 SMS UKASI, | G107: Саноат МФЙ, А.Йулдошев 1 тор кучаси, 37-уй | H107: 8 | I107: 1725725.7
A108: АНДИЖОН ВИЛОЯТИ | C108: Недозвон | D108: Кр-99029531-1 | E108: TOLIBJONOVA MAFTUNAXON OYBEK QIZI | F108: 77-039-54-54 SMS OZI, 90-220-91-91 SMS ZALOGADATEL, 94-385-88-88 SMS TOLOVCHI ABDULLOX, 90-542-32-22 SMS UKASI, 998902043130 ozi, 998902004000 SMS TO'LOVCHI, 998905445400 qaynotasi , | G108: ANDIJON VILOYATI ANDIJON TUMANI ISTIQLOL MFY OQ YOR KO’CHASI 163-UY | H108: 1 | I108: 1669612.4
A109: АНДИЖОН ВИЛОЯТИ | C109: Недозвон | D109: Кр-99038983-2 | E109: REJABOVA GULNOZA MAXAMMADJON QIZI | F109: 998331132300 SMS OZI olmaliqda kambinatda ishlid , 998931632300 SMS AKASI, 998987882323 SMS UKASI, 998944009532 SMS ONASI, | G109: ANDIJON VILOYATI QO’RG’ONTEPA TUMANI DEXQONCHEK MFY SAJDAGOX KO’CHASI 30-UY | H109: 8 | I109: 1614020.7
A110: АНДИЖОН ВИЛОЯТИ | C110: Недозвон | D110: Кр-99041191-1 | E110: SHOXINAZAROV ABDULLOH AZIZBEK O’G’LI | F110: +998880662277 SMS O’ZI, 998881005751 SMS ONASI, 998931005751 SMS DADASI, 998970272127 SMS DO’STI MUXAMMADSOLIQ, | G110: Экин тикин МФЙ, Шафтолизор кучаси, 252-уй | H110: 8 | I110: 1594020.9
A111: АНДИЖОН ВИЛОЯТИ | C111: Недозвон | D111: Кр-99063748-2 | E111: XURBOYEV MURODILJON MURODJON O’G’LI | F111: +998931757095 SMS O’ZI, 998505454475 SMS DADASI, 998938701978 SMS ONASI, 998971622313 SMS SINGLISI, | G111: ANDIJON VILOYATI IZBOSKAN TUMANI A. JOMIY MFY TASHABBUS MARKAZI KO’CHASI 15-UY | H111: 11 | I111: 1563242.2
A112: АНДИЖОН ВИЛОЯТИ | C112: Недозвон | D112: Кр-99044378-1 | E112: SHOKIROV NURULLO AXMADULLAYEVICH | F112: +998914912216 SMS O’ZI, 998770387887 SMS QIZI tel qilinmasin, 998779630238 SMS AYOLI , 998931144480 SMS O’G’LI, | G112: АНДИЖОН ВИЛОЯТИ АНДИЖОН ШАХРИ МАДАНИЯТ МФЙ, Т.КЕЛДИЕВ, uy:102 | I112: 1400789.4
A113: АНДИЖОН ВИЛОЯТИ | C113: Недозвон | D113: Кр-99039141-1 | E113: SAIDBEKOVA MOXINUR MUXAMMADJON QIZI | F113: 998970957667 SMS OZI, 998974114774 SMS AKASI begona, | G113: ANDIJON VILOYATI ANDIJON SHAHAR MASH’AL MFY T.REJAPOV 1-UY 53-XONADON | H113: 8 | I113: 1399536.1
A114: АНДИЖОН ВИЛОЯТИ | C114: Недозвон | D114: Кр-99040053-1 | E114: RUZIYEVA JAMILAXON XXX | F114: 998932443262 SMS OZI, 998947856262 SMS QIZI, 998999037159 SMS QIZI2, 998948551992 SMS QOSHNISI, | G114: ANDIJON VILOYATI ASAKA TUMANI NAVOIY MFY, ISTIQLOL KO’CHASI 95-UY | H114: 8 | I114: 1252416.6
A115: АНДИЖОН ВИЛОЯТИ | C115: Недозвон | D115: Кр-99050384-1 | E115: YUSUPOV MANSURBEK ODILJONOVICH | F115: +998914979790 SMS O’ZI, 998500407542 SMS UY, 998945631595 SMS AYOLI, 998974488280 SMS ONASI, | G115: ANDIJON VILOYATI IZBOSKAN TUMANI ROVOT MFY GAVXAR KO’CHASI 45-UY | H115: 8 | I115: 1121105
A116: АНДИЖОН ВИЛОЯТИ | C116: Недозвон | D116: Кр-99063628-3 | E116: TASHMATOV XUSNUTDIN ODILJANOVICH | F116: 998901705955 O’ZI, | G116: АНДИЖОН ВИЛОЯТИ АНДИЖОН ШАХAР АХМАД ЯССАВИЙ МФЙ ЛОЙИХАЛАШ КУЧАСИ 6-УЙ | H116: 8 | I116: 1036124.1
A117: АНДИЖОН ВИЛОЯТИ | C117: Недозвон | D117: Кр-99039608-1 | E117: FAXRUTDINOV FAZLITDIN XAYBATULLAYEVICH | F117: 998936926077 SMS OZI, 998951175010 SMS OGLI, 998977712560 SMS OGLI2, | G117: ANDIJON VILOYATI SHAXRIXON TUMANI MULLABOY MFY, AXMAD YASSAVIY KO’CHASI 28-UY | I117: 944176.12
A118: АНДИЖОН ВИЛОЯТИ | C118: Недозвон | D118: Кр-99035336-2 | E118: RO’ZIYEVA MUNIRAXON SULTONOVNA | F118: 998936907720 SMS OZI, 998949796867 SMS QIZI, 998504044603 SMS OGLI, 998934446258 SMS ONASI, | G118: ANDIJON VILOYATI BO’Z TUMANI MUSTAQILLIK KO’CHASI 70-UY,11-XONADON | H118: 8 | I118: 882398.54
A119: АНДИЖОН ВИЛОЯТИ | C119: Недозвон | D119: Кр-99036805-2 | E119: BESHBAYEVA OYAT KASIMOVA | F119: 998979805801 SMS ozi , 998950012711 SMS ogli , 998501114027 SMS kelini , 998938252911 SMS ukasi , 998979805801 SMS ozi , | G119: ANDIJON SHAHRI | H119: 8 | I119: 863490.41
A120: АНДИЖОН ВИЛОЯТИ | C120: Недозвон | D120: Кр-99027653-1 | E120: G’ANIYEV MARDONBEK DILMUROD O’G’LI | F120: 97-834-27-17 SMS O'ZI, 99-402-73-17 SMS ZALOGADATEL, 99-494-13-38 SMS KELINOYISI, 91-481-17-11 SMS DO’STI Begona , | G120: ANDIJON VILOYATI MARXAMAT TUMANI NAVRO’Z MFY CHILONZOR KO’CHASI 114-UY | H120: 8 | I120: 808361.49
A121: АНДИЖОН ВИЛОЯТИ | C121: Недозвон | D121: Кр-99041539-2 | E121: SHERALIYEV SARDORBEK SODIQJON O’G’LI | F121: 998914845776 SMS OZI, 998996325251 SMS AYOLI, 998992425251 SMS ONASI, +998914845776 Primary phone from road24, 998948642717 SMS O’ZI2, | G121: Андижон вилояти Андижон шахар Бунёдкор (9-сон) МФЙ, Қўш ариқ дахаси, 46-уй, 15-хонадон | H121: 8 | I121: 749081.73
A122: АНДИЖОН ВИЛОЯТИ | C122: Недозвон | D122: Кр-99033584-1 | E122: YUSUPJONOVNA GULCHEXRAXON DEKANBAYEVNA | F122: 998997661573 SMS O’ZI, 998931077229 SMS QIZI, 998949397229 SMS UKASI, 998914847800 SMS O’G’LI, | G122: ANDIJON VILOYATI XONOBOD SHAHAR ANXOR MFY XONOBOD KO’CHASI 122-UY 9-XONADON | H122: 1 | I122: 704948.04
A123: АНДИЖОН ВИЛОЯТИ | C123: Недозвон | D123: Кр-99038275-3 | E123: KARIMOVA XAMROXON MO’YDINOVNA | F123: 998508831410 SMS OZI, 998948881410 SMS OGLI, 998916012492 SMS KELINI, 998937359892 SMS AKASI, | G123: ANDIJON VILOYATI SHAXRIXON TUMANI YANGIMAXALLA MFY, OBOD KO’CHASI 75/1-UY | H123: 8 | I123: 664193.63
A124: АНДИЖОН ВИЛОЯТИ | C124: Недозвон | D124: Кр-99038275-2 | E124: KARIMOVA XAMROXON MO’YDINOVNA | F124: 998508831410 SMS OZI, 998948881410 SMS OGLI, 998916012492 SMS KELINI, 998937359892 SMS AKASI, | G124: ANDIJON VILOYATI SHAXRIXON TUMANI YANGIMAXALLA MFY, OBOD KO’CHASI 75/1-UY | H124: 8 | I124: 627170.47
A125: АНДИЖОН ВИЛОЯТИ | C125: Недозвон | D125: Кр-99031667-1 | E125: ASHUROV KOZIMJON IRGASHBAYEVCIH | F125: 97-330-80-02 SMS O’ZI Begona , 94-787-77-37 SMS AYOLI, 95-678-66-64 SMS KELINI, 99-918-60-71 SMS UKASI, | G125: ANDIJON VILOYATI ASAKA TUMANI ULUG’BEK MFY SAXIYLIK KO’CHASI 2-TOR 17-UY | I125: 500231.4
A126: АНДИЖОН ВИЛОЯТИ | C126: Недозвон | D126: Кр-99038164-1 | E126: TURSUNALIYEV SIROJIDDIN YUNUSALI O’G’LI | F126: 998883397171 SMS OZI, 998509978785 SMS AKASI, 998772880618 SMS OPASI, 998951552560 SMS DADASI, | G126: ANDIJON VILOYATI BULOQBOSHI TUMANI RIVOJ MFY,YANGI CHEK KO’CHASI 412-UY | I126: 484735.62
A127: АНДИЖОН ВИЛОЯТИ | C127: Недозвон | D127: Кр-99031828-2 | E127: SOXIBOV SHOXJAXON DIYORBEK O‘G‘LI | F127: 998931042419 SMS O'ZI, 998900174454 SMS O’RTOG’I Begona, 998941087800 SMS AKASI, 998914797800 SMS ONASI, +998943230050 Primary phone from road24 Begona, 998943230050 Primary phone from road24 Begona , | G127: Андижанская область, Пахтаобод тумани, Обод МСГ, ул. Обод, дом 8 | H127: 8 | I127: 348160.18
A128: АНДИЖОН ВИЛОЯТИ | C128: Недозвон | D128: Кр-99035091-1 | E128: YULBARSOVA XOLIDA NEMATOVNA | F128: 998882705757 SMS OZI, 998902542320 SMS ONASI, 998903347720 SMS OTASI, 998944585252 SMS OGLI Begona , 998200076374 SMS Ogli Tolovchi faqat shunga qilinsin , | G128: ANDIJON VILOYATI ANDIJON SHAHAR QORATUT MFY,5-KICHIK DAXA 2-UY,33-XONADON | H128: 7 | I128: 51759.73
A129: БУХОРО ВИЛОЯТИ | C129: Недозвон | D129: Кр-99040851-1 | E129: ZARIPOV NODIRBEK NAZIRJON O’G’LI | F129: 998938132602 SMS O’ZI, 998887531291 SMS OPASI, 998992523242 AMAKISI, 998787770222 SMS ISHXONASI, | G129: QORAKO’L TUMANI | H129: 194 | I129: 46319207 | K129: Telefon ko'tarmadi
A130: БУХОРО ВИЛОЯТИ | C130: Недозвон | D130: Кр-99039543-1 | E130: DJUMAYEV ZAVQIY LATIPOVICH | F130: 998901180010 SMS OZI , 998770240926 SMS UKASI, +998901180010 Primary phone from road24, 998950000118 SMS asilbek o'g'li, | G130: Богча МФЙ, Гараншоҳ қишлоғи, 52-C-уй | H130: 126 | I130: 45153274 | K130: Telefon ko'tarmadi
A131: БУХОРО ВИЛОЯТИ | C131: Недозвон | D131: Кр-99040567-1 | E131: ACHILOV BOBIR BURONOVICH | F131: 998505155499 SMS ONASI, 998931385554 SMS OGLI, 998936205499 SMS OZI, | G131: BUXORO VILOYATI, BUXORO SHAHAR, MUHAMMAD NARSHAXIY MFY, TOJI KARAYEV KO'CHASI, 86-UY | H131: 162 | I131: 31537466 | K131: Telefon ko'tarmadi | tel kotarmadi smsga jovob yozmadi telegramdan ham
A132: БУХОРО ВИЛОЯТИ | C132: Недозвон | D132: Кр-99031012-1 | E132: FARMONOVA GULCHEHRA MUSLIDDINOVNA | F132: 33-524-05-05 SMS O'ZI, 91-240-39-39 SMS ERI, 90-635-09-93 SMS ONASI, 50-884-90-24 SMS AKASI, 998914483333 SMS ELDOR , | G132: BUXORO VILOYATI G'IJDUVON TUMANI HAVZAK MFY, QATAG'AN KO'CHASI, 36-UY | H132: 18 | I132: 20000000 | K132: Telefon ko'tarmadi | tel uchiq uydilari kotarmayapti mahallasiga qldm ula aralawmimz dedi
A133: БУХОРО ВИЛОЯТИ | C133: Недозвон | D133: Кр-99063363-1 | E133: KOMILOVA ZEBO NURIDDINOVNA | F133: 998995031288 OZI, 998773127040 JIYANI, 998998621288 ONASI, 998770900005 DOSTI, | G133: BUXORO VILOYATI QORAKUL TUMANI XOJAKON MFY XUNARMANDLAR KO’CHASI 86-UY | H133: 11 | I133: 9752659.8 | K133: Telefon ko'tarmadi | ozi kotarmadi uydila blokka tqb qoywti relegram smsga javob yozmad
A134: БУХОРО ВИЛОЯТИ | C134: Недозвон | D134: Кр-99062884-1 | E134: MADIYEVA ISTAT RAVSHANOVNA | F134: +998997320621 SMS O’ZI, 998505742858 SMS O’G’LI, 998933080621 SMS KELINI, 998943960868 SMS QIZI, | G134: BUXORO VILOYATI JONDOR TUMANI ZARAFSHON MFY ZARAFSHON KO’CHASI 406-UY | H134: 8 | I134: 6912912.7 | K134: Telefon ko'tarmadi | xech kim kotarmadi bkokka tqb qoydi telegramdan yozdm atvet qmadi hali
A135: БУХОРО ВИЛОЯТИ | C135: Объезд | D135: Кр-99035221-3 | E135: SHUKUROV YUNUS UMAROVICH | F135: 998990297718 SMS O’ZI, 998996751234 SMS AYOLI, 998992231806 SMS QAYNONASI, 998992947718 SMS ONASI, | G135: Хужа Мушкин МФЙ, Алпомиш кучаси, 13/2-уй, 7-хонадон | H135: 8 | I135: 3784788.2 | K135: Uyiga borildi - va'da berdi | eri qamoqda xotini waroitm yoq tolov qlwga mowinani qayniopam ob qoygan qdiruvga berila dedi
A136: БУХОРО ВИЛОЯТИ | C136: Недозвон | D136: Кр-99027605-1 | E136: BARATOVA MAXFUZA TOLIBOVNA | F136: 97-084-88-33 sms O'ZI, 97-080-66-33 sms ERI, 99-775-20-70 sms QAYNI UKASI, 91-441-67-61 sms JIYANI, | G136: BUXORO VILOYATI, KOGON TUMANI, ISTIQBOL MFY, QOTONG'I q-q, 46-UY. | H136: 13 | I136: 3740803.6 | K136: Telefon ko'tarmadi | teli uchiq telegramdan yozdm atvet qmadi
A137: БУХОРО ВИЛОЯТИ | C137: Объезд | D137: Кр-99027688-2 | E137: HUSENOV BARNO HASANOVICH | F137: 94-003-53-53 sms O'ZI begana, 93-211-44-49 sms AYOLI, 93-558-53-33 sms O'G'LI, 50-720-12-44 sms QIZI, +998949965353 SMS O’ZI, 998507201244 SMS QIZI, 998932114449 SMS AYOLI, | G137: АРАБХОНА МФЙ, АРАБХОНА, | H137: 8 | I137: 2968080.1 | J137: 2968080.1 | K137: Uyiga borildi - to'ladi
A138: БУХОРО ВИЛОЯТИ | C138: Недозвон | D138: Кр-99027572-1 | E138: TO’YBOYEV BEHRUZ LUQMON O’G’LI | F138: 99-262-34-44 SMS O'ZI хоразимда харбий , 95-571-45-41 SMS XOTINI, 97-452-30-33 SMS DADASI, | G138: BUXORO VILOYATI G’IJDUVON TUMANI POZAGARI MAXALLASI XARCHXONA KUCHASI 133 UY | H138: 13 | I138: 2921973.6 | K138: Telefon ko'tarmadi | nomerlari xato telegramdan yozdm
A139: БУХОРО ВИЛОЯТИ | C139: Объезд | D139: Кр-99039770-1 | E139: SAFAROV SANJAR ADIZ O’G’LI | F139: 998912403939 SMS OZI TO'LOVCHI SHUNGA TEL QILINSIN, 998935133314 SMS AMAKISI, 998918225456 SMS OTASI, 998942432520 SMS ONASI, | G139: BUXORO VILOYATI BUXORO TUMANI GULSHANOBOD MFY LEYLAK QISHLOG'I 51-UY | H139: 8 | I139: 1736494.4 | K139: Uyiga borildi - va'da berdi
A140: БУХОРО ВИЛОЯТИ | C140: Недозвон | D140: Кр-99050700-1 | E140: OLIMOVA XADICHABONU MIRZOJAMSHID QIZI | F140: 998991477040 ozi, 998978549393 eri, 998952438448 onasi, 998936548228 opasi, | G140: BUXORO VILOYATI VOBKENT TUMANI | H140: 8 | I140: 666083.7 | K140: Telefon ko'tarmadi | hamma nomer xato kiritilgan
A141: БУХОРО ВИЛОЯТИ | C141: Объезд | D141: Кр-99039770-2 | E141: SAFAROV SANJAR ADIZ O’G’LI | F141: 998912403939 SMS OZI TO'LOVCHI SHUNGA TEL QILINSIN, 998935133314 SMS AMAKISI, 998918225456 SMS OTASI, 998942432520 SMS ONASI, | G141: BUXORO VILOYATI BUXORO TUMANI GULSHANOBOD MFY LEYLAK QISHLOG'I 51-UY | H141: 8 | I141: 58132.61 | K141: Uyiga borildi - va'da berdi
A142: ЖИЗЗАХ ВИЛОЯТИ | C142: Недозвон | D142: Кр-99046652-1 | E142: GENJEBAYEV MAKSETBAY REYMBAYEVICH | F142: +998919447218 SMS OZI , 998955395000 SMS HOTINI begona, 998972680202 SMS AKASI BEGONA, | G142: JIZZAX VILOYATI PAXTAKOR TUMANI DILOROM MFY NAVRUZ KUCHASI 1/15-UY | H142: 71 | I142: 26900901 | K142: Telefon ko'tarmadi
A143: ЖИЗЗАХ ВИЛОЯТИ | C143: Недозвон | D143: Кр-99025474-1 | E143: ABDULLAYEV ABDULAZIZ ABDUVAIT O’G’LI | F143: 97-789-92-05 SMS UZI , 88-517-95-05 SMS AYOLI , 97-608-08-98 SMS DUSTI , | G143: JIZZAX VILOYATI G’ALLAOROL TUMANI | H143: 18 | I143: 9294410.3 | K143: Telefon ko'tarmadi
A144: ЖИЗЗАХ ВИЛОЯТИ | C144: Недозвон | D144: Кр-99063460-1 | E144: AXMEDOV ALISHER KAMALOVICH | F144: 998991041481 AYOLI, 998993573881 UKASI, | G144: ШИРИН ҚФЙ, ШИРИН ҚФЙ, ҚУДУҚЧА ҚИШЛОҒИ, uy:Р.С | H144: 8 | I144: 8586667.4 | K144: Telefon ko'tarmadi
A145: ЖИЗЗАХ ВИЛОЯТИ | C145: Объезд | D145: Кр-99040635-1 | E145: JURAYEVA ZULAYXA LUTFULLAYEVNA | F145: 998915641958 SMS begona, 998938592525 SMS O`G`LI tolovchisi, 998943543086 SMS O`G`LI 2, 998931940082 SMS O`G`LI 3, 998943174556 SMS ONASI, 998932926008 Tolovchisini xotini, | G145: JIZZAX VILOYATI, DO’STLIK TUMANI, NAVRUZ MFY, IFTIXOR KUCHASI, 11-2 UY | H145: 41 | I145: 8093874.3 | K145: Uyiga borildi - va'da berdi
A146: ЖИЗЗАХ ВИЛОЯТИ | C146: Недозвон | D146: Кр-99036552-1 | E146: ALBEKOVA MUXABAT SAYLIYEVNA | F146: 998906437402 SMS TULOVCHI, 998884374488 SMS KUYOVI TOLOVCHI, 998905163139 SMS QIZI, 998915650972 SMS UZI, | G146: JIZZAX VILOYATI JIZZAX SHAHRI XAMID OLIMJON MFY QANGLI KUCHASI 18-UY | H146: 6 | I146: 7512709.3 | K146: Telefon ko'tarmadi | yorqin tema
A147: ЖИЗЗАХ ВИЛОЯТИ | C147: Объезд | D147: Кр-99036112-1 | E147: O’TASHEV RAVSHAN BOXTIYOR O’G’LI | F147: 998991037766 SMS OZI, 998946525295 SMS AKA TOLOVCHI, 998946738436 SMS AYOLI TOLOVCHI, 998944973835 SMS AYOLI, 998958735995 SMS TOLOVCHI, | G147: JIZZAX VILOYATI MIRZACHUL TUMANI PAXTAZOR SHFY BUNYODKOR KUCHASI 38-UY 2-XONADON | H147: 42 | I147: 6829564.9 | J147: 6829564.9 | K147: Uyiga borildi - to'ladi | mowin olingan
A148: ЖИЗЗАХ ВИЛОЯТИ | C148: Недозвон | D148: Кр-99033328-1 | E148: XOLBUTAYEV DILMUROD ABDUMALIKOVICH | F148: 998915680048 SMS O’ZI, 998994280048 SMS UKASI, 998990280048 SMS AYOLI BEGONA, 998900265356 SMS ONASI, | G148: JIZZAX VILOYATI ZOMIN TUMANI DASHTOBOD SHAXAR QORATEPA MFY SHIRIN KUCHASI | H148: 11 | I148: 6506790.9 | K148: Telefon ko'tarmadi
A149: ЖИЗЗАХ ВИЛОЯТИ | C149: Недозвон | D149: Кр-99063392-1 | E149: BERDIYAROV TO’RAMUROD XUDOYKULOVICH | F149: 998501568064 UZI, 998939931883 AYOLI, 998943438583 ONAS, | G149: БОГИШАМОЛ КФЙ, БОГИШАМОЛ КФЙ, МУГОЛ КИШЛОГИ, uy:РАКАМСИЗ | H149: 8 | I149: 6295100.6 | K149: Telefon ko'tarmadi
A150: ЖИЗЗАХ ВИЛОЯТИ | C150: Объезд | D150: Кр-99035257-1 | E150: ERGASHEV FARHOD RUSTAM O’G’LI | F150: 998902867999 SMS O’ZI, 998983002221 SMS BEGONA, 998988800454 SMS AKASI2, 998973261762 SMS Ayasi, 998995772760 sms dadasi begona , | G150: JIZZAX VILOYATI BAXMAL TUMANI USMAT SHAXARCHASI DO’STLIK MFY DO’STLIK KUCHASI 20-UY | H150: 1 | I150: 6261356.1 | K150: Uyiga borildi - va'da berdi
A151: ЖИЗЗАХ ВИЛОЯТИ | C151: Объезд | D151: Кр-99025603-3 | E151: AXMEDOVA MAXFUZA NIZOMIDDIN QIZI | F151: 94-340-56-52 SMS ERI TULOVCHI, 94-194-74-14 SMS ONASI, 94-572-25-30 SMS URTOGI, | G151: JIZZAX VILOYATI DO’STLIK TUMANI CHARAG’ON MANAS QFY 13-1 | H151: 120 | I151: 6223600.6 | K151: Uyiga borildi - va'da berdi | yorqin tema
A152: ЖИЗЗАХ ВИЛОЯТИ | C152: Объезд | D152: Кр-99040190-1 | E152: XODJIMURATOV MAMARAXIM USKANOVICH | F152: 998994798433 SMS OZI, 998992780316 SMS OZI NEW, 998773162199 SMS SINGLISI, 998990301519 SMS QIZI , 998773479799 SMS TO’LOVCHI, | G152: JIZZAX VILOYATI ZOMIN TUMANI NIHOL MFY YANGI OVUL QISHLOG’I 70-UY | H152: 8 | I152: 6042851.2 | K152: Uyiga borildi - va'da berdi | 20sigaca tulaydi
A153: ЖИЗЗАХ ВИЛОЯТИ | C153: Недозвон | D153: Кр-99005110-6 | E153: TURSUNOVA MAXBUBA OLIMJON KIZI | F153: 91-567-08-58 sms ukas tolovchi, 99-563-24-48 sms HO’JAYNI, 91-188-00-88 sms UKASI, 90-229-18-51 DADASI , 90-229-18-54 SMS UY, 90-025-93-95 SMS ONASI MAQSUDA, 998882955757 SMS TO’LOVCHI, 998880890111 uzi new, | G153: JIZZAX VILOYATI JIZZAX SHAHAR BUNYODKOR .M.F.Y YORQIN KO’CHASI 16-UY | H153: 12 | I153: 5486137.1 | K153: Telefon ko'tarmadi
A154: ЖИЗЗАХ ВИЛОЯТИ | C154: Объезд | D154: Кр-99030311-1 | E154: SHERANOV SHERZOD ZULFAROVICH | F154: 94-922-86-60 SMS O'ZI, 91-943-85-05 SMS O’ZI 2, 94-922-86-60 SMS UY, 93-304-52-56 SMS OTASI, | G154: JIZZAX VILOYATI ZARBDOR TUMANI DO’STLIK SHAXARCHASI SHODLIK MFY ISTIQBOL KUCHASI 43-UY | H154: 162 | I154: 5439016.6 | K154: Uyiga borildi - va'da berdi | yorqin tema
A155: ЖИЗЗАХ ВИЛОЯТИ | C155: Объезд | D155: Кр-99063375-1 | E155: AG’LAMOV AZIMXON AKRAM O’G’LI | F155: 998881511212 AKASI, 998915981212 AKASI, 998970105070 UZI, | G155: УЧАРИК МФЙ, ХАМЗАОБОД, ФИРДАВСИЙ, uy:9 | H155: 8 | I155: 5076077.1 | K155: Uyiga borildi
A156: ЖИЗЗАХ ВИЛОЯТИ | C156: Недозвон | D156: Кр-99028367-3 | E156: KARIMOV BOTIRJON RUZMATOVICH | F156: 91-564-03-10 SM S OZI, 91-591-45-24 SMS ATYOLI, 91-564-22-53 SMS QIZI, 95-996-66-77 sms sin, | G156: JIZZAX VILOYATI JIZZAX SHAHAR OBOD MFY FURQAT KUCHASI 28-UY | H156: 12 | I156: 4851421.4 | K156: Telefon ko'tarmadi
A157: ЖИЗЗАХ ВИЛОЯТИ | C157: Недозвон | D157: Кр-99042640-1 | E157: XO’JAQULOV FURQAT JAYNAROVICH | F157: +998771070575 SMS, 998932920870 SMS, 998990343029 SMS, | G157: JIZZAX VILOYATI ZAFAROBOD TUMANI BIRLIK QFY RUDAKIY KUCHASI 4-A UY | H157: 8 | I157: 4631446.2 | K157: Telefon ko'tarmadi
A158: ЖИЗЗАХ ВИЛОЯТИ | C158: Недозвон | D158: Кр-99063358-1 | E158: TURAKULOVA DILRABO KARIMOVNA | F158: 998888926464 UY, 998918951189 UZI, 998985611189 ERI, | G158: JIZZAX VILOYATI JIZZAX SHAHRI OBOD MFY MINORLI KUCHASI 126B-UY | H158: 8 | I158: 4212139.5 | K158: Telefon ko'tarmadi
A159: ЖИЗЗАХ ВИЛОЯТИ | C159: Недозвон | D159: Кр-99042221-2 | E159: MAMATQOSIMOV DOSTONJON YUSUF O’G’LI | F159: +998919420024 SMS, 998911963666 SMS, 998919430024 SMS, | G159: JIZZAX VILOYATI JIZZAX SHAHRI ULUG’BEK MFY SHIRIN KUCHASI 16/2-UY | H159: 8 | I159: 4005048.2 | K159: Telefon ko'tarmadi
... A174: ЖИЗЗАХ ВИЛОЯТИ | C174: Недозвон | D174: Кр-99038736-1 | E174: ARZIKULOV SOBIRJON BAXTIYOR O’G’LI | F174: 998940337077 SMS OZI, 998332952405 SMS DADASI, 998904951880 SMS ONASI, 998772679767 SMS UKASI, | G174: JIZZAX VILOYATI JIZZAX SHAHAR NAVRUZ MFY UZBEKISTAN KUCHASI 38-UY | H174: 7 | I174: 1741305 | K174: Telefon ko'tarmadi
A175: ЖИЗЗАХ ВИЛОЯТИ | C175: Недозвон | D175: Кр-99063112-1 | E175: USANOVA FOTIMA ABDURASHIDOVNA | F175: +998915026065 SMS OZI, 998700113077 KATTA O’G’LI, 998881459555 O’RTANCHA O’G’LI, | G175: BAXMAL TUMANI | I175: 1648406.6 | K175: Telefon ko'tarmadi
A176: ЖИЗЗАХ ВИЛОЯТИ | C176: Недозвон | D176: Кр-99026372-3 | E176: ARIPOV FAXRIDDIN JO’MANOVICH | F176: 94-138-50-20 SMS UZI , 91-209-90-77 SMS UZI, 94-001-51-35 SMS UY, 91-028-70-28 SMS AYOLI, | G176: JIZZAX VILOYATI MARJONBULOQ SHMB LALMIKOR MFY NAVRO’Z MAHALLASI 60-UY | H176: 8 | I176: 1497109.9 | K176: Telefon ko'tarmadi
A177: ЖИЗЗАХ ВИЛОЯТИ | C177: Недозвон | D177: Кр-99052917-1 | E177: ABDUALIMOV OZODJON ABDURAXIM O’G’LI | F177: 998911972123 SMS OZI, 998915681200 SMS AYOLI, 999156813002 SMS OZI 2, | G177: JIZZAX VILOYATI JIZZAX SHAHRI OQQURG'ONLIK MAHALLASI YU SALIMOV KUCHASI 70-UY | H177: 8 | I177: 1470294.8 | K177: Telefon ko'tarmadi
A178: ЖИЗЗАХ ВИЛОЯТИ | C178: Недозвон | D178: Кр-99044129-3 | E178: ANORBOYEV RABBIM QURBONOVICH | F178: +998911993133 SMS, 998915963134 SMS, 998918038686 SMS, | G178: JIZZAX VILOYATI JIZZAX SHAHRI ITTIFOQ MFY ITTIFOQ KUCHASI 36/30 - UY | H178: 11 | I178: 1407232.7 | K178: Telefon ko'tarmadi
A179: ЖИЗЗАХ ВИЛОЯТИ | C179: Объезд | D179: Кр-99030311-2 | E179: SHERANOV SHERZOD ZULFAROVICH | F179: 94-922-86-60 SMS O'ZI, 91-943-85-05 SMS O’ZI 2, 94-922-86-60 SMS UY, 93-304-52-56 SMS OTASI, | G179: JIZZAX VILOYATI ZARBDOR TUMANI DO’STLIK SHAXARCHASI SHODLIK MFY ISTIQBOL KUCHASI 43-UY | H179: 13 | I179: 1356589.8 | K179: Uyiga borildi - va'da berdi | yorqin tema
A180: ЖИЗЗАХ ВИЛОЯТИ | C180: Недозвон | D180: Кр-99041781-2 | E180: NORYIGITOV SAMANDAR O’TKIR O’G’LI | F180: +998997654666 SMS, 998973271427 SMS, 998990654666 SMS, | G180: JIZZAX VILOYATI YANGIOBOD TUMANI BALANDCHAQIR MFY MUSTAQILLIK SHOX KUCHASI 159-UY | H180: 8 | I180: 1337496.8 | K180: Telefon ko'tarmadi
A181: ЖИЗЗАХ ВИЛОЯТИ | C181: Недозвон | D181: Кр-99052995-1 | E181: JUMANOVA SHAYDO JONIQUL QIZI | F181: 998505100392 SMS ERI, 998933016150 SMS QAYNIONASI, | G181: JIZZAX VILOYATI SHAROF RASHIDOV TUMANI UMAR MAHALLASI KITOBXONLAR KUCHASI 59-UY | H181: 8 | I181: 1089859.5 | K181: Telefon ko'tarmadi
A182: ЖИЗЗАХ ВИЛОЯТИ | C182: Недозвон | D182: Кр-99013395-5 | E182: MUSAYEV BUNYOD KUDRATOVICH | F182: 97-527-01-28 SMS OZI (нотогри мижоз), 90-539-79-79 SMS OZI, 72-222-07-98 SMS ISHHONA, 91-209-34-34 SMS UKASI, | G182: JIZZAX VILOYATI JIZZAX SHAHAR TINCHLIK MFY SHEROBOD KUCHASI 9B-UY | H182: 8 | I182: 639758.78 | K182: XOLDAROV BAXTIYOR ALIM O’G’LI
A183: ЖИЗЗАХ ВИЛОЯТИ | C183: Недозвон | D183: Кр-99009799-7 | E183: ORTIQBOYEV SHAROF BAXRIDDIN O’G’LI | F183: 99-054-66-66 SMS UZI, 99-600-55-88 SMS ONASI begana , 99-054-66-66 SMS , 99-243-45-40 SMS AKASI begona, 998990526339 SMS SHAROF O’ZI, | G183: JIZZAX VILOYATI ZOMIN TUMANI BESHKUBI QFY BESHKUBI QISHLOG’I 7-UY | H183: 13 | I183: 518822.05 | K183: Telefon ko'tarmadi
A184: ЖИЗЗАХ ВИЛОЯТИ | C184: Недозвон | D184: Кр-99040853-1 | E184: USMANOV AZIZBEK MIRZABEK O’G’LI | F184: +998885222554 SMS OZI, 998880940530 SMS AYOLI, 998936250078 SMS tulovchi, | G184: Шодлик МФЙ, Кудук қишлоғи, 17/А-уй | H184: 8 | I184: 179205.01 | K184: Telefon ko'tarmadi
A185: ЖИЗЗАХ ВИЛОЯТИ | C185: Недозвон | D185: Кр-99031648-2 | E185: ABDULLAYEV JAVLONBEK ABDUMO’MIN O’G’LI | F185: 998990935493 SMS O’ZI, 998904995493 SMS AYOLI, 998991232675 SMS ONASI, 998915904820 SMS TOLOVCHI DADASI, | G185: JIZZAX VILOYATI ZOMIN TUMANI BUNYODKOR MFY DO’STOBOD KUCHASI 25-UY | H185: 13 | I185: 84159.19 | K185: Telefon ko'tarmadi
A186: КАШКАДАРЁ ВИЛОЯТИ | C186: Недозвон | D186: Кр-99040472-1 | E186: SHAXAROVA SHAXRIZODA FARXOD QIZI | F186: 998886727122 SMS OZI BEGONA, 998970809786 SMS AKASI, 998995850151 SMS OZI , 998945228482 SMS ZALOGADATEL , 998912120151 SMS NEW UZI , | G186: ЧУМИЧЛИ МФЙ, ЧУМИЧЛИ КИШЛОГИ, uy:Р/С | H186: 181 | I186: 42537374
A187: КАШКАДАРЁ ВИЛОЯТИ | C187: Недозвон | D187: Кр-99040100-1 | E187: KUDRATOV SANJAR DJURAYEVICH | F187: 998880634212 SMS OZI, 998970700407 SMS OILASI (BEGONA), 998972000300 SMS UKASI, 998996750200 SMS AKASI, 998972000300 uzi, | G187: QASHQADARYO VILOYATI QARSHI TUMANI TINCHLIK MFY, PARMITON QISHLOG’I 33-UY | H187: 11 | I187: 10058601
A188: КАШКАДАРЁ ВИЛОЯТИ | C188: Недозвон | D188: Кр-99038157-1 | E188: JUMAYEV ERNAZAR IBRAGIMOVICH | F188: 998973170009 SMS OZI BEGONA, 998972259900 SMS UKASI, 998882209990 SMS OTASI, 998973109990 SMS AKASI UZIII, | G188: QASHQADARYO VILOYATI MUBORAK TUMANI ISTIQLOL MFY NEFTCHILAR KUCHASI 1-32 UY | H188: 1 | I188: 7515687.1
A189: КАШКАДАРЁ ВИЛОЯТИ | C189: Недозвон | D189: Кр-99039828-1 | E189: BEGIMOV OBIDJON O’DILOVICH | F189: 998946151222 SMS OZI, 998887592404 SMS TOLOVCHI, 998959612802 SMS DADASI, 998977552404 SMS ONASI, | G189: QASHQADARYO VILOYATI QARSHI TUMANI KAT MFY CHORGUMBAZ QISHLOG’I YOSHLAR KUCHASI 19-UY | H189: 8 | I189: 6946986.4
A190: КАШКАДАРЁ ВИЛОЯТИ | C190: Недозвон | D190: Кр-99039293-1 | E190: NORBUTAYEVA YULDUZXON BAXTIYAROVNA | F190: 998973137733 SMS OZI, 998908668282 SMS OZI, 998993308084 SMS OILASI, | G190: QASHQADARYO VILOYATI QAMASHI TUMANI ZAFAR MFY IFTIXOR KO’CHASI 1/1-UY 21-XONADON | H190: 8 | I190: 5285333.3
A191: КАШКАДАРЁ ВИЛОЯТИ | C191: Недозвон | D191: Кр-99040420-1 | E191: ESHBO’RIYEV BOYMIRZA FARMON O’G’LI | F191: 998972221232 SMS OZI, 998990218033 SMS AKASI UZIIII, 998972966323 SMS OSHNASI, | G191: QASHQADARYO VILOYATI QARSHI TUMANI MUSTAQILLIK MFY KAMOLOT KO’CHASI 34-UY | H191: 8 | I191: 5099964.3
A192: КАШКАДАРЁ ВИЛОЯТИ | C192: Недозвон | D192: Кр-99039701-1 | E192: AXMADOV RAXMATJON ISKANDAR O’G’LI | F192: 999886758088 SMS OZI, 998973140057 SMS AKASI, 998973160057 SMS AKASI 2, 998886788088 SMS UZI NEW TO'LOVCHI , 998992130365 SMS AKASI Shahriyor, | G192: QASHQADARYO VILOYATI MIRISHKOR TUMANI GULISTON MFY XAMZA KUCHASI 34-UY | H192: 8 | I192: 5079894.7
A193: КАШКАДАРЁ ВИЛОЯТИ | C193: Недозвон | D193: Кр-99037316-1 | E193: XAMROYEVA DILRABO KUYLIYEVNA | F193: 998908819972 SMS OZI, 998906606361 SMS ONASI BEGONA QIZCHA, 998906851166 SMS OTASI, 998906831166 SMS AKASI (UZIII), | G193: QASHQADARYO VILOYATI QARSHI TUMANI NAVRUZ MFY BOBUR KUCHASI 16-UY | H193: 5 | I193: 4162035.4
A194: КАШКАДАРЁ ВИЛОЯТИ | C194: Недозвон | D194: Кр-99037284-1 | E194: XUDOYBERDIYEV SOBIRJON SODIQ O‘G‘LI | F194: 998977999498 SMS OZI бегона бич , 998912257806 SMS UKASI, 998906788694 SMS OILASI, 998914585278 SMS AKASI, +998914585278 Primary phone from road24, | G194: Кашкадарьинская область, Шахрисабзский район, Мироқи МФЙ, ул. Х Шукуров, дом 39 | H194: 6 | I194: 3536650.5
A195: КАШКАДАРЁ ВИЛОЯТИ | C195: Недозвон | D195: Кр-99040697-1 | E195: AMONOV JONIBEK IBODOVICH | F195: 998884250760 OTASI, 998919499191 AKASI, 998999432528 SMS UZI, 998933553606 SMS O'ZI TO'LOVCHI , 998987755060 SMS AMAKISI, | G195: АРАБХОНА МФЙ, Б.НАКШБАНДИЙ КЎЧАСИ, uy:Р/С | H195: 8 | I195: 3350497.6
A196: КАШКАДАРЁ ВИЛОЯТИ | C196: Недозвон | D196: Кр-99037441-4 | E196: KOSIMOV ABROR ABDISALOMOVICH | F196: 998887417117 SMS OZI, 998905175558 SMS AKASI BEGONA, 998941729897 SMS JURASI, | G196: QASHQADARYO VILOYATI G’UZOR TUMANI TINCHLIK MFY YANGI TONG KO’CHASI 765-UY | H196: 8 | I196: 3298891.1
A197: КАШКАДАРЁ ВИЛОЯТИ | C197: Недозвон | D197: Кр-99037888-1 | E197: BOLTAYEVA ZUHRA AHMAD QIZI | F197: 998945290771 SMS OZI, 998914576968 SMS SINGLISI BEGONA, 998932700506 SMS OPASI, 998944590080 SMS AKASI UZIII, | G197: QASHQADARYO VILOYATI MUBORAK TUMANI YOSHLIK MFY MR-N 2, 1/2 DOM 29 KVARTIRA | H197: 7 | I197: 3146847.5
... A215: КАШКАДАРЁ ВИЛОЯТИ | C215: Недозвон | D215: Кр-99038701-1 | E215: MAMATQULOVA MAFTUNA AZAMAT QIZI | F215: 998910740201 SMS OZI BEGONA, 998939024242 SMS AYOLI, 998914723980 SMS DADASI, 998918110201 SMS ONASI BEGONA, | G215: QASHQADARYO VILOYATI QARSHI SHAHAR KARLUK-BOGOT MFY AT-TERMIZIY KUCHASI 21 UY | H215: 6 | I215: 1282362.2
A216: КАШКАДАРЁ ВИЛОЯТИ | C216: Недозвон | D216: Кр-99040255-1 | E216: TO’RAYEVA INTIZOR HUSAN QIZI | F216: 998991985752 SMS OZI, 998976701098 SMS AYOLI, 998995078900 SMS DADASI, 998915004348 узи , | G216: QASHQADARYO VILOYATI KASBI TUMANI MIRZO ULUG’BEK MFY BAYDOQCHI QISHLOG’I ABDULLA ORIPOV KUCHASI 5-UY | I216: 1156874.1
A217: КАШКАДАРЁ ВИЛОЯТИ | C217: Недозвон | D217: Кр-99038978-3 | E217: ATAQULOV FERUZ JURABEK O’G’LI | F217: 998953853414 SMS OZI, 998990155371 SMS AYOLI BEGONA, 998991020088 SMS UYI, 998992381515 SMS AKASI, 998880003026 SMS OZI, 998951470012 UZI, | G217: Кашкадарьинская область, г. Карши, Арабхона МФЙ, ул. Мугжагул, дом 49 | H217: 8 | I217: 955756.32
A218: КАШКАДАРЁ ВИЛОЯТИ | C218: Недозвон | D218: Кр-99039600-1 | E218: SAFAROV JAMSHIDBEK HASAN O’G’LI | F218: 998770752671 SMS OZI, 999877859596 SMS TOLOVCHI, 998777859695 SMS TOLOVCHIN AYOLI, 998901671013 SMS UY, | G218: QASHQADARYO VILOYATI QAMASHI TUMANI QOLCHIN QFY 46 UY | H218: 1 | I218: 867618.93
A219: КАШКАДАРЁ ВИЛОЯТИ | C219: Недозвон | D219: Кр-99040396-1 | E219: KENJAYEV OTABEK ABDIRAXIM O’G’LI | F219: 998975897577 SMS OZI (BEGONA), 998990482034 SMS UKASI, 998770612003 SMS DADASI, | G219: QASHQADARYO VILOYATI SHAXRISABZ TUMANI OQ OLTIN MFY ANDAY KUCHASI 62-UY | H219: 8 | I219: 786401.12
...

Sheet Объезд
A1: ← Вернуться в отчёт
A2: Область | B2: Филиал | C2: Группа | D2: Код клиента | E2: Клиент | F2: Номер телефона | G2: Адрес | H2: Кол-во просроченных дней | I2: Итого просрочка | J2: Оплата | K2: Izoh
A3: БУХОРО ВИЛОЯТИ | C3: Объезд | D3: Кр-99035221-3 | E3: SHUKUROV YUNUS UMAROVICH | F3: 998990297718 SMS O’ZI, 998996751234 SMS AYOLI, 998992231806 SMS QAYNONASI, 998992947718 SMS ONASI, | G3: Хужа Мушкин МФЙ, Алпомиш кучаси, 13/2-уй, 7-хонадон | H3: 8 | I3: 3784788.2 | K3: Uyiga borildi - va'da berdi | eri qamoqda xotini waroitm yoq tolov qlwga mowinani qayniopam ob qoygan qdiruvga berila dedi
A4: БУХОРО ВИЛОЯТИ | C4: Объезд | D4: Кр-99027688-2 | E4: HUSENOV BARNO HASANOVICH | F4: 94-003-53-53 sms O'ZI begana, 93-211-44-49 sms AYOLI, 93-558-53-33 sms O'G'LI, 50-720-12-44 sms QIZI, +998949965353 SMS O’ZI, 998507201244 SMS QIZI, 998932114449 SMS AYOLI, | G4: АРАБХОНА МФЙ, АРАБХОНА, | H4: 8 | I4: 2968080.1 | J4: 2968080.1 | K4: Uyiga borildi - to'ladi
A5: БУХОРО ВИЛОЯТИ | C5: Объезд | D5: Кр-99039770-1 | E5: SAFAROV SANJAR ADIZ O’G’LI | F5: 998912403939 SMS OZI TO'LOVCHI SHUNGA TEL QILINSIN, 998935133314 SMS AMAKISI, 998918225456 SMS OTASI, 998942432520 SMS ONASI, | G5: BUXORO VILOYATI BUXORO TUMANI GULSHANOBOD MFY LEYLAK QISHLOG'I 51-UY | H5: 8 | I5: 1736494.4 | K5: Uyiga borildi - va'da berdi
A6: БУХОРО ВИЛОЯТИ | C6: Объезд | D6: Кр-99039770-2 | E6: SAFAROV SANJAR ADIZ O’G’LI | F6: 998912403939 SMS OZI TO'LOVCHI SHUNGA TEL QILINSIN, 998935133314 SMS AMAKISI, 998918225456 SMS OTASI, 998942432520 SMS ONASI, | G6: BUXORO VILOYATI BUXORO TUMANI GULSHANOBOD MFY LEYLAK QISHLOG'I 51-UY | H6: 8 | I6: 58132.61 | K6: Uyiga borildi - va'da berdi
A7: ЖИЗЗАХ ВИЛОЯТИ | C7: Объезд | D7: Кр-99040635-1 | E7: JURAYEVA ZULAYXA LUTFULLAYEVNA | F7: 998915641958 SMS begona, 998938592525 SMS O`G`LI tolovchisi, 998943543086 SMS O`G`LI 2, 998931940082 SMS O`G`LI 3, 998943174556 SMS ONASI, 998932926008 Tolovchisini xotini, | G7: JIZZAX VILOYATI, DO’STLIK TUMANI, NAVRUZ MFY, IFTIXOR KUCHASI, 11-2 UY | H7: 41 | I7: 8093874.3 | K7: Uyiga borildi - va'da berdi
A8: ЖИЗЗАХ ВИЛОЯТИ | C8: Объезд | D8: Кр-99036112-1 | E8: O’TASHEV RAVSHAN BOXTIYOR O’G’LI | F8: 998991037766 SMS OZI, 998946525295 SMS AKA TOLOVCHI, 998946738436 SMS AYOLI TOLOVCHI, 998944973835 SMS AYOLI, 998958735995 SMS TOLOVCHI, | G8: JIZZAX VILOYATI MIRZACHUL TUMANI PAXTAZOR SHFY BUNYODKOR KUCHASI 38-UY 2-XONADON | H8: 42 | I8: 6829564.9 | J8: 6829564.9 | K8: Uyiga borildi - to'ladi | mowin olingan
A9: ЖИЗЗАХ ВИЛОЯТИ | C9: Объезд | D9: Кр-99035257-1 | E9: ERGASHEV FARHOD RUSTAM O’G’LI | F9: 998902867999 SMS O’ZI, 998983002221 SMS BEGONA, 998988800454 SMS AKASI2, 998973261762 SMS Ayasi, 998995772760 sms dadasi begona , | G9: JIZZAX VILOYATI BAXMAL TUMANI USMAT SHAXARCHASI DO’STLIK MFY DO’STLIK KUCHASI 20-UY | H9: 1 | I9: 6261356.1 | K9: Uyiga borildi - va'da berdi
A10: ЖИЗЗАХ ВИЛОЯТИ | C10: Объезд | D10: Кр-99025603-3 | E10: AXMEDOVA MAXFUZA NIZOMIDDIN QIZI | F10: 94-340-56-52 SMS ERI TULOVCHI, 94-194-74-14 SMS ONASI, 94-572-25-30 SMS URTOGI, | G10: JIZZAX VILOYATI DO’STLIK TUMANI CHARAG’ON MANAS QFY 13-1 | H10: 120 | I10: 6223600.6 | K10: Uyiga borildi - va'da berdi | yorqin tema
A11: ЖИЗЗАХ ВИЛОЯТИ | C11: Объезд | D11: Кр-99040190-1 | E11: XODJIMURATOV MAMARAXIM USKANOVICH | F11: 998994798433 SMS OZI, 998992780316 SMS OZI NEW, 998773162199 SMS SINGLISI, 998990301519 SMS QIZI , 998773479799 SMS TO’LOVCHI, | G11: JIZZAX VILOYATI ZOMIN TUMANI NIHOL MFY YANGI OVUL QISHLOG’I 70-UY | H11: 8 | I11: 6042851.2 | K11: Uyiga borildi - va'da berdi | 20sigaca tulaydi
A12: ЖИЗЗАХ ВИЛОЯТИ | C12: Объезд | D12: Кр-99030311-1 | E12: SHERANOV SHERZOD ZULFAROVICH | F12: 94-922-86-60 SMS O'ZI, 91-943-85-05 SMS O’ZI 2, 94-922-86-60 SMS UY, 93-304-52-56 SMS OTASI, | G12: JIZZAX VILOYATI ZARBDOR TUMANI DO’STLIK SHAXARCHASI SHODLIK MFY ISTIQBOL KUCHASI 43-UY | H12: 162 | I12: 5439016.6 | K12: Uyiga borildi - va'da berdi | yorqin tema
A13: ЖИЗЗАХ ВИЛОЯТИ | C13: Объезд | D13: Кр-99063375-1 | E13: AG’LAMOV AZIMXON AKRAM O’G’LI | F13: 998881511212 AKASI, 998915981212 AKASI, 998970105070 UZI, | G13: УЧАРИК МФЙ, ХАМЗАОБОД, ФИРДАВСИЙ, uy:9 | H13: 8 | I13: 5076077.1 | K13: Uyiga borildi
A14: ЖИЗЗАХ ВИЛОЯТИ | C14: Объезд | D14: Кр-99030311-2 | E14: SHERANOV SHERZOD ZULFAROVICH | F14: 94-922-86-60 SMS O'ZI, 91-943-85-05 SMS O’ZI 2, 94-922-86-60 SMS UY, 93-304-52-56 SMS OTASI, | G14: JIZZAX VILOYATI ZARBDOR TUMANI DO’STLIK SHAXARCHASI SHODLIK MFY ISTIQBOL KUCHASI 43-UY | H14: 13 | I14: 1356589.8 | K14: Uyiga borildi - va'da berdi | yorqin tema
A15: КАШКАДАРЁ ВИЛОЯТИ | B15: SUPER BRANCH | C15: Объезд | D15: Кр-99035525-2 | E15: RO’ZIYEV AZIZJON FARXODOVICH | F15: 998903545851 SMS OZI , 998909434667 SMS AYOLI, 998973422225 SMS UKASI, 998717546462 SMS UKASI, | G15: QASHQADARYO VILOYATI SHAHRISABZ SHAHRI KATTACHUTON KO’CHASI 27-UY | H15: 8 | I15: 9773181.8 | K15: Uyiga borildi - va'da berdi
A16: КАШКАДАРЁ ВИЛОЯТИ | B16: SUPER BRANCH | C16: Объезд | D16: Кр-99041785-1 | E16: ABDIRAXMONOV USMON FARMON O’G’LI | F16: 998997194818 SMS OZI, 998919101910 SMS DOSTI, 998930724818 SMS UYI, | G16: QASHQADARYO VILOYATI QARSHI TUMANI ROVOT MFY S.NASAFIY KO’CHASI 85-UY | H16: 8 | I16: 4260208.2 | J16: 4260208.2 | K16: Uyiga borildi - to'ladi
A17: КАШКАДАРЁ ВИЛОЯТИ | B17: SUPER BRANCH | C17: Объезд | D17: Кр-99039445-1 | E17: MIRZAMURODOV SHOXRUZBEK DAVRON O’G’LI | F17: +998873999404 SMS O’ZI, 998888818005 SMS DOSTI, 998959006035 SMS DOSTI, 998990855744 UZI NEWW, | G17: Чувуллоқ МФЙ, Миллий хунармандлар кучаси, 86-уй | H17: 7 | I17: 4238092.9 | K17: Uyiga borildi - va'da berdi
A18: КАШКАДАРЁ ВИЛОЯТИ | B18: SUPER BRANCH | C18: Объезд | D18: Кр-99038081-1 | E18: ASHUROV MIRZA URALOVICH | F18: 998987750515 SMS OZI, 998880042215 SMS O’G’LI, 998906699171 SMS O’G’LI, 998972747000 SMS UKASI, | G18: QASHQADARYO VILOYATI QARSHI SHAHAR GUNGON MFY MUSA JALIL KUCHASI 48-UY | H18: 1 | I18: 3728488.9 | K18: Uyiga borildi - va'da berdi
A19: КАШКАДАРЁ ВИЛОЯТИ | B19: SUPER BRANCH | C19: Объезд | D19: Кр-99038818-4 | E19: AZIZOV ZAKIR TASHAROVICH | F19: 998992562088 SMS O’ZI, 998770306222 SMS O’G’LI, 998972226222 SMS UY BEGONAA, 998771003949 SMS O'ZI, | G19: КУРГОНЧА МФЙ, ТОР КЎЧАСИ, uy:28 | H19: 8 | I19: 3413704.5 | K19: Uyiga borildi - va'da berdi
A20: КАШКАДАРЁ ВИЛОЯТИ | B20: SUPER BRANCH | C20: Объезд | D20: Кр-99040370-1 | E20: AZIMOV HASAN G’AYRAT O’G’LI | F20: 998979514900 SMS OZI (BEGONA))), 998880073012 SMS AKASI (HAMKASBI), 998973863606 SMS DADASI (BEGONA), 998973183000 SMS DADASI UZIIII, | G20: QASHQADARYO VILOYATI SHAXRISABZ TUMANI LOLISTON MFY PAXTAKOR QISHLOG’I XISOR KUCHASI 45-UY | H20: 8 | I20: 3252149.3 | K20: Uyiga borildi - va'da berdi
A21: КАШКАДАРЁ ВИЛОЯТИ | B21: SUPER BRANCH | C21: Объезд | D21: Кр-99040694-2 | E21: TOSHPULATOV SHAHRIYOR XOLMUROD O’G’LI | F21: 998932061021 AKASI, 998952622787 UKASI, | G21: ОЛМАЗОР МФЙ, УЧТУТ, uy:Р/С | H21: 8 | I21: 3076095.6 | K21: Uyiga borildi - va'da berdi
A22: КАШКАДАРЁ ВИЛОЯТИ | B22: SUPER BRANCH | C22: Объезд | D22: Кр-99062619-1 | E22: QURBANOV BAXODIR JURAYEVICH | F22: 998940074848 узи, 998908819989 аели, 998913206851 дадаси, 998919624032 онаси, | G22: QASHQADARYO VILOYATI MUBORAK TUMANI BOBUR MFY BOBUR KUCHASI 1-UY 27-XONADON | H22: 8 | I22: 2852315.9 | J22: 2852315.9 | K22: Uyiga borildi - to'ladi
A23: КАШКАДАРЁ ВИЛОЯТИ | B23: SUPER BRANCH | C23: Объезд | D23: Кр-99040698-2 | E23: TOG’AYEV SHUHRAT NOSIROVICH | F23: 998900129666 o’g’li, 998940129666 ukasi, 998946700174 uzi new, | G23: АЛАЧАБОБ МФЙ, АЛАТУН, uy:Р/С | H23: 8 | I23: 2780111.8 | K23: Uyiga borildi - va'da berdi
A24: КАШКАДАРЁ ВИЛОЯТИ | B24: SUPER BRANCH | C24: Объезд | D24: Кр-99037164-1 | E24: IMOMOV FAYZULLA PARDAYEVICH | F24: 998919553110 SMS OZI, 998807931102 SMS OZI 2, 998906672203 SMS OILASI, 998889883110 SMS O’G’LI, | G24: QASHQADARYO VILOYATI YAKKABOG’ TUMANI SEROB MFY MINJIR QISHLOQI | H24: 11 | I24: 2174707.6 | K24: Uyiga borildi - va'da berdi
A25: КАШКАДАРЁ ВИЛОЯТИ | B25: SUPER BRANCH | C25: Объезд | D25: Кр-99037085-2 | E25: XAMRAYEVA GULNORA XURRAMOVNA | F25: 998979549700 SMS OZI (OG'LI) XUSAN, 998881941597 SMS O’G’LI, 998884287278 SMS UKASI (UZI), 998886757572 SMS AKASI, | G25: QASHQADARYO VILOYATI QARSHI TUMANI MEVAZOR MFY NAVRUZ QURG’ONI SHAHARCHASI 67/1 UY | H25: 8 | I25: 1943012.6 | K25: Uyiga borildi - va'da berdi | birorta nomeri ishlamayapti sms yozvordim
A26: КАШКАДАРЁ ВИЛОЯТИ | B26: SUPER BRANCH | C26: Объезд | D26: Кр-99037055-2 | E26: ISKANDAROV NURIDDIN NIZOMIDDIN O’G’LI | F26: 998881202280 SMS O’ZI, 998507104532 SMS OZI 2, 998880485080 SMS OSHNASI, 998200030241 SMS OSHNASI (begona), | G26: QASHQADARYO VILOYATI SHAHRISABZ TUMANI QUTCHI MFY,GULZOR KO’CHASI 80-UY | H26: 12 | I26: 1422441.4 | K26: Uyiga borildi - va'da berdi
A27: КАШКАДАРЁ ВИЛОЯТИ | B27: SUPER BRANCH | C27: Объезд | D27: Кр-99037316-2 | E27: XAMROYEVA DILRABO KUYLIYEVNA | F27: 998908819972 SMS OZI, 998906606361 SMS ONASI BEGONA QIZCHA, 998906851166 SMS OTASI, 998906831166 SMS AKASI (UZIII), | G27: QASHQADARYO VILOYATI QARSHI TUMANI NAVRUZ MFY BOBUR KUCHASI 16-UY | H27: 8 | I27: 1274783.3 | K27: Uyiga borildi - va'da berdi
A28: КАШКАДАРЁ ВИЛОЯТИ | B28: SUPER BRANCH | C28: Объезд | D28: Кр-99034450-3 | E28: MAHMATQOBILOV ELBEK PULAT O’G’LI | F28: 998957714245 SMS O’ZI, 998505882555 SMS DO’STI, 998934943260 SMS AYOLI, 998958830199 SMS OTASI, | G28: ЧАМБИЛ МФЙ, ОКЧОВА, uy:83. | H28: 8 | I28: 21815.95 | J28: 21815.95 | K28: Uyiga borildi - to'ladi
A29: КАШКАДАРЁ ВИЛОЯТИ | B29: Қарши филиали | C29: Объезд | D29: Кр-99041022-1 | E29: G’AFFOROV IXTIYOR UMAROVICH | F29: +998939071026 O’ZI, 998912275852 O’G’LI, 998947846809 OILASI, | G29: СЕВАЗ МФЙ, САРИОСИЁ ҚИШЛОҒИ, uy:Р/С | H29: 12 | I29: 3582105.3 | K29: Uyiga borildi - va'da berdi
A30: КАШКАДАРЁ ВИЛОЯТИ | B30: Қарши филиали | C30: Объезд | D30: Кр-99041223-1 | E30: ERMUMINOVA GULISTON YAKUBOVNA | F30: +998958859893 UZI, 998915604344 UKASI, 998973930817 ERI, 998973830817 SMS , | G30: КАШКАДАРЁ ВИЛОЯТИ ГУЗОР ТУМАНИ Пахтазор МФЙ, Лолазор қишлоғи, 980-уй | H30: 8 | I30: 2634597 | K30: Uyiga borildi - va'da berdi
A31: КАШКАДАРЁ ВИЛОЯТИ | B31: Қарши филиали | C31: Объезд | D31: Кр-99029105-1 | E31: MAHMUDOV OLIM OTAQULOVICH | F31: 95-178-02-25 SMS OZI TULOVCHISI, 99-152-62-55 SMS ONASI, 97-803-97-77 SMS AYOLI, 97-743-33-66 SMS ZALOGADATEL, 98-366-82-72 SMS ZALOGADATEL, 998777420100 UZI NEWW, | G31: QASHQADARYO VILOYATI QARSHI TUMANI CHAROG'ON QFY 33-UY | H31: 12 | I31: 1223525.7 | J31: 1223525.7 | K31: Uyiga borildi - to'ladi
A32: КОРАКАЛПОГИСТОН РЕСПУБЛИКАСИ | C32: Объезд | D32: Кр-99060325-1 | E32: SABIROVA NAZOKAT ORAZBAEVNA | F32: 998972205225 узи, 998913829870 аели, 998887555225 кизи, 998882552552 кизи, | G32: QORAQALPOGISTON RES NUKUS SHAHAR NAUBAXAR MFY NAUKANSHILAR KUSHASI 18 UY | H32: 102 | I32: 61887850 | K32: uyiga borildi MIBGA CHIQARILDI UYINI OLIB QO'YISHADI | 1518 | Telefon ko'tarmadi
A33: КОРАКАЛПОГИСТОН РЕСПУБЛИКАСИ | C33: Объезд | D33: Кр-99056113-1 | E33: TAJIMURATOVA NASIBA JUMAMBETOVNA | F33: 998959469019 SMS OZI , 998880042678 SMS OZI 2, 998902625683 SMS OZI 3, | G33: QARAQALPOGISTON RES NUKUS SHAHAR DOSLIQ GUZARI MFY A.DOSNAZAROV KUSHASI 131 UY 28 KVARTIRA | H33: 8 | I33: 5902766 | K33: AKASI BN GAPLASJDIM 20KUNI TO'LAYMAN UNDAN OLDIN ILOJIM YUQ DEDI TUSHUNTIRDIM PENYA QO'SHILADI QIYNALASIZ DEB | 1398 | Uyiga borildi - va'da berdi
A34: КОРАКАЛПОГИСТОН РЕСПУБЛИКАСИ | C34: Объезд | D34: Кр-99063474-1 | E34: AMETOV MIRZABEK SEYDAMETOVICH | F34: 998905945510 KELINI, 998913070180 OZI, 998913931343 OGLI, | G34: Кораколрогистон Рес Нукус щахар Ана сай МФЙ, Назархан кучаси, 10-уй | H34: 8 | I34: 5689954.1 | K34: 1782 | Uyiga borildi - va'da berdi
A35: КОРАКАЛПОГИСТОН РЕСПУБЛИКАСИ | C35: Объезд | D35: Кр-99062628-1 | E35: QALEKEEV QURBANBAY GENJEMURATOVICH | F35: 998337368081 OZI, 998912685205 AYOLI, 998996892535 OGLI, 998997573480 OGLI, | G35: QORAQALPOGISTON RES SHUMANAY TUMANI NAWRIZ MFY OZBEKISTAN KUSHASI 14 UY | H35: 12 | I35: 4175733.4 | K35: FILIAL BORDI 20KUNI AVANSDAN TASHAB BERAMAN DEDILA | 1591 | Va'da berdi
A36: КОРАКАЛПОГИСТОН РЕСПУБЛИКАСИ | C36: Объезд | D36: Кр-99046306-1 | E36: ALLAMURATOV SIPATDIN SHARAFATDINOVICH | F36: +998940899406 SMS OZI, 998886095115 SMS OPASI, 998997899406 SMS AYOLI, 998887068994 ayoli neww, | G36: Жаслык кучаси 24 уй | H36: 8 | I36: 3629261.1 | K36: QOZOQDA BUGUN TO'LOV QILISHADI EKAN | 1239 | Uyiga borildi - to'ladi
A37: КОРАКАЛПОГИСТОН РЕСПУБЛИКАСИ | C37: Объезд | D37: Кр-99057361-1 | E37: KULUMBETOVA ZIYADA JUMABAYEVNA | F37: 998906500325 oZI, 990977988897 o'G'LI, 998551084615 UY, 998972291204 QIZI, | G37: QORAQALPOGISTON RESPUBLIKASI XOJAYLI TUMANI | H37: 8 | I37: 3176244.7 | K37: KUYOVI BALNESAGA TUSHIB QOLIBDI 20-25GA TO'LOV QILIB BERAMAN DEDILA | 1429 | Uyiga borildi - va'da berdi
A38: КОРАКАЛПОГИСТОН РЕСПУБЛИКАСИ | C38: Объезд | D38: Кр-99062824-1 | E38: ALIYEV KUDIYAR ALLIYAROVICH | F38: 998933611148 SMS OANSI, 998972904286 SMS OZI, 998991623511 SMS AYOLI, 998991633511 SMS QIZI, | G38: QORAQOLPAGISTON RESPUBLIKASI NUKUS AMUDARYA MFY ELIM BAR KOCHASI 35-UY | H38: 8 | I38: 2755016.5 | K38: 1632 | Uyiga borildi
A39: КОРАКАЛПОГИСТОН РЕСПУБЛИКАСИ | C39: Объезд | D39: Кр-99048109-1 | E39: TOKIMBETOV KULMURAT ZARIPOVICH | F39: +998913895370 sms Ozi, 998906627173 sms akasi, 998913746773 sms Akasi, | G39: КОРАКАЛПОГИСТОН РЕСПУБЛИКАСИ Хужайи тумани Сабык МФЙ Саятхан Хамра 3 уй | H39: 8 | I39: 2301348.4 | K39: 7173 QARNDOWI AYTIB QO'YAMAN DEDILA BUGUN TO'LEMAN DEB AYTIBDILA | 1273 | Uyiga borildi - to'ladi
A40: КОРАКАЛПОГИСТОН РЕСПУБЛИКАСИ | C40: Объезд | D40: Кр-99048734-1 | E40: BERDIALIEV MURAT KUBEISINOVICH | F40: 998904247787 OYALI, 998906633888 OGLI, 998907037787 OZI, | G40: Qaraqalpogiston Respublikasi Nukus shahar Samanbay MFY Toktaw kushasi 25 uy | H40: 8 | I40: 2142177.8 | K40: TAKSICHI BU BO'LIB BO'LIB TO'LAYABDILA BUGUN KECHGA YANA TO'LAYDI | 1280 | Uyiga borildi - va'da berdi
A41: КОРАКАЛПОГИСТОН РЕСПУБЛИКАСИ | C41: Объезд | D41: Кр-99038025-1 | E41: AMINOV ARSLON RUSTAMOVICH | F41: 998952415212 SMS UZI, 998912551805 SMS UKASI, 990887732099 SMS UKASi 2, | G41: QORAQALPOG’ISTON RESPUBLIKASI TO’RTKO’L TUMANI TALABA MFY SEMASHKO KOCHASI 18A-UY | H41: 7 | I41: 1950012.7 | K41: FILIAL TO'LATTIRDI | 740 | Uyiga borildi - to'ladi
A42: КОРАКАЛПОГИСТОН РЕСПУБЛИКАСИ | C42: Объезд | D42: Кр-99063402-1 | E42: JAMGIRBAYEV SHOXZOD XALMURAT ULI | F42: 998906527006 OZI, 998913931005 AKASI, 998951773003 AKASI 2, | G42: QARAQALPOGISTON RES NUKUS SHAHAR NAUBAXAR MFY ELI AZAT KUSHASI 15 UY | H42: 8 | I42: 1762344.4 | K42: 1765 | Uyiga borildi - va'da berdi
A43: КОРАКАЛПОГИСТОН РЕСПУБЛИКАСИ | C43: Объезд | D43: Кр-99040984-1 | E43: UTAROV JAKSILIK DJITESOVICH | F43: 998913033891 SMS OZI, 998913917972 SMS AYOLI, 998991941402 SMS OGLI, | G43: NUKUS SHAHRI | H43: 11 | I43: 1675516.4 | K43: o'zi ishsiz 20kuni ayoli oylik oladi wundan to'layman deyabdila | 1039 | Uyiga borildi - va'da berdi
A44: КОРАКАЛПОГИСТОН РЕСПУБЛИКАСИ | C44: Объезд | D44: Кр-99064050-1 | E44: ESHIMBETOV QUDAYBERGEN AYAPBERGENOVICH | F44: 998877084162 OGLI, 998994004162 OZI, 998997484162 OYALI, | G44: QORAQLPOGISTON RES NUKUS SHAHAR Kutli-konis MFY, Uvaysiy ko’chasi, 18-uy | H44: 8 | I44: 1650780.2 | K44: 1868 | Uyiga borildi - va'da berdi
A45: КОРАКАЛПОГИСТОН РЕСПУБЛИКАСИ | C45: Объезд | D45: Кр-99033574-1 | E45: AMANBAEVA RAUSHAN XOJABAEVNA | F45: 998933668784 SMS O’ZI tuman tibbiyot birlashmasda hamshira, 998913038448 SMS ERI, 998900953787 SMS ONASI, 998913829597 SMS QIZI, 998937040224 SMS ERI NEW, | G45: NUKUS SHAHAR SHIMBOY GUZARI SAWKELI KUSHASI 107 UY | I45: 170388.71 | K45: RAQAMLARIGA TUSHA OLMADIM | 464 | Uyiga borildi - va'da berdi
A46: НАМАНГАН ВИЛОЯТИ | C46: Объезд | D46: Кр-99021020-4 | E46: ABDULLAYEV RAXMATULLOX MUXSIN O‘G‘LI | F46: 93-816-22-22 SMS UZI BEGONA, 90-792-00-77 SMS UZI 2, 88-250-00-05 SMS AKASI, 88-254-00-05 SMS ISHXONA begona, | G46: NAMANGAN SHAHRI G‘UNCHA MFY G‘UNCHA TOR KO‘CHASI 2 UY | H46: 13 | I46: 5181768.6 | K46: Uyiga borildi | undruvchi blan gaplashganakan bugun tolab qoyarkan
A47: НАМАНГАН ВИЛОЯТИ | C47: Объезд | D47: Кр-99040064-1 | E47: AXMADJONOVA MAVLUDA ABDURASUL QIZI | F47: 998932706992 SSMS OZI, 998932706992 SMS ERI, 998505257166 SMS DADASI begona , 998931649098 SMS ONASI begona, 998942762992 SMS ERI, | G47: NAMANGAN VILOYAT CHORTOQ TUMANI BOZORBOSHI MFY ZEBINISO KO'CHASI 39 UY | H47: 12 | I47: 3350519.9 | K47: Uyiga borildi | gaplashayabdi undruvchilar borib
A48: НАМАНГАН ВИЛОЯТИ | C48: Объезд | D48: Кр-99033809-1 | E48: BAYXANOV OLIM GULAMOVICH | F48: 998886267771 SMS O’ZI, 998935700636 SMS UKASI, 998339852021 SMS DADASI, 998882548111 SMS ONASI, 998999752666 SMS O'ZI, 998953000016 SMS uzi new, | G48: NAMANGAN VILOYATI NAMANGAN SHAHAR OBOD MFY ILG’OR 1 TOR KO’CHA 8 A UY | H48: 26 | I48: 3344464.2 | K48: Uyiga borildi | yopib beraman deyotganakan tez kunlarda
A49: НАМАНГАН ВИЛОЯТИ | C49: Объезд | D49: Кр-99040065-1 | E49: KAXXOROVA SEVARAXON XOSHIMJANOVNA | F49: 998948620378 SMS OZI, 998936435220 SMS UKASI TO'LOVCHI, 998507068998 SMS OGLI, 998948997875 SMS ERI begona, | G49: NAMANGAN VILOYAT YANGIQO'RG'ON TUMANI SUTLIBULOQ MFY, SADOQAT KO'CHASI 52 UY | H49: 12 | I49: 3020502.2 | K49: Uyiga borildi | klentni ukasi tolovchi hozir tololmaydi ekan puli yogan deb qaytib ketibdiundruvchilar
A50: НАМАНГАН ВИЛОЯТИ | C50: Объезд | D50: Кр-99036049-1 | E50: XAMIDJONOV BOBUR MUMINJON O’G’LI | F50: 998935299602 SMS OZI, 998942771083 SMS AKASI tolovchi, 998943048390 SMS OPASI, 998940015061 SMS AMAKISI, | G50: NAMANGAN VILOYATI UCHQO’RG’ON TUMANI ATLAS MFY USMON BAXSHI KO’CHA 2 UY | H50: 32 | I50: 2924740.3 | K50: Uyiga borildi | oy oxirida yopib berarkan
A51: НАМАНГАН ВИЛОЯТИ | C51: Объезд | D51: Кр-99040792-1 | E51: AXMADJANOVA MADINA MALIKJON QIZI | F51: 998950451616 SMS TO'LOVCHI, 998955750016 SMS AYOLI, | G51: ЧИНОР МФЙ, ЛАНГАР, 22 БЕРК КЎЧАСИ, uy:6 | H51: 8 | I51: 2488476.8 | K51: Uyiga borildi | bugun yopib berarkan
A52: НАМАНГАН ВИЛОЯТИ | C52: Объезд | D52: Кр-99040750-1 | E52: XAYDAROV IQBOLJON IMINJON O’G’LI | F52: 998996581133 SMS OZI, 998774457826 SMS UYI, 998939453448 SMS OPASI, 998367416462 SMS OPASI 2, | G52: NAMANGAN VILOYATI NORIN TUMANI QO’SHCHEK MFY,QO’SHCHEK KO’CHASI 88-UY | H52: 8 | I52: 1980907.2 | K52: Uyiga borildi | qsman tolov qilb berdi onasi qolganini ham yopib berarkan bir ikki kunda
A53: САМАРКАНД ВИЛОЯТИ | C53: Объезд | D53: Кр-99026954-6 | E53: AXROROV MEXROJ MASHRAFOVICH | F53: 99-783-00-20 SMS OZI tolovchi, 33-799-20-20 SMS UKASI, 91-702-64-03 SMS AYASI, 97-958-70-11 SMS AKASI, +998992719999 Primary phone from road24( БЕГОНА), 998992719999 Primary phone from road24( БЕГОНА), | G53: SAMARQAND VILOYATI SAMARQAND TUMANI QO’SHTAMG’ALI QFY JO’YISOY MFY | H53: 8 | I53: 5150210.4 | J53: 5150210.4 | K53: Uyiga borildi - to'ladi | yopildi
A54: САМАРКАНД ВИЛОЯТИ | C54: Объезд | D54: Кр-99038198-2 | E54: ABDUVOXIDOVA MAVLYUDA TOLIBOVNA | F54: 998902878483 SMS OZI, 998976156009 SMS ONASI, 998995514083 SMS SINGLISI, 998905059100 SMS YANGASI, +998902878483 SMS OZI, | G54: SAMARQAND VILOYATI PAYARIQ TUMANI JAVSHAR OTA MFY XIROSON KUCHASI 26-UY | H54: 8 | I54: 4146568.5 | J54: 4146568.5 | K54: Uyiga borildi - to'ladi | yopildi
A55: САМАРКАНД ВИЛОЯТИ | C55: Объезд | D55: Кр-99020836-8 | E55: ISMOILOV MUZAFFAR ALISHEROVICH | F55: 91-628-00-02 SMS, 90-286-00-02 SMS AKASI, 99-596-97-97 SMS ZALOGADATEL, 93-728-96-96 SMS ZALOGADATEL UKASI, 998902860002 SMS ZALOGADATEL, | G55: SAMARQAND CILOYATI PAYARIQ TUMANI GUZAL MFY OTABEK QUVVATOV KUCHASI 22-UY | H55: 8 | I55: 3766674.4 | K55: Uyiga borildi - va'da berdi
A56: САМАРКАНД ВИЛОЯТИ | C56: Объезд | D56: Кр-99059521-1 | E56: NEMATOVA LOLAXON FARXODJON QIZI | F56: +998944600370 SMS OZI, 998500105600 SMS UKASI, 998949230370 SMS ERI, 998979290370 SMS UYI, | G56: SAMARQAND VILOYATI PAYARIQ TUMANI ERNAZARQURG’ON MFY YANGI ZAMON KUCHASI 54-UY | H56: 8 | I56: 3575133 | K56: Uyiga borildi - va'da berdi
A57: САМАРКАНД ВИЛОЯТИ | C57: Объезд | D57: Кр-99030337-1 | E57: NABIYEV ABDUVORIS ABDUVOXIDOVCH | F57: 88-577-20-02 SMS UZI , 88-917-93-39 SMS AYOLI, 97-918-00-62 SMS uchaskavoy, 99-625-08-41 SMS UYI, | G57: SAMARQAND VILOYATI SAMARQAND TUMANI KO'LBA MFY KO'LBA QISHLOG'I | H57: 11 | I57: 3452322.4 | K57: Uyiga borildi - va'da berdi
A58: САМАРКАНД ВИЛОЯТИ | C58: Объезд | D58: Кр-99020836-6 | E58: ISMOILOV MUZAFFAR ALISHEROVICH | F58: 91-628-00-02 SMS, 90-286-00-02 SMS AKASI, 99-596-97-97 SMS ZALOGADATEL, 93-728-96-96 SMS ZALOGADATEL UKASI, 998902860002 SMS ZALOGADATEL, | G58: SAMARQAND CILOYATI PAYARIQ TUMANI GUZAL MFY OTABEK QUVVATOV KUCHASI 22-UY | H58: 8 | I58: 3319104.9 | K58: Uyiga borildi - va'da berdi
A59: САМАРКАНД ВИЛОЯТИ | C59: Объезд | D59: Кр-99040279-1 | E59: PARDAYEV MUHAMMAD ISLOMJON O’G’LI | F59: 998901030414 SMS OZI, 998915316369 SMS ZALOGATEL , 998906000208 SMS AKASI tulovchi, | G59: SAMARQAND VILOYATI PASTDARG'OM TUMANI QUYI DARG'OM MFY YOSHLAR KUCHASI 9-UY | H59: 8 | I59: 3306336 | J59: 3306336 | K59: Uyiga borildi - to'ladi | yopildi
A60: САМАРКАНД ВИЛОЯТИ | C60: Объезд | D60: Кр-99040174-1 | E60: ABSALOMOVA SADOKAT UCHKUNOVNA | F60: 998973421686 SMS OZI, 998977022672 SMS ERI, 998904491943 SMS QIZI, 998889151718 SMS UYI, | G60: SAMARQAND VILOYATI PAYARIQ TUMANI FIDAKOR MFY YOSHLIK KUCHASI 4-UY | H60: 8 | I60: 3107666.5 | K60: Uyiga borildi - va'da berdi
A61: САМАРКАНД ВИЛОЯТИ | C61: Объезд | D61: Кр-99040360-1 | E61: KUSHMURODOV RASHID XUROZOVICH | F61: +998936002584 SMS O’ZI, 998505003878 SMS AKASI 2, 998935692069 SMS AKASI, 998501202552 SMS TULOVCHI, 998889007404 SMS AYOLI, 998919650304 SMS AKASI, | G61: SAMARQAND VILOYATI PAYARIQ TUMANI BAXRIN MFY SARXOUS KUCHASI 71-UY | H61: 8 | I61: 2693401.9 | K61: Uyiga borildi - va'da berdi | borildi
A62: САМАРКАНД ВИЛОЯТИ | C62: Объезд | D62: Кр-99038198-1 | E62: ABDUVOXIDOVA MAVLYUDA TOLIBOVNA | F62: 998902878483 SMS OZI, 998976156009 SMS ONASI, 998995514083 SMS SINGLISI, 998905059100 SMS YANGASI, +998902878483 SMS OZI, | G62: SAMARQAND VILOYATI PAYARIQ TUMANI JAVSHAR OTA MFY XIROSON KUCHASI 26-UY | I62: 2339584.5 | K62: Uyiga borildi - va'da berdi
A63: САМАРКАНД ВИЛОЯТИ | C63: Объезд | D63: Кр-99012698-7 | E63: XAYDAROVA MOXIRA ESANOVNA | F63: 998954305444 SMS QIZI TOLOVCHI, 998885790746 SMS UZI, 998973948333 SMS QIZI, 97-223-07-46 SMS ERI, 998502206526 УЗИ МОХИРА, 998875010746 SMS OZI, 998889425455 SMS OZI 2, | G63: SAMARQAND VILOYATI SAMARQAND TUMANI OXALIK MFY OQ BUYRO QQ 19-UY | H63: 8 | I63: 2321085.4 | J63: 2321085.4 | K63: Uyiga borildi - to'ladi | yopildi
A64: САМАРКАНД ВИЛОЯТИ | C64: Объезд | D64: Кр-99027921-1 | E64: MIRASHIMOVA BASHORAT ORTIQOVNA | F64: 97-915-12-67 SMS OZI, 97-926-65-85 SMS OGLI, 97-931-00-85 SMS KATTA OGLI, 97-405-24-91 SMS KELINI, 998994270066 ogli bic , | G64: SAMARQAND VVILOYATI QO'SHROBOT TUMANI JO'SH OTA MFY JO'SH QFY | H64: 1 | I64: 2023323.4 | J64: 2023323.4 | K64: Uyiga borildi - to'ladi | yopildi
A65: САМАРКАНД ВИЛОЯТИ | C65: Объезд | D65: Кр-99040775-1 | E65: UMIRZOQOV JASURBEK NEYATULLO O’G’LI | F65: 998773446252 SMS OZI, 998771353464 SMS UKASI, 998930833517 SMS DADASI, 998940140909 SMS UY, 998773446252 SMS OZI, | G65: ISHTIXON TUMANI | H65: 8 | I65: 1967467.8 | K65: Uyiga borildi - va'da berdi | uyiga borildi
A66: САМАРКАНД ВИЛОЯТИ | C66: Объезд | D66: Кр-99007936-14 | E66: MAMASHARIPOV UTKIR MAMARZAYEVICH | F66: 99-344-03-45 SMS, 99-459-49-27 SMS AYOLI, 99-250-69-06 SMS ozi , 99-161-65-45 SMS UYI , 99-150-69-06 SMS ayoli , 77-080-89-01 SMS FARANGIZ SHU TOLOVCHI, +998957710587 SMS OZI, 998991198901 SMS UKASI, 998995398901 SMS UYI, 998990827644 tulovchi, 998500281120 SMS UYI, 998959584111 SMS AKASI, | G66: SAMARQAND VILOYATI OQDARYO TUMANI A.TEMUR MFY KALLAR QISHLOG’I | H66: 8 | I66: 1772928.7 | K66: Uyiga borildi - va'da berdi
A67: САМАРКАНД ВИЛОЯТИ | C67: Объезд | D67: Кр-99044880-1 | E67: SHAMSUTDINOV ALIBEK AMRITDIN O’G’LI | F67: +998775030831 SMS OZI, 998889181101 SMS AKASI, 998915294327 SMS UYI, 998990840360 SMS APASI, | G67: SAMARQAND VILOYATI PASTDARG’OM TUMANI JAG’OLBOYLI MFY JAG’OLBOYLI KUCHASI 16-UY | H67: 8 | I67: 1401165.1 | J67: 1401165.1 | K67: Uyiga borildi - to'ladi | yopildui
A68: САМАРКАНД ВИЛОЯТИ | C68: Объезд | D68: Кр-99007936-12 | E68: MAMASHARIPOV UTKIR MAMARZAYEVICH | F68: 99-344-03-45 SMS, 99-459-49-27 SMS AYOLI, 99-250-69-06 SMS ozi , 99-161-65-45 SMS UYI , 99-150-69-06 SMS ayoli , 77-080-89-01 SMS FARANGIZ SHU TOLOVCHI, +998957710587 SMS OZI, 998991198901 SMS UKASI, 998995398901 SMS UYI, 998990827644 tulovchi, 998500281120 SMS UYI, 998959584111 SMS AKASI, | G68: SAMARQAND VILOYATI OQDARYO TUMANI A.TEMUR MFY KALLAR QISHLOG’I | H68: 8 | I68: 1193053.1 | K68: Uyiga borildi - va'da berdi
A69: САМАРКАНД ВИЛОЯТИ | C69: Объезд | D69: Кр-99007936-11 | E69: MAMASHARIPOV UTKIR MAMARZAYEVICH | F69: 99-344-03-45 SMS, 99-459-49-27 SMS AYOLI, 99-250-69-06 SMS ozi , 99-161-65-45 SMS UYI , 99-150-69-06 SMS ayoli , 77-080-89-01 SMS FARANGIZ SHU TOLOVCHI, +998957710587 SMS OZI, 998991198901 SMS UKASI, 998995398901 SMS UYI, 998990827644 tulovchi, 998500281120 SMS UYI, 998959584111 SMS AKASI, | G69: SAMARQAND VILOYATI OQDARYO TUMANI A.TEMUR MFY KALLAR QISHLOG’I | H69: 1 | I69: 1176359 | K69: Uyiga borildi - va'da berdi
A70: САМАРКАНД ВИЛОЯТИ | C70: Объезд | D70: Кр-99040360-2 | E70: KUSHMURODOV RASHID XUROZOVICH | F70: +998936002584 SMS O’ZI, 998505003878 SMS AKASI 2, 998935692069 SMS AKASI, 998501202552 SMS TULOVCHI, 998889007404 SMS AYOLI, 998919650304 SMS AKASI, | G70: SAMARQAND VILOYATI PAYARIQ TUMANI BAXRIN MFY SARXOUS KUCHASI 71-UY | H70: 8 | I70: 572435.68 | K70: Uyiga borildi - va'da berdi | borildi
A71: САМАРКАНД ВИЛОЯТИ | C71: Объезд | D71: Кр-99038439-2 | E71: RAXMATOV ASILBEK OTABEK O’G’LI | F71: 998931744999 SMS OZI, 998934977010 SMS UKASI, 998939111879 SMS DADASI, 998775171404 SMS UYI, | G71: SAMARQAND VILOYATI PAYARIQ TUMANI MADANIYAT MFY BAXMALSOY KUCHASI 171-UY | H71: 13 | I71: 342959.3 | J71: 342959.3 | K71: Uyiga borildi - to'ladi | yopildi
A72: СУРХОНДАРЁ ВИЛОЯТИ | C72: Объезд | D72: Кр-99020891-4 | E72: KUNAROV UKTAM AMANDAVLATOVICH | F72: 91-515-78-00 SMS O'ZI TOLOVCHISI , 91-579-51-91 SMS UKASI, 91-911-56-67 SMS UY, 91-579-51-91 SMS BEGONA , | G72: ШЎРЧИ ШАҲРИ, БОБОТОГ МФЙ, ШЎРЧИ ШАҲРИ, БОБОТОГ МФЙ, ЎЗБЕКИСТОНСИ, uy:14 | H72: 8 | I72: 4832565.9 | K72: Uyiga borildi - va'da berdi | bugun hal qladi | 111
A73: СУРХОНДАРЁ ВИЛОЯТИ | C73: Объезд | D73: Кр-99027939-1 | E73: TURAYEVA ADOLAT TOSHBOYEVNA | F73: 91-078-04-96 SMS, 91-233-33-57 SMS UY, 91-575-71-70 SMS OILASI, 91-588-17-69 SMS O’ZI, 97-261-88-46 javlon aka javob degan, 998992184093 SMS O'ZI 2, | G73: SURXONDARYO VILOYATI UZUNSHO’RCHI TUMANI DO’STLIK MFY HAMKOR KUCHASI 104-UY | H73: 1 | I73: 4226143.1 | J73: 4226143.1 | K73: Uyiga borildi - to'ladi | filialga tolad | 223
A74: СУРХОНДАРЁ ВИЛОЯТИ | C74: Объезд | D74: Кр-99028408-1 | E74: MALLAYEVA DILAFRUZ ABDULLAYEVNA | F74: 91-585-67-12 SMS OZI BEGONA, 91-585-28-03 SMS UY, 998996777207 SMS TO'LOVCHI, 91-900-17-24 SMS OILASI, | G74: SURXONDARYO VILOYAT SHO’RCHI TUMANI JALOIR QFY DUSTLIK MFY DUSTLIK KO’CHASI 59-UY | H74: 6 | I74: 2817448.8 | K74: Uyiga borildi - va'da berdi | 232
A75: СУРХОНДАРЁ ВИЛОЯТИ | C75: Объезд | D75: Кр-99062762-2 | E75: BO’RIYEVA DILFUZA RO’ZIBOYEVNA | F75: +998919107277 SMS O’ZI, 998947994446 SMS ERI, | G75: ТЕРМИЗ ТУМАНИ НУРАФШОН МФЙ, БУНЁДКОР КУЧА uy:53 | H75: 8 | I75: 2532663.3 | K75: Uyiga borildi - va'da berdi | filialga vada berdi ertaga 6 gaca | 1618
A76: СУРХОНДАРЁ ВИЛОЯТИ | C76: Объезд | D76: Кр-99035996-1 | E76: ALMARDONOV BOBOMUROD BOBORAXMATOVICH | F76: 998995444686 SMS OZI, 998883176868 SMS SHERIGI, 998978967555 SMS UY, 998975502586 SMS, | G76: SURXONDARYO VILOYATI DENOV TUMANI FAYZLI MFY BUYUK IPAKYULI KO'CHASI 1-UY | H76: 1 | I76: 2248695.2 | K76: Uyiga borildi - va'da berdi | filialga ertaga tolo qlad | 613
A77: СУРХОНДАРЁ ВИЛОЯТИ | C77: Объезд | D77: Кр-99032593-1 | E77: DAVLATOV FARXOD RAJABALIYEVICH | F77: 998995882144 SMS O’ZI, 998954747270 SMS O’G’LI, 998995737252 SMS ONASI, 998990169073 SMS UY, | G77: SURXONDARYO VILOYATI DENOV TUMANI SEBZOR MFY MAKTAB KO’CHASI 15-UY | H77: 1 | I77: 1299053.2 | J77: 1299053.2 | K77: Uyiga borildi - to'ladi | toladi filialga | 404
A78: СУРХОНДАРЁ ВИЛОЯТИ | C78: Объезд | D78: Кр-99057140-1 | E78: XUSHBAQOVA ZEBINISO ABDUMALIK QIZI | F78: 998932372417 OZI, 998937930462 ONASI, 998917259222 OGLI, | G78: SURXONDARYO VILOYAT TERMIZ SHAXAR BOG’ZOR MFY ZAVQIY KO’CHASI 24A-UY | H78: 8 | I78: 970609.56 | J78: 970609.56 | K78: Uyiga borildi - to'ladi | filialga toladi | 1416
A79: СУРХОНДАРЁ ВИЛОЯТИ | C79: Объезд | D79: Кр-99022504-3 | E79: MUQUMOVA MAXFURAT QUVOTOVNA | F79: 91-229-38-19 SMS, 91-715-95-96 SMS UY, 91-075-20-16 SMS O’G’LI BEKZOD, 998917191006 SMS ozi, 998882439996 SMS OZI TOLOVCHI , 998887239996 SMS new uzi, | G79: SURXONDARYO VILOYATI SHO’RCHI TUMANI YANGIBOZOR QFY OQQURG’ON MFY MUSTAQILLIK KO’CHASI 132-UY | H79: 1 | I79: 920442.18 | K79: Uyiga borildi - va'da berdi | wu xafta yopb berad | 130
A80: СУРХОНДАРЁ ВИЛОЯТИ | C80: Объезд | D80: Кр-99039613-1 | E80: XAMIDOV SHERALI TOXIR O’G’LI | F80: 998930779988 SMS OZI TERMIZ XODIM , | G80: SURXONDARYO VILOYAT TERMIZ SHAXAR ESKI SHAXAR MYF BIRDAMLIK KO’CHASI 2-BURILISH 52 UY | I80: 565490.38 | K80: Uyiga borildi - va'da berdi | oy oxrgaca tolo qlad | 895
A81: СУРХОНДАРЁ ВИЛОЯТИ | C81: Объезд | D81: Кр-99022606-3 | E81: DJANGIBOYEVA MAXFIRAT JUMAYEVNA | F81: 91-969-15-33 SMS, 90-073-43-83 SMS UY, 90-295-92-88 SMS ZALOGADATEL, 90-249-94-60 SMS begona, 95-216-37-08 SMS eri, 998919099460 SMS ozi , 998936209288 SMS ozi new , | G81: ШЎРЧИ ҚФЙ, ОЙНАКЎЛ МФЙ, БУНЁДКОР 49-УЙ | H81: 8 | I81: 167906.71 | K81: Uyiga borildi - va'da berdi | 133
A82: СУРХОНДАРЁ ВИЛОЯТИ | C82: Объезд | D82: Кр-99022504-4 | E82: MUQUMOVA MAXFURAT QUVOTOVNA | F82: 91-229-38-19 SMS, 91-715-95-96 SMS UY, 91-075-20-16 SMS O’G’LI BEKZOD, 998917191006 SMS ozi, 998882439996 SMS OZI TOLOVCHI , 998887239996 SMS new uzi, | G82: SURXONDARYO VILOYATI SHO’RCHI TUMANI YANGIBOZOR QFY OQQURG’ON MFY MUSTAQILLIK KO’CHASI 132-UY | H82: 11 | I82: 17475.77 | K82: Uyiga borildi - va'da berdi | yopildi | 131
A83: ТОШКЕНТ ШАХРИ | C83: Объезд | D83: Кр-99039089-1 | E83: SHARIPOVA NARGIZA XUSNITDINOVNA | F83: 998909167565 SMS OZI, 998900136157 SMS SINGLISI, 998951320107 SMS JIYANI, | G83: TOSHKENT SHAHAR SIRG’ALI TUMANI SERGILI 5-MAVZESI, 67-UY, 11-XONADON | H83: 175 | I83: 42668102 | K83: Uyiga borildi - va'da berdi | o'zi o'lgan akasi to'lidi
A84: ТОШКЕНТ ШАХРИ | C84: Объезд | D84: Кр-99040408-4 | E84: XODIYEV FARRUX FURQAT O’G’LI | F84: 998995705902 SMS OZI, 998977357760 SMS SHERIGI, 998817877602 SMS SHERIGI 2, | G84: TOSHKENT SHAHAR YUNUSOBOD TUMANI 11 KVARTAL,57-UY,46-XONADON | H84: 11 | I84: 13974380 | K84: Uyiga borildi - va'da berdi
A85: ТОШКЕНТ ШАХРИ | C85: Объезд | D85: Кр-99058714-1 | E85: MAXMATQULOV AKROM ABDIRAXMONOVICH | F85: 998909404168 SMS OZI, 998931464168 SMS AYOLI, 998933034168 SMS OGLI, 998983644168 SMS OZI, | G85: TOSHKENT SHAHAR YANGIHAYOT TUMANI YANGIHAYOT MFY TURSUNZODA KOCHASI 10-UY 164-XONODON | H85: 11 | I85: 12139785 | K85: Uyiga borildi - va'da berdi
A86: ТОШКЕНТ ШАХРИ | C86: Объезд | D86: Кр-99062871-2 | E86: YUGAY ANDREY VITALEVICH | F86: 998771690087 SMS AKASI, 998971327478 SMS SINGLISI, 998991350078 SMS UKASI, 998996382633 SMS AYOLI, | G86: TOSHKENT SHAHAR YASHNOBOD TUMANI 1-TUZEL MAVZESI 33-UY 40-XONADON | H86: 8 | I86: 7380474.5 | K86: Uyiga borildi - va'da berdi
A87: ТОШКЕНТ ШАХРИ | C87: Объезд | D87: Кр-99039812-4 | E87: ISRAILOVA DILDORA ABDUJALILOVNA | G87: Олмос МФЙ, Яккатол,3 тор кўчаси, 38/2-уй, 35-хонадон | H87: 8 | I87: 5858734 | K87: Uyiga borildi - va'da berdi
A88: ТОШКЕНТ ШАХРИ | C88: Объезд | D88: Кр-99017842-6 | E88: YAKUBJANOV ASADJON AXMADJANOVICH | F88: 99-482-80-45 sms OZI, 97-715-15-83 sms AYOLI, 91-008-35-35 sms O'G'LI, 99-482-80-45 sms OZI, | G88: TOSHKENT SHAHRI SERGELI TUMANI | H88: 5 | I88: 4757650.3 | J88: 4757650.3 | K88: Uyiga borildi - to'ladi
A89: ТОШКЕНТ ШАХРИ | C89: Объезд | D89: Кр-99044706-1 | E89: CHUTBAYEV DOSTON CHARI O’G’LI | F89: 998947771061 SMS AKASI, 998949341916 SMS OZI, 998977277200 SMS AKASI2, | G89: Daryobo’yi MFY, Daryo bo’yi 1-tor ko’chasi, 26-б-uy | H89: 8 | I89: 4629304.8 | K89: Uyiga borildi - va'da berdi
A90: ТОШКЕНТ ШАХРИ | C90: Объезд | D90: Кр-99044187-1 | E90: AKMALDINOV NURIDDIN FAXRIDINOVICH | F90: 998770509929 SMS O’ZI, 998950126264 SMS OYISI, 998976333666 SMS SINGLISI, 998992193943 SMS UKASI, | G90: ОХАНГАРОБО КУЧАСИ 1 ТОР 67 УЙ | H90: 8 | I90: 4295232.8 | K90: Uyiga borildi - va'da berdi
A91: ТОШКЕНТ ШАХРИ | C91: Объезд | D91: Кр-99063089-1 | E91: YUZBAYEV DILMUROD ALLAMURAD O’G’LI | F91: 998946736370 OZI, 998940206370 AYOLI, 998500573637 DOSTI, | G91: TOSHKENT SHAHAR YASHNOBOD TUMANI BOYQO’RG’ON KO’CHASI 11/3 UY,63-A XONADON | H91: 8 | I91: 3507336.8 | K91: Uyiga borildi - va'da berdi
A92: ТОШКЕНТ ШАХРИ | C92: Объезд | D92: Кр-99063244-1 | E92: QUDRATXODJAYEV BEHZOD SHUXRATOVICH | F92: 998200001426 SMS OZI, 998997012006 SMS JIYANI, 998998604005 SMS OANSI, | G92: TOSHKENT SHAHAR YUNUSOBOD TUMANI O’LKAOBOD KOCHASI 4-UY | H92: 13 | I92: 3189339.2 | J92: 3189339.2 | K92: Uyiga borildi - to'ladi
A93: ТОШКЕНТ ШАХРИ | C93: Объезд | D93: Кр-99044138-2 | E93: ABDURASHIDOV ABDULAZIZ ABDULATIF O’G’LI | F93: 998946236666 SMS OZI 2, 998946638777 SMS OZI, 998983664777 SMS UKASI, | G93: Oltin vodiy MFY, Samo 1-berk ko’chasi, 18-uy | H93: 8 | I93: 2828306.4 | J93: 2828306.4 | K93: Uyiga borildi - to'ladi
A94: ТОШКЕНТ ШАХРИ | C94: Объезд | D94: Кр-99037634-2 | E94: XUDOYBERGANOV DONIYOR TUYG’UN O’G’LI | F94: 998946895455 SMS O’ZI, 998950051505 SMS DO’STI, 998900543915 SMS O’ZI, 998331775455 SMS UKASI, | G94: Бободехкон МФЙ, Хусайни, туп. 2 кучаси, 9-уй | H94: 8 | I94: 2516559.5 | J94: 2516559.5 | K94: Uyiga borildi - to'ladi
A95: ТОШКЕНТ ШАХРИ | C95: Объезд | D95: Кр-99057349-1 | E95: XOLXO’JAYEV SHERZOD NIG’MONXO’JA O’G’LI | F95: 998900230492 SMS OZI, 998977499495 SMS UKASI begona tel qilinmasin, 998909010493 SMS ONASI, 998903530373 SMS OSHNASI, | G95: TOSHKENT SHAHAR YANGIHAYOT TUMANI CHORTOK MFY, BIRLIK KO’CHASI 73-UY | H95: 8 | I95: 1586742.4 | K95: Uyiga borildi - va'da berdi
A96: ТОШКЕНТ ШАХРИ | C96: Объезд | D96: Кр-99041437-1 | E96: MUSAYEV NODIR TOXTASINOVICH | F96: +998974400425 SMS O’ZI, 998909391070 SMS DO’STI, 998909485772 SMS KENOYISI, 998950760939 SMS OKASI, | G96: ТОШКЕНТ ШАХРИ ЯШНОБОД ТУМАНИ БЕҲИЗОР МФЙ, ШОХСАНАМ КЎЧАСИ, uy:104 (4-ХОНАДОН) | H96: 8 | I96: 1360281.3 | J96: 1360281.3 | K96: Uyiga borildi - to'ladi
A97: ТОШКЕНТ ШАХРИ | C97: Объезд | D97: Кр-99041945-3 | E97: BEKMATOVA MAXMUDA AKRAMOVNA | F97: 998903154326 SMS QIZI, 998903970616 SMS OZI, 998946472100 SMS GAROVCHI, 998977078333 SMS OGLI, | G97: MUYNOQ KO’CHASI 116-UY | H97: 8 | I97: 972330.93 | K97: Uyiga borildi - va'da berdi
A98: ФАРГОНА ВИЛОЯТИ | C98: Объезд | D98: Кр-99036825-1 | E98: RAXMANKULOVA RANO EMINOVNA | F98: 998916619568 SMS OZI, 998916667777 SMS OGLI BEGONA, 998992041119 SMS OGLI 2, 998902741221 SMS UYI BEGONA, 998972711111 SMS , | G98: FARG’ONA VILOYATI FARG’ONA SHAHAR OQARIQ MFY OQARIQ KO’CHASI 350-A UY | H98: 120 | I98: 53771510 | K98: Uyiga borildi | 20648677.87
A99: ФАРГОНА ВИЛОЯТИ | C99: Объезд | D99: Кр-99044960-2 | E99: ABDULLAYEV BEGALI MIRZAJONOVICH | F99: +998508786500 SMS O’ZI Ишсиз тел қилинмасин, 998908562142 AYOLI Боғчада зам директор тел қилинмасин, 998911448272 O’G’LI 2 тел қилинмасин, 998993646566 O’G’LI тел қилинмасин, | G99: FARG’ONA VILOYATI BESHARIQ TUMANI SHOBERDI MFY GULYOR KO’CHASI 40-UY | H99: 133 | I99: 46884562 | K99: Uyiga borildi - va'da berdi | 11979165
A100: ФАРГОНА ВИЛОЯТИ | C100: Объезд | D100: Кр-99060331-1 | E100: UMAROVA EXTIBOR SOTVOLDIYEVNA | F100: 998905331878 узи, 998932974444 невара, 998982775557 уй, 998943313223 эри, | G100: FARG’ONA VILOYATI, FARG’ONA SHAHRI, FARG’ONA MFY, FITRAT KO’CHASI, 27-UY | H100: 41 | I100: 32347767 | K100: Uyiga borildi - va'da berdi | ERTAGA KECHROQA FILALGA BORIB TOLAB QOYADI EKAN | 9776256.28
...

Sheet Оплатили без разговора
A1: ← Вернуться в отчёт
A2: Область | B2: Филиал | C2: Группа | D2: Код клиента | E2: Клиент | F2: Номер телефона | G2: Адрес | H2: Кол-во просроченных дней | I2: Итого просрочка | J2: Оплата | K2: Izoh
