Workbook
Name Print_Titles: Ввод!$4:$5
Name БазоваяПапка: Справочники!$N$1

Sheet Ввод
A2: Дата отчёта: | C2: 46282
E4: ПОРТФЕЛЬ | G4: ПРОСРОЧКА | K4: ДОЗВОНИЛИСЬ / ОБЕЩАЛИ | O4: НЕ ДОЗВОНИЛИСЬ / ОБЪЕЗД | S4: ОПЛАЧЕНО ЗА ДЕНЬ | Y4: ЭФФЕКТИВНОСТЬ И НАГРУЗКА
A5: № | B5: Область | C5: Ответственный | D5: Сотруд- ников | E5: Портфель, сум | F5: Портфель, шт | G5: Просрочка, сум | H5: Просрочка, шт | I5: % к портфелю | J5: % к кол-ву | K5: Дозвон, сум | L5: Дозвон, шт | M5: Обещали, сум | N5: Обещали, шт | O5: Не дозв., сум | P5: Не дозв., шт | Q5: Объезд, сум | R5: Объезд, шт | S5: Оплатил дозвон, сум | T5: Оплатил дозвон, шт | U5: Объезд оплатил, сум | V5: Объезд оплатил, шт | W5: Оплачено, сум | X5: Оплачено, шт | Y5: % дозвона (шт) | Z5: % обещаний (от дозвона) | AA5: Просрочка на 1 сотр. | AB5: Дозвон на 1 сотр. | AE5: служ. (для сортировки)
A6: 1 | B6: АНДИЖОН ВИЛОЯТИ | C6: =IFERROR(INDEX(Справочники!$D$4:$D$21,MATCH($B6,Справочники!$B$4:$B$21,0)),"") | D6: =SUMIF(Справочники!$H$4:$H$21,$B6,Справочники!$E$4:$E$21) -> 0 | E6: 2.1670184e+10 | F6: 445 | G6: =$K6+$O6 -> 2.1699731e+08 | H6: =$L6+$P6 -> 32 | I6: =IFERROR($G6/$E6,"") -> 0.010013635 | J6: =IFERROR($H6/$F6,"") -> 0.071910112 | K6: 5.2922391e+08 | L6: 87 | M6: 5.130247e+08 | N6: 84 | O6: 2.4056174e+08 | P6: 28 | Q6: 84857504 | R6: 13 | S6: 4657532 | T6: 3 | U6: 6438354 | V6: 3 | W6: 11095886 | X6: 6 | Y6: =IFERROR($L6/$H6,"") -> 0 | Z6: =IFERROR($N6/$L6,"") | AA6: =IFERROR($H6/$D6,"") | AB6: =IFERROR($L6/$D6,"") | AE6: =IFERROR($Y6,0)+ROW()/1000000 -> 6e-06
A7: 2 | B7: БУХОРО ВИЛОЯТИ | C7: =IFERROR(INDEX(Справочники!$D$4:$D$21,MATCH($B7,Справочники!$B$4:$B$21,0)),"") | D7: =SUMIF(Справочники!$H$4:$H$21,$B7,Справочники!$E$4:$E$21) -> 0 | E7: 5.1231734e+09 | F7: 167 | G7: =$K7+$O7 -> 2.0266951e+08 | H7: =$L7+$P7 -> 18 | I7: =IFERROR($G7/$E7,"") -> 0.03955937 | J7: =IFERROR($H7/$F7,"") -> 0.10778443 | K7: 40258501 | L7: 13 | M7: 39046202 | N7: 12 | O7: 1.8764791e+08 | P7: 27 | Q7: 4643386.1 | R7: 3 | S7: 1265879 | T7: 1 | U7: 3762109 | V7: 2 | W7: 5027988 | X7: 3 | Y7: =IFERROR($L7/$H7,"") -> 0 | Z7: =IFERROR($N7/$L7,"") | AA7: =IFERROR($H7/$D7,"") | AB7: =IFERROR($L7/$D7,"") | AE7: =IFERROR($Y7,0)+ROW()/1000000 -> 7e-06
A8: 3 | B8: ЖИЗЗАХ ВИЛОЯТИ | C8: =IFERROR(INDEX(Справочники!$D$4:$D$21,MATCH($B8,Справочники!$B$4:$B$21,0)),"") | D8: =SUMIF(Справочники!$H$4:$H$21,$B8,Справочники!$E$4:$E$21) -> 0 | E8: 1.3904205e+10 | F8: 493 | G8: =$K8+$O8 -> 2.498528e+08 | H8: =$L8+$P8 -> 51 | I8: =IFERROR($G8/$E8,"") -> 0.017969585 | J8: =IFERROR($H8/$F8,"") -> 0.10344828 | K8: 1.1962063e+08 | L8: 31 | M8: 1.0777361e+08 | N8: 22 | O8: 1.5680618e+08 | P8: 40 | Q8: 55296772 | R8: 15 | S8: 11847018 | T8: 9 | U8: 11722636 | V8: 4 | W8: 23569654 | X8: 13 | Y8: =IFERROR($L8/$H8,"") -> 0.39215686 | Z8: =IFERROR($N8/$L8,"") -> 0.95 | AA8: =IFERROR($H8/$D8,"") | AB8: =IFERROR($L8/$D8,"") | AE8: =IFERROR($Y8,0)+ROW()/1000000 -> 0.39216486
A9: 4 | B9: КАШКАДАРЁ ВИЛОЯТИ | C9: =IFERROR(INDEX(Справочники!$D$4:$D$21,MATCH($B9,Справочники!$B$4:$B$21,0)),"") | D9: =SUMIF(Справочники!$H$4:$H$21,$B9,Справочники!$E$4:$E$21) -> 0 | E9: 1.2186569e+10 | F9: 418 | G9: =$K9+$O9 -> 2.0555796e+08 | H9: =$L9+$P9 -> 33 | I9: =IFERROR($G9/$E9,"") -> 0.016867583 | J9: =IFERROR($H9/$F9,"") -> 0.078947368 | K9: 94171739 | L9: 27 | M9: 87135274 | N9: 22 | O9: 2.8220861e+08 | P9: 76 | Q9: 53867850 | R9: 12 | S9: 7036464.7 | T9: 5 | U9: 6953038.8 | V9: 6 | W9: 13989503 | X9: 11 | Y9: =IFERROR($L9/$H9,"") -> 0.87878788 | Z9: =IFERROR($N9/$L9,"") -> 0.62068966 | AA9: =IFERROR($H9/$D9,"") | AB9: =IFERROR($L9/$D9,"") | AE9: =IFERROR($Y9,0)+ROW()/1000000 -> 0.87879688
A10: 5 | B10: КОРАКАЛПОГИСТОН РЕСПУБЛИКАСИ | C10: =IFERROR(INDEX(Справочники!$D$4:$D$21,MATCH($B10,Справочники!$B$4:$B$21,0)),"") | D10: =SUMIF(Справочники!$H$4:$H$21,$B10,Справочники!$E$4:$E$21) -> 0 | E10: 1.1119545e+10 | F10: 269 | G10: =$K10+$O10 -> 2.5963958e+08 | H10: =$L10+$P10 -> 26 | I10: =IFERROR($G10/$E10,"") -> 0.023349839 | J10: =IFERROR($H10/$F10,"") -> 0.096654275 | K10: 1.754022e+08 | L10: 46 | M10: 1.7181797e+08 | N10: 43 | O10: 1.0934341e+08 | P10: 15 | Q10: 35606179 | R10: 8 | S10: 2771230 | T10: 3 | U10: 1767587.4 | V10: 1 | W10: 4538817.4 | X10: 4 | Y10: =IFERROR($L10/$H10,"") -> 0.76923077 | Z10: =IFERROR($N10/$L10,"") -> 0.2 | AA10: =IFERROR($H10/$D10,"") | AB10: =IFERROR($L10/$D10,"") | AE10: =IFERROR($Y10,0)+ROW()/1000000 -> 0.76924077
A11: 6 | B11: НАВОИЙ ВИЛОЯТИ | C11: =IFERROR(INDEX(Справочники!$D$4:$D$21,MATCH($B11,Справочники!$B$4:$B$21,0)),"") | D11: =SUMIF(Справочники!$H$4:$H$21,$B11,Справочники!$E$4:$E$21) -> 0 | E11: 6.476845e+09 | F11: 209 | G11: =$K11+$O11 -> 1.0708535e+08 | H11: =$L11+$P11 -> 18 | I11: =IFERROR($G11/$E11,"") -> 0.016533567 | J11: =IFERROR($H11/$F11,"") -> 0.086124402 | K11: 75426904 | L11: 24 | M11: 27253009 | N11: 8 | O11: 1.2636505e+08 | P11: 33 | Q11: 4302470.6 | R11: 1 | S11: 13858448 | T11: 8 | U11: 0 | V11: 0 | W11: 13858448 | X11: 8 | Y11: =IFERROR($L11/$H11,"") -> 0.055555556 | Z11: =IFERROR($N11/$L11,"") -> 1 | AA11: =IFERROR($H11/$D11,"") | AB11: =IFERROR($L11/$D11,"") | AE11: =IFERROR($Y11,0)+ROW()/1000000 -> 0.055566556
A12: 7 | B12: НАМАНГАН ВИЛОЯТИ | C12: =IFERROR(INDEX(Справочники!$D$4:$D$21,MATCH($B12,Справочники!$B$4:$B$21,0)),"") | D12: =SUMIF(Справочники!$H$4:$H$21,$B12,Справочники!$E$4:$E$21) -> 0 | E12: 1.4729616e+10 | F12: 438 | G12: =$K12+$O12 -> 5.9799851e+08 | H12: =$L12+$P12 -> 62 | I12: =IFERROR($G12/$E12,"") -> 0.040598377 | J12: =IFERROR($H12/$F12,"") -> 0.14155251 | K12: 4.6590436e+08 | L12: 73 | M12: 30120826 | N12: 9 | O12: 4.1608266e+08 | P12: 60 | Q12: 15522112 | R12: 5 | S12: 0 | T12: 0 | U12: 0 | V12: 0 | W12: 0 | X12: 0 | Y12: =IFERROR($L12/$H12,"") -> 0.48387097 | Z12: =IFERROR($N12/$L12,"") -> 1 | AA12: =IFERROR($H12/$D12,"") | AB12: =IFERROR($L12/$D12,"") | AE12: =IFERROR($Y12,0)+ROW()/1000000 -> 0.48388297
A13: 8 | B13: САМАРКАНД ВИЛОЯТИ | C13: =IFERROR(INDEX(Справочники!$D$4:$D$21,MATCH($B13,Справочники!$B$4:$B$21,0)),"") | D13: =SUMIF(Справочники!$H$4:$H$21,$B13,Справочники!$E$4:$E$21) -> 0 | E13: 1.6007859e+10 | F13: 549 | G13: =$K13+$O13 -> 2.6721243e+08 | H13: =$L13+$P13 -> 61 | I13: =IFERROR($G13/$E13,"") -> 0.016692577 | J13: =IFERROR($H13/$F13,"") -> 0.11111111 | K13: 1.3439362e+08 | L13: 35 | M13: 1.121437e+08 | N13: 26 | O13: 3.5827007e+08 | P13: 92 | Q13: 75252986 | R13: 18 | S13: 22249925 | T13: 9 | U13: 11412968 | V13: 5 | W13: 33662893 | X13: 14 | Y13: =IFERROR($L13/$H13,"") -> 0.24590164 | Z13: =IFERROR($N13/$L13,"") -> 1 | AA13: =IFERROR($H13/$D13,"") | AB13: =IFERROR($L13/$D13,"") | AE13: =IFERROR($Y13,0)+ROW()/1000000 -> 0.24591464
A14: 9 | B14: СИРДАРЁ ВИЛОЯТИ | C14: =IFERROR(INDEX(Справочники!$D$4:$D$21,MATCH($B14,Справочники!$B$4:$B$21,0)),"") | D14: =SUMIF(Справочники!$H$4:$H$21,$B14,Справочники!$E$4:$E$21) -> 0 | E14: 7.1897605e+09 | F14: 151 | G14: =$K14+$O14 -> 97690450 | H14: =$L14+$P14 -> 17 | I14: =IFERROR($G14/$E14,"") -> 0.013587441 | J14: =IFERROR($H14/$F14,"") -> 0.11258278 | K14: 0 | L14: 0 | M14: 0 | N14: 0 | O14: 1.8944731e+08 | P14: 46 | Q14: 0 | R14: 0 | S14: 0 | T14: 0 | U14: 0 | V14: 0 | W14: 0 | X14: 0 | Y14: =IFERROR($L14/$H14,"") -> 0.58823529 | Z14: =IFERROR($N14/$L14,"") -> 0.1 | AA14: =IFERROR($H14/$D14,"") | AB14: =IFERROR($L14/$D14,"") | AE14: =IFERROR($Y14,0)+ROW()/1000000 -> 0.58824929
A15: 10 | B15: СУРХОНДАРЁ ВИЛОЯТИ | C15: =IFERROR(INDEX(Справочники!$D$4:$D$21,MATCH($B15,Справочники!$B$4:$B$21,0)),"") | D15: =SUMIF(Справочники!$H$4:$H$21,$B15,Справочники!$E$4:$E$21) -> 0 | E15: 1.6585229e+10 | F15: 558 | G15: =$K15+$O15 -> 1.0837511e+09 | H15: =$L15+$P15 -> 97 | I15: =IFERROR($G15/$E15,"") -> 0.065344354 | J15: =IFERROR($H15/$F15,"") -> 0.17383513 | K15: 9.1438827e+08 | L15: 131 | M15: 9.0575483e+08 | N15: 128 | O15: 5.7548904e+08 | P15: 85 | Q15: 36126179 | R15: 8 | S15: 8633442.8 | T15: 3 | U15: 4139105.1 | V15: 2 | W15: 12772548 | X15: 5 | Y15: =IFERROR($L15/$H15,"") -> 0.18556701 | Z15: =IFERROR($N15/$L15,"") -> 0.11111111 | AA15: =IFERROR($H15/$D15,"") | AB15: =IFERROR($L15/$D15,"") | AE15: =IFERROR($Y15,0)+ROW()/1000000 -> 0.18558201
A16: 11 | B16: ТОШКЕНТ ВИЛОЯТИ | C16: =IFERROR(INDEX(Справочники!$D$4:$D$21,MATCH($B16,Справочники!$B$4:$B$21,0)),"") | D16: =SUMIF(Справочники!$H$4:$H$21,$B16,Справочники!$E$4:$E$21) -> 0 | E16: 3.6871387e+10 | F16: 842 | G16: =$K16+$O16 -> 8.8698663e+08 | H16: =$L16+$P16 -> 93 | I16: =IFERROR($G16/$E16,"") -> 0.024056232 | J16: =IFERROR($H16/$F16,"") -> 0.11045131 | K16: 0 | L16: 0 | M16: 0 | N16: 0 | O16: 1.2813068e+09 | P16: 216 | Q16: 0 | R16: 0 | S16: 0 | T16: 0 | U16: 0 | V16: 0 | W16: 0 | X16: 0 | Y16: =IFERROR($L16/$H16,"") -> 0 | Z16: =IFERROR($N16/$L16,"") | AA16: =IFERROR($H16/$D16,"") | AB16: =IFERROR($L16/$D16,"") | AE16: =IFERROR($Y16,0)+ROW()/1000000 -> 1.6e-05
A17: 12 | B17: ТОШКЕНТ ШАХРИ | C17: =IFERROR(INDEX(Справочники!$D$4:$D$21,MATCH($B17,Справочники!$B$4:$B$21,0)),"") | D17: =SUMIF(Справочники!$H$4:$H$21,$B17,Справочники!$E$4:$E$21) -> 0 | E17: 4.3531855e+10 | F17: 908 | G17: =$K17+$O17 -> 1.6257267e+09 | H17: =$L17+$P17 -> 115 | I17: =IFERROR($G17/$E17,"") -> 0.037345679 | J17: =IFERROR($H17/$F17,"") -> 0.12665198 | K17: 1.326472e+08 | L17: 33 | M17: 1.2627665e+08 | N17: 30 | O17: 1.5459964e+09 | P17: 173 | Q17: 48453884 | R17: 9 | S17: 6370552.4 | T17: 3 | U17: 0 | V17: 0 | W17: 6370552.4 | X17: 3 | Y17: =IFERROR($L17/$H17,"") -> 0 | Z17: =IFERROR($N17/$L17,"") | AA17: =IFERROR($H17/$D17,"") | AB17: =IFERROR($L17/$D17,"") | AE17: =IFERROR($Y17,0)+ROW()/1000000 -> 1.7e-05
... A19: 14 | B19: ХОРАЗМ ВИЛОЯТИ | C19: =IFERROR(INDEX(Справочники!$D$4:$D$21,MATCH($B19,Справочники!$B$4:$B$21,0)),"") | D19: =SUMIF(Справочники!$H$4:$H$21,$B19,Справочники!$E$4:$E$21) -> 0 | E19: 2.0499096e+10 | F19: 504 | G19: =$K19+$O19 -> 2.9345986e+08 | H19: =$L19+$P19 -> 49 | I19: =IFERROR($G19/$E19,"") -> 0.014315746 | J19: =IFERROR($H19/$F19,"") -> 0.097222222 | K19: 1.2207456e+08 | L19: 46 | M19: 1.0797075e+08 | N19: 37 | O19: 4.5230045e+08 | P19: 92 | Q19: 44122728 | R19: 11 | S19: 14103813 | T19: 9 | U19: 7019065.5 | V19: 2 | W19: 21122878 | X19: 11 | Y19: =IFERROR($L19/$H19,"") -> 0.46938776 | Z19: =IFERROR($N19/$L19,"") -> 0.26086957 | AA19: =IFERROR($H19/$D19,"") | AB19: =IFERROR($L19/$D19,"") | AE19: =IFERROR($Y19,0)+ROW()/1000000 -> 0.46940676
B20: ИТОГО | D20: =SUM(D6:D19) -> 0 | E20: =SUM(E6:E19) -> 2.4329876e+11 | F20: =SUM(F6:F19) -> 6312 | G20: =SUM(G6:G19) -> 6.9014395e+09 | H20: =SUM(H6:H19) -> 725 | I20: =IFERROR($G20/$E20,"") -> 0.02836611 | J20: =IFERROR($H20/$F20,"") -> 0.11486058 | K20: =SUM(K6:K19) -> 1.1882477e+09 | L20: =SUM(L6:L19) -> 166 | M20: =SUM(M6:M19) -> 7.4828599e+08 | N20: =SUM(N6:N19) -> 96 | O20: =SUM(O6:O19) -> 0 | P20: =SUM(P6:P19) -> 0 | Q20: =SUM(Q6:Q19) -> 5.7131919e+09 | R20: =SUM(R6:R19) -> 559 | ... X20: =SUM(X6:X19) -> 28 | Y20: =IFERROR($L20/$H20,"") -> 0.22896552 | Z20: =IFERROR($N20/$L20,"") -> 0.57831325 | AA20: =IFERROR($H20/$D20,"") | AB20: =IFERROR($L20/$D20,"")
B23: ОТКРЫТЬ СПИСОК КЛИЕНТОВ
B24: Область | C24: Дозв. | D24: Обещ. | E24: Опл. | F24: Не дозв. | G24: Объезд | H24: Опл. без разг. | I24: Всего
B25: АНДИЖОН ВИЛОЯТИ | C25: ▸ | D25: ▸ | E25: ▸ | F25: ▸ | G25: ▸ | I25: ▸
B26: БУХОРО ВИЛОЯТИ | C26: ▸ | D26: ▸ | E26: ▸ | F26: ▸ | G26: ▸ | I26: ▸
B27: ЖИЗЗАХ ВИЛОЯТИ | C27: ▸ | D27: ▸ | E27: ▸ | F27: ▸ | G27: ▸ | I27: ▸
B28: КАШКАДАРЁ ВИЛОЯТИ | C28: ▸ | D28: ▸ | E28: ▸ | F28: ▸ | G28: ▸ | I28: ▸
B29: КОРАКАЛПОГИСТОН РЕСПУБЛИКАСИ | C29: ▸ | D29: ▸ | E29: ▸ | F29: ▸ | G29: ▸ | I29: ▸
B30: НАВОИЙ ВИЛОЯТИ | C30: ▸ | D30: ▸ | E30: ▸ | F30: ▸ | G30: ▸ | I30: ▸
B31: НАМАНГАН ВИЛОЯТИ | C31: ▸ | D31: ▸ | F31: ▸ | G31: ▸
B32: САМАРКАНД ВИЛОЯТИ | C32: ▸ | D32: ▸ | E32: ▸ | F32: ▸ | G32: ▸ | I32: ▸
B33: СИРДАРЁ ВИЛОЯТИ | F33: ▸
B34: СУРХОНДАРЁ ВИЛОЯТИ | C34: ▸ | D34: ▸ | E34: ▸ | F34: ▸ | G34: ▸ | I34: ▸
B35: ТОШКЕНТ ВИЛОЯТИ | F35: ▸
B36: ТОШКЕНТ ШАХРИ | C36: ▸ | D36: ▸ | E36: ▸ | F36: ▸ | G36: ▸ | I36: ▸
B37: ФАРГОНА ВИЛОЯТИ | C37: ▸ | D37: ▸ | E37: ▸ | F37: ▸ | G37: ▸ | I37: ▸
B38: ХОРАЗМ ВИЛОЯТИ | C38: ▸ | D38: ▸ | E38: ▸ | F38: ▸ | G38: ▸ | I38: ▸

Sheet Отчёт_дня
A3: Дата отчёта: | C3: =Ввод!$C$2 -> 46272
A6: 1. ПОКАЗАТЕЛИ ДНЯ
A7: Портфель, сум | D7: =Ввод!$E$20 -> 2.4329876e+11
A8: Просрочка, сум | D8: =Ввод!$G$20 -> 6.9014395e+09
A9: % просрочки к портфелю | D9: =Ввод!$I$20 -> 0.02836611
A10: Просрочка, шт | D10: =Ввод!$H$20 -> 725
A11: Дозвонились, шт | D11: =Ввод!$L$20 -> 166
A12: % дозвона | D12: =Ввод!$Y$20 -> 0.22896552
A13: Обещали оплату, шт | D13: =Ввод!$N$20 -> 96
A14: Не дозвонились, шт | D14: =Ввод!$P$20 -> 559
A15: Объезд, шт | D15: =Ввод!$R$20 -> 2
A16: Оплачено за день, сум | D16: =Ввод!$W$20 -> 0
A19: 2. ДЕТАЛИЗАЦИЯ ПО ОБЛАСТЯМ
A21: Область | B21: Ответственный | C21: Сотруд- ников | D21: % дозвона | E21: Просрочка на 1 сотр. | F21: Оплачено, сум | G21: Оценка
A22: =Ввод!$B$6 -> АНДИЖОН ВИЛОЯТИ | B22: =Ввод!$C$6 | C22: =Ввод!$D$6 -> 0 | D22: =IFERROR(Ввод!$Y$6,0) -> 0 | E22: =IFERROR(Ввод!$AA$6,0) | F22: =Ввод!$W$6 -> 0 | G22: =IF(Ввод!$H$6=0,"Нет данных",IF($D22>=0.8,"Отлично",IF($D22>=0.5,"Хорошо","Требует внимания"))) -> Требует внимания
A23: =Ввод!$B$7 -> БУХОРО ВИЛОЯТИ | B23: =Ввод!$C$7 | C23: =Ввод!$D$7 -> 0 | D23: =IFERROR(Ввод!$Y$7,0) -> 0 | E23: =IFERROR(Ввод!$AA$7,0) | F23: =Ввод!$W$7 -> 0 | G23: =IF(Ввод!$H$7=0,"Нет данных",IF($D23>=0.8,"Отлично",IF($D23>=0.5,"Хорошо","Требует внимания"))) -> Требует внимания
A24: =Ввод!$B$8 -> ЖИЗЗАХ ВИЛОЯТИ | B24: =Ввод!$C$8 | C24: =Ввод!$D$8 -> 0 | D24: =IFERROR(Ввод!$Y$8,0) -> 0.39215686 | E24: =IFERROR(Ввод!$AA$8,0) | F24: =Ввод!$W$8 -> 0 | G24: =IF(Ввод!$H$8=0,"Нет данных",IF($D24>=0.8,"Отлично",IF($D24>=0.5,"Хорошо","Требует внимания"))) -> Требует внимания
A25: =Ввод!$B$9 -> КАШКАДАРЁ ВИЛОЯТИ | B25: =Ввод!$C$9 | C25: =Ввод!$D$9 -> 0 | D25: =IFERROR(Ввод!$Y$9,0) -> 0.87878788 | E25: =IFERROR(Ввод!$AA$9,0) | F25: =Ввод!$W$9 -> 0 | G25: =IF(Ввод!$H$9=0,"Нет данных",IF($D25>=0.8,"Отлично",IF($D25>=0.5,"Хорошо","Требует внимания"))) -> Отлично
A26: =Ввод!$B$10 -> КОРАКАЛПОГИСТОН РЕСПУБЛИКАСИ | B26: =Ввод!$C$10 | C26: =Ввод!$D$10 -> 0 | D26: =IFERROR(Ввод!$Y$10,0) -> 0.76923077 | E26: =IFERROR(Ввод!$AA$10,0) | F26: =Ввод!$W$10 -> 0 | G26: =IF(Ввод!$H$10=0,"Нет данных",IF($D26>=0.8,"Отлично",IF($D26>=0.5,"Хорошо","Требует внимания"))) -> Хорошо
A27: =Ввод!$B$11 -> НАВОИЙ ВИЛОЯТИ | B27: =Ввод!$C$11 | C27: =Ввод!$D$11 -> 0 | D27: =IFERROR(Ввод!$Y$11,0) -> 0.055555556 | E27: =IFERROR(Ввод!$AA$11,0) | F27: =Ввод!$W$11 -> 0 | G27: =IF(Ввод!$H$11=0,"Нет данных",IF($D27>=0.8,"Отлично",IF($D27>=0.5,"Хорошо","Требует внимания"))) -> Требует внимания
A28: =Ввод!$B$12 -> НАМАНГАН ВИЛОЯТИ | B28: =Ввод!$C$12 | C28: =Ввод!$D$12 -> 0 | D28: =IFERROR(Ввод!$Y$12,0) -> 0.48387097 | E28: =IFERROR(Ввод!$AA$12,0) | F28: =Ввод!$W$12 -> 0 | G28: =IF(Ввод!$H$12=0,"Нет данных",IF($D28>=0.8,"Отлично",IF($D28>=0.5,"Хорошо","Требует внимания"))) -> Требует внимания
A29: =Ввод!$B$13 -> САМАРКАНД ВИЛОЯТИ | B29: =Ввод!$C$13 | C29: =Ввод!$D$13 -> 0 | D29: =IFERROR(Ввод!$Y$13,0) -> 0.24590164 | E29: =IFERROR(Ввод!$AA$13,0) | F29: =Ввод!$W$13 -> 0 | G29: =IF(Ввод!$H$13=0,"Нет данных",IF($D29>=0.8,"Отлично",IF($D29>=0.5,"Хорошо","Требует внимания"))) -> Требует внимания
A30: =Ввод!$B$14 -> СИРДАРЁ ВИЛОЯТИ | B30: =Ввод!$C$14 | C30: =Ввод!$D$14 -> 0 | D30: =IFERROR(Ввод!$Y$14,0) -> 0.58823529 | E30: =IFERROR(Ввод!$AA$14,0) | F30: =Ввод!$W$14 -> 0 | G30: =IF(Ввод!$H$14=0,"Нет данных",IF($D30>=0.8,"Отлично",IF($D30>=0.5,"Хорошо","Требует внимания"))) -> Хорошо
A31: =Ввод!$B$15 -> СУРХОНДАРЁ ВИЛОЯТИ | B31: =Ввод!$C$15 | C31: =Ввод!$D$15 -> 0 | D31: =IFERROR(Ввод!$Y$15,0) -> 0.18556701 | E31: =IFERROR(Ввод!$AA$15,0) | F31: =Ввод!$W$15 -> 0 | G31: =IF(Ввод!$H$15=0,"Нет данных",IF($D31>=0.8,"Отлично",IF($D31>=0.5,"Хорошо","Требует внимания"))) -> Требует внимания
A32: =Ввод!$B$16 -> ТОШКЕНТ ВИЛОЯТИ | B32: =Ввод!$C$16 | C32: =Ввод!$D$16 -> 0 | D32: =IFERROR(Ввод!$Y$16,0) -> 0 | E32: =IFERROR(Ввод!$AA$16,0) | F32: =Ввод!$W$16 -> 0 | G32: =IF(Ввод!$H$16=0,"Нет данных",IF($D32>=0.8,"Отлично",IF($D32>=0.5,"Хорошо","Требует внимания"))) -> Требует внимания
A33: =Ввод!$B$17 -> ТОШКЕНТ ШАХРИ | B33: =Ввод!$C$17 | C33: =Ввод!$D$17 -> 0 | D33: =IFERROR(Ввод!$Y$17,0) -> 0 | E33: =IFERROR(Ввод!$AA$17,0) | F33: =Ввод!$W$17 -> 0 | G33: =IF(Ввод!$H$17=0,"Нет данных",IF($D33>=0.8,"Отлично",IF($D33>=0.5,"Хорошо","Требует внимания"))) -> Требует внимания
A34: =Ввод!$B$18 -> ФАРГОНА ВИЛОЯТИ | B34: =Ввод!$C$18 | C34: =Ввод!$D$18 -> 0 | D34: =IFERROR(Ввод!$Y$18,0) -> 0 | E34: =IFERROR(Ввод!$AA$18,0) | F34: =Ввод!$W$18 -> 0 | G34: =IF(Ввод!$H$18=0,"Нет данных",IF($D34>=0.8,"Отлично",IF($D34>=0.5,"Хорошо","Требует внимания"))) -> Требует внимания
A35: =Ввод!$B$19 -> ХОРАЗМ ВИЛОЯТИ | B35: =Ввод!$C$19 | C35: =Ввод!$D$19 -> 0 | D35: =IFERROR(Ввод!$Y$19,0) -> 0.46938776 | E35: =IFERROR(Ввод!$AA$19,0) | F35: =Ввод!$W$19 -> 0 | G35: =IF(Ввод!$H$19=0,"Нет данных",IF($D35>=0.8,"Отлично",IF($D35>=0.5,"Хорошо","Требует внимания"))) -> Требует внимания
A41: 6. ЛИДЕРЫ И ОТСТАЮЩИЕ ПО % ДОЗВОНА (по областям)
A42: Лидеры | C42: % дозвона | E42: Требуют внимания | H42: % дозвона
A43: =IFERROR(INDEX(Ввод!$B$6:$B$19,MATCH(LARGE(Ввод!$AE$6:$AE$19,1),Ввод!$AE$6:$AE$19,0)),"") -> КАШКАДАРЁ ВИЛОЯТИ | C43: =IFERROR(INDEX(Ввод!$Y$6:$Y$19,MATCH(LARGE(Ввод!$AE$6:$AE$19,1),Ввод!$AE$6:$AE$19,0)),"") -> 0.87878788 | E43: =IFERROR(INDEX(Ввод!$B$6:$B$19,MATCH(SMALL(Ввод!$AE$6:$AE$19,1),Ввод!$AE$6:$AE$19,0)),"") -> АНДИЖОН ВИЛОЯТИ | H43: =IFERROR(INDEX(Ввод!$Y$6:$Y$19,MATCH(SMALL(Ввод!$AE$6:$AE$19,1),Ввод!$AE$6:$AE$19,0)),"") -> 0
A44: =IFERROR(INDEX(Ввод!$B$6:$B$19,MATCH(LARGE(Ввод!$AE$6:$AE$19,2),Ввод!$AE$6:$AE$19,0)),"") -> КОРАКАЛПОГИСТОН РЕСПУБЛИКАСИ | C44: =IFERROR(INDEX(Ввод!$Y$6:$Y$19,MATCH(LARGE(Ввод!$AE$6:$AE$19,2),Ввод!$AE$6:$AE$19,0)),"") -> 0.76923077 | E44: =IFERROR(INDEX(Ввод!$B$6:$B$19,MATCH(SMALL(Ввод!$AE$6:$AE$19,2),Ввод!$AE$6:$AE$19,0)),"") -> БУХОРО ВИЛОЯТИ | H44: =IFERROR(INDEX(Ввод!$Y$6:$Y$19,MATCH(SMALL(Ввод!$AE$6:$AE$19,2),Ввод!$AE$6:$AE$19,0)),"") -> 0
A45: =IFERROR(INDEX(Ввод!$B$6:$B$19,MATCH(LARGE(Ввод!$AE$6:$AE$19,3),Ввод!$AE$6:$AE$19,0)),"") -> СИРДАРЁ ВИЛОЯТИ | C45: =IFERROR(INDEX(Ввод!$Y$6:$Y$19,MATCH(LARGE(Ввод!$AE$6:$AE$19,3),Ввод!$AE$6:$AE$19,0)),"") -> 0.58823529 | E45: =IFERROR(INDEX(Ввод!$B$6:$B$19,MATCH(SMALL(Ввод!$AE$6:$AE$19,3),Ввод!$AE$6:$AE$19,0)),"") -> ТОШКЕНТ ВИЛОЯТИ | H45: =IFERROR(INDEX(Ввод!$Y$6:$Y$19,MATCH(SMALL(Ввод!$AE$6:$AE$19,3),Ввод!$AE$6:$AE$19,0)),"") -> 0

Sheet Дашборд
A3: Дата отчёта: | C3: =Ввод!$C$2 -> 46272 | E3: Просрочка, сум | H3: =Ввод!$G$20 -> 6.9014395e+09
E4: Оплачено за день, сум | H4: =Ввод!$W$20 -> 0
E5: Просрочка на 1 сотрудника, шт | H5: =IFERROR(Ввод!$H$20/Ввод!$D$20,0) -> 0
A7: СВОД ПО ОБЛАСТЯМ
A8: Область | B8: Тип | C8: Сотруд- ников | D8: Портфель, сум | E8: Просрочка, сум | F8: % просрочки | G8: Просрочка, шт | H8: Дозвон, шт | I8: % дозвона | J8: Просрочка на 1 сотр. | K8: Обещали, шт | L8: Оплачено, сум | M8: Оценка | N8: Область
A9: =Ввод!$B$6 -> АНДИЖОН ВИЛОЯТИ | C9: =Ввод!$D$6 -> 0 | D9: =Ввод!$E$6 -> 2.1670184e+10 | E9: =Ввод!$G$6 -> 2.1699731e+08 | F9: =IFERROR($E9/$D9,0) -> 0.010013635 | G9: =Ввод!$H$6 -> 32 | H9: =Ввод!$L$6 -> 0 | I9: =IFERROR($H9/$G9,0) -> 0 | J9: =IFERROR($G9/$C9,0) -> 0 | K9: =Ввод!$N$6 -> 0 | L9: =Ввод!$W$6 -> 0 | M9: =IF($G9=0,"Нет данных",IF($I9>=0.8,"Отлично",IF($I9>=0.5,"Хорошо","Требует внимания"))) -> Требует внимания | N9: =IFERROR(INDEX(Справочники!$H$4:$H$21,MATCH($A9,Справочники!$B$4:$B$21,0)),"")
A10: =Ввод!$B$7 -> БУХОРО ВИЛОЯТИ | C10: =Ввод!$D$7 -> 0 | D10: =Ввод!$E$7 -> 5.1231734e+09 | E10: =Ввод!$G$7 -> 2.0266951e+08 | F10: =IFERROR($E10/$D10,0) -> 0.03955937 | G10: =Ввод!$H$7 -> 18 | H10: =Ввод!$L$7 -> 0 | I10: =IFERROR($H10/$G10,0) -> 0 | J10: =IFERROR($G10/$C10,0) -> 0 | K10: =Ввод!$N$7 -> 0 | L10: =Ввод!$W$7 -> 0 | M10: =IF($G10=0,"Нет данных",IF($I10>=0.8,"Отлично",IF($I10>=0.5,"Хорошо","Требует внимания"))) -> Требует внимания | N10: =IFERROR(INDEX(Справочники!$H$4:$H$21,MATCH($A10,Справочники!$B$4:$B$21,0)),"")
A11: =Ввод!$B$8 -> ЖИЗЗАХ ВИЛОЯТИ | C11: =Ввод!$D$8 -> 0 | D11: =Ввод!$E$8 -> 1.3904205e+10 | E11: =Ввод!$G$8 -> 2.498528e+08 | F11: =IFERROR($E11/$D11,0) -> 0.017969585 | G11: =Ввод!$H$8 -> 51 | H11: =Ввод!$L$8 -> 20 | I11: =IFERROR($H11/$G11,0) -> 0.39215686 | J11: =IFERROR($G11/$C11,0) -> 0 | K11: =Ввод!$N$8 -> 19 | L11: =Ввод!$W$8 -> 0 | M11: =IF($G11=0,"Нет данных",IF($I11>=0.8,"Отлично",IF($I11>=0.5,"Хорошо","Требует внимания"))) -> Требует внимания | N11: =IFERROR(INDEX(Справочники!$H$4:$H$21,MATCH($A11,Справочники!$B$4:$B$21,0)),"")
A12: =Ввод!$B$9 -> КАШКАДАРЁ ВИЛОЯТИ | C12: =Ввод!$D$9 -> 0 | D12: =Ввод!$E$9 -> 1.2186569e+10 | E12: =Ввод!$G$9 -> 2.0555796e+08 | F12: =IFERROR($E12/$D12,0) -> 0.016867583 | G12: =Ввод!$H$9 -> 33 | H12: =Ввод!$L$9 -> 29 | I12: =IFERROR($H12/$G12,0) -> 0.87878788 | J12: =IFERROR($G12/$C12,0) -> 0 | K12: =Ввод!$N$9 -> 18 | L12: =Ввод!$W$9 -> 0 | M12: =IF($G12=0,"Нет данных",IF($I12>=0.8,"Отлично",IF($I12>=0.5,"Хорошо","Требует внимания"))) -> Отлично | N12: =IFERROR(INDEX(Справочники!$H$4:$H$21,MATCH($A12,Справочники!$B$4:$B$21,0)),"")
A13: =Ввод!$B$10 -> КОРАКАЛПОГИСТОН РЕСПУБЛИКАСИ | C13: =Ввод!$D$10 -> 0 | D13: =Ввод!$E$10 -> 1.1119545e+10 | E13: =Ввод!$G$10 -> 2.5963958e+08 | F13: =IFERROR($E13/$D13,0) -> 0.023349839 | G13: =Ввод!$H$10 -> 26 | H13: =Ввод!$L$10 -> 20 | I13: =IFERROR($H13/$G13,0) -> 0.76923077 | J13: =IFERROR($G13/$C13,0) -> 0 | K13: =Ввод!$N$10 -> 4 | L13: =Ввод!$W$10 -> 0 | M13: =IF($G13=0,"Нет данных",IF($I13>=0.8,"Отлично",IF($I13>=0.5,"Хорошо","Требует внимания"))) -> Хорошо | N13: =IFERROR(INDEX(Справочники!$H$4:$H$21,MATCH($A13,Справочники!$B$4:$B$21,0)),"")
A14: =Ввод!$B$11 -> НАВОИЙ ВИЛОЯТИ | C14: =Ввод!$D$11 -> 0 | D14: =Ввод!$E$11 -> 6.476845e+09 | E14: =Ввод!$G$11 -> 1.0708535e+08 | F14: =IFERROR($E14/$D14,0) -> 0.016533567 | G14: =Ввод!$H$11 -> 18 | H14: =Ввод!$L$11 -> 1 | I14: =IFERROR($H14/$G14,0) -> 0.055555556 | J14: =IFERROR($G14/$C14,0) -> 0 | K14: =Ввод!$N$11 -> 1 | L14: =Ввод!$W$11 -> 0 | M14: =IF($G14=0,"Нет данных",IF($I14>=0.8,"Отлично",IF($I14>=0.5,"Хорошо","Требует внимания"))) -> Требует внимания | N14: =IFERROR(INDEX(Справочники!$H$4:$H$21,MATCH($A14,Справочники!$B$4:$B$21,0)),"")
A15: =Ввод!$B$12 -> НАМАНГАН ВИЛОЯТИ | C15: =Ввод!$D$12 -> 0 | D15: =Ввод!$E$12 -> 1.4729616e+10 | E15: =Ввод!$G$12 -> 5.9799851e+08 | F15: =IFERROR($E15/$D15,0) -> 0.040598377 | G15: =Ввод!$H$12 -> 62 | H15: =Ввод!$L$12 -> 30 | I15: =IFERROR($H15/$G15,0) -> 0.48387097 | J15: =IFERROR($G15/$C15,0) -> 0 | K15: =Ввод!$N$12 -> 30 | L15: =Ввод!$W$12 -> 0 | M15: =IF($G15=0,"Нет данных",IF($I15>=0.8,"Отлично",IF($I15>=0.5,"Хорошо","Требует внимания"))) -> Требует внимания | N15: =IFERROR(INDEX(Справочники!$H$4:$H$21,MATCH($A15,Справочники!$B$4:$B$21,0)),"")
A16: =Ввод!$B$13 -> САМАРКАНД ВИЛОЯТИ | C16: =Ввод!$D$13 -> 0 | D16: =Ввод!$E$13 -> 1.6007859e+10 | E16: =Ввод!$G$13 -> 2.6721243e+08 | F16: =IFERROR($E16/$D16,0) -> 0.016692577 | G16: =Ввод!$H$13 -> 61 | H16: =Ввод!$L$13 -> 15 | I16: =IFERROR($H16/$G16,0) -> 0.24590164 | J16: =IFERROR($G16/$C16,0) -> 0 | K16: =Ввод!$N$13 -> 15 | L16: =Ввод!$W$13 -> 0 | M16: =IF($G16=0,"Нет данных",IF($I16>=0.8,"Отлично",IF($I16>=0.5,"Хорошо","Требует внимания"))) -> Требует внимания | N16: =IFERROR(INDEX(Справочники!$H$4:$H$21,MATCH($A16,Справочники!$B$4:$B$21,0)),"")
A17: =Ввод!$B$14 -> СИРДАРЁ ВИЛОЯТИ | C17: =Ввод!$D$14 -> 0 | D17: =Ввод!$E$14 -> 7.1897605e+09 | E17: =Ввод!$G$14 -> 97690450 | F17: =IFERROR($E17/$D17,0) -> 0.013587441 | G17: =Ввод!$H$14 -> 17 | H17: =Ввод!$L$14 -> 10 | I17: =IFERROR($H17/$G17,0) -> 0.58823529 | J17: =IFERROR($G17/$C17,0) -> 0 | K17: =Ввод!$N$14 -> 1 | L17: =Ввод!$W$14 -> 0 | M17: =IF($G17=0,"Нет данных",IF($I17>=0.8,"Отлично",IF($I17>=0.5,"Хорошо","Требует внимания"))) -> Хорошо | N17: =IFERROR(INDEX(Справочники!$H$4:$H$21,MATCH($A17,Справочники!$B$4:$B$21,0)),"")
A18: =Ввод!$B$15 -> СУРХОНДАРЁ ВИЛОЯТИ | C18: =Ввод!$D$15 -> 0 | D18: =Ввод!$E$15 -> 1.6585229e+10 | E18: =Ввод!$G$15 -> 1.0837511e+09 | F18: =IFERROR($E18/$D18,0) -> 0.065344354 | G18: =Ввод!$H$15 -> 97 | H18: =Ввод!$L$15 -> 18 | I18: =IFERROR($H18/$G18,0) -> 0.18556701 | J18: =IFERROR($G18/$C18,0) -> 0 | K18: =Ввод!$N$15 -> 2 | L18: =Ввод!$W$15 -> 0 | M18: =IF($G18=0,"Нет данных",IF($I18>=0.8,"Отлично",IF($I18>=0.5,"Хорошо","Требует внимания"))) -> Требует внимания | N18: =IFERROR(INDEX(Справочники!$H$4:$H$21,MATCH($A18,Справочники!$B$4:$B$21,0)),"")
A19: =Ввод!$B$16 -> ТОШКЕНТ ВИЛОЯТИ | C19: =Ввод!$D$16 -> 0 | D19: =Ввод!$E$16 -> 3.6871387e+10 | E19: =Ввод!$G$16 -> 8.8698663e+08 | F19: =IFERROR($E19/$D19,0) -> 0.024056232 | G19: =Ввод!$H$16 -> 93 | H19: =Ввод!$L$16 -> 0 | I19: =IFERROR($H19/$G19,0) -> 0 | J19: =IFERROR($G19/$C19,0) -> 0 | K19: =Ввод!$N$16 -> 0 | L19: =Ввод!$W$16 -> 0 | M19: =IF($G19=0,"Нет данных",IF($I19>=0.8,"Отлично",IF($I19>=0.5,"Хорошо","Требует внимания"))) -> Требует внимания | N19: =IFERROR(INDEX(Справочники!$H$4:$H$21,MATCH($A19,Справочники!$B$4:$B$21,0)),"")
A20: =Ввод!$B$17 -> ТОШКЕНТ ШАХРИ | C20: =Ввод!$D$17 -> 0 | D20: =Ввод!$E$17 -> 4.3531855e+10 | E20: =Ввод!$G$17 -> 1.6257267e+09 | F20: =IFERROR($E20/$D20,0) -> 0.037345679 | G20: =Ввод!$H$17 -> 115 | H20: =Ввод!$L$17 -> 0 | I20: =IFERROR($H20/$G20,0) -> 0 | J20: =IFERROR($G20/$C20,0) -> 0 | K20: =Ввод!$N$17 -> 0 | L20: =Ввод!$W$17 -> 0 | M20: =IF($G20=0,"Нет данных",IF($I20>=0.8,"Отлично",IF($I20>=0.5,"Хорошо","Требует внимания"))) -> Требует внимания | N20: =IFERROR(INDEX(Справочники!$H$4:$H$21,MATCH($A20,Справочники!$B$4:$B$21,0)),"")
A21: =Ввод!$B$18 -> ФАРГОНА ВИЛОЯТИ | C21: =Ввод!$D$18 -> 0 | D21: =Ввод!$E$18 -> 1.7403439e+10 | E21: =Ввод!$G$18 -> 806811380 | F21: =IFERROR($E21/$D21,0) -> 0.046359308 | G21: =Ввод!$H$18 -> 53 | H21: =Ввод!$L$18 -> 0 | I21: =IFERROR($H21/$G21,0) -> 0 | J21: =IFERROR($G21/$C21,0) -> 0 | K21: =Ввод!$N$18 -> 0 | L21: =Ввод!$W$18 -> 0 | M21: =IF($G21=0,"Нет данных",IF($I21>=0.8,"Отлично",IF($I21>=0.5,"Хорошо","Требует внимания"))) -> Требует внимания | N21: =IFERROR(INDEX(Справочники!$H$4:$H$21,MATCH($A21,Справочники!$B$4:$B$21,0)),"")
A22: =Ввод!$B$19 -> ХОРАЗМ ВИЛОЯТИ | C22: =Ввод!$D$19 -> 0 | D22: =Ввод!$E$19 -> 2.0499096e+10 | E22: =Ввод!$G$19 -> 2.9345986e+08 | F22: =IFERROR($E22/$D22,0) -> 0.014315746 | G22: =Ввод!$H$19 -> 49 | H22: =Ввод!$L$19 -> 23 | I22: =IFERROR($H22/$G22,0) -> 0.46938776 | J22: =IFERROR($G22/$C22,0) -> 0 | K22: =Ввод!$N$19 -> 6 | L22: =Ввод!$W$19 -> 0 | M22: =IF($G22=0,"Нет данных",IF($I22>=0.8,"Отлично",IF($I22>=0.5,"Хорошо","Требует внимания"))) -> Требует внимания | N22: =IFERROR(INDEX(Справочники!$H$4:$H$21,MATCH($A22,Справочники!$B$4:$B$21,0)),"")
A27: ИТОГО | C27: =SUM(C9:C26) -> 0 | D27: =SUM(D9:D26) -> 2.4329876e+11 | E27: =SUM(E9:E26) -> 6.9014395e+09 | F27: =IFERROR($E27/$D27,0) -> 0.02836611 | G27: =SUM(G9:G26) -> 725 | H27: =SUM(H9:H26) -> 166 | I27: =IFERROR($H27/$G27,0) -> 0.22896552 | J27: =IFERROR($G27/$C27,0) -> 0 | K27: =SUM(K9:K26) -> 96 | L27: =SUM(L9:L26) -> 0 | M27: =IF($I27>=0.8,"Отлично",IF($I27>=0.5,"Хорошо","Требует внимания")) -> Требует внимания

Sheet Справочники
A3: № | B3: Филиал (точно как в файлах) | C3: Тип | D3: Ответственный (Ф.И.О.) | E3: Кол-во сотрудников | F3: Телефон | G3: Норматив % просрочки | H3: Область | K3: Оценка эффективности | N3: Статус проверки
A4: 1 | B4: Урганч филиали | C4: Регион | D4: — впишите — | E4: 0 | F4: +998 __ ___ __ __ | G4: 0.05 | H4: ХОРАЗМ ВИЛОЯТИ | K4: Отлично (≥80% дозвона) | N4: Не проверено
A5: 2 | B5: Самарқанд филиали | C5: Регион | D5: — впишите — | E5: 0 | F5: +998 __ ___ __ __ | G5: 0.05 | H5: САМАРКАНД ВИЛОЯТИ | K5: Хорошо (50–79%) | N5: Проверено куратором
A6: 3 | B6: Денов филиали | C6: Регион | D6: — впишите — | E6: 0 | F6: +998 __ ___ __ __ | G6: 0.05 | H6: СУРХОНДАРЁ ВИЛОЯТИ | K6: Требует внимания (<50%)
A7: 4 | B7: Жиззах филиали | C7: Регион | D7: — впишите — | E7: 0 | F7: +998 __ ___ __ __ | G7: 0.05 | H7: ЖИЗЗАХ ВИЛОЯТИ | K7: Нет данных
A8: 5 | B8: Андижон филиали | C8: Регион | D8: — впишите — | E8: 0 | F8: +998 __ ___ __ __ | G8: 0.05 | H8: АНДИЖОН ВИЛОЯТИ
A9: 6 | B9: Наманган филиали | C9: Регион | D9: — впишите — | E9: 0 | F9: +998 __ ___ __ __ | G9: 0.05 | H9: НАМАНГАН ВИЛОЯТИ
A10: 7 | B10: Фарғона филиали | C10: Регион | D10: — впишите — | E10: 0 | F10: +998 __ ___ __ __ | G10: 0.05 | H10: ФАРГОНА ВИЛОЯТИ
A11: 8 | B11: Қарши филиали | C11: Регион | D11: — впишите — | E11: 0 | F11: +998 __ ___ __ __ | G11: 0.05 | H11: КАШКАДАРЁ ВИЛОЯТИ
A12: 9 | B12: Нукус филиали | C12: Регион | D12: — впишите — | E12: 0 | F12: +998 __ ___ __ __ | G12: 0.05 | H12: КОРАКАЛПОГИСТОН РЕСПУБЛИКАСИ
A13: 10 | B13: Навоий филиали | C13: Регион | D13: — впишите — | E13: 0 | F13: +998 __ ___ __ __ | G13: 0.05 | H13: НАВОИЙ ВИЛОЯТИ
A14: 11 | B14: Бухоро филиали | C14: Регион | D14: — впишите — | E14: 0 | F14: +998 __ ___ __ __ | G14: 0.05 | H14: БУХОРО ВИЛОЯТИ
A15: 12 | B15: Термиз филиали | C15: Регион | D15: — впишите — | E15: 0 | F15: +998 __ ___ __ __ | G15: 0.05 | H15: СУРХОНДАРЁ ВИЛОЯТИ
A16: 13 | B16: Гулистон филиали | C16: Регион | D16: — впишите — | E16: 0 | F16: +998 __ ___ __ __ | G16: 0.05 | H16: СИРДАРЁ ВИЛОЯТИ
A17: 14 | B17: Олмалиқ филиали | C17: Регион | D17: — впишите — | E17: 0 | F17: +998 __ ___ __ __ | G17: 0.05 | H17: ТОШКЕНТ ВИЛОЯТИ
A18: 15 | B18: Чирчик филиали | C18: Регион | D18: — впишите — | E18: 0 | F18: +998 __ ___ __ __ | G18: 0.05 | H18: ТОШКЕНТ ВИЛОЯТИ
A19: 16 | B19: Янги Йул филиали | C19: Регион | D19: — впишите — | E19: 0 | F19: +998 __ ___ __ __ | G19: 0.05 | H19: ТОШКЕНТ ВИЛОЯТИ
... A21: 18 | B21: BOSH OFIS | C21: Центральное | D21: — впишите — | E21: 0 | F21: +998 __ ___ __ __ | G21: 0.05 | H21: ТОШКЕНТ ШАХРИ
B22: ИТОГО | E22: =SUM(E4:E21) -> 0

Sheet Дозвонились
A1: ← Вернуться в отчёт
A2: Область | B2: Филиал | C2: Группа | D2: Код клиента | E2: Клиент | F2: Номер телефона | G2: Адрес | H2: Кол-во просроченных дней | I2: Итого просрочка | J2: Оплата | K2: Izoh
A3: АНДИЖОН ВИЛОЯТИ | C3: Обещал | D3: Кр-99062885-1 | E3: KASIMXODJAYEV ABDUXALIL ABDUMAJITOVICH | F3: +998916208060 SMS O’ZI, 998914781293 SMS AYOLI, 998916028060 SMS UY, 998976208060 SMS O’ZI2, | G3: ANDIJON VILOYATI ANDIJON SHAHAR MAYDONBOZOR MFY YAXSHI KO’CHASI 61/59-UY | H3: 10 | I3: 14507308 | K3: Va'da berdi | 1-2 kunda hal qiladi | 4383561.643835616 | 10123746.15
A4: АНДИЖОН ВИЛОЯТИ | C4: Обещал | D4: Кр-99058759-1 | E4: RAXMANOV DILSHODBEK TO’XTASINOVICH | F4: 998889930005 SMS OZI, 998955173700 SMS AYOLI, 998979970184 SMS UKASI, 998949300052 SMS OZI 2, | G4: ANDIJON VILOYATI QO’RG’ONTEPA TUMANI DEXQONCHEK MFY ERKIN IJOD KO’CHASI 74-UY | H4: 13 | I4: 13767147 | K4: Va'da berdi | 25 kunga hal qiladi | 5342465.7534246575 | 8424681.47
A5: АНДИЖОН ВИЛОЯТИ | C5: Обещал | D5: Кр-99047889-1 | E5: SHIRMATOV MUXAMMADOZOD QODIRALI O’G’LI | F5: +998911715500 SMS O’ZI, 998772495500 SMS OG’LI, 998972225500 SMS UY, 998998173300 SMS NEVARASI, | G5: ANDIJON VILOYATI ANDIJON SHAHAR ISTIQLOL MFY OBOD 1-TOR KO’CHASI 5-UY | H5: 13 | I5: 12856969 | K5: Va'da berdi | 25 kunga hal qiladi | 4630136.98630137 | 8226832.27
A6: АНДИЖОН ВИЛОЯТИ | C6: Обещал | D6: Кр-99060389-1 | E6: SULTANOVA XAMIDA ULJABEKOVNA | F6: +998934141584 SMS O’ZI, 998973243443 SMS KELINI, 998979753443 SMS O’G’LI, 998993200858 SMS XO’JAYNI, | G6: Andijon viloyati Andijon shahar Sadoqat MFY Fuzuliy ko’chasi 49-uy | H6: 10 | I6: 12724541 | K6: Va'da berdi | dushanba seshanba kuni | 3835616.438356164 | 8888924.39
A7: АНДИЖОН ВИЛОЯТИ | C7: Обещал | D7: Кр-99061048-1 | E7: ORIFJANOV NODIRBEK OMANJANOVICH | F7: 998916841884 uzi, 998335177797 ayoli, 998944870903 onasi, | G7: ANDIJON VILOYATI QO’RG’ONTEPA TUMANI SAVAY YANGI BO’STON MFY BARKAMOL KO’CHASI 58-UY | H7: 13 | I7: 11960620 | K7: Va'da berdi | shu hafta hal qilib berdi | 4273972.602739726 | 7686647.26
A8: АНДИЖОН ВИЛОЯТИ | C8: Обещал | D8: Кр-99061572-1 | E8: AXMEDOV JAVOHIRBEK TOJIDIN O’G’LI | F8: 998907726810 узи, 998910676800 аели, 998882357585 укаси, 998974054333 укаси, | G8: ANDIJON VILOYATI ANDIJON TUMANI NURAFSHON MFY YANGI TURMUSH KO’CHASI 69A-UY | H8: 13 | I8: 11959423 | K8: Va'da berdi | 25 kunga hal qiladi | 4273972.602739726 | 7685450.86
A9: АНДИЖОН ВИЛОЯТИ | C9: Обещал | D9: Кр-99024542-1 | E9: XALMATOV ADIL PAZILOVICH | F9: 77-123-13-10 SMS OZI, 98-707-22-92 SMS OZI, 90-541-13-18 SMS OZI, 998880072292 УГЛИ шохрух, | G9: ANDIJON VILOYATI ANDIJON SHAHAR ISLOMOBOD MFY 7-TOR MUXITDINOV 21-UY | H9: 8 | I9: 11534220 | K9: Va'da berdi | 25 kuni tolaydi | 5041095.890410959 | 6493123.81
A10: АНДИЖОН ВИЛОЯТИ | C10: Обещал | D10: Кр-99063922-3 | E10: RUZIYEVA RANO KABILOVNA | F10: +998905437075 SMS O’ZI, 998902597075 SMS UY, 998906257691 SMS OPASI, 998921519222 SMS QIZI, | G10: ANDIJON VILOYATI ANDIJON SHAHAR O’ZBEGIM MFY, A. MUSAYE KO’CHASI 4-UY 31-XONADON | H10: 10 | I10: 11102362 | K10: Va'da berdi | dushanba kuni tolaydi | 3835616.438356164 | 7266745.79
A11: АНДИЖОН ВИЛОЯТИ | C11: Обещал | D11: Кр-99063424-2 | E11: TURSUNOV RAXMATILLO IKRAMJANOVICH | F11: 998702250075 SMS OZI, 998886020075 SMS UKASI2, 998889248080 SMS AYOLI, 998970711009 SMS UKASI, | G11: ANDIJON VILOYATI QO’RG’ONTEPA TUMANI | H11: 10 | I11: 10783206 | K11: Va'da berdi | 25 kuni tolaydi | 3013698.6301369863 | 7769507.51
A12: АНДИЖОН ВИЛОЯТИ | C12: Обещал | D12: Кр-99033455-2 | E12: ABDULAZIZOV NOZIMJON NASIBJONOVICH | F12: 998934104844 SMS O’ZI, 998000048002 SMS O’ZI 2, 998932544648 SMS AYOLI, 998936913859 SMS XAMKASBI, 998948770475 SMS otasi new , | G12: ANDIJON VILOYATI PAXTAOBOD TUMANI MA’RIFAT MFY,MA’RIFAT KO’CHASI 47-UY | H12: 6 | I12: 10697383 | K12: Va'da berdi | 1-2 kunda hal qiladi | 2465753.4246575343 | 8231629.93
A13: АНДИЖОН ВИЛОЯТИ | C13: Дозвон | D13: Кр-99039306-1 | E13: ODILJONOV ABDULAZIZ UMIDJON O’G’LI | F13: 998934153932 SMS OZI, 998937810042 SMS ONASI, 998937810094 SMS OTASI, 998941051030 SMS AKASI, | G13: ANDIJON VILOYATI ANDIJON SHAHAR DALVARZIN MFY A.ASHUROV 3-TOR KO’CHASI 4-UY | H13: 14 | I13: 10688765 | J13: 3835616 | K13: To'ladi | 3835616.4383561644 | 6853149.05
A14: АНДИЖОН ВИЛОЯТИ | C14: Обещал | D14: Кр-99062998-1 | E14: TURDIMAMATOV ERKINJON ABDUMANNABOVICH | F14: +998880040107 SMS O’ZI, 998884772717 SMS O’G’LI, 998914870066 SMS AYOLI, 998941068585 SMS QIZI, | G14: ANDIJON VILOYATI BO’STON TUMANI MADANIYAT MFY, TINCHLIK KO’CHASI 3-UY | H14: 10 | I14: 10186881 | K14: Va'da berdi | dushanba kuni tolaydi | 3287671.2328767125 | 6899210.02
A15: АНДИЖОН ВИЛОЯТИ | C15: Обещал | D15: Кр-99057627-1 | E15: ABDUGANIYEVA MATLUBAXON XXX | F15: 998911757604 SMS OZI, 998902011084 SMS OGLI, 998910611084 SMS KELIMI, 998907620065 SMS QUDASI, | G15: ANDIJON VILOYATI ANDIJON SHAHAR QORATUT MFY 5-KICHIK NOXIYA KO’CHASI 17-UY, 78-XONADON | H15: 13 | I15: 9732853.8 | K15: Va'da berdi | shu hafta hal qilib berdi | 4630136.98630137 | 5102716.8
A16: АНДИЖОН ВИЛОЯТИ | C16: Обещал | D16: Кр-99063505-1 | E16: QORABOYEV XURSANBEK XXX | F16: +998950760759 SMS O’ZI, 998937805535 SMS QIZI, 998947861300 SMS O’G’LI, 998948630360 SMS AYOLI, 998932428771 SMS Tolovchi Azamat , | G16: ANDIJON VILOYATI ASAKA TUMANI NAMUNA BO’STON MFY QIPCHOQ KO’CHASI 53-UY | H16: 10 | I16: 9187621.6 | K16: Va'da berdi | 18-19 kuni tolaydi | 3835616.438356164 | 5352005.14
A17: АНДИЖОН ВИЛОЯТИ | C17: Обещал | D17: Кр-99033808-2 | E17: NASIRDINOV MANOPJON PATTAYEVICH | F17: 998931053080 SMS O’ZI meva sotadi , 998900000000 SMS, +998916126328 SMS O’ZI, 998916031864 SMS O’ZI2, 998943877760 SMS O’G’LI, | G17: ANDIJON VILOYATI ANDIJON TUMANI GUMBAZ MFY SHODIYONA KO’CHASI 65-UY | H17: 10 | I17: 9130923.9 | K17: Va'da berdi | 25 gacha hal qiladi | 2739726.02739726 | 6391197.88
A18: АНДИЖОН ВИЛОЯТИ | C18: Обещал | D18: Кр-99057460-1 | E18: ONORBOY O’G’LI PULATJON XXX | F18: 998953135155 SMS UZI, 998954616995 SMS AYOLI, 998902025254 SMS AKASI, 998772639874 SMS OPASI, | G18: ANDIJON VILOYATI QO’RG’ONTEPA TUMANI DARDOK, NAVOIY MFY YANGI OBOD KO’CHASI 334-UY | H18: 10 | I18: 9110715.3 | K18: Va'da berdi | oyni oxirigacha hal qiladi | 2739726.02739726 | 6370989.29
A19: АНДИЖОН ВИЛОЯТИ | C19: Обещал | D19: Кр-99062903-1 | E19: BAZARBAYEV ISMOILJON IBRAXIMOVICH | F19: +998902581505 SMS O’ZI, 998774300260 SMS AYOLI, 998932477040 SMS UY, 998943338444 SMS O’ZI 2, | G19: ANDIJON VILOYATI ANDIJON SHAHAR XAMDO’STLIK MFY IFTIXOR KO’CHASI 64-UY | H19: 10 | I19: 9070252.6 | K19: Va'da berdi | 19-20 kuni hal qiladi | 3287671.2328767125 | 5782581.32
A20: АНДИЖОН ВИЛОЯТИ | C20: Обещал | D20: Кр-99061829-1 | E20: JO’RAYEV BAXTIYAR BAZAROVICH | F20: 998994380553 ozi, 998944172190 ayoli, 998500450753 ogli, | G20: Манзил: ANDIJON VILOYATI ASAKA TUMANI FAROVON MFY UZUN KO’CHASI 64-UY | H20: 10 | I20: 9054359.3 | K20: Va'da berdi | dushanba kuni tolaydi | 2739726.02739726 | 6314633.3
A21: АНДИЖОН ВИЛОЯТИ | C21: Обещал | D21: Кр-99050885-1 | E21: TAYLAKOVA MA’MURAXON NEMATJANOVNA | F21: 998501951880 SMS OZI, 998941173187 SMS UAKSI, 998936318477 SMS SINGLISI, 998970174417 SMS KELINI, | G21: ANDIJON VILOYATI ANDIJON SHAHAR BUNYODKOR MFY QO’SH ARIQ DAXASI 46-UY 31-XONADON | H21: 10 | I21: 9000036.9 | K21: Va'da berdi | dushanba seshanba kuni | 2739726.02739726 | 6260310.86
A22: АНДИЖОН ВИЛОЯТИ | C22: Обещал | D22: Кр-99044950-1 | E22: MAMAYUNUSOV SOBIRJON YUSUPOVICH | F22: +998903831002 SMS O’ZI, 998500448004 SMS O’ZI2, 998902202308 SMS QIZI, 998910697782 SMS XO’JAYNI, | G22: АНДИЖОН ВИЛОЯТИ МАРХАМАТ ТУМАНИ ГУЛИСТОН МФЙ, ФИДОКОР КЎЧАСИ, uy:Р/С | H22: 13 | I22: 8994448.5 | K22: Va'da berdi | shu hafta hal qilib berdi | 3205479.452054795 | 5788969.04
A23: АНДИЖОН ВИЛОЯТИ | C23: Обещал | D23: Кр-99063433-1 | E23: MAMIROV SHAVKATBEK BURIBAYEVICH | F23: +998914753616 SMS O’ZI, 998774111767 SMS AYOLI, 998902076067 SMS KELINI, 998905536067 SMS O’G’LI, | G23: ANDIJON VILOYATI ANDIJON TUMANI TOSHLOQ MFY, MIRZA KO’CHASI 798-UY | H23: 10 | I23: 8973303.2 | K23: Va'da berdi | oyni oxirigacha hal qiladi | 2739726.02739726 | 6233577.22
A24: АНДИЖОН ВИЛОЯТИ | C24: Обещал | D24: Кр-99033504-1 | E24: NIYAZOV XAYBATULLA BURXANOVICH | F24: 998979926505 SMS OZI, 998501881794 SMS O'G'LI, 998951679511 SMS KELINI, 998507199794 SMS QIZI, | G24: ANDIJON VILOYATI ASAKA TUMANI QADRIYAT MFY HUMO KO’CHASI 39-UY 28- XONADON | H24: 10 | I24: 8118559.8 | K24: Va'da berdi | 25 gacha hal qiladi | 2465753.4246575343 | 5652806.42
A25: АНДИЖОН ВИЛОЯТИ | C25: Обещал | D25: Кр-99039487-1 | E25: USMANOV RAXMANALI XXX | F25: 998507778257 SMS OZI, 998949595701 SMS AYOLI, 998330880202 SMS OGLI, 998505081800 SMS KELINI, | G25: ANDIJON VILOYATI JALOLQUDUQ TUMANI OLMAZOR MFY OTASHKALB KO’CHASI 26-UY | H25: 7 | I25: 7796182.4 | K25: Va'da berdi | oyni oxirigacha hal qiladi | 1917808.2191780822 | 5878374.15
... A68: АНДИЖОН ВИЛОЯТИ | C68: Обещал | D68: Кр-99063829-1 | E68: MIRZAYEV ABDULAZIZ RUSTAMOVICH | F68: 998773674777 SMS ONASI, 998940207105 SMS UZI, 998970610099 SSM AKASI, 998990723095 SMS DOSTI, | G68: Quvvatmurod MFY, Dilkushod ko’chasi, 139-uy | H68: 3 | I68: 3406936.5 | K68: Va'da berdi | akasi oldi aytib qoyadi ekan | 205479.45205479453 | 3201457
A69: АНДИЖОН ВИЛОЯТИ | C69: Дозвон | D69: Кр-99039609-1 | E69: TOJIDINOVA MUXARRAMXON KOBULOVNA | F69: 998940331487 SMS OZI, 998950978615 SMS XOJAYINI, 998903870911 SMS OGLI, 998934168183 SMS AKASI, | G69: ANDIJON VILOYATI MARXAMAT TUMANI MIRISHKOLAR MFY, DORBOZ KO’CHASI 45-UY | H69: 3 | I69: 3360170 | J69: 410958 | K69: To'ladi | 410958.90410958906 | 2949211.13
A70: АНДИЖОН ВИЛОЯТИ | C70: Обещал | D70: Кр-99040988-1 | E70: ISAQJONOV PAXLAVONJON XUSNIDDIN O’G’LI | F70: +998888008486 SMS O’ZI, 998770009233 SMS UKASI, 998991498699 SMS AYOLI, | G70: ТОПТИҚ МФЙ, ТОПТИҚ КЎЧАСИ, uy:Р/С | H70: 15 | I70: 3315627.6 | K70: Va'da berdi | 25 kunga hal qiladi | 1232876.7123287672 | 2082750.87
A71: АНДИЖОН ВИЛОЯТИ | C71: Обещал | D71: Кр-99037428-1 | E71: TOLIPOV MUHIDDIN AVAZJON O’G’LI | F71: 998505111153 SMS UZI , 998995001004 SMS OZI 2, 998911717258 SMS ISHXONASI, 998998677258 SMS AYOLI, | G71: ANDIJON VILOYATI BULOQBOSHI TUMANI FAROVON MFY OXANGARON KO’CHASI 46-UY | H71: 1 | I71: 3247405.4 | K71: Va'da berdi | shu hafta hal qiladi | 136986.301369863 | 3110419.08
A72: АНДИЖОН ВИЛОЯТИ | C72: Обещал | D72: Кр-99046070-1 | E72: MADAMINOV UMIDILLO MANSURJON O’G’LI | F72: +998993039777 SMS O’ZI, 998950549306 SMS AYOLI, 998979959266 SMS UKASI, 998994069576 SMS ONASI, | G72: Andijon viloyati Paxtaobod tumani Soybo’yi MFY Soybo’yi ko’chasi, 40-yu | H72: 10 | I72: 3192409.6 | K72: Va'da berdi | dushanba seshanba kuni | 2191780.821917808 | 1000628.83
A73: АНДИЖОН ВИЛОЯТИ | C73: Обещал | D73: Кр-99040884-2 | E73: ABDILAJONOV LATIPJON XXX | F73: +998950121049 SMS O’ZI, 998871087272 SMS O’G’LI, 998936770060 SMS NABIRASI, 998955801953 SMS AYOLI, | G73: ХЎЖАТЕПА МФЙ, МАШИНАСОЗЛАР КЎЧАСИ, uy:Р/С | H73: 14 | I73: 3101599 | K73: Va'da berdi | shu hafta hal qilib berdi | 2684931.506849315 | 416667.49
A74: АНДИЖОН ВИЛОЯТИ | C74: Обещал | D74: Кр-99063829-2 | E74: MIRZAYEV ABDULAZIZ RUSTAMOVICH | F74: 998773674777 SMS ONASI, 998940207105 SMS UZI, 998970610099 SSM AKASI, 998990723095 SMS DOSTI, | G74: Quvvatmurod MFY, Dilkushod ko’chasi, 139-uy | H74: 3 | I74: 2725548.6 | K74: Va'da berdi | akasi oldi aytib qoyadi ekan | 164383.56164383562 | 2561165
A75: АНДИЖОН ВИЛОЯТИ | C75: Обещал | D75: Кр-99027758-1 | E75: TO’LANBOYEV DONIYORBEK BAXTIYORJON O’G’LI | F75: 91-137-25-32 SMS O'ZI, 93-413-04-41 SMS AKASI бегона, 93-436-04-41 SMS OWNASI, 33-711-02-00 SMS BOLLARI, 998882341189 SMS onasi new, 998934364004 SMS new ozi , 998937891414 SMS ayoli (begona tek qlinmasin!!!!), 998934360440 SMS ozi new, 998882341189 SMS onasi new, | G75: ANDIJON VILOYATI ANDIJON SHAHAR BOG’ISHAMOL MFY K. DJABBAROV KO’CHASI 5-UY | H75: 3 | I75: 2683298 | K75: Va'da berdi | 20 kunga hal qiladi | 410958.90410958906 | 2272339.07
A76: АНДИЖОН ВИЛОЯТИ | C76: Обещал | D76: Кр-99038903-1 | E76: G’OFUROVA SANTALATXON TOXIRJON QIZI | F76: 998942572820 SMS OZI , 998931161001 SMS OZI 2 begona , 998935511000 SMS QAYNI SINGLISI, 998939856162 SMS QAYSINI, | G76: ANDIJON VILOYATI ANDIJON TUMANI DARXON MFY, ZAROBOD KO’CHASI 91-UY | H76: 1 | I76: 2622309.2 | K76: Va'da berdi | shu hafta hal qiladi | 109589.04109589041 | 2512720.12
A77: АНДИЖОН ВИЛОЯТИ | C77: Обещал | D77: Кр-99039608-1 | E77: FAXRUTDINOV FAZLITDIN XAYBATULLAYEVICH | F77: 998936926077 SMS OZI, 998951175010 SMS OGLI, 998977712560 SMS OGLI2, | G77: ANDIJON VILOYATI SHAXRIXON TUMANI MULLABOY MFY, AXMAD YASSAVIY KO’CHASI 28-UY | H77: 3 | I77: 2588011.7 | K77: Va'da berdi | bugun hal qiladi | 1643835.6164383562 | 944176.12
A78: АНДИЖОН ВИЛОЯТИ | C78: Обещал | D78: Кр-99062971-1 | E78: ABDULLAYEV O’TKIRBEK MAMASIDIKOVICH | F78: +998932333213 SMS O’ZI, 998507033213 SMS UY, 998931033213 SMS O’G’LI, 998946107010 SMS O’G’LI, | G78: ANDIJON VILOYATI ANDIJON TUMANI CHEM MFY, GULSHAN KO’CHASI 88-UY | H78: 10 | I78: 2448077.5 | K78: Va'da berdi | 25 gacha hal qiladi | 1095890.410958904 | 1352187.12
A79: АНДИЖОН ВИЛОЯТИ | C79: Обещал | D79: Кр-99041191-1 | E79: SHOXINAZAROV ABDULLOH AZIZBEK O’G’LI | F79: +998880662277 SMS O’ZI, 998881005751 SMS ONASI, 998931005751 SMS DADASI, 998970272127 SMS DO’STI MUXAMMADSOLIQ, | G79: Экин тикин МФЙ, Шафтолизор кучаси, 252-уй | H79: 10 | I79: 2283916 | K79: Va'da berdi | bugun erta hal qiladi | 684931.506849315 | 1598984.53
A80: АНДИЖОН ВИЛОЯТИ | C80: Дозвон | D80: Кр-99004621-4 | E80: NADIROV MURODJON BAXRAMJON O’G’LI | F80: 90-543-11-01 SMS, 99-327-66-67 sms танимийди, 90-528-19-14 SMS TANIMASAKAN , 91-175-12-12 SMS ortogi, +998905431101 SMS O’ZI, 998887838780 SMS AKASI, 998946398780 SMS JIYANI ASADBEK, 998977268780 SMS UKASI, | G80: Саноат МФЙ, А.Йулдошев 1 тор кучаси, 37-уй | H80: 10 | I80: 2150272.7 | J80: 410958 | K80: To'ladi | 410958.90410958906 | 1739313.84
A81: АНДИЖОН ВИЛОЯТИ | C81: Обещал | D81: Кр-99038983-2 | E81: REJABOVA GULNOZA MAXAMMADJON QIZI | F81: 998331132300 SMS OZI olmaliqda kambinatda ishlid , 998931632300 SMS AKASI, 998987882323 SMS UKASI, 998944009532 SMS ONASI, | G81: ANDIJON VILOYATI QO’RG’ONTEPA TUMANI DEXQONCHEK MFY SAJDAGOX KO’CHASI 30-UY | H81: 10 | I81: 1986455.7 | K81: Va'da berdi | bugun erta hal qiladi | 364383.5616438356 | 1622072.12
A82: АНДИЖОН ВИЛОЯТИ | C82: Обещал | D82: Кр-99029531-1 | E82: TOLIBJONOVA MAFTUNAXON OYBEK QIZI | F82: 77-039-54-54 SMS OZI, 90-220-91-91 SMS ZALOGADATEL, 94-385-88-88 SMS TOLOVCHI ABDULLOX, 90-542-32-22 SMS UKASI, 998902043130 ozi, 998902004000 SMS TO'LOVCHI, 998905445400 qaynotasi , | G82: ANDIJON VILOYATI ANDIJON TUMANI ISTIQLOL MFY OQ YOR KO’CHASI 163-UY | H82: 3 | I82: 1957283.7 | K82: Va'da berdi | bugun erta hal qiladi | 287671.23287671234 | 1669612.43
A83: АНДИЖОН ВИЛОЯТИ | C83: Обещал | D83: Кр-99039141-1 | E83: SAIDBEKOVA MOXINUR MUXAMMADJON QIZI | F83: 998970957667 SMS OZI, 998974114774 SMS AKASI begona, | G83: ANDIJON VILOYATI ANDIJON SHAHAR MASH’AL MFY T.REJAPOV 1-UY 53-XONADON | H83: 10 | I83: 1954465.3 | K83: Va'da berdi | 20 gacha hal qiladi | 547945.205479452 | 1406520.06
A84: АНДИЖОН ВИЛОЯТИ | C84: Обещал | D84: Кр-99063628-3 | E84: TASHMATOV XUSNUTDIN ODILJANOVICH | F84: 998901705955 O’ZI, | G84: АНДИЖОН ВИЛОЯТИ АНДИЖОН ШАХAР АХМАД ЯССАВИЙ МФЙ ЛОЙИХАЛАШ КУЧАСИ 6-УЙ | H84: 10 | I84: 1588633.2 | K84: Va'da berdi | Farrux aka bn gaplashgan | 547945.205479452 | 1040687.97
A85: АНДИЖОН ВИЛОЯТИ | C85: Обещал | D85: Кр-99027653-1 | E85: G’ANIYEV MARDONBEK DILMUROD O’G’LI | F85: 97-834-27-17 SMS O'ZI, 99-402-73-17 SMS ZALOGADATEL, 99-494-13-38 SMS KELINOYISI, 91-481-17-11 SMS DO’STI Begona , | G85: ANDIJON VILOYATI MARXAMAT TUMANI NAVRO’Z MFY CHILONZOR KO’CHASI 114-UY | H85: 10 | I85: 1301512.2 | K85: Va'da berdi | shu hafta oxiriga tashlab beradi ekan ozi rusda ekan | 493150.68493150687 | 808361.49
A86: АНДИЖОН ВИЛОЯТИ | C86: Обещал | D86: Кр-99035336-2 | E86: RO’ZIYEVA MUNIRAXON SULTONOVNA | F86: 998936907720 SMS OZI, 998949796867 SMS QIZI, 998504044603 SMS OGLI, 998934446258 SMS ONASI, | G86: ANDIJON VILOYATI BO’Z TUMANI MUSTAQILLIK KO’CHASI 70-UY,11-XONADON | H86: 10 | I86: 1268111 | K86: Va'da berdi | 20 kunga hal qiladi | 383561.6438356164 | 884549.36
A87: АНДИЖОН ВИЛОЯТИ | C87: Обещал | D87: Кр-99036805-2 | E87: BESHBAYEVA OYAT KASIMOVA | F87: 998979805801 SMS ozi , 998950012711 SMS ogli , 998501114027 SMS kelini , 998938252911 SMS ukasi , 998979805801 SMS ozi , | G87: ANDIJON SHAHRI | H87: 10 | I87: 1141809.7 | K87: Va'da berdi | 20-25 kuni hal qiladi | 273972.602739726 | 867837.09
A88: АНДИЖОН ВИЛОЯТИ | C88: Обещал | D88: Кр-99038164-1 | E88: TURSUNALIYEV SIROJIDDIN YUNUSALI O’G’LI | F88: 998883397171 SMS OZI, 998509978785 SMS AKASI, 998772880618 SMS OPASI, 998951552560 SMS DADASI, | G88: ANDIJON VILOYATI BULOQBOSHI TUMANI RIVOJ MFY,YANGI CHEK KO’CHASI 412-UY | H88: 3 | I88: 1060078.1 | K88: Va'da berdi | 20 kunga hal qiladi | 575342.4657534247 | 484735.62
A89: АНДИЖОН ВИЛОЯТИ | C89: Обещал | D89: Кр-99038275-3 | E89: KARIMOVA XAMROXON MO’YDINOVNA | F89: 998508831410 SMS OZI, 998948881410 SMS OGLI, 998916012492 SMS KELINI, 998937359892 SMS AKASI, | G89: ANDIJON VILOYATI SHAXRIXON TUMANI YANGIMAXALLA MFY, OBOD KO’CHASI 75/1-UY | H89: 10 | I89: 913144.31 | K89: Va'da berdi | shu hafta hal qiladi | 246575.34246575343 | 666568.97
A90: БУХОРО ВИЛОЯТИ | B90: SUPER BRANCH | C90: Обещал | D90: Кр-99063363-1 | E90: KOMILOVA ZEBO NURIDDINOVNA | F90: 998995031288 OZI, 998773127040 JIYANI, 998998621288 ONASI, 998770900005 DOSTI, | G90: BUXORO VILOYATI QORAKUL TUMANI XOJAKON MFY XUNARMANDLAR KO’CHASI 86-UY | H90: 9 | I90: 9248185.5 | K90: Va'da berdi | 39 | 12614632.016630135
A91: БУХОРО ВИЛОЯТИ | B91: SUPER BRANCH | C91: Обещал | D91: Кр-99033006-2 | E91: AMIRQULOV AZIZBEK FARXOD O’G’LI | F91: 998943206655 SMS O’ZI , 998930065166 SMS AKASI, 998940514494 SMS UKASI, | G91: BUXORO VILOYATI KORAKO’L TUMANI DARG’ALI MFY OQG’UN QISHLOG’I 22-UY | H91: 12 | I91: 2230158.7 | K91: Va'da berdi | 10 | 2423559.9516438358
A92: БУХОРО ВИЛОЯТИ | B92: SUPER BRANCH | C92: Обещал | D92: Кр-99057620-1 | E92: SADRIDDINOV SAVRIDDIN HUSNIDDIN O’G’LI | F92: 998997027515 SMS UZI, 998906367515 SMS OTASI, 998997077515 SMS ONASI, 998918087515 SMS AKASI, | G92: BUXORO VILOYATI VOBKENT TUMANI KO'LXATIB MFY, NAVOIY KO'CHASI, 4-UY | H92: 7 | I92: 1850061.8 | K92: Va'da berdi | 34 | 2387048.071369863
A93: БУХОРО ВИЛОЯТИ | B93: SUPER BRANCH | C93: Обещал | D93: Кр-99033006-3 | E93: AMIRQULOV AZIZBEK FARXOD O’G’LI | F93: 998943206655 SMS O’ZI , 998930065166 SMS AKASI, 998940514494 SMS UKASI, | G93: BUXORO VILOYATI KORAKO’L TUMANI DARG’ALI MFY OQG’UN QISHLOG’I 22-UY | H93: 0 | I93: 1673796.4 | K93: Va'da berdi | 11 | 1673796.38
A94: БУХОРО ВИЛОЯТИ | B94: SUPER BRANCH | C94: Обещал | D94: Кр-99039939-1 | E94: TUXTAYEVA NARGIZA JURAYEVNA | F94: 998918365488 SMS OZI, 998903407973 SMS ONASI, 998331951802 SMS ERI, 998994452534 SMS UY, | G94: BUXORO VILOYATI BUXORO SHAHAR FOSHUN MFY ALPOMISH KO'CHASI, 17/3 UY, 10-XONADON | H94: 7 | I94: 1602703.8 | K94: Va'da berdi | 24 | 2358394.8329041097
A95: БУХОРО ВИЛОЯТИ | B95: SUPER BRANCH | C95: Обещал | D95: Кр-99036367-2 | E95: BEHBUDOV ASLBEK RIZAMATOVICH | F95: +998947812907 SMS O’ZI, 998914462869 SMS OTASI, 998948795777 SMS JIYANI, 998997034797 SMS ONASI, | G95: BUXORO VILOYATI QORAKO’L TUMANI KUYI JANPAR 101-UY | H95: 7 | I95: 1095014.7 | K95: Va'da berdi | 16 | 1460127.68369863
A96: БУХОРО ВИЛОЯТИ | B96: Бухоро филиали | C96: Обещал | D96: Кр-99062884-1 | E96: MADIYEVA ISTAT RAVSHANOVNA | F96: +998997320621 SMS O’ZI, 998505742858 SMS O’G’LI, 998933080621 SMS KELINI, 998943960868 SMS QIZI, | G96: BUXORO VILOYATI JONDOR TUMANI ZARAFSHON MFY ZARAFSHON KO’CHASI 406-UY | H96: 7 | I96: 6933746 | K96: Va'da berdi | 37 | 8771645.565780822
A97: БУХОРО ВИЛОЯТИ | B97: Бухоро филиали | C97: Обещал | D97: Кр-99062677-2 | E97: POCHCHOYEVA ZULAYXO TOLIBJONOVNA | F97: +998932594485 SMS O’ZI, 998952224447 SMS ERI, 998992304600 SMS QAYNONASI, 998995554600 SMS QAYNOTA, 998939564485 узи 2, | G97: BUXORO VILOYAT JONDOR TUMAN IBN SINO MFY ASBOBSOZ KO’CHA 130-UY | H97: 7 | I97: 4279787.4 | K97: Va'da berdi | 35 | 5555825.088054795
A98: БУХОРО ВИЛОЯТИ | B98: Бухоро филиали | C98: Обещал | D98: Кр-99035221-3 | E98: SHUKUROV YUNUS UMAROVICH | F98: 998990297718 SMS O’ZI, 998996751234 SMS AYOLI, 998992231806 SMS QAYNONASI, 998992947718 SMS ONASI, | G98: Хужа Мушкин МФЙ, Алпомиш кучаси, 13/2-уй, 7-хонадон | H98: 7 | I98: 3797288.2 | K98: Va'da berdi | 15 | 4756192.459671233
A99: БУХОРО ВИЛОЯТИ | B99: Бухоро филиали | C99: Обещал | D99: Кр-99027572-1 | E99: TO’YBOYEV BEHRUZ LUQMON O’G’LI | F99: 99-262-34-44 SMS O'ZI хоразимда харбий , 95-571-45-41 SMS XOTINI, 97-452-30-33 SMS DADASI, | G99: BUXORO VILOYATI G’IJDUVON TUMANI POZAGARI MAXALLASI XARCHXONA KUCHASI 133 UY | H99: 11 | I99: 2921973.6 | K99: Va'da berdi | 4 | 3663423.4540547943
A100: БУХОРО ВИЛОЯТИ | B100: Бухоро филиали | C100: Обещал | D100: Кр-99037180-2 | E100: YULDASHEVA DILNOZA FAXRIDINOVNA | F100: 998914076943 SMS OZI, 998907441349 SMS ERI , 998941250707 SMS JIYANI, 998507056161 SMS AMAKISI, +998914076943 SMS O’ZI, | G100: ИСТИКБОЛ МФЙ, ШУРОБОД, 67-УЙ | H100: 5 | I100: 2742706.8 | K100: Va'da berdi | 18 | 3349626.5284931506
A101: БУХОРО ВИЛОЯТИ | B101: Бухоро филиали | C101: Дозвон | D101: Кр-99019690-4 | E101: HAYDAROV FURQAT RAXMATILLOYEVICH | F101: 97-488-07-66 SMS O'ZI, 88-301-90-93 SMS AKASI, 97-296-06-93 SMS UY, 93-841-53-50 SMS AYOLI, 998505999203 SMS O'ZI2, | G101: BUXORO VILOYAT BUXORO SHAHRI BESHKAPPA KO'CHASI 106 UY | H101: 9 | I101: 1212298.9 | J101: 1265879 | K101: To'ladi | 1 | 1265879.6719178082
A102: БУХОРО ВИЛОЯТИ | B102: Бухоро филиали | C102: Обещал | D102: Кр-99027688-2 | E102: HUSENOV BARNO HASANOVICH | F102: 94-003-53-53 sms O'ZI begana, 93-211-44-49 sms AYOLI, 93-558-53-33 sms O'G'LI, 50-720-12-44 sms QIZI, +998949965353 SMS O’ZI, 998507201244 SMS QIZI, 998932114449 SMS AYOLI, | G102: АРАБХОНА МФЙ, АРАБХОНА, | H102: 7 | I102: 670779.48 | K102: Va'da berdi | 5 | 1302705.5112054795
A103: ЖИЗЗАХ ВИЛОЯТИ | C103: Обещал | D103: Кр-99047637-1 | E103: AZIMOV ASADBEK OTABEK O’G’LI | F103: +998905382222 SMS NOMER, 998971120007 SMS O’ZI, 998991937773 begonA EKAN, | G103: JIZZAX VILOYATI JIZZAX SHAHRI TURON MFY SAYILJOYI KUCHASI 21-UY | H103: 73 | I103: 20202260 | K103: Va'da berdi | filyal keliwi kerak
A104: ЖИЗЗАХ ВИЛОЯТИ | C104: Обещал | D104: Кр-99056937-2 | E104: RASHIDOVA NASIBA YAKUBOVNA | F104: 998889541771 SMS OZI, 998843817712 SMS OZI2, 998974390219 SMS KELINI, | G104: JIZZAX VILOYATI JIZZAX SHAHAR MIRZO ULUG'BEK MAHALLASI 2-UY 10-XONADON | H104: 13 | I104: 8261002.2 | K104: Va'da berdi | kecgaca tolaydi
A105: ЖИЗЗАХ ВИЛОЯТИ | C105: Обещал | D105: Кр-99040635-1 | E105: JURAYEVA ZULAYXA LUTFULLAYEVNA | F105: 998915641958 SMS begona, 998938592525 SMS O`G`LI tolovchisi, 998943543086 SMS O`G`LI 2, 998931940082 SMS O`G`LI 3, 998943174556 SMS ONASI, 998932926008 Tolovchisini xotini, | G105: JIZZAX VILOYATI, DO’STLIK TUMANI, NAVRUZ MFY, IFTIXOR KUCHASI, 11-2 UY | H105: 43 | I105: 8146268.7 | K105: Va'da berdi | bugun tolaydi
A106: ЖИЗЗАХ ВИЛОЯТИ | C106: Обещал | D106: Кр-99036112-1 | E106: O’TASHEV RAVSHAN BOXTIYOR O’G’LI | F106: 998991037766 SMS OZI, 998946525295 SMS AKA TOLOVCHI, 998946738436 SMS AYOLI TOLOVCHI, 998944973835 SMS AYOLI, 998958735995 SMS TOLOVCHI, | G106: JIZZAX VILOYATI MIRZACHUL TUMANI PAXTAZOR SHFY BUNYODKOR KUCHASI 38-UY 2-XONADON | H106: 44 | I106: 6856165.8 | K106: Va'da berdi | mowin olingan
A107: ЖИЗЗАХ ВИЛОЯТИ | C107: Обещал | D107: Кр-99033328-1 | E107: XOLBUTAYEV DILMUROD ABDUMALIKOVICH | F107: 998915680048 SMS O’ZI, 998994280048 SMS UKASI, 998990280048 SMS AYOLI BEGONA, 998900265356 SMS ONASI, | G107: JIZZAX VILOYATI ZOMIN TUMANI DASHTOBOD SHAXAR QORATEPA MFY SHIRIN KUCHASI | H107: 13 | I107: 6506790.9 | K107: Va'da berdi | 5 6 gaca tulaydi
A108: ЖИЗЗАХ ВИЛОЯТИ | C108: Обещал | D108: Кр-99028038-1 | E108: XAZRATKULOVA RAYXON TURSUNBAYEVNA | F108: 998772725500 SMS OZI, 998951307770 SMS UKASI, 998904928594 SMS ZOLOGATEL, | G108: JIZZAX VILOYATI JIZZAX SHAHRI OBOD MFY XALQLAR DUSTLIGI KUCHASI 101-A UY 23-XONADON | H108: 8 | I108: 5917963.6 | K108: Va'da berdi | wu hafta ohirgaca yopadi timur aka bilan gaplawgan ekan
A109: ЖИЗЗАХ ВИЛОЯТИ | C109: Обещал | D109: Кр-99005110-6 | E109: TURSUNOVA MAXBUBA OLIMJON KIZI | F109: 91-567-08-58 sms ukas tolovchi, 99-563-24-48 sms HO’JAYNI, 91-188-00-88 sms UKASI, 90-229-18-51 DADASI , 90-229-18-54 SMS UY, 90-025-93-95 SMS ONASI MAQSUDA, 998882955757 SMS TO’LOVCHI, 998880890111 uzi new, | G109: JIZZAX VILOYATI JIZZAX SHAHAR BUNYODKOR .M.F.Y YORQIN KO’CHASI 16-UY | H109: 14 | I109: 5523834.8 | K109: Va'da berdi | bugun tolaydi kecgaca
A110: ЖИЗЗАХ ВИЛОЯТИ | C110: Обещал | D110: Кр-99038849-1 | E110: XASANOV INOMJON USMONOVICH | F110: 998977931100 SMS SINGLISI, 998916262046 SMS OZI, 998976831100 SMS SINGLISI 2, 998915665348 SMS AYOLI, | G110: ДУСТЛИК, ДУСТЛИК, Э.АШИРМАТОВ, uy:Р/С | H110: 2 | I110: 5384444 | K110: Va'da berdi | kecgaca tolaydi
A111: ЖИЗЗАХ ВИЛОЯТИ | C111: Обещал | D111: Кр-99042115-1 | E111: MIRZAYEV OYBEK SUNATILLAYEVICH | F111: +998902659695 SMS, 998915909006 SMS, 998974559695 SMS, | G111: JIZZAX VILOYATI SH.RASHIDOV TUMANI TOKCHILIK MFY ZARGARLIK KUCHASI 2-UY | H111: 10 | I111: 4457135.3 | K111: Va'da berdi | ertaga aniq yopad kecgaca
A112: ЖИЗЗАХ ВИЛОЯТИ | C112: Обещал | D112: Кр-99063504-1 | E112: MIRZAYEVA LOBARXON ERGASHEVNA | F112: 998933556974 UZI, 998934026974 ERI, 998958832266 TO’LOVCHI, | G112: ТОШКЕСГАН КФЙ, ЛОЙИХАДАГИ КЎЧА, uy:РАКАМСИЗ | H112: 10 | I112: 4425062.2 | K112: Va'da berdi | duwanba tulaydi
A113: ЖИЗЗАХ ВИЛОЯТИ | C113: Обещал | D113: Кр-99057340-1 | E113: SUYUNOVA UMIDA ILHOM QIZI | F113: 998995542023 SMS ERI, 998930913798 SMS UZI, 998943461045 SMS UY, 998901020807 SMS Akasi, | G113: JIZZAX VILOYATI MIRZACHO'L TUMANI IPAK YULI QFY YANGI XAYOT KUCHASI 29-UY | H113: 10 | I113: 3800442.9 | K113: Va'da berdi | 12da tel qiliw kerak
A114: ЖИЗЗАХ ВИЛОЯТИ | C114: Обещал | D114: Кр-99011601-4 | E114: JO’RAQULOV JAVLONJON QAHRAMON O’G’LI | F114: 88-126-00-25 SMS UZI, 97-482-53-53 SMS AYOLI, 88-437-53-53 SMS OTASI, 97-127-53-53 SMS AYOLI, 998776406865 SMS Ukasi tolovchi, | G114: JIZZAX VILOYATI JIZZAX TUMANI OLMACHI MAHALLASI OLMACHI KUCHASI 9/9 UY | H114: 14 | I114: 3593058.5 | K114: Va'da berdi | kecga iwdan ciqib filyalga oborb beradi
... A118: ЖИЗЗАХ ВИЛОЯТИ | C118: Обещал | D118: Кр-99039288-1 | E118: YAKUBOV BUNYOD NEMATILLAYEVICH | F118: 998904878684 SMS OZI, 998886441986 SMS AYOLI, 998932988684 SMS OZI, 998773450986 SMS SINGLISI, | G118: JIZZAX VILOYATI DUSTLIK TUMANI MEVAZOR QFY LOLAZOR KUCHASI 35-UY | H118: 15 | I118: 3193775.5 | K118: Va'da berdi | bugun tolaydi
A119: ЖИЗЗАХ ВИЛОЯТИ | C119: Дозвон | D119: Кр-99055031-1 | E119: PARDAYEVA XAFIZA AKRAMOVNA | F119: 998995900655 SMS OZI, 998997473110 SMS OZI, 998958160926 SMS O'G'LI, | G119: JIZZAX VILOYATI G'ALLAOROL TUMANI MIRZABULOQ QFY NAYMAN KUCHASI 36-UY | H119: 10 | I119: 3028615.3 | J119: 3028615.3 | K119: To'ladi
A120: ЖИЗЗАХ ВИЛОЯТИ | C120: Дозвон | D120: Кр-99052894-1 | E120: SUVONQULOV SHAXRIYOR MIRZABEK O’G’LI | F120: 998943079900 SMS OZI, 998932800094 SMS AKASI, 998938265665 SMS AKASI 2, 999839712506 SMS UKASI, | G120: JIZZAX VILOYATI SHAROF RASHIDOV TUMANI QANG'LI QFY NURAFSHON MFY OBOD KUCHASI 9-UY | H120: 10 | I120: 2557891.2 | J120: 2557891.2 | K120: To'ladi
A121: ЖИЗЗАХ ВИЛОЯТИ | C121: Обещал | D121: Кр-99039314-1 | E121: IZBOSAROV BUNYODBEK BEHZOD O’G’LI | F121: 998919400878 SMS UZI, 998886647070 SMS AKASI, 998991900011 SMS KATTA AKASI, 998996100011 SMS ADASI, | G121: JIZZAX VILOYATI PAXTAKOR TUMANI TOSHKENT MFY NURAFSHON KUCHASI 7/1-UY | H121: 14 | I121: 2480562.3 | K121: Va'da berdi | 20sigaca tolaydi dedi jurasi
A122: ЖИЗЗАХ ВИЛОЯТИ | C122: Обещал | D122: Кр-99046098-1 | E122: RAMAZANOV IXTIYOR BAXTIYOR O’G’LI | F122: 998915983004 SMS, 998945960080 SMS, 998950800277 SMS, | G122: JIZZAX VILOYATI, JIZZAX SHAHRI, TINCHLIK MFY, S.KARIMOV KO’CHASI, 5/17-UY | H122: 13 | I122: 2261681.8 | K122: Va'da berdi | ertaga aniq yopad kecgaca
A123: ЖИЗЗАХ ВИЛОЯТИ | C123: Обещал | D123: Кр-99034257-1 | E123: MURADOV SHOKIRJON ABDULLAYEVICH | F123: 998950381202 SMS OZI, 998957986998 SMS SINI, 998933680979 SMS AYOLI, 998991677998 SMS KELINI, 998950240408 SMS O’G’LI TO’LOVCHI, | G123: JIZZAX VILOYATI G’ALLAOROL TUMANI MADANIYAT MFY QANGLIOBOD SHAXARCHASI 265-UY | H123: 10 | I123: 2226012.5 | K123: Va'da berdi | bugun qisman tolaydi qoganini ertaga tolaydi
A124: ЖИЗЗАХ ВИЛОЯТИ | C124: Обещал | D124: Кр-99039656-1 | E124: XOLBEKOV ULUG’BEK SULTONBEK O’G’LI | F124: 998995620921 SMS OZI, 998919931111 SMS AKASI, 998940131831 SMS TOLOVCHI, | G124: JIZZAX VILOYATI SHAROF RASHIDOV TUMANI QO’SHBARMOQ QFY Q.RUMIY KUCHASI 2-UY | H124: 2 | I124: 2047668.6 | K124: Va'da berdi | ertaga aniq yopadi bolib tulayapti
A125: ЖИЗЗАХ ВИЛОЯТИ | C125: Дозвон | D125: Кр-99039329-1 | E125: TURSUNMATOV ABDULAZIZ ALIAKBAR O’G’LI | F125: +998947200340 SMS OZI, 998772942607 SMS DADASI, 998990231125 SMS AKASI, 998999992897 SMS UKASI, | G125: МУГОЛ КФЙ, МУГОЛ КФЙ, ЛОЙИХАДАГИ, uy:Р.С | H125: 10 | I125: 1773514.2 | J125: 1773514.2 | K125: To'ladi
A126: ЖИЗЗАХ ВИЛОЯТИ | C126: Дозвон | D126: Кр-99041692-1 | E126: XAYDAROVA MUHABBAT KAMOL QIZI | F126: +998871055002 SMS OZI, 998879530070 SMS AYOLI, 998918910095 SMS AKASI, 998918910095 SMS UKASI, | G126: JIZZAX VILOYATI JIZZAX TUMANI QANGLI MFY FAROVON KUCHASI 36-UY | H126: 10 | I126: 1763084.6 | J126: 1763084.6 | K126: To'ladi
A127: ЖИЗЗАХ ВИЛОЯТИ | C127: Обещал | D127: Кр-99028367-3 | E127: KARIMOV BOTIRJON RUZMATOVICH | F127: 91-564-03-10 SM S OZI, 91-591-45-24 SMS ATYOLI, 91-564-22-53 SMS QIZI, 95-996-66-77 sms sin, | G127: JIZZAX VILOYATI JIZZAX SHAHAR OBOD MFY FURQAT KUCHASI 28-UY | H127: 14 | I127: 1482189.5 | K127: Va'da berdi | kecgaca tolaydi
A128: ЖИЗЗАХ ВИЛОЯТИ | C128: Дозвон | D128: Кр-99033516-1 | E128: MIRZAMAXMUDOV ODILJON ALLAYOR O’G’LI | F128: 998997449700 SMS O’ZI, 998912084455 SMS O’ZI, 998338382297 SMS DO’STI, 998991332871 SMS ONASI, 998950702444 SMS AKASI, 998336669700 SMS OZI YANGI, 998932947066 SMS ABDUNABI ORTOGI, | G128: JIZZAX VILOYATI BAXMAL TUMANI UDAMALI QISHLOG’I 63-UY | H128: 3 | I128: 1079691.8 | J128: 1079691.8 | K128: To'ladi
A129: ЖИЗЗАХ ВИЛОЯТИ | C129: Дозвон | D129: Кр-99046548-1 | E129: BOYMURZAYEV HASAN NAZAR O’G’LI | F129: 998996766010 узи, 998954330009 укаси, 998919446010 уй, | G129: JIZZAX VILOYATI SHAROF RASHIDOV TUMANI PAXTOBOD QFY YAXTANLIK MAHALLASI | H129: 10 | I129: 793050.32 | J129: 793050.32 | K129: To'ladi
A130: ЖИЗЗАХ ВИЛОЯТИ | C130: Обещал | D130: Кр-99031804-1 | E130: USMANOV GAYRAT IMAMOVICH | F130: 998974360075 SMS O’ZI , 998995299620 SMS SHERIGI, 998911969620 SMS AYOLI, 998990360075 SMS ozi new, 998992408008 SMS tolovchi new, 998931444446 SMS TO’LOVCHI NEW, 998770367771 SMS NEW UZI, 998990367771 SMS Tolovchi new, | G130: JIZZAX VILOYATI SH.RASHIDOV TUMANI QO’SHBARMOQ QFY UCHARIQ MAHALLASI ROHAT KUCHASI 15-UY | H130: 1 | I130: 696594.48 | K130: Va'da berdi | ertaga tulaydi
A131: ЖИЗЗАХ ВИЛОЯТИ | C131: Дозвон | D131: Кр-99045797-2 | E131: QARSHIBAYEV RUSLAN QAXRAMON O’G’LI | F131: +998900251515 SMS, 998902978487 SMS, 998992408778 SMS, | G131: JIZZAX VILOYATI SH.RASHIDOV TUMANI TOSHKENTLIK MFY QATORTOL KUCHASI 7-UY | H131: 10 | I131: 386582.6 | J131: 386582.6 | K131: To'ladi
A132: ЖИЗЗАХ ВИЛОЯТИ | C132: Дозвон | D132: Кр-99016886-4 | E132: NORBOYEV UTKIR XUDOYBOKOVICH | F132: 903111781 SMS UZI new, 992851781 SMS AYOLI Begona, 991760374 SMS AKASI, 955557476 SMS AKASI, | G132: JIZZAX VILOYATI ZOMIN TUMANI G'ALLAKOR QFY BAYMOQLI QISHLOG'I YANGI HAYOT KUCHASI 36-UY | H132: 1 | I132: 270598.44 | J132: 270598.44 | K132: To'ladi
A133: ЖИЗЗАХ ВИЛОЯТИ | C133: Дозвон | D133: Кр-99034148-3 | E133: SAYFUTDINOVA GAVXAR SHUXRATOVNA | F133: 998903111016 SMS OZI, 998976480208 SMS ERI TOLOVCHI, 998912093311 SMS HAMKASBI, 998712267815 SMS UY, | G133: JIZZAX VILOYATI SH.RASHIDOV TUMANI ZIYOKOR QFY M.ESHONQULOV KUCHASI 125-UY | H133: 10 | I133: 193989.59 | J133: 193989.59 | K133: To'ladi
A134: КАШКАДАРЁ ВИЛОЯТИ | C134: Обещал | D134: Кр-99036435-3 | E134: JO’RAQULOV MANSUR QULMUROT O’G’LI | F134: 998997330311 SMS O’ZI, 998333400311 SMS AYOLI, 998942976783 SMS O’ZI 2, 998881365522 SMS UKASI , | G134: ЧИРОКЧИ МФЙ, ЧИРОКЧИ, uy:Р/С | H134: 13 | I134: 17475594 | K134: Va'da berdi | 20 da to'laydi
A135: КАШКАДАРЁ ВИЛОЯТИ | C135: Обещал | D135: Кр-99035525-2 | E135: RO’ZIYEV AZIZJON FARXODOVICH | F135: 998903545851 SMS OZI , 998909434667 SMS AYOLI, 998973422225 SMS UKASI, 998717546462 SMS UKASI, | G135: QASHQADARYO VILOYATI SHAHRISABZ SHAHRI KATTACHUTON KO’CHASI 27-UY | H135: 10 | I135: 9849521.7 | K135: Va'da berdi | shanba kuni pulim bo'ladi to'lavoramn dedi
A136: КАШКАДАРЁ ВИЛОЯТИ | C136: Обещал | D136: Кр-99038157-1 | E136: JUMAYEV ERNAZAR IBRAGIMOVICH | F136: 998973170009 SMS OZI BEGONA, 998972259900 SMS UKASI, 998882209990 SMS OTASI, 998973109990 SMS AKASI UZIII, | G136: QASHQADARYO VILOYATI MUBORAK TUMANI ISTIQLOL MFY NEFTCHILAR KUCHASI 1-32 UY | H136: 3 | I136: 7515687.1 | K136: Va'da berdi | bugun bittasi pul beradi kartadan yechib ketadi dedi
A137: КАШКАДАРЁ ВИЛОЯТИ | C137: Обещал | D137: Кр-99012796-5 | E137: SATTOROV JOBIR JAMOL O’G’LI | F137: 91-959-12-51 SMS, 90-615-02-67 SMS AYOLI, 99-113-18-42 SMS UKASI, 91-466-71-07 SMS AYASI, 998900702002 SMS , 998973106292 SMS XOLAVACHCHASI, 998991131842 SMS garov egasi, 998919531115 SMS uzi ZALOG EGASI, 998886220020 SMS TO'LOVCHI, | G137: QASHQADARYO VILOYATI KOSON TUMANI PAXTAZOR MFY X TEMIROV KO’CHASI 22-UY | H137: 10 | I137: 6180702.3 | K137: Va'da berdi | 21- kun to'lov bo'ladi dedi
A138: КАШКАДАРЁ ВИЛОЯТИ | C138: Обещал | D138: Кр-99034170-3 | E138: YUSUPOV OBID XOMETOVICH | F138: 998883831111 SMS O’ZI, 998973871111 SMS O’G’LI, 998973801991 SMS UKASI, 998912621111 SMS AKASI, | G138: QASHQADARYO VILOYATI SHAXRISABZ TUMANI XONTEPA MFY SHUKRONA 32 UY | H138: 10 | I138: 5901069.2 | K138: Va'da berdi | juma kun abetdn kn yopvoradi
A139: КАШКАДАРЁ ВИЛОЯТИ | C139: Обещал | D139: Кр-99039293-1 | E139: NORBUTAYEVA YULDUZXON BAXTIYAROVNA | F139: 998973137733 SMS OZI, 998908668282 SMS OZI, 998993308084 SMS OILASI, | G139: QASHQADARYO VILOYATI QAMASHI TUMANI ZAFAR MFY IFTIXOR KO’CHASI 1/1-UY 21-XONADON | H139: 10 | I139: 5305025.2 | K139: Va'da berdi | erte kechgacha yopamn dedi
A140: КАШКАДАРЁ ВИЛОЯТИ | C140: Обещал | D140: Кр-99039445-1 | E140: MIRZAMURODOV SHOXRUZBEK DAVRON O’G’LI | F140: +998873999404 SMS O’ZI, 998888818005 SMS DOSTI, 998959006035 SMS DOSTI, 998990855744 UZI NEWW, | G140: Чувуллоқ МФЙ, Миллий хунармандлар кучаси, 86-уй | H140: 9 | I140: 4255261.6 | K140: Va'da berdi | dushanba kun tolaydi
A141: КАШКАДАРЁ ВИЛОЯТИ | C141: Обещал | D141: Кр-99036016-1 | E141: NORBOYEV UTKIR KERKIYEVICH | F141: 998977715284 SMS O’ZI, 998937090588 SMS AYOLI , 998971152626 SMS DO’STI , 998884982107 SMS DO’STI , 998991912626 SMS TULOVCHI1, | G141: QASHQADARYO VILOYATI QAMASHI TUMANI PASTTOL QISHLOG’I 3/12 XONADON | H141: 2 | I141: 3797862.4 | K141: Va'da berdi | ertaga aniq to'lov bo'ladi dedi
A142: КАШКАДАРЁ ВИЛОЯТИ | C142: Обещал | D142: Кр-99038081-1 | E142: ASHUROV MIRZA URALOVICH | F142: 998987750515 SMS OZI, 998880042215 SMS O’G’LI, 998906699171 SMS O’G’LI, 998972747000 SMS UKASI, | G142: QASHQADARYO VILOYATI QARSHI SHAHAR GUNGON MFY MUSA JALIL KUCHASI 48-UY | H142: 3 | I142: 3728488.9 | K142: Va'da berdi | bugun oyligim tushushi kk bugun yopamn dedi 0515
A143: КАШКАДАРЁ ВИЛОЯТИ | C143: Обещал | D143: Кр-99038818-4 | E143: AZIZOV ZAKIR TASHAROVICH | F143: 998992562088 SMS O’ZI, 998770306222 SMS O’G’LI, 998972226222 SMS UY BEGONAA, 998771003949 SMS O'ZI, | G143: КУРГОНЧА МФЙ, ТОР КЎЧАСИ, uy:28 | H143: 10 | I143: 3422858.7 | K143: Va'da berdi | ss=hanba kuni to'liman deb
A144: КАШКАДАРЁ ВИЛОЯТИ | C144: Обещал | D144: Кр-99035261-1 | E144: BOYMATOV ULUG’BEK MUSULMONOVICH | F144: 998910081104 SMS OZI, 998997472245 SMS AKASI, 998973868211 SMS ULUG’BEK, 998973800007 SMS AKASI (BEGONA))), | G144: QASHQADARYO VILOYATI KITOB TUMANI SHARQ YULDUZI MFY RUS QISHLOG’I MADAMIN KUCHASI 653-UY | H144: 2 | I144: 2813692.7 | K144: Va'da berdi | 21 da to'lov qilamn dedi
A145: КАШКАДАРЁ ВИЛОЯТИ | C145: Обещал | D145: Кр-99020798-2 | E145: AZIZOV JASURBEK BAXODIR O’G’LI | F145: 998939308088 SMS O’ZI, 998335880100 SMS AKASI, 998342233302 SMS AKASI 2, | G145: QASHQADARYO VILOYATI QARSHI SHAHAR AROVUL MFY JAYXUN 2 KO’CHASI 29- UY | H145: 1 | I145: 2760594.6 | K145: Va'da berdi | kechgacha to'liman dedi
...

Sheet Обещали
A1: ← Вернуться в отчёт
A2: Область | B2: Филиал | C2: Группа | D2: Код клиента | E2: Клиент | F2: Номер телефона | G2: Адрес | H2: Кол-во просроченных дней | I2: Итого просрочка | J2: Оплата | K2: Izoh
A3: АНДИЖОН ВИЛОЯТИ | C3: Обещал | D3: Кр-99062885-1 | E3: KASIMXODJAYEV ABDUXALIL ABDUMAJITOVICH | F3: +998916208060 SMS O’ZI, 998914781293 SMS AYOLI, 998916028060 SMS UY, 998976208060 SMS O’ZI2, | G3: ANDIJON VILOYATI ANDIJON SHAHAR MAYDONBOZOR MFY YAXSHI KO’CHASI 61/59-UY | H3: 10 | I3: 14507308 | K3: Va'da berdi | 1-2 kunda hal qiladi | 4383561.643835616 | 10123746.15
A4: АНДИЖОН ВИЛОЯТИ | C4: Обещал | D4: Кр-99058759-1 | E4: RAXMANOV DILSHODBEK TO’XTASINOVICH | F4: 998889930005 SMS OZI, 998955173700 SMS AYOLI, 998979970184 SMS UKASI, 998949300052 SMS OZI 2, | G4: ANDIJON VILOYATI QO’RG’ONTEPA TUMANI DEXQONCHEK MFY ERKIN IJOD KO’CHASI 74-UY | H4: 13 | I4: 13767147 | K4: Va'da berdi | 25 kunga hal qiladi | 5342465.7534246575 | 8424681.47
A5: АНДИЖОН ВИЛОЯТИ | C5: Обещал | D5: Кр-99047889-1 | E5: SHIRMATOV MUXAMMADOZOD QODIRALI O’G’LI | F5: +998911715500 SMS O’ZI, 998772495500 SMS OG’LI, 998972225500 SMS UY, 998998173300 SMS NEVARASI, | G5: ANDIJON VILOYATI ANDIJON SHAHAR ISTIQLOL MFY OBOD 1-TOR KO’CHASI 5-UY | H5: 13 | I5: 12856969 | K5: Va'da berdi | 25 kunga hal qiladi | 4630136.98630137 | 8226832.27
A6: АНДИЖОН ВИЛОЯТИ | C6: Обещал | D6: Кр-99060389-1 | E6: SULTANOVA XAMIDA ULJABEKOVNA | F6: +998934141584 SMS O’ZI, 998973243443 SMS KELINI, 998979753443 SMS O’G’LI, 998993200858 SMS XO’JAYNI, | G6: Andijon viloyati Andijon shahar Sadoqat MFY Fuzuliy ko’chasi 49-uy | H6: 10 | I6: 12724541 | K6: Va'da berdi | dushanba seshanba kuni | 3835616.438356164 | 8888924.39
A7: АНДИЖОН ВИЛОЯТИ | C7: Обещал | D7: Кр-99061048-1 | E7: ORIFJANOV NODIRBEK OMANJANOVICH | F7: 998916841884 uzi, 998335177797 ayoli, 998944870903 onasi, | G7: ANDIJON VILOYATI QO’RG’ONTEPA TUMANI SAVAY YANGI BO’STON MFY BARKAMOL KO’CHASI 58-UY | H7: 13 | I7: 11960620 | K7: Va'da berdi | shu hafta hal qilib berdi | 4273972.602739726 | 7686647.26
A8: АНДИЖОН ВИЛОЯТИ | C8: Обещал | D8: Кр-99061572-1 | E8: AXMEDOV JAVOHIRBEK TOJIDIN O’G’LI | F8: 998907726810 узи, 998910676800 аели, 998882357585 укаси, 998974054333 укаси, | G8: ANDIJON VILOYATI ANDIJON TUMANI NURAFSHON MFY YANGI TURMUSH KO’CHASI 69A-UY | H8: 13 | I8: 11959423 | K8: Va'da berdi | 25 kunga hal qiladi | 4273972.602739726 | 7685450.86
A9: АНДИЖОН ВИЛОЯТИ | C9: Обещал | D9: Кр-99024542-1 | E9: XALMATOV ADIL PAZILOVICH | F9: 77-123-13-10 SMS OZI, 98-707-22-92 SMS OZI, 90-541-13-18 SMS OZI, 998880072292 УГЛИ шохрух, | G9: ANDIJON VILOYATI ANDIJON SHAHAR ISLOMOBOD MFY 7-TOR MUXITDINOV 21-UY | H9: 8 | I9: 11534220 | K9: Va'da berdi | 25 kuni tolaydi | 5041095.890410959 | 6493123.81
A10: АНДИЖОН ВИЛОЯТИ | C10: Обещал | D10: Кр-99063922-3 | E10: RUZIYEVA RANO KABILOVNA | F10: +998905437075 SMS O’ZI, 998902597075 SMS UY, 998906257691 SMS OPASI, 998921519222 SMS QIZI, | G10: ANDIJON VILOYATI ANDIJON SHAHAR O’ZBEGIM MFY, A. MUSAYE KO’CHASI 4-UY 31-XONADON | H10: 10 | I10: 11102362 | K10: Va'da berdi | dushanba kuni tolaydi | 3835616.438356164 | 7266745.79
A11: АНДИЖОН ВИЛОЯТИ | C11: Обещал | D11: Кр-99063424-2 | E11: TURSUNOV RAXMATILLO IKRAMJANOVICH | F11: 998702250075 SMS OZI, 998886020075 SMS UKASI2, 998889248080 SMS AYOLI, 998970711009 SMS UKASI, | G11: ANDIJON VILOYATI QO’RG’ONTEPA TUMANI | H11: 10 | I11: 10783206 | K11: Va'da berdi | 25 kuni tolaydi | 3013698.6301369863 | 7769507.51
A12: АНДИЖОН ВИЛОЯТИ | C12: Обещал | D12: Кр-99033455-2 | E12: ABDULAZIZOV NOZIMJON NASIBJONOVICH | F12: 998934104844 SMS O’ZI, 998000048002 SMS O’ZI 2, 998932544648 SMS AYOLI, 998936913859 SMS XAMKASBI, 998948770475 SMS otasi new , | G12: ANDIJON VILOYATI PAXTAOBOD TUMANI MA’RIFAT MFY,MA’RIFAT KO’CHASI 47-UY | H12: 6 | I12: 10697383 | K12: Va'da berdi | 1-2 kunda hal qiladi | 2465753.4246575343 | 8231629.93
A13: АНДИЖОН ВИЛОЯТИ | C13: Обещал | D13: Кр-99062998-1 | E13: TURDIMAMATOV ERKINJON ABDUMANNABOVICH | F13: +998880040107 SMS O’ZI, 998884772717 SMS O’G’LI, 998914870066 SMS AYOLI, 998941068585 SMS QIZI, | G13: ANDIJON VILOYATI BO’STON TUMANI MADANIYAT MFY, TINCHLIK KO’CHASI 3-UY | H13: 10 | I13: 10186881 | K13: Va'da berdi | dushanba kuni tolaydi | 3287671.2328767125 | 6899210.02
A14: АНДИЖОН ВИЛОЯТИ | C14: Обещал | D14: Кр-99057627-1 | E14: ABDUGANIYEVA MATLUBAXON XXX | F14: 998911757604 SMS OZI, 998902011084 SMS OGLI, 998910611084 SMS KELIMI, 998907620065 SMS QUDASI, | G14: ANDIJON VILOYATI ANDIJON SHAHAR QORATUT MFY 5-KICHIK NOXIYA KO’CHASI 17-UY, 78-XONADON | H14: 13 | I14: 9732853.8 | K14: Va'da berdi | shu hafta hal qilib berdi | 4630136.98630137 | 5102716.8
... A86: АНДИЖОН ВИЛОЯТИ | C86: Обещал | D86: Кр-99038275-3 | E86: KARIMOVA XAMROXON MO’YDINOVNA | F86: 998508831410 SMS OZI, 998948881410 SMS OGLI, 998916012492 SMS KELINI, 998937359892 SMS AKASI, | G86: ANDIJON VILOYATI SHAXRIXON TUMANI YANGIMAXALLA MFY, OBOD KO’CHASI 75/1-UY | H86: 10 | I86: 913144.31 | K86: Va'da berdi | shu hafta hal qiladi | 246575.34246575343 | 666568.97
A87: БУХОРО ВИЛОЯТИ | B87: SUPER BRANCH | C87: Обещал | D87: Кр-99063363-1 | E87: KOMILOVA ZEBO NURIDDINOVNA | F87: 998995031288 OZI, 998773127040 JIYANI, 998998621288 ONASI, 998770900005 DOSTI, | G87: BUXORO VILOYATI QORAKUL TUMANI XOJAKON MFY XUNARMANDLAR KO’CHASI 86-UY | H87: 9 | I87: 9248185.5 | K87: Va'da berdi | 39 | 12614632.016630135
A88: БУХОРО ВИЛОЯТИ | B88: SUPER BRANCH | C88: Обещал | D88: Кр-99033006-2 | E88: AMIRQULOV AZIZBEK FARXOD O’G’LI | F88: 998943206655 SMS O’ZI , 998930065166 SMS AKASI, 998940514494 SMS UKASI, | G88: BUXORO VILOYATI KORAKO’L TUMANI DARG’ALI MFY OQG’UN QISHLOG’I 22-UY | H88: 12 | I88: 2230158.7 | K88: Va'da berdi | 10 | 2423559.9516438358
A89: БУХОРО ВИЛОЯТИ | B89: SUPER BRANCH | C89: Обещал | D89: Кр-99057620-1 | E89: SADRIDDINOV SAVRIDDIN HUSNIDDIN O’G’LI | F89: 998997027515 SMS UZI, 998906367515 SMS OTASI, 998997077515 SMS ONASI, 998918087515 SMS AKASI, | G89: BUXORO VILOYATI VOBKENT TUMANI KO'LXATIB MFY, NAVOIY KO'CHASI, 4-UY | H89: 7 | I89: 1850061.8 | K89: Va'da berdi | 34 | 2387048.071369863
A90: БУХОРО ВИЛОЯТИ | B90: SUPER BRANCH | C90: Обещал | D90: Кр-99033006-3 | E90: AMIRQULOV AZIZBEK FARXOD O’G’LI | F90: 998943206655 SMS O’ZI , 998930065166 SMS AKASI, 998940514494 SMS UKASI, | G90: BUXORO VILOYATI KORAKO’L TUMANI DARG’ALI MFY OQG’UN QISHLOG’I 22-UY | H90: 0 | I90: 1673796.4 | K90: Va'da berdi | 11 | 1673796.38
A91: БУХОРО ВИЛОЯТИ | B91: SUPER BRANCH | C91: Обещал | D91: Кр-99039939-1 | E91: TUXTAYEVA NARGIZA JURAYEVNA | F91: 998918365488 SMS OZI, 998903407973 SMS ONASI, 998331951802 SMS ERI, 998994452534 SMS UY, | G91: BUXORO VILOYATI BUXORO SHAHAR FOSHUN MFY ALPOMISH KO'CHASI, 17/3 UY, 10-XONADON | H91: 7 | I91: 1602703.8 | K91: Va'da berdi | 24 | 2358394.8329041097
A92: БУХОРО ВИЛОЯТИ | B92: SUPER BRANCH | C92: Обещал | D92: Кр-99036367-2 | E92: BEHBUDOV ASLBEK RIZAMATOVICH | F92: +998947812907 SMS O’ZI, 998914462869 SMS OTASI, 998948795777 SMS JIYANI, 998997034797 SMS ONASI, | G92: BUXORO VILOYATI QORAKO’L TUMANI KUYI JANPAR 101-UY | H92: 7 | I92: 1095014.7 | K92: Va'da berdi | 16 | 1460127.68369863
A93: БУХОРО ВИЛОЯТИ | B93: Бухоро филиали | C93: Обещал | D93: Кр-99062884-1 | E93: MADIYEVA ISTAT RAVSHANOVNA | F93: +998997320621 SMS O’ZI, 998505742858 SMS O’G’LI, 998933080621 SMS KELINI, 998943960868 SMS QIZI, | G93: BUXORO VILOYATI JONDOR TUMANI ZARAFSHON MFY ZARAFSHON KO’CHASI 406-UY | H93: 7 | I93: 6933746 | K93: Va'da berdi | 37 | 8771645.565780822
A94: БУХОРО ВИЛОЯТИ | B94: Бухоро филиали | C94: Обещал | D94: Кр-99062677-2 | E94: POCHCHOYEVA ZULAYXO TOLIBJONOVNA | F94: +998932594485 SMS O’ZI, 998952224447 SMS ERI, 998992304600 SMS QAYNONASI, 998995554600 SMS QAYNOTA, 998939564485 узи 2, | G94: BUXORO VILOYAT JONDOR TUMAN IBN SINO MFY ASBOBSOZ KO’CHA 130-UY | H94: 7 | I94: 4279787.4 | K94: Va'da berdi | 35 | 5555825.088054795
A95: БУХОРО ВИЛОЯТИ | B95: Бухоро филиали | C95: Обещал | D95: Кр-99035221-3 | E95: SHUKUROV YUNUS UMAROVICH | F95: 998990297718 SMS O’ZI, 998996751234 SMS AYOLI, 998992231806 SMS QAYNONASI, 998992947718 SMS ONASI, | G95: Хужа Мушкин МФЙ, Алпомиш кучаси, 13/2-уй, 7-хонадон | H95: 7 | I95: 3797288.2 | K95: Va'da berdi | 15 | 4756192.459671233
A96: БУХОРО ВИЛОЯТИ | B96: Бухоро филиали | C96: Обещал | D96: Кр-99027572-1 | E96: TO’YBOYEV BEHRUZ LUQMON O’G’LI | F96: 99-262-34-44 SMS O'ZI хоразимда харбий , 95-571-45-41 SMS XOTINI, 97-452-30-33 SMS DADASI, | G96: BUXORO VILOYATI G’IJDUVON TUMANI POZAGARI MAXALLASI XARCHXONA KUCHASI 133 UY | H96: 11 | I96: 2921973.6 | K96: Va'da berdi | 4 | 3663423.4540547943
A97: БУХОРО ВИЛОЯТИ | B97: Бухоро филиали | C97: Обещал | D97: Кр-99037180-2 | E97: YULDASHEVA DILNOZA FAXRIDINOVNA | F97: 998914076943 SMS OZI, 998907441349 SMS ERI , 998941250707 SMS JIYANI, 998507056161 SMS AMAKISI, +998914076943 SMS O’ZI, | G97: ИСТИКБОЛ МФЙ, ШУРОБОД, 67-УЙ | H97: 5 | I97: 2742706.8 | K97: Va'da berdi | 18 | 3349626.5284931506
A98: БУХОРО ВИЛОЯТИ | B98: Бухоро филиали | C98: Обещал | D98: Кр-99027688-2 | E98: HUSENOV BARNO HASANOVICH | F98: 94-003-53-53 sms O'ZI begana, 93-211-44-49 sms AYOLI, 93-558-53-33 sms O'G'LI, 50-720-12-44 sms QIZI, +998949965353 SMS O’ZI, 998507201244 SMS QIZI, 998932114449 SMS AYOLI, | G98: АРАБХОНА МФЙ, АРАБХОНА, | H98: 7 | I98: 670779.48 | K98: Va'da berdi | 5 | 1302705.5112054795
A99: ЖИЗЗАХ ВИЛОЯТИ | C99: Обещал | D99: Кр-99047637-1 | E99: AZIMOV ASADBEK OTABEK O’G’LI | F99: +998905382222 SMS NOMER, 998971120007 SMS O’ZI, 998991937773 begonA EKAN, | G99: JIZZAX VILOYATI JIZZAX SHAHRI TURON MFY SAYILJOYI KUCHASI 21-UY | H99: 73 | I99: 20202260 | K99: Va'da berdi | filyal keliwi kerak
A100: ЖИЗЗАХ ВИЛОЯТИ | C100: Обещал | D100: Кр-99056937-2 | E100: RASHIDOVA NASIBA YAKUBOVNA | F100: 998889541771 SMS OZI, 998843817712 SMS OZI2, 998974390219 SMS KELINI, | G100: JIZZAX VILOYATI JIZZAX SHAHAR MIRZO ULUG'BEK MAHALLASI 2-UY 10-XONADON | H100: 13 | I100: 8261002.2 | K100: Va'da berdi | kecgaca tolaydi
A101: ЖИЗЗАХ ВИЛОЯТИ | C101: Обещал | D101: Кр-99040635-1 | E101: JURAYEVA ZULAYXA LUTFULLAYEVNA | F101: 998915641958 SMS begona, 998938592525 SMS O`G`LI tolovchisi, 998943543086 SMS O`G`LI 2, 998931940082 SMS O`G`LI 3, 998943174556 SMS ONASI, 998932926008 Tolovchisini xotini, | G101: JIZZAX VILOYATI, DO’STLIK TUMANI, NAVRUZ MFY, IFTIXOR KUCHASI, 11-2 UY | H101: 43 | I101: 8146268.7 | K101: Va'da berdi | bugun tolaydi
A102: ЖИЗЗАХ ВИЛОЯТИ | C102: Обещал | D102: Кр-99036112-1 | E102: O’TASHEV RAVSHAN BOXTIYOR O’G’LI | F102: 998991037766 SMS OZI, 998946525295 SMS AKA TOLOVCHI, 998946738436 SMS AYOLI TOLOVCHI, 998944973835 SMS AYOLI, 998958735995 SMS TOLOVCHI, | G102: JIZZAX VILOYATI MIRZACHUL TUMANI PAXTAZOR SHFY BUNYODKOR KUCHASI 38-UY 2-XONADON | H102: 44 | I102: 6856165.8 | K102: Va'da berdi | mowin olingan
A103: ЖИЗЗАХ ВИЛОЯТИ | C103: Обещал | D103: Кр-99033328-1 | E103: XOLBUTAYEV DILMUROD ABDUMALIKOVICH | F103: 998915680048 SMS O’ZI, 998994280048 SMS UKASI, 998990280048 SMS AYOLI BEGONA, 998900265356 SMS ONASI, | G103: JIZZAX VILOYATI ZOMIN TUMANI DASHTOBOD SHAXAR QORATEPA MFY SHIRIN KUCHASI | H103: 13 | I103: 6506790.9 | K103: Va'da berdi | 5 6 gaca tulaydi
A104: ЖИЗЗАХ ВИЛОЯТИ | C104: Обещал | D104: Кр-99028038-1 | E104: XAZRATKULOVA RAYXON TURSUNBAYEVNA | F104: 998772725500 SMS OZI, 998951307770 SMS UKASI, 998904928594 SMS ZOLOGATEL, | G104: JIZZAX VILOYATI JIZZAX SHAHRI OBOD MFY XALQLAR DUSTLIGI KUCHASI 101-A UY 23-XONADON | H104: 8 | I104: 5917963.6 | K104: Va'da berdi | wu hafta ohirgaca yopadi timur aka bilan gaplawgan ekan
A105: ЖИЗЗАХ ВИЛОЯТИ | C105: Обещал | D105: Кр-99005110-6 | E105: TURSUNOVA MAXBUBA OLIMJON KIZI | F105: 91-567-08-58 sms ukas tolovchi, 99-563-24-48 sms HO’JAYNI, 91-188-00-88 sms UKASI, 90-229-18-51 DADASI , 90-229-18-54 SMS UY, 90-025-93-95 SMS ONASI MAQSUDA, 998882955757 SMS TO’LOVCHI, 998880890111 uzi new, | G105: JIZZAX VILOYATI JIZZAX SHAHAR BUNYODKOR .M.F.Y YORQIN KO’CHASI 16-UY | H105: 14 | I105: 5523834.8 | K105: Va'da berdi | bugun tolaydi kecgaca
A106: ЖИЗЗАХ ВИЛОЯТИ | C106: Обещал | D106: Кр-99038849-1 | E106: XASANOV INOMJON USMONOVICH | F106: 998977931100 SMS SINGLISI, 998916262046 SMS OZI, 998976831100 SMS SINGLISI 2, 998915665348 SMS AYOLI, | G106: ДУСТЛИК, ДУСТЛИК, Э.АШИРМАТОВ, uy:Р/С | H106: 2 | I106: 5384444 | K106: Va'da berdi | kecgaca tolaydi
A107: ЖИЗЗАХ ВИЛОЯТИ | C107: Обещал | D107: Кр-99042115-1 | E107: MIRZAYEV OYBEK SUNATILLAYEVICH | F107: +998902659695 SMS, 998915909006 SMS, 998974559695 SMS, | G107: JIZZAX VILOYATI SH.RASHIDOV TUMANI TOKCHILIK MFY ZARGARLIK KUCHASI 2-UY | H107: 10 | I107: 4457135.3 | K107: Va'da berdi | ertaga aniq yopad kecgaca
A108: ЖИЗЗАХ ВИЛОЯТИ | C108: Обещал | D108: Кр-99063504-1 | E108: MIRZAYEVA LOBARXON ERGASHEVNA | F108: 998933556974 UZI, 998934026974 ERI, 998958832266 TO’LOVCHI, | G108: ТОШКЕСГАН КФЙ, ЛОЙИХАДАГИ КЎЧА, uy:РАКАМСИЗ | H108: 10 | I108: 4425062.2 | K108: Va'da berdi | duwanba tulaydi
A109: ЖИЗЗАХ ВИЛОЯТИ | C109: Обещал | D109: Кр-99057340-1 | E109: SUYUNOVA UMIDA ILHOM QIZI | F109: 998995542023 SMS ERI, 998930913798 SMS UZI, 998943461045 SMS UY, 998901020807 SMS Akasi, | G109: JIZZAX VILOYATI MIRZACHO'L TUMANI IPAK YULI QFY YANGI XAYOT KUCHASI 29-UY | H109: 10 | I109: 3800442.9 | K109: Va'da berdi | 12da tel qiliw kerak
A110: ЖИЗЗАХ ВИЛОЯТИ | C110: Обещал | D110: Кр-99011601-4 | E110: JO’RAQULOV JAVLONJON QAHRAMON O’G’LI | F110: 88-126-00-25 SMS UZI, 97-482-53-53 SMS AYOLI, 88-437-53-53 SMS OTASI, 97-127-53-53 SMS AYOLI, 998776406865 SMS Ukasi tolovchi, | G110: JIZZAX VILOYATI JIZZAX TUMANI OLMACHI MAHALLASI OLMACHI KUCHASI 9/9 UY | H110: 14 | I110: 3593058.5 | K110: Va'da berdi | kecga iwdan ciqib filyalga oborb beradi
... A182: КОРАКАЛПОГИСТОН РЕСПУБЛИКАСИ | C182: Обещал | D182: Кр-99019952-8 | E182: URAZIMBETOVA SHOHISTA GULIMBAYEVNA | F182: 99-186-59-19 SMS UZI, 998995033939 SMS ERI, 998940910907 SMS UZI, 998771152010 OGLI, | G182: QORAQALPOG’ISTON RESPUBLIKASI BERUNIY TUMANI BERUNIY OFY GULZOR KO’CHA | H182: 14 | I182: 736259.75 | K182: Va'da berdi | SMS YOZDIM | 86
A183: КОРАКАЛПОГИСТОН РЕСПУБЛИКАСИ | C183: Обещал | D183: Кр-99030419-1 | E183: SHERIPBAYEV RO’ZIMBOY JUMANIYOZ O’G’LI | F183: 88-306-18-12 SMS O’ZI, 88-507-44-54 SMS ONASI, 91-265-54-59 SMS DUSTI, 99-952-06-66 SMS DUSTI 2 GAPLASHMAYABDI EKAN, 998913051812 SMS O'ZI, 998885001812 SMS UZi new, | G183: QORAQALPOG’ISTON RESPUBLIKASI TO’RTKO’L TUMANI TOZOBOG’YOP MAXALLASI YANGIBOG’ KUCHASI 259 UY | I183: 705565.89 | K183: Va'da berdi | TELEGRAMDAN GAPLASHDIM HAFTA OXIRIGA DEDILA BUGUNGA TAWAB BERING DEB YOZDIM | 275
A184: КОРАКАЛПОГИСТОН РЕСПУБЛИКАСИ | C184: Обещал | D184: Кр-99054971-1 | E184: SAPARNIYAZOV ABATBAY AUYEZBAYEVICH | F184: 998331346724 SMS OZI, 998992978025 SMS OYALI, 998936871998 SMS O'G'LI, 998944768865 SMS QIZI, 998912671001 SMS NEW , | G184: QARAQALPOGISTON RES NUKUS SHADLI AWIL MFY ALTIN TAJ KUSHASI 17 UY | H184: 10 | I184: 603790.2 | K184: Va'da berdi | 1998 BEGONA 8865 XOTINI BN GAPLASHDIM HOZIR ISHDAMAN DEDI BORIB AYTAMAN TO'LAYMIZ DEDI ERI ERTAGA | 1240
A185: КОРАКАЛПОГИСТОН РЕСПУБЛИКАСИ | C185: Обещал | D185: Кр-99052913-1 | E185: SAPARIMBETOVA DILARA ARTIKBAEVNA | F185: 998918730764 SMS OZI, 998913750057 SMS OGLI, 998137175772 SMS OGLI 2, 998919289383 SMS QIZI, 998885022001 O'G'LI, | G185: QARAQALPOGISTON RES NUKUS SHAHAR JAYXUN MFY QIZIL UY KUSHASI 50 A UY | H185: 10 | I185: 573746.36 | K185: Va'da berdi | O'G'LIM TO'LEDI HOZIR PULI YUQ EDI BOLISHI BN TO'LAYMIZ DEYABDI | 1212
A186: НАВОИЙ ВИЛОЯТИ | C186: Обещал | D186: Кр-99063368-1 | E186: SHODIYEV G’ULOM BOBOYOROVICH | F186: 998501569527 O’G’LI, 998880859593 O’ZI, 998932797793 KICHIK O’G’LI, | G186: NAVOIY VILOYATI,NAVBAHOR TUMANI,XASHMAN MFY,QO’RG’ONTEPA KOCHASI,70 UY | H186: 10 | I186: 6414130.6 | K186: Va'da berdi | ertaga tolov qiladi kotta ogli
A187: НАВОИЙ ВИЛОЯТИ | C187: Обещал | D187: Кр-99035137-1 | E187: SHARIPOVA SHOXSANAM QULMANOVNA | F187: 998913302232 SMS O’ZI alisheraka ozimizzi xodim , 998997919190 SMS XOJAYINI , 998913302232 SMS O’ZI , 998936699696 SMS Alisher aka uzimizni xodim, | G187: NAVOIY VILOYATI KALOVAT MFY | H187: 8 | I187: 5823994 | K187: Va'da berdi
A188: НАВОИЙ ВИЛОЯТИ | C188: Обещал | D188: Кр-99043204-3 | E188: JUMAYEV ULUGBEK NEGMURODOVICH | F188: +998959603353 SMS UZI, 998700311935 UGLI, 998878397744 UZI 2 NOMERI, 998952281158 AYOLI, | G188: NAVOIY VILOYATI,KARMANA TUMANI,DEGARON MFY,TEPAARIQ KUCHASI,30 UY | H188: 10 | I188: 5097555.7 | K188: Va'da berdi | bugun pulini olim tolavoradi
A189: НАВОИЙ ВИЛОЯТИ | C189: Обещал | D189: Кр-99034721-1 | E189: CHORIYEV AZIZJON YULDOSHEVICH | F189: 998883220044 SMS OZI, 998999510500 SMS OPASI, 998902350505 SMS AKASI, 998939500080 SMS UY, | G189: NAVOIY VILOYATI QIZILTEPA TUMANI ZARMETAN MFY KURGONTEPA QISHLOG’I 4 UY | H189: 10 | I189: 3933875.7 | K189: Va'da berdi | ertaga
A190: НАВОИЙ ВИЛОЯТИ | C190: Обещал | D190: Кр-99030758-1 | E190: BOBOYEV SAYYOD RAXIMOVICH | F190: 99-556-83-44 SMS O’ZI, 99-516-78-86 SMS AYOLI , 99-967-26-24 SMS SIN , 95-132-22-03 SMS SIN 2 , 998995038828 SMS JIYANI TOLOVCHI , | G190: NAVOIY VILOYATI NUROTA TUMANI SENTOB MFY SENTOB QISHLOG’I | H190: 3 | I190: 2981308.9 | K190: Va'da berdi | ertaga tolov qilib qoyaman ddi
A191: НАВОИЙ ВИЛОЯТИ | C191: Обещал | D191: Кр-99027864-1 | E191: CHULIYEVA DILDORA NEMATILLO QIZI | F191: 91-308-57-37 SMS UZI, 91-965-91-86 SMS ERI O'QITUVCHI QARSHIDA DEHXONOBODDA, 88-795-92-00 SMS ZALOGADATEL, 77-052-92-01 SMS ZALOGADATEL, 998770529186 SMS sodiq tolovchi , | G191: NAVOIY VILOYATI NAVBAXOR TUMANI HALOVAT-TEPA MFY ELPARVAR KO’CHASI 77-UY | H191: 3 | I191: 1561417.8 | K191: Va'da berdi | man bilan aloqada telofonini kotarib turipti ogilm bugun yopvorsa kerak ddi
A192: НАВОИЙ ВИЛОЯТИ | C192: Обещал | D192: Кр-99064028-1 | E192: BOLTAYEV UKTAMJON IBODILLOYEVICH | F192: 998907319493 AYOLI, 998992749373 DADASI, 998995829229 O’ZI, | G192: NAQSHBANDIY 30 A UY | H192: 10 | I192: 983029.76 | K192: Va'da berdi | bugun soat 3-4lada
A193: НАВОИЙ ВИЛОЯТИ | C193: Обещал | D193: Кр-99035085-3 | E193: FARMONOV AZIM BAXTIYOROVICH | F193: 998932789282 SMS OZI, 998996750553 SMS OTASI, 998931738287 SMS XOTINI, | G193: NAVOIY VILOYATI NAVBAXOR TUMANI SARBOZOR MFY YANGIQO’RG’ON 77-UY | H193: 14 | I193: 457696.79 | K193: Va'da berdi | soat 6 gacham
A194: НАМАНГАН ВИЛОЯТИ | C194: Обещал | D194: Кр-99027270-2 | E194: ISLOMOV MAMADALIXON TOLIBXON O’G’LI | F194: 95-000-22-92 SMS O'ZI, 99-398-23-92 SMS OZ'I 2, 91-365-08-04 SMS AYOLI, 91-355-24-41 SMS UKASI, 93-490-51-33 ozi , | G194: NAMANGAN VILOYATI KOSONSOY TUMANI CHINDOVUL QFY ZAMONDOSH MFY 110-UY | H194: 38 | I194: 7644771.1 | K194: Va'da berdi | bugun tolab berarkan | Стандартрый
A195: НАМАНГАН ВИЛОЯТИ | C195: Обещал | D195: Кр-99031356-1 | E195: NAJMUTDINOV ILXOM ODILXANOVICH | F195: 91-052-70-73 SMS OZI, 90-551-31-48 SMS OZI 2, 69-221-50-02 SMS UY, 90-599-89-89 SMS OZI 3, +998776680451 SMS O’ZI, 998957196160 ozi new new, | G195: NAMANGAN VILOYATI NAMANGAN SHAHAR GULBOG’ MFY GULBOG’ KO’CHA 15 UY | H195: 15 | I195: 6661253.8 | K195: Va'da berdi | ertaga tolab berarkan | Стандартрый
... A219: САМАРКАНД ВИЛОЯТИ | C219: Обещал | D219: Кр-99045552-2 | E219: SODIQOV SAIDUMAR FURQAT O’G’LI | F219: +998990261798 SMS OZI, 998770860861 SMS DADASI, 998937731398 SMS UYI, 998941046261 SMS ONASI, +998700366363 Primary phone from road24, 998700366363 Primary phone from road24, 998990261798 SMS OZI, | G219: SAMARQAND VILOYATI NUROBOD TUMANI MASHAL MFY DALABOG’ KUCHASI 126-UY | H219: 10 | I219: 1250884.3 | K219: Va'da berdi | filialga borib ruxsat ob keldi kin ro tolashga
A220: САМАРКАНД ВИЛОЯТИ | C220: Обещал | D220: Кр-99025772-7 | E220: SHAROPOV SHERZOD O’RUNOVICH | F220: 99-193-84-84 SMS UZI, 90-600-66-78 SMS ZALOGADATEL, 90-600-66-78 SMS UYI, 99-161-66-78 SMS UKASI 2, +998991938484 SMS OZI, | G220: SAMARQAND VILOYATI URGUT TUMANI DUSTLIK MFY A.TEMUR KUCHASI 83-UY | I220: 1247329.2 | K220: Va'da berdi | 2 kundan kinga
A221: САМАРКАНД ВИЛОЯТИ | C221: Обещал | D221: Кр-99030240-4 | E221: BABAJONOV MASHIROB OLMASOVICH | F221: 50-552-16-74 SMS O’ZI, 93-045-82-83 SMS UKASI JASUR TULOVCHI , 93-037-26-83 SMS AYOLI, 93-990-90-27 SMS UYI, 998949032282 SMS ukasi tulovchi, | G221: SAMARQAND VIL PASTDARG'OM TUM P.BOG'ANALI QISHLOG'I YANGI UZBEKISTON koch | H221: 10 | I221: 1175899.7 | K221: Va'da berdi | ertaga toliq yopad
A222: САМАРКАНД ВИЛОЯТИ | C222: Обещал | D222: Кр-99033239-3 | E222: KOBILOV XURSHED SHUXRATOVICH | F222: 998941333868 SMS O’ZI, 998942822026 SMS AKASI TO’LOVCHI, 998991364741 SMS UY, 998933388883 SMS AYOLI, | G222: SAMARQAND VILOYATI SAMARQAND SHAHRI PARRANDACHILIK MFY | H222: 10 | I222: 1007206.5 | K222: Va'da berdi | ertaga 5 gacha tolov qiladi tolovchi ayolini nomerini ishlatyapti
A223: САМАРКАНД ВИЛОЯТИ | C223: Обещал | D223: Кр-99035569-2 | E223: MANSUROV NODIRBEK SIROJITDINOVICH | F223: 998992365131 SMS OZI, 998942265131 SMS AYOLI, 998992984910 SMS OPASI, 998423551312 SMS OZI, | G223: SAMARQAND VILOYATI NARPAY TUMANI KOZIKENT MFY DAMCHA KUCHASI 139-UY | H223: 14 | I223: 818162.24 | K223: Va'da berdi | 4 gacha tolov
A224: САМАРКАНД ВИЛОЯТИ | C224: Обещал | D224: Кр-99055726-1 | E224: TO’RAYEVA ZUMRAD JO’RABEK QIZI | F224: 998997767207 SMS ERI , 998995857802 SMS OZI , 998979180228 SMS UYI, 998904638777 SMS UKASI, | G224: SAMARQAND VILOYATI PASTDARG'OM TUMANI IIB томонидан 09.03.2017 йилда берилган | H224: 10 | I224: 659613.96 | K224: Va'da berdi | ukasi bn gaplashilindi bugun tolov qiladi aytad
A225: САМАРКАНД ВИЛОЯТИ | C225: Обещал | D225: Кр-99057434-1 | E225: AKRAMOV KOMIL MAVLONOVICH | F225: 998996215271 SMS UZI, 998994131573 SMS AYOLI, 998993114953 SMS UGLI, 998953469498 SMS UYI, | G225: SAMARQAND VILOYATI OQDARYO TUMANI DO'STLIK MFY YANGI QISHLOQ QISHLOG'I | H225: 10 | I225: 647118.83 | K225: Va'da berdi | bugun tolid
A226: САМАРКАНД ВИЛОЯТИ | C226: Обещал | D226: Кр-99040360-2 | E226: KUSHMURODOV RASHID XUROZOVICH | F226: +998936002584 SMS O’ZI, 998505003878 SMS AKASI 2, 998935692069 SMS AKASI, 998501202552 SMS TULOVCHI, 998889007404 SMS AYOLI, 998919650304 SMS AKASI, | G226: SAMARQAND VILOYATI PAYARIQ TUMANI BAXRIN MFY SARXOUS KUCHASI 71-UY | H226: 10 | I226: 575789.3 | K226: Va'da berdi
A227: САМАРКАНД ВИЛОЯТИ | C227: Обещал | D227: Кр-99004885-4 | E227: USMONOVA GULJAXON ABDIJABBOROVNA | F227: 99-038-39-85 SMS UZI, 99-131-46-67 SMS HO’JAYINI, 99-448-74-56 SMS DADASI SHU ODAMGA TEL QILINMASIN 2 GURIPPA NOGIRON MAZZASI BOMIY QOVOTI, 99-413-90-93 SMS UKASI TANIMASIKAN , 99-131-46-67 SMS eri, | G227: SAMARQAND VILOYATI ISHTIHON TUMANI O’RTA QISHLOQ Q.F.Y QO’RSHIQ QISHLOG’I 33-UY | H227: 1 | I227: 294493.61 | K227: Va'da berdi | bugun tolavorad
A228: САМАРКАНД ВИЛОЯТИ | C228: Обещал | D228: Кр-99040012-1 | E228: QURBONOVA MOXIGUL MELIQULOVNA | F228: 999895870313 SMS OZI, 998889384114 SMS ERI, 998883670313 SMS OGLI, 998993764700 SMS UYI, | G228: SAMARQAND VILOYATI URGUT TUMANI QORATEPA MFY QUZICHI QISHLOG'I | I228: 49577.2 | K228: Va'da berdi | abetdan kin tolid
A229: СУРХОНДАРЁ ВИЛОЯТИ | C229: Обещал | D229: Кр-99031106-8 | E229: ESHONQULOVA MALOXAT DONIYOROVNA | F229: 998994258000 SMS O’ZI TULOVCHI, 998998278000 SMS OZI, 97-076-99-01 SMS SINGLISI, 998770889901 SMS uzi new raqami, 998996799892 SMS UKASI, 998997113009 SMS O’ZI, | G229: SH.RASHIDOV 186-UY 7-XONADON | H229: 104 | I229: 74884301 | K229: Va'da berdi | abror ogan | 305
A230: СУРХОНДАРЁ ВИЛОЯТИ | C230: Обещал | D230: Кр-99062062-1 | E230: QAMBAROV ZUXRUDDIN IKROMIDDIN O’G’LI | F230: 998997113009 SMS Шахноз тўловчи, | G230: SURXONDARYO VILOYATI DENOV SHAHRI NURLI MANZIL MFY MADANIYAT 152-UY 27-XONADON | H230: 104 | I230: 65116939 | K230: Va'da berdi | wahnoz tolidi | 1396
A231: СУРХОНДАРЁ ВИЛОЯТИ | C231: Обещал | D231: Кр-99035360-1 | E231: JO’RAYEV ILYOS SHAXRIYOROVICH | F231: 998973507711 SMS O’ZI, 999880757000 SMS UY, 998771073599 SMS OILASI, 998919095500 SMS AKASI, 998500088102 SMS UZI 2, | G231: SURXONDARYO VILOYATI DENOV TUMANI FARG’ONA QFY OLOVUDDIN MFY SHAXROBOD 27-UY | H231: 93 | I231: 46898957 | K231: Va'da berdi | abror olgan | 508
A232: СУРХОНДАРЁ ВИЛОЯТИ | C232: Обещал | D232: Кр-99038710-1 | E232: MURATOV JALOLIDDIN FAZLIDDIN O’G’LI | F232: 998330007577 SMS OZI, 998997577136 SMS OZI , 998777779397 SMS OTASI, | G232: SURAXNDARYO VILOYATI DENOV TUMANI OLAYURT KO’CHASI 29-UY | H232: 162 | I232: 43817088 | K232: Va'da berdi | shaxnoz ogan | 718
A233: СУРХОНДАРЁ ВИЛОЯТИ | C233: Обещал | D233: Кр-99028747-1 | E233: PIRMATOV SHOMUROD EGAMBERDI O’G’LI | F233: 99-169-60-68 SMS uzi, 95-257-44-05 SMS akasi, 91-991-09-67 SMS uy, 77-173-73-89 SMS oilasi, | G233: SURXONDARYO VILOYATI DENOV TUMANI | H233: 182 | I233: 28020402 | K233: Va'da berdi | abror tolo qlad | 212
A234: СУРХОНДАРЁ ВИЛОЯТИ | C234: Обещал | D234: Кр-99047243-1 | E234: XOLMO’MINOV ZAFARBEK ILHOM O’G’LI | F234: +998931295565 SMS O’ZI, 998774107913 SMS ONASI, 998935993630 SMS TO'LOVCHI, | G234: ТОРЗОР КУЧАСИ 13А УЙ | H234: 164 | I234: 26394832 | K234: Va'da berdi | abror tolaga | 1128
A235: СУРХОНДАРЁ ВИЛОЯТИ | C235: Обещал | D235: Кр-99024295-1 | E235: QAHHOROVA MA’RIFAT AMONOVNA | F235: +998937270186 SMS O’ZI, 998947131008 SMS QIZI, 998990866375 SMS O’ZI, | G235: ШЕРОБОД ТУМАН САРИҚАМИШ ҚФЙ, МЕХРОБОД МФЙ, СЕПЛОН КУЧ uy:51А | H235: 164 | I235: 25469079 | K235: Va'da berdi | oy oxrgaca yopaman dd | 127
A236: СУРХОНДАРЁ ВИЛОЯТИ | C236: Обещал | D236: Кр-99032943-1 | E236: RAXIMBADALOV ALISHER NAMAZALIYEVICH | F236: 998978490308 SMS O’ZI, 998995767713 SMS OTASI, 998904101090 SMS ONASI, 998950442969 SMS AMAKISI, | G236: SURXONDARYO VILOYATI UZUN TUMANI ITTIFOQ MFY SHODLIK KO’CHASI 98-UY | H236: 148 | I236: 20532398 | K236: Va'da berdi | abrorga tolaga | 371
A237: СУРХОНДАРЁ ВИЛОЯТИ | C237: Обещал | D237: Кр-99037217-1 | E237: XUDOYBERDIYEV RUSTAM ASHIROVICH | F237: 998888080583 SMS OZI, 998952608388 SMS UKASI, 998952688984 SMS AKASI, 998990619488 SMS UY, | G237: SURXONDARYO VILOYATI DENOV TUMANI SH.RASHIDOV SIU OQQO’RG’ON MFY TONYULDUZU 112-UY | H237: 133 | I237: 20054550 | K237: Va'da berdi | Shaxnoz olgan | 623
A238: СУРХОНДАРЁ ВИЛОЯТИ | C238: Обещал | D238: Кр-99029760-1 | E238: MENGNAROV ERKIN DJABBAROVICH | F238: 90-294-46-11 uzi, 97-331-00-95 UY, 88-617-09-99 OILASI, 998959405510 SMS OGLI , | G238: SURXANDARYO VILOYATI DENOV TUMANI CHUQURQISHLOQ MFY SURXONOBOD KO’CHASI 58-UY | H238: 122 | I238: 19463414 | K238: Va'da berdi | abror ogan | 255
A239: СУРХОНДАРЁ ВИЛОЯТИ | C239: Обещал | D239: Кр-99044052-1 | E239: DJABBOROVA NODIRA MELIQULOVNA | F239: +998887191000 SMS O’ZI, 998902493639 SMS UY, 998910791549 SMS ONASI, | G239: СУРХОНДАРЁ ВИЛОЯТИ ДЕНОВ ТУМАНИ И.ТУРАЕВ СИУ, НАМУНА МФЙ, uy:48 | H239: 104 | I239: 19454323 | K239: Va'da berdi | abror ogan | 1080
A240: СУРХОНДАРЁ ВИЛОЯТИ | C240: Обещал | D240: Кр-99030594-1 | E240: SHAIMOV NODIRBEK ISMOILOVICH | F240: 97-076-89-99 SMS O’ZI, 97-194-39-99 SMS UKASI, 99-599-99-43 SMS UKASI 2 begona tel qimanglar, 50-071-10-03 SMS UY begona, | G240: SURXONDARYO VILOYATI DENOV TUMANI XAZARBOG QFY CHORGUL MFY TARQULAT KO’CHASI 12-UY | H240: 157 | I240: 18273643 | K240: Va'da berdi | abrorga tolaga | 281
... A317: СУРХОНДАРЁ ВИЛОЯТИ | C317: Обещал | D317: Кр-99043043-1 | E317: BOYQULOV FIRDAVS ABDUVOXID O’G’LI | F317: 998944361003 SMS O’ZI, 998991351177 SMS UY, 998996660094 SMS AKASI, | G317: Сурхандарьинская область, Денауский район, Хазарбоғ СИУ, Чим МСГ, ул. Гулистон, дом 6 | H317: 10 | I317: 2027247.4 | K317: Va'da berdi | mowinasn urvogan oy oxrgaca yopad | 1073
A318: СУРХОНДАРЁ ВИЛОЯТИ | C318: Обещал | D318: Кр-99040374-1 | E318: KARSHIYEV TAJIMURAT PRIMOVICH | F318: 998993876160 SMS OZI, 998997284700 SMS OGLI, 998991496886 SMS OGLI, | G318: SURXONDARYO VILOYATI QUMQO'RG'ON TUMANI DAVLATSOY MAXALLASI USTALAR KO'CHASI 26-UY | I318: 1996808.6 | K318: Va'da berdi | 21 sanaga tolo qlad | 887
A319: СУРХОНДАРЁ ВИЛОЯТИ | C319: Обещал | D319: Кр-99025697-2 | E319: KIPCHAKOV RUSTAM SULTANOVICH | F319: 91-134-38-00 SMS, 90-246-76-15 SMS UY, 95-103-38-00 SMS OILASI, 91-967-50-50 SMS O’G’LI, | G319: SURXONDARYO VILOYATI DENOV SHAXAR ISTIQLOL MFY XUSAYN BOYQORO KOCHASI 5-UY | H319: 10 | I319: 1977259.2 | K319: Va'da berdi | abror bn wahnoz tolidi | 147
A320: СУРХОНДАРЁ ВИЛОЯТИ | C320: Обещал | D320: Кр-99038061-1 | E320: NAZRULLAYEV SHUHRAT ABDULLAYEVICH | F320: 998505894240 SMS OZI, 998955401190 SMS UYI, 998934306997 SMS UYI, 998952680122 SMS AYOLI, | G320: SURXONDARYO VILOYATI DENOV TUMANI SOXIBKOR MFY OYBARAK 98 UY | H320: 6 | I320: 1975539 | K320: Va'da berdi | abror olgan | 677
A321: СУРХОНДАРЁ ВИЛОЯТИ | C321: Обещал | D321: Кр-99029311-1 | E321: RAJABOVA DILAFRUZ ABDUMALIKOVNA | F321: 33-377-52-60 SMS, 33-411-04-47 SMS UY, 97-536-30-01 SMS OILASI, 33-719-00-81 SMS , | G321: SURXONDARYO VILOYATI DENOV TUMANI VODIY MFY FARG’ONA 71-UY | H321: 8 | I321: 1953350.1 | K321: Va'da berdi | wahnozga tolaga | 233
A322: СУРХОНДАРЁ ВИЛОЯТИ | C322: Обещал | D322: Кр-99033369-1 | E322: SHAMANOV XASAN RAVSHAN O’G’LI | F322: 998772651883 SMS O’ZI QIBRAYDA KAROBKA SEXDA ISHLIDI , 998930634268 SMS AYOLI, 998507727494 SMS AYOLI2, 998978070064 SMS otasi, | G322: SURXONDARYO VILOYATI TERMIZ SHAHRI ALPOMISH MFY 5-KICHIK DAHA KO’CHASI 12-DOM 20-KVARTIRA | H322: 10 | I322: 1913183.4 | K322: Va'da berdi | kyngi xafta | 389
A323: СУРХОНДАРЁ ВИЛОЯТИ | C323: Обещал | D323: Кр-99022239-3 | E323: MAXMUDOV AZAMAT ABDUXALIMOVICH | F323: 99-428-85-81 SMS, 93-838-85-01 SMS UY, 91-581-86-56 SMS ZALOGADATEL, 998947851179 shu raqamdan tel qildi azamat , | G323: SURXONDARYO VILOYATI SARIOSIYO TUMANI SUFIYON QFY NIHOLZOR MFY TINCHLIK K’OCHASI 46-UY | H323: 10 | I323: 1876409 | K323: Va'da berdi | 20 cisidan kyn tolov qlad | 113
A324: СУРХОНДАРЁ ВИЛОЯТИ | C324: Обещал | D324: Кр-99027695-1 | E324: JO’RAYEV SHERALI AZAMOVICH | F324: 94-456-81-79 SMS O'ZI, 91-237-79-81 SMS OG’LI, 91-910-15-76 SMS ZALAGATEL, 90-889-89-62 SMS UY, | G324: SURXONDARYO DENOV TUMANI QORAHON MFY BOG’ISHAMOL KO’CHASI 78-UY | H324: 10 | I324: 1841115.5 | K324: Va'da berdi | abror ogan | 179
A325: СУРХОНДАРЁ ВИЛОЯТИ | C325: Обещал | D325: Кр-99039843-1 | E325: MARDAYEV RUSLAN MAMATALIYEVICH | F325: 998970397888 SMS OZI, 998975310659 SMS OTASAI, 998976961461 SMS ONASI, 998886929191 SMS UKASI, | G325: SURXONDARYO VILOYAT MUZRABOT TUMAN XALQYO’LI MFY O’RMON XO’JALIGI KO’CHASI 34-UY | H325: 10 | I325: 1792346.8 | K325: Va'da berdi | 19sanaga tolov | 839
A326: СУРХОНДАРЁ ВИЛОЯТИ | C326: Обещал | D326: Кр-99030736-2 | E326: MAMATMURADOVA SURAYYO XOLMO’MINOVNA | F326: 99-258-33-31 SMS O’ZI HARBIY begona , 97-689-76-76 SMS UY, 95-254-38-31 SMS OILASI, 95-238-32-31 SMS, | G326: SURXONDARYO VILOYATI DENOV TUMANI MUQUMIY MFY BOG’ZOR KO’CHASI 2-UY | H326: 3 | I326: 1675812.1 | K326: Va'da berdi | wu xafta tolo qlad | 296
A327: СУРХОНДАРЁ ВИЛОЯТИ | C327: Обещал | D327: Кр-99037942-1 | E327: YODGOROV XAMRO ESHONQULOVICH | F327: 998919696012 SMS OZI, 998901201798 SMS UYI, 998991828111 SMS TULOVCHI UG`LI MUHRIDDIN, 998952435111 SMS ONASI, | G327: SURXONDARYO VILOYATI SARIOSIYO TUMANI SHAXRIOBOD MFY SOADATMAN 2-UY | I327: 1674909.8 | K327: Va'da berdi | ertaga tolov | 667
A328: СУРХОНДАРЁ ВИЛОЯТИ | C328: Обещал | D328: Кр-99029526-3 | E328: QAYUMOV XASAN XAYRULLAYEVICH | F328: 97-693-95-55 SMS , 90-266-26-26 SMS AKASI, 90-266-32-66 SMS ONASI, 77-023-72-32 SMS UY, 998996726826 SMS TOLOVCHI , | G328: SURXONDARYO VILOYATI DENOV TUMANI BOBIR MFY BOBUR 25-UY | H328: 10 | I328: 1625182 | K328: Va'da berdi | oy oxrgaca yopad | 243
A329: СУРХОНДАРЁ ВИЛОЯТИ | C329: Обещал | D329: Кр-99027715-1 | E329: SHODMONOVA MAFTUNA OBIDJONOVNA | F329: 97-225-11-27 SMS ERI UQITUVCHI TOLOVCHI , 91-966-11-27 SMS UY, 90-568-35-85 SMS ONASI, 97-551-16-69 SMS ISHXONA, | G329: SURXONDARYO UZUN TUMANI YANGIRO’ZG’OR MFY DO’STLIK KO’CHASI 855-UY | H329: 10 | I329: 1607988.1 | K329: Va'da berdi | abrorga tolaga | 181
A330: СУРХОНДАРЁ ВИЛОЯТИ | C330: Обещал | D330: Кр-99061106-1 | E330: ESHMURODOV JUMMANAZAR ALIMOVICH | F330: 998885680272 SMS UY, 998952357793 SMS UZI, 998995853555 SMS OILASI, | G330: SURXONDARYO VILOYATI DENOV TUMANI TOTUVLIK MFY GULLIRANO 74-UY | H330: 10 | I330: 1533268.1 | K330: Va'da berdi | wahnoz tolo qlad | 1376
A331: СУРХОНДАРЁ ВИЛОЯТИ | C331: Обещал | D331: Кр-99035581-3 | E331: SAYDALIYEV BAXTINUR BAXRIDDIN O’G’LI | F331: 998919090044 SMS OZI, 998945824941 SMS UY, 998931229717 SMS AYOLI, 998885510044 SMS UKASI, 998880940070 SMS uzi new, 998917240044 SMS O’ZI, 998952236442 SMS AYOLI, 998917240044 NEW OZI, | G331: Сурхондарё вилояти Кизирик Тумани Работак МФЙ, Абдулла Қаххор 1 кучаси, 21...-уй | H331: 10 | I331: 1425548.6 | K331: Va'da berdi | 20 dan kyn tolo qlad | 517
A332: СУРХОНДАРЁ ВИЛОЯТИ | C332: Обещал | D332: Кр-99030710-1 | E332: JUMANAZAROV XUSAN XXX | F332: 99-754-22-05 SMS O’ZI, 99-457-96-55 SMS O’ZI, 94-656-19-77 SMS O’GLI, 88-808-34-33 SMS UY, | G332: SURXONDARYO VILOYATI OLTINSOY TUMANI OLTINSOY QFY JIYANBOBO MFY MEYVAZOR 47-UY | H332: 3 | I332: 1423299.2 | K332: Va'da berdi | otasi bn gaplawdm 2-3 kunda tolov qlad | 294
A333: СУРХОНДАРЁ ВИЛОЯТИ | C333: Обещал | D333: Кр-99063093-1 | E333: SHOPULATOV JAHONGIR OTABEK O’G’LI | F333: 998937989939 OZI, 998919065400 AKASI, | G333: SURXONDARYO VILOYATI TERMIZ TUMAN JOYJANGAL MFY NURONIY KO’CHASI 102-UY | I333: 1354109.6 | K333: Va'da berdi | oy oxirida | 1501
A334: СУРХОНДАРЁ ВИЛОЯТИ | C334: Обещал | D334: Кр-99007175-2 | E334: KOHAROV USMON ERGASHOVICH | F334: 91-580-94-59 SMS, 90-747-47-68 SMS XOTINI NILUFDAR OPA, 91-513-87-87 SMS O’G’LI MIROLIM, 99-979-13-85 SMS UY, | G334: SURXONDARYO VILOYATI QUMQO’RG’ON TUMANI NAVBAHOR MFY AT-TERMIZIY KO’CHASI 7-UY | H334: 10 | I334: 1348290.9 | K334: Va'da berdi | keca qisman tolad bugun erte yopad | 20
A335: СУРХОНДАРЁ ВИЛОЯТИ | C335: Обещал | D335: Кр-99040068-3 | E335: BAZAROV AXMAT ESHMAMATOVICH | F335: 998973505961 SMS AYOLI, 998976942461 SMS OZI, 998918171212 SMS QIZI, 998976396767 SMS OGLI, 998903579595 SMS UY, | G335: SURXONDARYO VILOYATI DENOV TUMANI OZOD MFY NURLI HAYOT KO’CHASI 45-UY | H335: 10 | I335: 1295114.3 | K335: Va'da berdi | 22 ga tolo qlad | 858
A336: СУРХОНДАРЁ ВИЛОЯТИ | C336: Обещал | D336: Кр-99037364-1 | E336: MAMARASULOV BAXODIRJON BAXTIYOROVICH | F336: 998953305005 SMS, 998951925005 SMS OZI, 998978151968 SMS UY, 998952120535 SMS , | G336: SURXONDARYO VILOYATI DENOV SHAHAR QUYOSHLIYURT MFY FIRDAVS 1-UY | H336: 3 | I336: 1277712.1 | K336: Va'da berdi | kyngi xafta tolo qlaman dd | 636
A337: СУРХОНДАРЁ ВИЛОЯТИ | C337: Обещал | D337: Кр-99029195-4 | E337: ESHBAYEVA GULBAHOR OMANDAVLATOVNA | F337: 998904180270 SMS O’ZI, 998994490270 SMS UY, 998330750020 SMS UKASI, 998993808096 SMS UKASI, 998999661002 SMS TULOVCHI, | G337: SURXONDARYO VILOYATI QUMQURG’ON TUMANI CHUKIRLI MFY BO’LAK TEPA KO’CHASI 28-UY | H337: 10 | I337: 1202412.9 | K337: Va'da berdi | bugun nasb tolo qlad | 229
A338: СУРХОНДАРЁ ВИЛОЯТИ | C338: Обещал | D338: Кр-99036107-2 | E338: ZIKIROV ALISHER KUDRATOVICH | F338: 998957668603 SMS O’ZI, 998991970555 SMS JIYANI , 998882444737 AKASI, 998990380351 SMS AYOLI , | G338: SURXONDARYO VILOYATI DENOV TUMANI ISTIQBOL MFY SATTOR YODGOROV 35-UY | H338: 10 | I338: 1179868.5 | K338: Va'da berdi | 20sanaga tolov | 560
A339: СУРХОНДАРЁ ВИЛОЯТИ | C339: Обещал | D339: Кр-99032451-1 | E339: MAMAJONOVA MAXFUZA SAMIJONOVNA | F339: 998942099378 SMS UKASI, 998337682003 SMS O’G’LI, 998992711325 SMS OILASI begona, 998938808307 SMS O’ZI, | G339: SURXONDARYO VILOYATI DENOV TUMANI BUYUK KELAJAK MFY TURSUNZODA KO’CHASI 11-UY | H339: 9 | I339: 1113629.8 | K339: Va'da berdi | ukasi tolovci stroykada iwlidi kunlik tolov qlad | 353
A340: СУРХОНДАРЁ ВИЛОЯТИ | C340: Обещал | D340: Кр-99062784-2 | E340: ESHMUMINOV ALLAMUROD PANJI O’G’LI | F340: +998938173666 SMS O’ZI, 998940242987 SMS AKASI, 998990905996 SMS ONASI, 998500056666 uzi new, | G340: ШЕРОБОД ТУМАНИ ЁШЛИК МФЙ, Ш.ЖУМАЕВ КУЧАСИ, uy:44 | H340: 10 | I340: 1110259.6 | K340: Va'da berdi | ownasi bn gaplawdm etaman dd | 1438
A341: СУРХОНДАРЁ ВИЛОЯТИ | C341: Обещал | D341: Кр-99041744-1 | E341: KARIMOVA MADINA SOTTOR QIZI | F341: 998975527101 SMS OZI, 998881927101 SMS UY, 999872010159 SMS OILASI, 998785510044 SMS UKASI, 998957737555 SMS ERI, | G341: SURXONDARYO VILOYATI DENOV TUMANI BUYUKIPAK YULI MFY I.KARIMOV 70-UY | H341: 10 | I341: 1024167.3 | K341: Va'da berdi | 20 dan kyn tolo qlad | 1018
...

Sheet Оплатили
A1: ← Вернуться в отчёт
A2: Область | B2: Филиал | C2: Группа | D2: Код клиента | E2: Клиент | F2: Номер телефона | G2: Адрес | H2: Кол-во просроченных дней | I2: Итого просрочка | J2: Оплата | K2: Izoh
A3: АНДИЖОН ВИЛОЯТИ | C3: Объезд | D3: Кр-99057085-1 | E3: YULDASHEVA NILUFAR KAMILOVNA | F3: 998872557757 SMS OZI, 998982700122 SMS OGLI, 998772581112 SMS QIZI, 998882331807 SMS JIYANI, | G3: ANDIJON VILOYATI ANDIJON TUMANI ZANGIBOBO MFY PORLOQ KO’CHASI 306-UY | H3: 13 | I3: 15030583 | J3: 5342465 | K3: Uyiga borildi - to'ladi | 5342465.7534246575 | 9688117.5
A4: АНДИЖОН ВИЛОЯТИ | C4: Дозвон | D4: Кр-99039306-1 | E4: ODILJONOV ABDULAZIZ UMIDJON O’G’LI | F4: 998934153932 SMS OZI, 998937810042 SMS ONASI, 998937810094 SMS OTASI, 998941051030 SMS AKASI, | G4: ANDIJON VILOYATI ANDIJON SHAHAR DALVARZIN MFY A.ASHUROV 3-TOR KO’CHASI 4-UY | H4: 14 | I4: 10688765 | J4: 3835616 | K4: To'ladi | 3835616.4383561644 | 6853149.05
A5: АНДИЖОН ВИЛОЯТИ | C5: Дозвон | D5: Кр-99039609-1 | E5: TOJIDINOVA MUXARRAMXON KOBULOVNA | F5: 998940331487 SMS OZI, 998950978615 SMS XOJAYINI, 998903870911 SMS OGLI, 998934168183 SMS AKASI, | G5: ANDIJON VILOYATI MARXAMAT TUMANI MIRISHKOLAR MFY, DORBOZ KO’CHASI 45-UY | H5: 3 | I5: 3360170 | J5: 410958 | K5: To'ladi | 410958.90410958906 | 2949211.13
A6: АНДИЖОН ВИЛОЯТИ | C6: Объезд | D6: Кр-99037425-1 | E6: SHUKUROV QUVONCHBEK XABIBILLAYEVICH | F6: 998905271070 SMS OZI, 998901707424 SMS OGLI, 998914865970 SMS AYOLI, 998953475970 SMS QIZI, | G6: ANDIJON VILOYATI ANDIJON TUMANI YUKSALISH MFY YUKSALISH KO’CHASI 19-UY | H6: 2 | I6: 2889861.2 | J6: 273972 | K6: Uyiga borildi - to'ladi | 273972.602739726 | 2615888.63
A7: АНДИЖОН ВИЛОЯТИ | C7: Объезд | D7: Кр-99063106-1 | E7: SOTVOLDIYEVA MAXMUDAXON QOSIMOVNA | F7: 998770492346 OZI, 998931092588 OGLI, 998937212671 OPASI, 998942592770 DUGONASI, | G7: ANDIJON VILOYATI QO’RG’ONTEPA TUMANI UCHQUN MFY ISTIQBOL KO’CHASI 16 UY | H7: 10 | I7: 2695142.3 | J7: 821917 | K7: Uyiga borildi - to'ladi | 821917.8082191781 | 1873224.48
A8: АНДИЖОН ВИЛОЯТИ | C8: Дозвон | D8: Кр-99004621-4 | E8: NADIROV MURODJON BAXRAMJON O’G’LI | F8: 90-543-11-01 SMS, 99-327-66-67 sms танимийди, 90-528-19-14 SMS TANIMASAKAN , 91-175-12-12 SMS ortogi, +998905431101 SMS O’ZI, 998887838780 SMS AKASI, 998946398780 SMS JIYANI ASADBEK, 998977268780 SMS UKASI, | G8: Саноат МФЙ, А.Йулдошев 1 тор кучаси, 37-уй | H8: 10 | I8: 2150272.7 | J8: 410958 | K8: To'ladi | 410958.90410958906 | 1739313.84
A9: БУХОРО ВИЛОЯТИ | B9: SUPER BRANCH | C9: Объезд | D9: Кр-99019690-5 | E9: HAYDAROV FURQAT RAXMATILLOYEVICH | F9: 97-488-07-66 SMS O'ZI, 88-301-90-93 SMS AKASI, 97-296-06-93 SMS UY, 93-841-53-50 SMS AYOLI, 998505999203 SMS O'ZI2, | G9: BUXORO VILOYAT BUXORO SHAHRI BESHKAPPA KO'CHASI 106 UY | H9: 7 | I9: 2199808.5 | J9: 2484160 | K9: Uyiga borildi - to'ladi | 2 | 2484160.2179178083
A10: БУХОРО ВИЛОЯТИ | B10: SUPER BRANCH | C10: Объезд | D10: Кр-99019690-6 | E10: HAYDAROV FURQAT RAXMATILLOYEVICH | F10: 97-488-07-66 SMS O'ZI, 88-301-90-93 SMS AKASI, 97-296-06-93 SMS UY, 93-841-53-50 SMS AYOLI, 998505999203 SMS O'ZI2, | G10: BUXORO VILOYAT BUXORO SHAHRI BESHKAPPA KO'CHASI 106 UY | H10: 7 | I10: 1144641.8 | J10: 1277949 | K10: Uyiga borildi - to'ladi | 3 | 1277949.4817260276
A11: БУХОРО ВИЛОЯТИ | B11: Бухоро филиали | C11: Дозвон | D11: Кр-99019690-4 | E11: HAYDAROV FURQAT RAXMATILLOYEVICH | F11: 97-488-07-66 SMS O'ZI, 88-301-90-93 SMS AKASI, 97-296-06-93 SMS UY, 93-841-53-50 SMS AYOLI, 998505999203 SMS O'ZI2, | G11: BUXORO VILOYAT BUXORO SHAHRI BESHKAPPA KO'CHASI 106 UY | H11: 9 | I11: 1212298.9 | J11: 1265879 | K11: To'ladi | 1 | 1265879.6719178082
A12: ЖИЗЗАХ ВИЛОЯТИ | C12: Объезд | D12: Кр-99038833-1 | E12: XOSILBEKOV SHUXRAT SAFAROVICH | F12: 998941957573 SMS O’ZI, 998935570175 SMS AYOLI, 998945160190 SMS UKASI, 998947277308 SMS SINGLISI, | G12: ZOMIN TUMANI | H12: 1 | I12: 7710284 | J12: 7710284 | K12: Uyiga borildi - to'ladi
A13: ЖИЗЗАХ ВИЛОЯТИ | C13: Дозвон | D13: Кр-99055031-1 | E13: PARDAYEVA XAFIZA AKRAMOVNA | F13: 998995900655 SMS OZI, 998997473110 SMS OZI, 998958160926 SMS O'G'LI, | G13: JIZZAX VILOYATI G'ALLAOROL TUMANI MIRZABULOQ QFY NAYMAN KUCHASI 36-UY | H13: 10 | I13: 3028615.3 | J13: 3028615.3 | K13: To'ladi
A14: ЖИЗЗАХ ВИЛОЯТИ | C14: Дозвон | D14: Кр-99052894-1 | E14: SUVONQULOV SHAXRIYOR MIRZABEK O’G’LI | F14: 998943079900 SMS OZI, 998932800094 SMS AKASI, 998938265665 SMS AKASI 2, 999839712506 SMS UKASI, | G14: JIZZAX VILOYATI SHAROF RASHIDOV TUMANI QANG'LI QFY NURAFSHON MFY OBOD KUCHASI 9-UY | H14: 10 | I14: 2557891.2 | J14: 2557891.2 | K14: To'ladi
A15: ЖИЗЗАХ ВИЛОЯТИ | C15: Объезд | D15: Кр-99041710-1 | E15: MAMARAJABOVA ZULOYXA ABDUMALIK QIZI | F15: 998339269697 SMS, 998931049616 SMS, | G15: JIZZAX VILOYATI BAXMAL TUMANI TONGOTAR MFY QUSHTEPA QISHLOGI 65-UY | H15: 10 | I15: 2497483.1 | J15: 2497483.1 | K15: Uyiga borildi - to'ladi | qisman tolov qildi
A16: ЖИЗЗАХ ВИЛОЯТИ | C16: Дозвон | D16: Кр-99039329-1 | E16: TURSUNMATOV ABDULAZIZ ALIAKBAR O’G’LI | F16: +998947200340 SMS OZI, 998772942607 SMS DADASI, 998990231125 SMS AKASI, 998999992897 SMS UKASI, | G16: МУГОЛ КФЙ, МУГОЛ КФЙ, ЛОЙИХАДАГИ, uy:Р.С | H16: 10 | I16: 1773514.2 | J16: 1773514.2 | K16: To'ladi
A17: ЖИЗЗАХ ВИЛОЯТИ | C17: Дозвон | D17: Кр-99041692-1 | E17: XAYDAROVA MUHABBAT KAMOL QIZI | F17: +998871055002 SMS OZI, 998879530070 SMS AYOLI, 998918910095 SMS AKASI, 998918910095 SMS UKASI, | G17: JIZZAX VILOYATI JIZZAX TUMANI QANGLI MFY FAROVON KUCHASI 36-UY | H17: 10 | I17: 1763084.6 | J17: 1763084.6 | K17: To'ladi
A18: ЖИЗЗАХ ВИЛОЯТИ | C18: Объезд | D18: Кр-99026372-3 | E18: ARIPOV FAXRIDDIN JO’MANOVICH | F18: 94-138-50-20 SMS UZI , 91-209-90-77 SMS UZI, 94-001-51-35 SMS UY, 91-028-70-28 SMS AYOLI, | G18: JIZZAX VILOYATI MARJONBULOQ SHMB LALMIKOR MFY NAVRO’Z MAHALLASI 60-UY | H18: 10 | I18: 1508602.4 | J18: 1508602.4 | K18: Uyiga borildi - to'ladi
A19: ЖИЗЗАХ ВИЛОЯТИ | C19: Дозвон | D19: Кр-99033516-1 | E19: MIRZAMAXMUDOV ODILJON ALLAYOR O’G’LI | F19: 998997449700 SMS O’ZI, 998912084455 SMS O’ZI, 998338382297 SMS DO’STI, 998991332871 SMS ONASI, 998950702444 SMS AKASI, 998336669700 SMS OZI YANGI, 998932947066 SMS ABDUNABI ORTOGI, | G19: JIZZAX VILOYATI BAXMAL TUMANI UDAMALI QISHLOG’I 63-UY | H19: 3 | I19: 1079691.8 | J19: 1079691.8 | K19: To'ladi
A20: ЖИЗЗАХ ВИЛОЯТИ | C20: Дозвон | D20: Кр-99046548-1 | E20: BOYMURZAYEV HASAN NAZAR O’G’LI | F20: 998996766010 узи, 998954330009 укаси, 998919446010 уй, | G20: JIZZAX VILOYATI SHAROF RASHIDOV TUMANI PAXTOBOD QFY YAXTANLIK MAHALLASI | H20: 10 | I20: 793050.32 | J20: 793050.32 | K20: To'ladi
A21: ЖИЗЗАХ ВИЛОЯТИ | C21: Дозвон | D21: Кр-99045797-2 | E21: QARSHIBAYEV RUSLAN QAXRAMON O’G’LI | F21: +998900251515 SMS, 998902978487 SMS, 998992408778 SMS, | G21: JIZZAX VILOYATI SH.RASHIDOV TUMANI TOSHKENTLIK MFY QATORTOL KUCHASI 7-UY | H21: 10 | I21: 386582.6 | J21: 386582.6 | K21: To'ladi
A22: ЖИЗЗАХ ВИЛОЯТИ | C22: Дозвон | D22: Кр-99016886-4 | E22: NORBOYEV UTKIR XUDOYBOKOVICH | F22: 903111781 SMS UZI new, 992851781 SMS AYOLI Begona, 991760374 SMS AKASI, 955557476 SMS AKASI, | G22: JIZZAX VILOYATI ZOMIN TUMANI G'ALLAKOR QFY BAYMOQLI QISHLOG'I YANGI HAYOT KUCHASI 36-UY | H22: 1 | I22: 270598.44 | J22: 270598.44 | K22: To'ladi
A23: ЖИЗЗАХ ВИЛОЯТИ | C23: Дозвон | D23: Кр-99034148-3 | E23: SAYFUTDINOVA GAVXAR SHUXRATOVNA | F23: 998903111016 SMS OZI, 998976480208 SMS ERI TOLOVCHI, 998912093311 SMS HAMKASBI, 998712267815 SMS UY, | G23: JIZZAX VILOYATI SH.RASHIDOV TUMANI ZIYOKOR QFY M.ESHONQULOV KUCHASI 125-UY | H23: 10 | I23: 193989.59 | J23: 193989.59 | K23: To'ladi
A24: ЖИЗЗАХ ВИЛОЯТИ | C24: Объезд | D24: Кр-99034201-1 | E24: OCHILOV TO’LQIN ABDUALIMOVICH | F24: 998902294031 SMS OZI, 998915676560 SMS AYOLI, 998912080702 SMS KELINI, 998915960702 SMS SINGLI, | G24: JIZZAX VILOYATI JIZZAX TUMANI QULAMA QFY A.NAVOIY KUCHASI 27-UY | I24: 6266.97 | J24: 6266.97 | K24: Uyiga borildi - to'ladi
A25: КАШКАДАРЁ ВИЛОЯТИ | C25: Дозвон | D25: Кр-99041095-1 | E25: DJABBAROV NA’MAT MUSTAFAYEVICH | F25: +998973142870 OZI, 998952339919 UYI, 998973129919 O’G’LI TO'LOVCHI, | G25: КАШКАДАРЁ ВИЛОЯТИ КАРШИ ТУМАНИ УЗУМЗОР МФЙ, ЛАГМОН ҚИШЛОҒИ, uy:77 | H25: 10 | I25: 2502672.1 | J25: 2502672.1 | K25: To'ladi
A26: КАШКАДАРЁ ВИЛОЯТИ | C26: Дозвон | D26: Кр-99035132-1 | E26: OCHILOV OYBEK ISROIL O’G’LI | F26: 998995008899 SMS O’ZI , 998507575193 SMS UKASI , 998500011995 SMS OILASI , 998507575293 SMS UKASI 2, 998972230068 SMS DADASI, | G26: QASHQADARYO VILOYATI KOSON TUMANI USHOKTEPA MFY USHOKTEPA KUCHASI 21 UY | H26: 8 | I26: 2196036.8 | J26: 2196036.8 | K26: To'ladi
A27: КАШКАДАРЁ ВИЛОЯТИ | C27: Дозвон | D27: Кр-99037164-1 | E27: IMOMOV FAYZULLA PARDAYEVICH | F27: 998919553110 SMS OZI, 998807931102 SMS OZI 2, 998906672203 SMS OILASI, 998889883110 SMS O’G’LI, | G27: QASHQADARYO VILOYATI YAKKABOG’ TUMANI SEROB MFY MINJIR QISHLOQI | H27: 13 | I27: 2187130.4 | J27: 2187130.4 | K27: To'ladi
A28: КАШКАДАРЁ ВИЛОЯТИ | C28: Объезд | D28: Кр-99037085-2 | E28: XAMRAYEVA GULNORA XURRAMOVNA | F28: 998979549700 SMS OZI (OG'LI) XUSAN, 998881941597 SMS O’G’LI, 998884287278 SMS UKASI (UZI), 998886757572 SMS AKASI, | G28: QASHQADARYO VILOYATI QARSHI TUMANI MEVAZOR MFY NAVRUZ QURG’ONI SHAHARCHASI 67/1 UY | H28: 10 | I28: 1951671.2 | J28: 1951671.2 | K28: Uyiga borildi - to'ladi
A29: КАШКАДАРЁ ВИЛОЯТИ | C29: Объезд | D29: Кр-99038805-1 | E29: ESHQULOV ABROR AZAMATOVICH | F29: 998976776676 SMS O’ZI, 998990647161 SMS AYOLI, 998972560232 SMS AKASI , 998947061030 SMS ONASI, | G29: QARSHI TUMANI | H29: 6 | I29: 1414554.5 | J29: 1414554.5 | K29: Uyiga borildi - to'ladi
A30: КАШКАДАРЁ ВИЛОЯТИ | C30: Объезд | D30: Кр-99035313-4 | E30: OMONOV RO’YIDDIN ADASH O’G’LI | F30: 998906167214 SMS OILASI, 998913830559 SMS AKASI UZIII TO'LOVCHI, 998993830559 SMS OILASI, 998914682525 SMS UKASI (POCHCHASI), | G30: QASHQADARYO VILOYATI QARSHI TUMANI TINCHLIK MFY PARMITON QISHLOG’I 13-UY | H30: 10 | I30: 1341477.2 | J30: 1341477.2 | K30: Uyiga borildi - to'ladi
A31: КАШКАДАРЁ ВИЛОЯТИ | C31: Объезд | D31: Кр-99035313-2 | E31: OMONOV RO’YIDDIN ADASH O’G’LI | F31: 998906167214 SMS OILASI, 998913830559 SMS AKASI UZIII TO'LOVCHI, 998993830559 SMS OILASI, 998914682525 SMS UKASI (POCHCHASI), | G31: QASHQADARYO VILOYATI QARSHI TUMANI TINCHLIK MFY PARMITON QISHLOG’I 13-UY | H31: 3 | I31: 999946.2 | J31: 999946.2 | K31: Uyiga borildi - to'ladi
A32: КАШКАДАРЁ ВИЛОЯТИ | C32: Объезд | D32: Кр-99038004-1 | E32: RAXMONOVA NILUFAR RAXMIDDIN QIZI | F32: 998889543030 SMS OZI, 998882070694 SMS OILASI, 998979537171 SMS AKASI, 998991689400 SMS AKASI, 998974380089 SMS TO'LOVCHI, | G32: КАШКАДАРЁ ВИЛОЯТИ КОСОН ТУМАНИ Эсабой МФЙ Эсабой кучаси 31-уй | H32: 10 | I32: 779178.8 | J32: 779178.8 | K32: Uyiga borildi - to'ladi
A33: КАШКАДАРЁ ВИЛОЯТИ | C33: Объезд | D33: Кр-99040703-2 | E33: SHOMURODOV BEKMUROD SHERQULOVICH | F33: +998934213611 sms uzi , 998333993611 sms ogli, 998773004642 sms ayoli , 998996862082 sms uzi2, | G33: КАЗОКЛИ МФЙ, КАЗОКЛИ, uy:Р/С | I33: 466210.86 | J33: 466210.86 | K33: Uyiga borildi - to'ladi
A34: КАШКАДАРЁ ВИЛОЯТИ | C34: Дозвон | D34: Кр-99057087-1 | E34: XAYITOV ZIKIR SHERKULOVICH | F34: 998992669600 SMS OZI, 998934260277 SMS AYOLI, 998932305610 SMS UKASI, 998944826069 OG'LI TULOVCHI SHU, | G34: QASHQADARYO VILOYATI KOSON TUMANI MULALI MFY KORABAYIR KUCHASI 11-UY | H34: 10 | I34: 133373.48 | J34: 133373.48 | K34: To'ladi
A35: КАШКАДАРЁ ВИЛОЯТИ | C35: Дозвон | D35: Кр-99036035-1 | E35: NIZOMIDDINOV DOSTON RUSTAM O’G’LI | F35: 998939041565 SMS O’ZI, 998904280599 SMS OSHNASI, 998934227104 SMS DADASI, 998934211708 SMS UKASI , | G35: QASHQADARYO VILOYATI QARSHI SHAHRI MAGZON MFY GULBOG’KUCHASI 24-UY | H35: 1 | I35: 17251.88 | J35: 17251.88 | K35: To'ladi
A36: КОРАКАЛПОГИСТОН РЕСПУБЛИКАСИ | C36: Объезд | D36: Кр-99063402-1 | E36: JAMGIRBAYEV SHOXZOD XALMURAT ULI | F36: 998906527006 OZI, 998913931005 AKASI, 998951773003 AKASI 2, | G36: QARAQALPOGISTON RES NUKUS SHAHAR NAUBAXAR MFY ELI AZAT KUSHASI 15 UY | H36: 10 | I36: 1767587.4 | J36: 1767587.4 | K36: Uyiga borildi - to'ladi | 1552
A37: КОРАКАЛПОГИСТОН РЕСПУБЛИКАСИ | C37: Дозвон | D37: Кр-99064050-1 | E37: ESHIMBETOV QUDAYBERGEN AYAPBERGENOVICH | F37: 998877084162 OGLI, 998994004162 OZI, 998997484162 OYALI, | G37: QORAQLPOGISTON RES NUKUS SHAHAR Kutli-konis MFY, Uvaysiy ko’chasi, 18-uy | H37: 10 | I37: 1657657.3 | J37: 1657657.3 | K37: To'ladi | KECHA GAPLASHGANDIM BUGUN TO'LAVORIBDILA | 1636
A38: КОРАКАЛПОГИСТОН РЕСПУБЛИКАСИ | C38: Дозвон | D38: Кр-99041071-1 | E38: SABZADAYEV ALLIYAR SMAILOVICH | F38: 998933614898 SMS OZI, 998956580267 SMS AYOLI, 998994521515 SMS UGLI, | G38: NUKUS SHAHAR | H38: 13 | I38: 1313001.4 | J38: 500000 | K38: To'ladi | KECHAA QISMAN TO'LOV QILDI BUGUN 500MING ANORDAN TO'LADI | 956
A39: КОРАКАЛПОГИСТОН РЕСПУБЛИКАСИ | C39: Дозвон | D39: Кр-99039490-1 | E39: SAFARBAYEV SUROJ ROZUMBAYEVICH | F39: 998970834467 SMS OZI, 998770929111 SMS AYOLI, 998335387575 SMS DOSTI, 998919911936 SMS OZI 2, 998991193691 SMS OZI NEWW, 998935673747 SMS TO'LOVCHI , | G39: QORAQALPOG’ISTON RESPUBLIKASI AMUDARYO TUMANI QIZILCHOLI MFY,YOSHLAR HIYOBONI 31-UY,32-XONADON | H39: 8 | I39: 613572.75 | J39: 613572.75 | K39: To'ladi | TO'LADI | 798
A40: НАВОИЙ ВИЛОЯТИ | C40: Дозвон | D40: Кр-99041260-1 | E40: ERMAMATOV MAMADIYAR ALIKULOVICH | F40: 998940674371 SMS OZI, 998930829871 SMS ONASI, 998883690021 SMS KELINI, 998934611115 SMS QIZI, | G40: NAVOIY VILOYATI ,KONIMEX TUMANI,GULISTON MFY,QUNG'IROT KO'CHASI 38 UY | H40: 10 | I40: 3049333.3 | J40: 3049333.3 | K40: To'ladi
A41: НАВОИЙ ВИЛОЯТИ | C41: Дозвон | D41: Кр-99029541-2 | E41: ISMOILOV FARRUH ZARIF O’G’LI | F41: 90-000-88-04 SMS OZI, 77-085-01-41 SMS XONADONI, 99-548-09-10 SMS HAMKASBI, | G41: NAVOIY VILOYATI KARMANA TUMANI MIR-SAID BAHROM MFY BOBO-DEHQON KO’CHASI 13-UY | H41: 10 | I41: 2346956 | J41: 2346956 | K41: To'ladi
A42: НАВОИЙ ВИЛОЯТИ | C42: Дозвон | D42: Кр-99036084-1 | E42: GOFUROV ZOIR MUXAMADOVICH | F42: 998913300303 SMS O’ZI , 998945220003 SMS O’G’LI, | G42: NAVOIY VILOYATI QIZILTEPA TUMANI BASHIR MFY MUG’JIN QFY 117-UY | H42: 2 | I42: 2270857.5 | J42: 2270857.5 | K42: To'ladi
A43: НАВОИЙ ВИЛОЯТИ | C43: Дозвон | D43: Кр-99029982-2 | E43: IBROGIMOV BOBIR ISROILOVICH | F43: 97-322-80-02 SMS UZI EKONOM ZONADA ISHLIDI , 88-053-30-57 SMS O’G’LI, 97-797-05-79 SMS XOTINI, 97-323-21-13 SMS UKASI, 998931757725 SMS UGLI GMZ DA ISHLIDI , 998970857101 SMS O'ZI, 998888027725 SMS o'g'li javohir 1ci bub wunga tel qlinsin, | G43: O’RIKZOR KO’CHASI, 10 UY | H43: 10 | I43: 2192870.1 | J43: 2192870.1 | K43: To'ladi
A44: НАВОИЙ ВИЛОЯТИ | C44: Дозвон | D44: Кр-99037388-2 | E44: RASULOVA MADINA ABDURASHIT QIZI | F44: 998937549991 SMS OZI, 998943478788 SMS ERI, 998906558555 SMS OPASI, 998943124440 SMS ONASI, 998937502343 ERI NEW, | G44: NAVOIY VILOYATI NUROTA TUMANI, G’AFUR G’ULOM MFY, XOLMUROD RAXIMOV KO’CHASI 12-UY | H44: 10 | I44: 1894973.9 | J44: 1894973.9 | K44: To'ladi
A45: НАВОИЙ ВИЛОЯТИ | C45: Дозвон | D45: Кр-99029541-3 | E45: ISMOILOV FARRUH ZARIF O’G’LI | F45: 90-000-88-04 SMS OZI, 77-085-01-41 SMS XONADONI, 99-548-09-10 SMS HAMKASBI, | G45: NAVOIY VILOYATI KARMANA TUMANI MIR-SAID BAHROM MFY BOBO-DEHQON KO’CHASI 13-UY | H45: 10 | I45: 1168529.5 | J45: 1168529.5 | K45: To'ladi
... A52: САМАРКАНД ВИЛОЯТИ | C52: Объезд | D52: Кр-99062811-2 | E52: SHOKIROV SAVRIDDIN SALOHIDDIN O’G’LI | F52: +998931430020 SMS OZI, 998505711620 SMS OPASI, 998937243255 SMS UKASI, | G52: SAMARQAND VILOYATI TAYLOQ TUMANI YANGI XAYOT MFY CHOVONDOZ KUCHASI | H52: 10 | I52: 2882928 | J52: 2882928 | K52: Uyiga borildi - to'ladi | yopildi
A53: САМАРКАНД ВИЛОЯТИ | C53: Дозвон | D53: Кр-99042245-1 | E53: NORMURADOV ELYOR RASULOVICH | F53: +998941882897 SMS OZI, 998904480702 SMS UKASI, 998931882987 SMS AYOLI, 998990693739 SMS UYI, | G53: SAMARQAND VILOYATI JONBOY TUMANI QANGLI MFY KURKAM DIYOR KUCHASI | I53: 2367581.7 | J53: 2367581.7 | K53: To'ladi | yopildi
A54: САМАРКАНД ВИЛОЯТИ | C54: Дозвон | D54: Кр-99036483-1 | E54: HASANOV XURSHID ABDURASHIDOVICH | F54: 998881911012 SMS OZI, 998995111012 SMS AYOLI, 998995711037 SMS ONASI , 998992767791 SMS UKASI , | G54: SAMARQAND VILOYATI ISHTIXON TUMANI QAYIRMA MFY TUYABOY OVUL QISHLOG`I 75-UY | H54: 14 | I54: 2321551.9 | J54: 2321551.9 | K54: To'ladi | yopildi
A55: САМАРКАНД ВИЛОЯТИ | C55: Дозвон | D55: Кр-99033491-1 | E55: XAYDAROV G’AYRATJON ABDUSAIDOVICH | F55: 998509986314 SMS O’ZI, 998932214141 SMS TO’LOVCHISI, 998946797965 SMS UKASI, 998399874554 SMS UY, 998773437901 oilasi, | G55: SAMARQAND VILOYATI NARPAY TUMANI KUK OTA MFY KUK OTA QISHLOG’I 119-UY | H55: 6 | I55: 2288572.9 | J55: 2288572.9 | K55: To'ladi | toladi jaxon akani kartasiga
A56: САМАРКАНД ВИЛОЯТИ | C56: Дозвон | D56: Кр-99063189-1 | E56: BURONOV BUNYOD KAMOLIDDIN O’G’LI | F56: 998941864114 OZI, 998944894114 AYOLI, 998937236606 UKASI, 998946815515 UYI, | G56: SAMARQAND VILOYATI NARPAY TUMANI TINCHLIK MFY PULKAN SHOIR KUCHASI 26-UY | H56: 10 | I56: 1079412.8 | J56: 1079412.8 | K56: To'ladi | yopildi
A57: САМАРКАНД ВИЛОЯТИ | C57: Объезд | D57: Кр-99008241-6 | E57: KOMILOV SHERZOD NAJIMOVICH | F57: 99-593-55-60 SMS, 94-002-49-62 SMS OGLI бегона, 93-295-08-33 SMS KUYOVI, 99-224-49-92 SMS KUYOVI, 998950205560 Yangi raqami Tolovchi, 932950833 SMS KUYOVI, 940024962 SMS OGLI бегона, 992244992 SMS KUYOVI, 995935560 SMS, | G57: SAMARQAND VILOYATI KATTAQO’RG’ON TUMANI MULLAKICHKINA | H57: 2 | I57: 921961.21 | J57: 921961.21 | K57: Uyiga borildi - to'ladi | yopildi
A58: САМАРКАНД ВИЛОЯТИ | C58: Объезд | D58: Кр-99034419-1 | E58: ABDULLAYEVA SOADAT ALLAMURADOVNA | F58: 998991332753 SMS O’ZI, 998942561450 SMS O’G’LI, 998992742115 SMS NABIRASI, | G58: SAMARQAND VILOYATI PAXTACHI TUMANI ZARAFSHON MFY ORZU KUCHASI 34-UY | I58: 777575.78 | J58: 777575.78 | K58: Uyiga borildi - to'ladi | yopildi
A59: САМАРКАНД ВИЛОЯТИ | C59: Дозвон | D59: Кр-99031289-3 | E59: GAFUROV SUXROB SATTTAROVICH | F59: 94-283-06-62 SMS O’ZI, 88-409-37-37 SMS O'G'LI wu tolovchi bich , 95-217-27-63 SMS AYOLI, 99-116-68-87 SMS UYI, | G59: SAMARQAND VILOYATI SAMARQAND SHAHAR ISTIKBOL MFY 39-UY | H59: 10 | I59: 508663.91 | J59: 508663.91 | K59: To'ladi | yopildi filial tolid bugu
A60: САМАРКАНД ВИЛОЯТИ | C60: Дозвон | D60: Кр-99028632-1 | E60: ELMURODOV SUNNATILLO BOBOKANOVICH | F60: 99-335-21-54 SMS UZI, 94-896-12-60 SMS ONASI, 93-431-70-29 SMS OTASI, 93-272-69-89 SMS AKASI, | G60: SAMARQAND VILOYATI PAXTACHI TUMANI QORATEPA MFY BOG’IRAVON KO’CHASI 83-UY | H60: 1 | I60: 14105.49 | J60: 14105.49 | K60: To'ladi | yopildi
A61: САМАРКАНД ВИЛОЯТИ | C61: Дозвон | D61: Кр-99038885-1 | E61: ILXOMOV SARDORBEK SOLEJONOVICH | F61: 998957772001 SMS O’ZI, 998994054504 SMS UKASI, 998700100130 SMS AKASI, 998997134102 SMS UYI, | G61: SAMARQAND VILOYATI SAMARQAND TUMAN | I61: 10158.54 | J61: 10158.54 | K61: To'ladi | yopildi
A62: СУРХОНДАРЁ ВИЛОЯТИ | C62: Дозвон | D62: Кр-99012050-5 | E62: CHARIYEV ABDUMUROD SAFAROVICH | F62: 99-959-11-12 SMS OZI, 90-267-67-12 SMS UY, 95-525-89-85 SMS ZALOGODATEL, 99-240-98-85 SMS ZALOGODATEL (NOMERI бегона), 95-525-89-83 SMS BEGONA, | G62: SURXONDARYO VILOYATI DENOV TUMANI NAVBAHOR MFY QUSHBULOQ KO’CHASI 34-UY | H62: 31 | I62: 4131036.1 | J62: 4131036.1 | K62: To'ladi | oylik tolovi yopild | 39
A63: СУРХОНДАРЁ ВИЛОЯТИ | C63: Дозвон | D63: Кр-99030725-1 | E63: XAMROYEV MAXSUDBEK BAXODIROVICH | F63: 97-535-78-88 SMS O’ZI BEGONA , 97-193-78-88 SMS UY, 88-848-22-99 SMS OILASI, 88-839-19-89 SMS JIYANI, | G63: SURXONDARYO VILOYATI DENOV TUMANI GAXANA M.F.Y KO’RKAM 33-UY | H63: 3 | I63: 2969871.4 | J63: 2969871.4 | K63: To'ladi | oylik tolovi yopild | 295
A64: СУРХОНДАРЁ ВИЛОЯТИ | C64: Объезд | D64: Кр-99035996-1 | E64: ALMARDONOV BOBOMUROD BOBORAXMATOVICH | F64: 998995444686 SMS OZI, 998883176868 SMS SHERIGI, 998978967555 SMS UY, 998975502586 SMS, | G64: SURXONDARYO VILOYATI DENOV TUMANI FAYZLI MFY BUYUK IPAKYULI KO'CHASI 1-UY | H64: 3 | I64: 2248695.2 | J64: 2248695.2 | K64: Uyiga borildi - to'ladi | toladi | 544
A65: СУРХОНДАРЁ ВИЛОЯТИ | C65: Объезд | D65: Кр-99038010-1 | E65: ABDURAXIMOVA MUNAVVAR XO’SHBOQ QIZI | F65: 998942004892 SMS OZI, 998958987789 SMS UYI , 998958110962 SMS SINGLISi, 998945300101 SMS UYI 2 , | G65: SURXONDARYO VILOYATI DENOV TUMANI ELOBOD MFY NURLISAODAT 19-UY | H65: 9 | I65: 1890410 | J65: 1890410 | K65: Uyiga borildi - to'ladi | oylik tolovi yopild | 671
A66: СУРХОНДАРЁ ВИЛОЯТИ | C66: Дозвон | D66: Кр-99038230-1 | E66: TO’XTAYEVA PARDAXOL BAHODIROVNA | F66: 998978488184 SMS OZI, 998950408184 SMS ERI, 998992198184 SMS UYI, 998950408184 SMS O’G’LI, | G66: SURXONDARYO VILOYATI DENOV TUMANI NAMUNA MFY YANGI XAYOT KO’CHASI 10-UY | H66: 2 | I66: 1532535.4 | J66: 1532535.4 | K66: To'ladi | oylik tolovi yopild | 698
A67: ТОШКЕНТ ШАХРИ | C67: Дозвон | D67: Кр-99038864-1 | E67: NIGMATULLAYEV BAXROM BAXODIR O’G’LI | F67: 998946885606 SMS OZI, 998886759119 SMS OZI2, 998900435343 SMS AYOLI, | G67: IIV26266 | H67: 2 | I67: 3129967.8 | J67: 3129967.8 | K67: To'ladi
A68: ТОШКЕНТ ШАХРИ | C68: Дозвон | D68: Кр-99063089-1 | E68: YUZBAYEV DILMUROD ALLAMURAD O’G’LI | F68: 998946736370 OZI, 998940206370 AYOLI, 998500573637 DOSTI, | G68: TOSHKENT SHAHAR YASHNOBOD TUMANI BOYQO’RG’ON KO’CHASI 11/3 UY,63-A XONADON | H68: 10 | I68: 2619777.1 | J68: 2619777.1 | K68: To'ladi | 3-4kunda yopadi
A69: ТОШКЕНТ ШАХРИ | C69: Дозвон | D69: Кр-99036425-1 | E69: XALMUXAMEDOV DILSHOD FURKATOVICH | F69: 998946982030 SMS OZI, 998935421667 SMS JIYANI, 998946242030 SMS AYOLI, 998946982030 SMS OZI, | G69: TOSHKENT SHAHAR YUNUSOBOD TUMANI ,14-MAVZE,8-UY,53-XONADON | H69: 23 | I69: 620807.53 | J69: 620807.53 | K69: To'ladi
A70: ФАРГОНА ВИЛОЯТИ | C70: Объезд | D70: Кр-99041275-1 | E70: JUMAMATOVA ZULXUMOR ISAKOVNA | F70: +998907788327 O’ZI, 998947215300 UY, 998982787707 ERI, 998987781111 O’G’LI TOLOVCHI, | G70: 13-СИМТЕПА (Х.ИБРАГИМОВА) МФЙ, ОБИХАЁТ (ШОКИРОВА) КЎЧАСИ, uy:32А | H70: 73 | I70: 10626970 | J70: 2964372 | K70: Uyiga borildi - to'ladi | 2964372.32
A71: ФАРГОНА ВИЛОЯТИ | C71: Дозвон | D71: Кр-99039434-1 | E71: ILYASOVA AZIZA RAVSHANBEKOVNA | F71: 998916776263 SMS OZI, 998911145898 SMS DADASI, 998901793077 SMS OPASI, 998913976968 SMS QIZI, | G71: FARG’ONA VILOYATI OLTIARIQ TUMANI SHODLIK MFY U YUSUPOV KO’CHASI 4-XONADON | H71: 9 | I71: 7190909.9 | J71: 3249066 | K71: To'ladi | 3249066.04
A72: ФАРГОНА ВИЛОЯТИ | C72: Дозвон | D72: Кр-99039349-1 | E72: MAMADJANOV AKMALJON AKRAMOVICH | F72: 998976675000 SMS OZI, 998931377454 SMS AYOLI, 998994417770 SMS OGLI, 998941766699 SMS QIZI begona , | G72: FARG’ONA VILOYATI RISHTON TUMANI MINOR MFY M.IBRAGIMOV KO’CHASI 8-XONADON | H72: 8 | I72: 6075344.6 | J72: 2995672 | K72: To'ladi | 2995672.25
A73: ФАРГОНА ВИЛОЯТИ | C73: Объезд | D73: Кр-99037178-1 | E73: NURULLAYEV XOKIMJON OBIDDINOVICH | F73: 998972141971 SMS OZI, 998888141973 SMS AYOLI, 998903020279 SMS OGLI ABDULXAFIZ O'G'LI, 998905371938 SMS KELINI, | G73: FARG’ONA VILOYATI FARG’ONA SHAHAR NAFOSAT MFY XAZINA QASHAKAR KO’CHASI 224-UY | H73: 13 | I73: 5182807.5 | J73: 2258677 | K73: Uyiga borildi - to'ladi | 2258677.98
... A85: ФАРГОНА ВИЛОЯТИ | C85: Дозвон | D85: Кр-99028625-1 | E85: NURMATOV DOSTONBEK DILSHOD O’G’LI | F85: 91-108-98-98 SMS OZI, 90-273-64-43 SMS UKASI, 90-273-64-43 SMS UKASI 2, 88-949-78-78 SMS AKASI, | G85: FARG’ONA VILOYATI RISHTON TUMANI OQ ER MFY NAVRUZ KO’CHASI 41-XONADON | H85: 1 | I85: 362078.83 | J85: 362078 | K85: To'ladi | 362078.83
A86: ХОРАЗМ ВИЛОЯТИ | B86: SUPER BRANCH | C86: Объезд | D86: Кр-99052981-1 | E86: MADRAXIMOVA ZEBINISO MADRIMOVNA | F86: 998791161524 SMS OZI, 998995969099 SMS UKASI, 998975271155 SMS OPASI, 998721152582 SMS OPASI, | G86: XORAZM VILOYATI YANGIARIQ TUMANI YANGI OBOD MFY YANGI OBOD KO’CHASI 40-UY | H86: 10 | I86: 5119065.5 | J86: 5119065.5 | K86: Uyiga borildi - to'ladi | yopaildi | 1221
A87: ХОРАЗМ ВИЛОЯТИ | B87: SUPER BRANCH | C87: Объезд | D87: Кр-99040505-1 | E87: EGAMOVA XOLISXON ALLABERGANOVNA | F87: 998934531982 SMS ERI, 998934268290 SMS OZI, 998997464344 SMS AKASI, 998991167127 SMS UKASI, | G87: XORAZM VILOYATI URGANCH SHAHAR MASHAL MFY XIVA 2-YULAK 3-UY | H87: 10 | I87: 5037207.6 | J87: 1900000 | K87: Uyiga borildi - to'ladi | 1,9 mln tolov qildi qolganini 20-sanagacha yopad | 903
A88: ХОРАЗМ ВИЛОЯТИ | B88: SUPER BRANCH | C88: Дозвон | D88: Кр-99062488-1 | E88: ABDULLAYEVA MUXADDAS URAZBAYEVNA | F88: 998919977070 SMS ERI, 998992147010 SMS OZI, 998957458000 SMS OGLI, 998886012424 SMS QIZI, | G88: XORAZM VILOYATI URGANCH SHAHRI SAXOVAT MFY FERUZ KUCHASI 82-UY | H88: 10 | I88: 3911626 | J88: 3911626 | K88: To'ladi | abetgacha tolid | 1400
A89: ХОРАЗМ ВИЛОЯТИ | B89: SUPER BRANCH | C89: Дозвон | D89: Кр-99026626-1 | E89: MATYAKUBOVA OLIYA SULTANOVNA | F89: 998974569970 SMS O'ZI, 998976078717 SMS DILSHODA HAMKASBI, 998505722508 SMS O'G'LI, 998999692091 SMS QIZI, | G89: XORAZM VILOYATI QO’SHKO’PIR TUMANI XAYROBOD QFY XAYROBOD MFY MADANIYAT KO’CHASI 48-UY | H89: 13 | I89: 2128873.3 | J89: 2128873.3 | K89: To'ladi | Abetdan kegin yopad | 159
A90: ХОРАЗМ ВИЛОЯТИ | B90: SUPER BRANCH | C90: Дозвон | D90: Кр-99048302-1 | E90: NURMATOV OG‘ABEK FAXRIDDIN O‘G‘LI | F90: +998919981626 Primary phone from road24, 998919981626 Primary phone from road24, 998905580815 SMS OTASI, 998910908909 SMS AKASI, | G90: Хорезмская область, Шаватский район, Каткалъа ССГ, Янги турмуш МСГ, ул. Бунёдкор, дом 33 | I90: 149474.25 | J90: 149474.25 | K90: To'ladi | yarim soat ichida yopad | 1147
A91: ХОРАЗМ ВИЛОЯТИ | B91: SUPER BRANCH | C91: Дозвон | D91: Кр-99012130-5 | E91: SHAXNAZAROV TEMIRBEK UMIDBEK O’G’LI | F91: 99-542-98-19 SMS O’ZI, 99-541-98-19 SMS OTASI, 93-752-68-98 SMS UKASI BOBUR, 99-157-47-40 SMS SINGLISI(BEGONA), 998993812882 SMS UZI NEW, | G91: XORAZM VILOYATI URGANCH TUMANI YUQORIBOG’ MFY OQ OLTIN KOCHASI 34-UY | H91: 15 | I91: 118020.11 | J91: 118020.11 | K91: To'ladi | bugun yopilad | 43
A92: ХОРАЗМ ВИЛОЯТИ | B92: Урганч филиали | C92: Дозвон | D92: Кр-99032651-1 | E92: OTAJONOV QUVANDIQ OTAJONOVICH | F92: 998939280990 SMS O’G’LI, 998888692895 SMS AYOLI, 998970241820 SMS UY, 998720260692 SMS UY 2, | G92: XONQA TUMANI MADANIY YER MFY ALPOMISH KUCHASI 22A UY | H92: 3 | I92: 4668102.9 | J92: 4668102.9 | K92: To'ladi | 18-20 bilan gaplashdim buugn yopad | 361
A93: ХОРАЗМ ВИЛОЯТИ | B93: Урганч филиали | C93: Дозвон | D93: Кр-99029634-2 | E93: TADJIBAYEV AXMEDJAN SABUROVICH | F93: 97-526-60-60 SMS OGLI, 99-668-33-31 SMS OZI, 97-518-77-71 SMS QO'SHNISI, 99-447-95-24 SMS KELINI, 998954973339 SMS Ozi new, | G93: XORAZM VILOYATI GURLAN TUMANI YANGI ASR MAXALLASI NUKUS KUCHASI 65-UY | H93: 1 | I93: 2206588.8 | J93: 2206588.8 | K93: To'ladi | buugn yopad ogli Rassiyadan pul tashid | 253
A94: ХОРАЗМ ВИЛОЯТИ | B94: Урганч филиали | C94: Дозвон | D94: Кр-99030792-3 | E94: XAYTBAYEVA DINORA MADIYOR QIZI | F94: 94-112-51-61 SMS ERI (begona), 95-046-90-95 SMS O’ZI, 88-755-79-81 SMS YANGASI, 95-215-79-25 SMS JIYANI, | G94: XORAZM VILOYATI GURLAN TUMANI VAZIR QFY OLCHIN MFY NURLI IZ KUCHASI 54-UY | H94: 1 | I94: 881526.03 | J94: 881526.03 | K94: To'ladi | yopildi | 299
A95: ХОРАЗМ ВИЛОЯТИ | B95: Урганч филиали | C95: Дозвон | D95: Кр-99012130-4 | E95: SHAXNAZAROV TEMIRBEK UMIDBEK O’G’LI | F95: 99-542-98-19 SMS O’ZI, 99-541-98-19 SMS OTASI, 93-752-68-98 SMS UKASI BOBUR, 99-157-47-40 SMS SINGLISI(BEGONA), 998993812882 SMS UZI NEW, | G95: XORAZM VILOYATI URGANCH TUMANI YUQORIBOG’ MFY OQ OLTIN KOCHASI 34-UY | H95: 10 | I95: 31458.28 | J95: 31458.28 | K95: To'ladi | bugun yopilad | 42
A96: ХОРАЗМ ВИЛОЯТИ | B96: Урганч филиали | C96: Дозвон | D96: Кр-99029595-1 | E96: OZODOV MUHIDDIN KAMOLIDDIN O’G’LI | F96: 94-113-10-31 SMS O'ZI, 94-725-82-84 SMS AKASI, 93-748-83-84 SMS KELINOYISI, | G96: XORAZM VILOYATI XONQA TUMANI BARKAMOLLIK MAXALLASI NODIRABEGIM KUCHASI 29 UY | H96: 2 | I96: 8142.81 | J96: 8142.81 | K96: To'ladi | Abetgacha yopad | 249

Sheet Не дозвонились
A1: ← Вернуться в отчёт
A2: Область | B2: Филиал | C2: Группа | D2: Код клиента | E2: Клиент | F2: Номер телефона | G2: Адрес | H2: Кол-во просроченных дней | I2: Итого просрочка | J2: Оплата | K2: Izoh
A3: АНДИЖОН ВИЛОЯТИ | C3: Недозвон | D3: Кр-99050899-1 | E3: ERGASHOV ELYORBEK NE’MATJONOVICH | F3: 998774544221 SMS OZI, 998902062924 SMS AYOLI, 998022181812 SMS OZI, 998902533553 SMS AKASI, | G3: ANDIJON VILOYATI BO’Z TUMANI GUZAR MFY, O’ZBEKISTON KO’CHASI 489-UY | H3: 104 | I3: 57529092 | K3: Telefon ko'tarmadi | muommoli klent | 28493150.684931505 | 29035941.11
A4: АНДИЖОН ВИЛОЯТИ | C4: Недозвон | D4: Кр-99059626-1 | E4: ABDURAXMONOVA MANZURAXON IBRAGIMDJONOVNA | F4: 998972041812 SMS OZI, 998910530105 SMS OGLI, 998502108587 SMS QIZI, 998883838387 SMS KELINI, | G4: ANDIJON VILOYATI ASAKA TUMANI CHEK MFY XAMDO’STLIK KO’CHASI 157-UY | H4: 43 | I4: 32783127 | K4: Telefon ko'tarmadi | umumiy summaga xatlov qilindi | 15315068.493150685 | 17468058.58
A5: АНДИЖОН ВИЛОЯТИ | C5: Объезд | D5: Кр-99038794-1 | E5: TOSHXO’JAYEV FAZLIDDIN ZOKIRJON O’G’LI | F5: 998903807010 SMS OZI, 998916197010 SMS AYOLI, 998954779770 SMS ONASI ОГАЙНИСИНИ НОМЕРИ , 998505114440 SMS AKASI бегона , | G5: ANDIJON VILOYATI ANDIJON SHAXAR ISLOMOBOD MFY, MIRPO’STIN KO’CHASI 40 B-UY 31-XONADON | H5: 59 | I5: 21106705 | K5: Uyiga borildi - va'da berdi | 16164383.561643835 | 4942321.34
A6: АНДИЖОН ВИЛОЯТИ | C6: Объезд | D6: Кр-99057085-1 | E6: YULDASHEVA NILUFAR KAMILOVNA | F6: 998872557757 SMS OZI, 998982700122 SMS OGLI, 998772581112 SMS QIZI, 998882331807 SMS JIYANI, | G6: ANDIJON VILOYATI ANDIJON TUMANI ZANGIBOBO MFY PORLOQ KO’CHASI 306-UY | H6: 13 | I6: 15030583 | J6: 5342465 | K6: Uyiga borildi - to'ladi | 5342465.7534246575 | 9688117.5
A7: АНДИЖОН ВИЛОЯТИ | C7: Объезд | D7: Кр-99063020-2 | E7: XALIMOV ILXOMJON DJALILOVICH | F7: 998979950022 OZI, 998941030105 ONASI, 998945616463 JIYANI, 998993478909 KELINI, | G7: ANDIJON VILOYATI ASAKA TUMANI BOBUR MFY KARVONSAROY KO’CHASI 135 UY | H7: 13 | I7: 11945563 | K7: Uyiga borildi - va'da berdi | 4273972.602739726 | 7671589.99
A8: АНДИЖОН ВИЛОЯТИ | C8: Недозвон | D8: Кр-99058489-1 | E8: UZOQOVA IRODA IBROYIMJONOVNA | F8: 998976388885 SMS OZI, 998882215555 SMS XOJAYINI, 998366944492 SMS OZI 2, | G8: ANDIJON VILOYATI ANDIJON TUMANI CHEM MFY ZARQAYNAR KO’CHASI 18-UY | H8: 13 | I8: 11060321 | K8: Telefon ko'tarmadi | oyni oxirigacha hal qiladi | 4273972.602739726 | 6786348.3
A9: АНДИЖОН ВИЛОЯТИ | C9: Объезд | D9: Кр-99061813-1 | E9: AXMEDOVA LOLAXON XASANOVNA | F9: 998939680860 узи, 998948093111 угли, 998772093139 угли, 998990300805 угли, | G9: ANDIJON VILOYATI IZBOSKAN TUMANI CHEKYO MFY ABU ALI IBN SINO KO’CHASI 27-UY | H9: 10 | I9: 8193435.2 | K9: Uyiga borildi - va'da berdi | 2465753.4246575343 | 5727681.79
A10: АНДИЖОН ВИЛОЯТИ | C10: Объезд | D10: Кр-99063311-2 | E10: MAHKAMOVA MAVLUDA QORATOYEVNA | F10: +998907574245 SMS O’ZI, 998931041313 SMS JIYANI, 998937834245 SMS O’ZI2, 998949998375 SMS OPASI, | G10: ANDIJON VILOYATI IZBOSKAN TUMANI YUQORI MFY DAMBA KO’CHASI 10-UY | H10: 10 | I10: 7235757.5 | K10: Uyiga borildi - va'da berdi | 2191780.821917808 | 5043976.65
A11: АНДИЖОН ВИЛОЯТИ | C11: Недозвон | D11: Кр-99049616-1 | E11: DAVIDOV MAMIRJON NEMATJONOVICH | F11: 998883672747 OZI, | G11: IIV3411 | H11: 10 | I11: 7109688.2 | K11: Telefon ko'tarmadi | tg ham yoq mahallaga chiqdim | 1561643.8356164382 | 5548044.31
A12: АНДИЖОН ВИЛОЯТИ | C12: Недозвон | D12: Кр-99041941-1 | E12: DAMINOV UMIDJON OMADJON O’G’LI | F12: +998942579577 SMS O’ZI, 998700811712 SMS DADASI, 998934125332 SMS ONASI, 998979407999 SMS AKASI, | G12: Сой МФЙ, Оби хаёт кучаси, 30-уй | H12: 10 | I12: 6397727.2 | K12: Telefon ko'tarmadi | tg dan aloqaga chiqdim | 1917808.219178082 | 4479919.03
A13: АНДИЖОН ВИЛОЯТИ | C13: Недозвон | D13: Кр-99040471-1 | E13: ABDULLAYEVA FERUZAXON RAPIKOVNA | F13: 998958551476 SMS OZI, | G13: ANDIJON VILOYATI XO’JAOBOD TUMANI KO’PRIKBOSHI MFY, KO’CHAK KO’CHASI 64-UY | H13: 10 | I13: 6362503.7 | K13: Telefon ko'tarmadi | tg ham chiqmadi mahallaga chiqdim | 1917808.219178082 | 4444695.52
A14: АНДИЖОН ВИЛОЯТИ | C14: Недозвон | D14: Кр-99025777-1 | E14: KALIKBAYEV BEGZAD KUTTIBEKOVICH | F14: 998901728454 SMS OZI, 998907632123 SMS AYOLI, 998901738454 SMS OGLI, | G14: Ҳамкорлик МФЙ, Ўш кучаси, 212 д-уй, 28-хонадон | H14: 10 | I14: 5673337.3 | K14: Telefon ko'tarmadi | tg dan yozdim | 2191780.821917808 | 3481556.46
A15: АНДИЖОН ВИЛОЯТИ | C15: Недозвон | D15: Кр-99004638-1 | E15: KIMSANOV ALIMARDON DILSHOD O’G’LI | F15: 998943870087 SMS OZI, 998992729515 SMS AYOLI Begona, 998947830087 SMS UY, 998772874929 SMS ONASI, | G15: ANDIJON VILOYATI PAXTAOBOD TUMANI UYG’UR QFY ZIYOLI MFY BOXOR KO’CHASI 53-UY | H15: 10 | I15: 5456850.1 | K15: Telefon ko'tarmadi | ishlaydigan nomeri yoq Sanjar akani bilan gaplashdim rusda ekan ozi tg sini berdi | 1643835.6164383562 | 3813014.49
A16: АНДИЖОН ВИЛОЯТИ | C16: Объезд | D16: Кр-99029207-1 | E16: SOBIROVA SADOQATOY RAXIMJON QIZI | F16: 94-542-12-54 SMS TOLOVCHI, 93-849-22-52 SMS TOLOVCHI XOJAYINI tanmiman ddi , 94-282-31-32 TOLOVCHI ukasi , 95-022-11-55 TOLOVCHIS OGLI, | G16: ANDIJON VILOYATI PAXTAOBOD TUMANI AXILLIK MFY AXILLIK KO’CHASI 4-UY | H16: 10 | I16: 5333808.6 | K16: Uyiga borildi - va'da berdi | 1917808.219178082 | 3416000.38
A17: АНДИЖОН ВИЛОЯТИ | C17: Недозвон | D17: Кр-99031869-1 | E17: YULCHIYEVA MOHLAROYIM G’ULOMJON QIZI | F17: 998992413100 SMS O’ZI shu nomerda , 998940710693 SMS Akasi hal qladi, 998332063030 SMS AKASI 2, 998939176131 SMS ozi, 998334070099 SMS kelnoysi , +998940240402 SMS O’ZI, 998336625864 SMS ELINOYISI, 998700350061 SMS KELINOYISI, | G17: ANDIJON VILOYATI SHAXRIXON TUMANI CHO’JA MFY CHO’JA KO’CHASI 71-UY | H17: 3 | I17: 4481804.1 | K17: Telefon ko'tarmadi | tolovchi akasi akasi bn boglanib bolmadi tg dan yozdim | 616438.3561643836 | 3865365.78
A18: АНДИЖОН ВИЛОЯТИ | C18: Недозвон | D18: Кр-99035320-1 | E18: O’RINOVA MAMLAKATXON SOBIRJONOVNA | F18: 998944000211 SMS OZI, 998944260191 SMS AYOLI, 998959914040 SMS UKASI, 998993020471 SMS SHERIGI, | G18: ANDIJON VILOYATI BALIQCHI TUMANI MUQANNA MFY, MUQANNA KO’CHASI 22-UY | H18: 2 | I18: 4465888.6 | K18: Telefon ko'tarmadi | tg dan yozdim | 438356.16438356164 | 4027532.4
... A22: АНДИЖОН ВИЛОЯТИ | C22: Объезд | D22: Кр-99041539-1 | E22: SHERALIYEV SARDORBEK SODIQJON O’G’LI | F22: 998914845776 SMS OZI, 998996325251 SMS AYOLI, 998992425251 SMS ONASI, +998914845776 Primary phone from road24, 998948642717 SMS O’ZI2, | G22: Андижон вилояти Андижон шахар Бунёдкор (9-сон) МФЙ, Қўш ариқ дахаси, 46-уй, 15-хонадон | H22: 10 | I22: 2922859.2 | K22: Uyiga borildi - va'da berdi | 547945.205479452 | 2374914
A23: АНДИЖОН ВИЛОЯТИ | C23: Объезд | D23: Кр-99037425-1 | E23: SHUKUROV QUVONCHBEK XABIBILLAYEVICH | F23: 998905271070 SMS OZI, 998901707424 SMS OGLI, 998914865970 SMS AYOLI, 998953475970 SMS QIZI, | G23: ANDIJON VILOYATI ANDIJON TUMANI YUKSALISH MFY YUKSALISH KO’CHASI 19-UY | H23: 2 | I23: 2889861.2 | J23: 273972 | K23: Uyiga borildi - to'ladi | 273972.602739726 | 2615888.63
A24: АНДИЖОН ВИЛОЯТИ | C24: Объезд | D24: Кр-99044378-2 | E24: SHOKIROV NURULLO AXMADULLAYEVICH | F24: +998914912216 SMS O’ZI, 998770387887 SMS QIZI tel qilinmasin, 998779630238 SMS AYOLI , 998931144480 SMS O’G’LI, | G24: АНДИЖОН ВИЛОЯТИ АНДИЖОН ШАХРИ МАДАНИЯТ МФЙ, Т.КЕЛДИЕВ, uy:102 | H24: 10 | I24: 2714002.7 | K24: Uyiga borildi - va'da berdi | 821917.8082191781 | 1892084.88
A25: АНДИЖОН ВИЛОЯТИ | C25: Объезд | D25: Кр-99063106-1 | E25: SOTVOLDIYEVA MAXMUDAXON QOSIMOVNA | F25: 998770492346 OZI, 998931092588 OGLI, 998937212671 OPASI, 998942592770 DUGONASI, | G25: ANDIJON VILOYATI QO’RG’ONTEPA TUMANI UCHQUN MFY ISTIQBOL KO’CHASI 16 UY | H25: 10 | I25: 2695142.3 | J25: 821917 | K25: Uyiga borildi - to'ladi | 821917.8082191781 | 1873224.48
A26: АНДИЖОН ВИЛОЯТИ | C26: Объезд | D26: Кр-99063748-2 | E26: XURBOYEV MURODILJON MURODJON O’G’LI | F26: +998931757095 SMS O’ZI, 998505454475 SMS DADASI, 998938701978 SMS ONASI, 998971622313 SMS SINGLISI, | G26: ANDIJON VILOYATI IZBOSKAN TUMANI A. JOMIY MFY TASHABBUS MARKAZI KO’CHASI 15-UY | H26: 13 | I26: 2457473.8 | K26: Uyiga borildi - va'da berdi | 890410.9589041095 | 1567062.79
A27: АНДИЖОН ВИЛОЯТИ | C27: Недозвон | D27: Кр-99049616-2 | E27: DAVIDOV MAMIRJON NEMATJONOVICH | F27: 998883672747 OZI, | G27: IIV3411 | I27: 1896080.3 | K27: Telefon ko'tarmadi | tg ham yoq mahallaga chiqdim | 0 | 1896080.33
A28: АНДИЖОН ВИЛОЯТИ | C28: Недозвон | D28: Кр-99031869-3 | E28: YULCHIYEVA MOHLAROYIM G’ULOMJON QIZI | F28: 998992413100 SMS O’ZI shu nomerda , 998940710693 SMS Akasi hal qladi, 998332063030 SMS AKASI 2, 998939176131 SMS ozi, 998334070099 SMS kelnoysi , +998940240402 SMS O’ZI, 998336625864 SMS ELINOYISI, 998700350061 SMS KELINOYISI, | G28: ANDIJON VILOYATI SHAXRIXON TUMANI CHO’JA MFY CHO’JA KO’CHASI 71-UY | H28: 10 | I28: 1629813 | K28: Telefon ko'tarmadi | tolovchi akasi akasi bn boglanib bolmadi tg dan yozdim | 767123.2876712328 | 862689.75
A29: АНДИЖОН ВИЛОЯТИ | C29: Объезд | D29: Кр-99044378-1 | E29: SHOKIROV NURULLO AXMADULLAYEVICH | F29: +998914912216 SMS O’ZI, 998770387887 SMS QIZI tel qilinmasin, 998779630238 SMS AYOLI , 998931144480 SMS O’G’LI, | G29: АНДИЖОН ВИЛОЯТИ АНДИЖОН ШАХРИ МАДАНИЯТ МФЙ, Т.КЕЛДИЕВ, uy:102 | I29: 1400789.4 | K29: Uyiga borildi - va'da berdi | 0 | 1400789.42
A30: АНДИЖОН ВИЛОЯТИ | C30: Объезд | D30: Кр-99041539-2 | E30: SHERALIYEV SARDORBEK SODIQJON O’G’LI | F30: 998914845776 SMS OZI, 998996325251 SMS AYOLI, 998992425251 SMS ONASI, +998914845776 Primary phone from road24, 998948642717 SMS O’ZI2, | G30: Андижон вилояти Андижон шахар Бунёдкор (9-сон) МФЙ, Қўш ариқ дахаси, 46-уй, 15-хонадон | H30: 10 | I30: 931523.62 | K30: Uyiga borildi - va'da berdi | 178082.19178082192 | 753441.43
A31: БУХОРО ВИЛОЯТИ | C31: Недозвон | D31: Кр-99040851-1 | E31: ZARIPOV NODIRBEK NAZIRJON O’G’LI | F31: 998938132602 SMS O’ZI, 998887531291 SMS OPASI, 998992523242 AMAKISI, 998787770222 SMS ISHXONASI, | G31: QORAKO’L TUMANI | H31: 196 | I31: 46319207
A32: БУХОРО ВИЛОЯТИ | C32: Недозвон | D32: Кр-99039543-1 | E32: DJUMAYEV ZAVQIY LATIPOVICH | F32: 998901180010 SMS OZI , 998770240926 SMS UKASI, +998901180010 Primary phone from road24, 998950000118 SMS asilbek o'g'li, | G32: Богча МФЙ, Гараншоҳ қишлоғи, 52-C-уй | H32: 128 | I32: 45153274
A33: БУХОРО ВИЛОЯТИ | C33: Недозвон | D33: Кр-99040567-1 | E33: ACHILOV BOBIR BURONOVICH | F33: 998505155499 SMS ONASI, 998931385554 SMS OGLI, 998936205499 SMS OZI, | G33: BUXORO VILOYATI, BUXORO SHAHAR, MUHAMMAD NARSHAXIY MFY, TOJI KARAYEV KO'CHASI, 86-UY | H33: 164 | I33: 27072033
A34: БУХОРО ВИЛОЯТИ | C34: Недозвон | D34: Кр-99048166-1 | E34: KURBANOV DILMUROD TUYMURADOVICH | F34: +998936859009 SMS O’ZI, 998505100034 SMS QIZI, 998931361133 SMS O’G’LI, 998956001133 SMS AYOLI, | G34: BUXORO VILOYATI, BUXORO SHAHAR, IBN SINO MFY, BAHOUDDIN NAQSH BAND KO’CHASI,197-UY, 91-XONADON | H34: 10 | I34: 2512617.5
A35: БУХОРО ВИЛОЯТИ | C35: Недозвон | D35: Кр-99041320-3 | E35: SHODIYEV ULUG’BEK SALIMOVICH | F35: +998914431901 sms o’zi, 998907119935 sms onasi, 998912408206 sms ayoli, 998914471901 sms o’zi 2, | G35: Бухарская область, Гиждуванский район, Соктари МСГ, Соктари, дом 239 | H35: 10 | I35: 2086853
A36: БУХОРО ВИЛОЯТИ | C36: Недозвон | D36: Кр-99047434-2 | E36: UMRZOQOV FAXRIDDIN AXMEDJONOVICH | F36: 998959754272 O`ZI, 998941220757 AYOLI, 998945457562 DO`STI, 998959754272 uzi, 998941220757 ayoli, 998945457562 dosti, | G36: Бухоро шахар коракул тумани Мустакиллик 50 уй | H36: 10 | I36: 1823550.5
A37: БУХОРО ВИЛОЯТИ | C37: Недозвон | D37: Кр-99039770-1 | E37: SAFAROV SANJAR ADIZ O’G’LI | F37: 998912403939 SMS OZI TO'LOVCHI SHUNGA TEL QILINSIN, 998935133314 SMS AMAKISI, 998918225456 SMS OTASI, 998942432520 SMS ONASI, | G37: BUXORO VILOYATI BUXORO TUMANI GULSHANOBOD MFY LEYLAK QISHLOG'I 51-UY | H37: 10 | I37: 1751579.6
A38: БУХОРО ВИЛОЯТИ | C38: Недозвон | D38: Кр-99041716-1 | E38: ODINAYEV ASLON AZIMOVICH | F38: +998872504057 SMS O’ZI, 998905122625 SMS DO’STI, 998912479697 SMS O’G’LI, 998978588778 SMS O’G’LI 2, 998882802662 yangi nomer o'zi, | G38: Убачули МФЙ, Мевазор кучаси, 96-уй | H38: 10 | I38: 1731791.3
A39: БУХОРО ВИЛОЯТИ | C39: Недозвон | D39: Кр-99063280-1 | E39: QURBONOV XUSHVAQT G’ULOMOVICH | F39: +998914177518 SMS O’ZI, 998990454555 SMS AYOLI, 998993454441 SMS DO’STI, | G39: OLOT TUMANI | H39: 10 | I39: 1539082.2
A40: БУХОРО ВИЛОЯТИ | C40: Недозвон | D40: Кр-99040456-1 | E40: TEMIROV NODIRBEK G’OLIBJON OG’LI | F40: 998902981307 SMS OZI, 998995556077 SMS AMAKISI, 998918381398 SMS OTASI, 998906110811 SMS ONASI, | G40: BUXORO VILOYATI G'IJDUVON TUMANI ZARANGARI MFY, BO'LAKIYON QISHLOG'I 36-UY | H40: 10 | I40: 1444589.2
A41: БУХОРО ВИЛОЯТИ | C41: Недозвон | D41: Кр-99049211-1 | E41: ADIZOV AZAMAT SHOYIMOVICH | F41: 998940642993 SMS JIYANI, 998942218131 SMS O’ZI, 998978055824 SMS UKASI, 998999767786 SMS AYOLI, | G41: GULISTON, DOM 56 | H41: 10 | I41: 724068.93
A42: БУХОРО ВИЛОЯТИ | C42: Недозвон | D42: Кр-99044175-1 | E42: MURODOV MUROD UMAR O’G’LI | F42: +998995624067 SMS O’ZI, 998914450878 SMS DO’STI, 998918384026 SMS ONASI, 998948893111 SMS DO’STI, | G42: Паноб МФЙ, Янги ҳаёт қишлоғи, 138-уй | I42: 359713.31
A43: БУХОРО ВИЛОЯТИ | C43: Недозвон | D43: Кр-99039770-2 | E43: SAFAROV SANJAR ADIZ O’G’LI | F43: 998912403939 SMS OZI TO'LOVCHI SHUNGA TEL QILINSIN, 998935133314 SMS AMAKISI, 998918225456 SMS OTASI, 998942432520 SMS ONASI, | G43: BUXORO VILOYATI BUXORO TUMANI GULSHANOBOD MFY LEYLAK QISHLOG'I 51-UY | H43: 10 | I43: 58404.13
A44: БУХОРО ВИЛОЯТИ | B44: SUPER BRANCH | C44: Недозвон | D44: Кр-99036711-1 | E44: ERGASHOV ALISHER NARZULLAYEVICH | F44: 998934784464 SMS O’ZI, 998939569626 SMS OTASI, 998931571911 SMS ONASI, 998930052290 SMS SINGLISI , | G44: BUXORO VILOYATI, QORAKO'L TUMANI, ISTIQLOL MFY, YANGI QISHLOQ KO'CHASI, 15-UY | H44: 0 | I44: 5020948.3 | K44: Telefon ko'tarmadi | 17 | 5020948.32
A45: БУХОРО ВИЛОЯТИ | B45: SUPER BRANCH | C45: Недозвон | D45: Кр-99028153-4 | E45: GOIPOV EL’BRUS RAXMADOVICH | F45: 94-120-61-31 SMS OZI, 94-219-60-83 SMS AYOLI, 94-782-03-28 OGLI (бегана), 94-382-28-11 SMS QIZI, | G45: BUXORO VILOYATI OLOT TUMANI XIDREYLI MFY 141-UY | H45: 7 | I45: 4981347.2 | K45: Telefon ko'tarmadi | 6 | 6076799.22479452
A46: БУХОРО ВИЛОЯТИ | B46: SUPER BRANCH | C46: Недозвон | D46: Кр-99033022-1 | E46: ASKAROV SHOHBOZ ULUG’BEKOVICH | F46: 998944219181 SMS OIZ, 998796441812 SMS OZI 2, 998931971731 SMS AYOLI, | G46: TOSHKENT SHAHAR, YANGIHAYOT TUMANI, YANGI DARXON MFY, NAVRO'Z KOCHASI 16-UY | H46: 7 | I46: 3163951.3 | K46: Telefon ko'tarmadi | 12 | 4075301.6135342466
A47: БУХОРО ВИЛОЯТИ | B47: SUPER BRANCH | C47: Недозвон | D47: Кр-99038162-1 | E47: DJAMOLOV BOBIR BAHRIDDINOVICH | F47: 998914174488 SMS OZI, 998914182244 SMS OZI, 998934225600 SMS O’G’LI Бехруз шу номерга қилинсин, 998930807508 SMS O’G’LI, | G47: BUXORO VILOYATI, VOBKENT TUMANI, ROZMOZ MFY, ELACH KO'CHASI, 4-UY | H47: 0 | I47: 2825554.5 | K47: Telefon ko'tarmadi | 20 | 2825554.48
A48: БУХОРО ВИЛОЯТИ | B48: SUPER BRANCH | C48: Объезд | D48: Кр-99019690-5 | E48: HAYDAROV FURQAT RAXMATILLOYEVICH | F48: 97-488-07-66 SMS O'ZI, 88-301-90-93 SMS AKASI, 97-296-06-93 SMS UY, 93-841-53-50 SMS AYOLI, 998505999203 SMS O'ZI2, | G48: BUXORO VILOYAT BUXORO SHAHRI BESHKAPPA KO'CHASI 106 UY | H48: 7 | I48: 2199808.5 | J48: 2484160 | K48: Uyiga borildi - to'ladi | 2 | 2484160.2179178083
A49: БУХОРО ВИЛОЯТИ | B49: SUPER BRANCH | C49: Недозвон | D49: Кр-99038109-1 | E49: QO’YLIYEV SARDOR SATTOR O’G’LI | F49: 998885546677 SMS OZI, 998954741616 SMS AKASI, 998990748047 SMS OPASI, 998883041232 SMS UYI, | G49: BUXORO VILOYATI KOGON TUMANI, NIYOZ HOJI MFY, VADAN QISHLOG'I 88-UY | H49: 0 | I49: 1763754.3 | K49: Telefon ko'tarmadi | 19 | 1763754.28
A50: БУХОРО ВИЛОЯТИ | B50: SUPER BRANCH | C50: Объезд | D50: Кр-99019690-6 | E50: HAYDAROV FURQAT RAXMATILLOYEVICH | F50: 97-488-07-66 SMS O'ZI, 88-301-90-93 SMS AKASI, 97-296-06-93 SMS UY, 93-841-53-50 SMS AYOLI, 998505999203 SMS O'ZI2, | G50: BUXORO VILOYAT BUXORO SHAHRI BESHKAPPA KO'CHASI 106 UY | H50: 7 | I50: 1144641.8 | J50: 1277949 | K50: Uyiga borildi - to'ladi | 3 | 1277949.4817260276
A51: БУХОРО ВИЛОЯТИ | B51: Бухоро филиали | C51: Недозвон | D51: Кр-99031012-1 | E51: FARMONOVA GULCHEHRA MUSLIDDINOVNA | F51: 33-524-05-05 SMS O'ZI, 91-240-39-39 SMS ERI, 90-635-09-93 SMS ONASI, 50-884-90-24 SMS AKASI, 998914483333 SMS ELDOR , | G51: BUXORO VILOYATI G'IJDUVON TUMANI HAVZAK MFY, QATAG'AN KO'CHASI, 36-UY | H51: 14 | I51: 20000000 | K51: Telefon ko'tarmadi | 7 | 22753613.007123288
A52: БУХОРО ВИЛОЯТИ | B52: Бухоро филиали | C52: Недозвон | D52: Кр-99034426-1 | E52: AZIZOV ILXOM BAXTIYAROVICH | F52: 998905146560 SMS OZI, 998907121044 SMS AYOLI, 998938741010 SMS OTASI, 998936421010 SMS ONASI, 998936421010 толовчичи шодиёр, | G52: BUXORO VILOYATI BUXORO SHAHAR TOJIQARAYEV MFY 61-UY | H52: 0 | I52: 4716159 | K52: Telefon ko'tarmadi | 14 | 4716159.04
A53: БУХОРО ВИЛОЯТИ | B53: Бухоро филиали | C53: Недозвон | D53: Кр-99033611-1 | E53: ELMURODOVA ZEBINISO ODILOVNA | F53: 998939904907 SMS O’ZI, 998939983008 SMS ERI, 998943754907 SMS OTASI, 998931374907 SMS O’G’LI, 998501888730 SMS ERI 2, 998501204758 to'lovchi, | G53: BUXORO VILOYATI SHOFIRKON TUMANI PATTAXON MFY, YANGIOBOD q-q, 18-UY | H53: 0 | I53: 2701930.7 | K53: Telefon ko'tarmadi | 13 | 2701930.7
A54: БУХОРО ВИЛОЯТИ | B54: Бухоро филиали | C54: Недозвон | D54: Кр-99031584-1 | E54: NOROVA IRODA NE’MATOVNA | F54: 90-809-45-45 SMS O'ZI, 93-372-19-81 SMS QIZI MAFTUNA, 50-758-04-06 SMS QIZI MAHSUDA tanimidi, 91-016-68-42 SMS ONASI, 950378185 opchasi, 998774080081 узи , | G54: BUXORO VILOYATI QORAKO’L TUMANI TASHABBUS MFY ADXAM / YUNUSOBOD TUMANI 2-MAVZE 31-UY 45-XONADON | H54: 7 | I54: 1661100.2 | K54: Telefon ko'tarmadi | 8 | 1902638.9762191782
A55: БУХОРО ВИЛОЯТИ | B55: Бухоро филиали | C55: Недозвон | D55: Кр-99062864-1 | E55: MAXMUDOV ALIAKBAR SAIDJONOVICH | F55: +998900650514 SMS, 998507103377 SMS UY, 998905128669 SMS AYOLI, | G55: BUXORO VILOYATI BUXORO SHAHAR AVSHORMAHALLA MFY 77-UY | H55: 7 | I55: 1525915.6 | K55: Telefon ko'tarmadi | 36 | 1850059.660630137
A56: БУХОРО ВИЛОЯТИ | B56: Бухоро филиали | C56: Объезд | D56: Кр-99032591-1 | E56: BOZOROV DILSHOD OLIM O’G’LI | F56: 998995853782 SMS O’G’LI, 998940186667 SMS AYOLI(BEGONA), 998938997077 SMS ONASI, 998930831515 SMS HAMKASBI бегона , | G56: BUXORO VILOYATI ROMITAN TUMANI O'TABEK MFY, PITMON q-q, 6-uy | H56: 0 | I56: 1298935.7 | K56: Uyiga borildi - va'da berdi | 9 | 1298935.71
A57: БУХОРО ВИЛОЯТИ | B57: Навоий филиали | C57: Недозвон | D57: Кр-99063975-1 | E57: QUZIYEV MAQSUD HIKMATULLOYEVICH | F57: 998912463904 SINGLISI, 998933147491 AYOLI, 998996229992 O’ZI, | G57: SDFC | H57: 7 | I57: 2067102.9 | K57: Telefon ko'tarmadi | 40 | 3026001.612958904
A58: ЖИЗЗАХ ВИЛОЯТИ | C58: Недозвон | D58: Кр-99046652-1 | E58: GENJEBAYEV MAKSETBAY REYMBAYEVICH | F58: +998919447218 SMS OZI , 998955395000 SMS HOTINI begona, 998972680202 SMS AKASI BEGONA, | G58: JIZZAX VILOYATI PAXTAKOR TUMANI DILOROM MFY NAVRUZ KUCHASI 1/15-UY | H58: 73 | I58: 27141691 | K58: Telefon ko'tarmadi
A59: ЖИЗЗАХ ВИЛОЯТИ | C59: Недозвон | D59: Кр-99025474-1 | E59: ABDULLAYEV ABDULAZIZ ABDUVAIT O’G’LI | F59: 97-789-92-05 SMS UZI , 88-517-95-05 SMS AYOLI , 97-608-08-98 SMS DUSTI , | G59: JIZZAX VILOYATI G’ALLAOROL TUMANI | H59: 20 | I59: 9294410.3 | K59: Telefon ko'tarmadi
A60: ЖИЗЗАХ ВИЛОЯТИ | C60: Недозвон | D60: Кр-99063460-1 | E60: AXMEDOV ALISHER KAMALOVICH | F60: 998991041481 AYOLI, 998993573881 UKASI, | G60: ШИРИН ҚФЙ, ШИРИН ҚФЙ, ҚУДУҚЧА ҚИШЛОҒИ, uy:Р.С | H60: 10 | I60: 8621519 | K60: Telefon ko'tarmadi
A61: ЖИЗЗАХ ВИЛОЯТИ | C61: Объезд | D61: Кр-99038833-1 | E61: XOSILBEKOV SHUXRAT SAFAROVICH | F61: 998941957573 SMS O’ZI, 998935570175 SMS AYOLI, 998945160190 SMS UKASI, 998947277308 SMS SINGLISI, | G61: ZOMIN TUMANI | H61: 1 | I61: 7710284 | J61: 7710284 | K61: Uyiga borildi - to'ladi
A62: ЖИЗЗАХ ВИЛОЯТИ | C62: Объезд | D62: Кр-99036552-1 | E62: ALBEKOVA MUXABAT SAYLIYEVNA | F62: 998906437402 SMS TULOVCHI, 998884374488 SMS KUYOVI TOLOVCHI, 998905163139 SMS QIZI, 998915650972 SMS UZI, | G62: JIZZAX VILOYATI JIZZAX SHAHRI XAMID OLIMJON MFY QANGLI KUCHASI 18-UY | H62: 8 | I62: 7549466.1 | K62: Uyiga borildi - va'da berdi | yorqin tema
A63: ЖИЗЗАХ ВИЛОЯТИ | C63: Объезд | D63: Кр-99063392-1 | E63: BERDIYAROV TO’RAMUROD XUDOYKULOVICH | F63: 998501568064 UZI, 998939931883 AYOLI, 998943438583 ONAS, | G63: БОГИШАМОЛ КФЙ, БОГИШАМОЛ КФЙ, МУГОЛ КИШЛОГИ, uy:РАКАМСИЗ | H63: 10 | I63: 6308129.3 | K63: Uyiga borildi - va'da berdi
A64: ЖИЗЗАХ ВИЛОЯТИ | C64: Недозвон | D64: Кр-99035257-1 | E64: ERGASHEV FARHOD RUSTAM O’G’LI | F64: 998902867999 SMS O’ZI, 998983002221 SMS BEGONA, 998988800454 SMS AKASI2, 998973261762 SMS Ayasi, 998995772760 sms dadasi begona , | G64: JIZZAX VILOYATI BAXMAL TUMANI USMAT SHAXARCHASI DO’STLIK MFY DO’STLIK KUCHASI 20-UY | H64: 3 | I64: 6261356.1 | K64: Telefon ko'tarmadi
A65: ЖИЗЗАХ ВИЛОЯТИ | C65: Недозвон | D65: Кр-99025603-3 | E65: AXMEDOVA MAXFUZA NIZOMIDDIN QIZI | F65: 94-340-56-52 SMS ERI TULOVCHI, 94-194-74-14 SMS ONASI, 94-572-25-30 SMS URTOGI, | G65: JIZZAX VILOYATI DO’STLIK TUMANI CHARAG’ON MANAS QFY 13-1 | H65: 122 | I65: 6223600.6 | K65: Telefon ko'tarmadi | yorqin tema
A66: ЖИЗЗАХ ВИЛОЯТИ | C66: Недозвон | D66: Кр-99040190-1 | E66: XODJIMURATOV MAMARAXIM USKANOVICH | F66: 998994798433 SMS OZI, 998992780316 SMS OZI NEW, 998773162199 SMS SINGLISI, 998990301519 SMS QIZI , 998773479799 SMS TO’LOVCHI, | G66: JIZZAX VILOYATI ZOMIN TUMANI NIHOL MFY YANGI OVUL QISHLOG’I 70-UY | H66: 10 | I66: 6063681.2 | K66: Telefon ko'tarmadi
A67: ЖИЗЗАХ ВИЛОЯТИ | C67: Объезд | D67: Кр-99030311-1 | E67: SHERANOV SHERZOD ZULFAROVICH | F67: 94-922-86-60 SMS O'ZI, 91-943-85-05 SMS O’ZI 2, 94-922-86-60 SMS UY, 93-304-52-56 SMS OTASI, | G67: JIZZAX VILOYATI ZARBDOR TUMANI DO’STLIK SHAXARCHASI SHODLIK MFY ISTIQBOL KUCHASI 43-UY | H67: 164 | I67: 5460425.9 | K67: Uyiga borildi - va'da berdi | yorqin tema
A68: ЖИЗЗАХ ВИЛОЯТИ | C68: Объезд | D68: Кр-99021925-1 | E68: ISMOILOVA NARGIZA ABDUSALIYEVNA | F68: 998938567000 SMS O’ZI, 998501040408 SMS ERI, 998943437777 SMS ERI , 998905160057 SMS ERINI UKASI, 998931070408 tolovchi eri , 998971299092 sms tulovchi, 998508043200 FARUX TULOVCHISI, | G68: JIZZAX VILOYATI SHAROF RASHIDOV TUMANI QANG'LI QFY ARISHLI MAHALLASI ZIYOKOR KUCHASI 4-UY | H68: 3 | I68: 5112052.5 | K68: Uyiga borildi - va'da berdi
A69: ЖИЗЗАХ ВИЛОЯТИ | C69: Объезд | D69: Кр-99042640-1 | E69: XO’JAQULOV FURQAT JAYNAROVICH | F69: +998771070575 SMS, 998932920870 SMS, 998990343029 SMS, | G69: JIZZAX VILOYATI ZAFAROBOD TUMANI BIRLIK QFY RUDAKIY KUCHASI 4-A UY | H69: 10 | I69: 4645444 | K69: Uyiga borildi - va'da berdi
A70: ЖИЗЗАХ ВИЛОЯТИ | C70: Недозвон | D70: Кр-99063358-1 | E70: TURAKULOVA DILRABO KARIMOVNA | F70: 998888926464 UY, 998918951189 UZI, 998985611189 ERI, | G70: JIZZAX VILOYATI JIZZAX SHAHRI OBOD MFY MINORLI KUCHASI 126B-UY | H70: 10 | I70: 4224639.5 | K70: Telefon ko'tarmadi
A71: ЖИЗЗАХ ВИЛОЯТИ | C71: Объезд | D71: Кр-99063375-1 | E71: AG’LAMOV AZIMXON AKRAM O’G’LI | F71: 998881511212 AKASI, 998915981212 AKASI, 998970105070 UZI, | G71: УЧАРИК МФЙ, ХАМЗАОБОД, ФИРДАВСИЙ, uy:9 | H71: 10 | I71: 3915897.3 | K71: Uyiga borildi - va'da berdi
A72: ЖИЗЗАХ ВИЛОЯТИ | C72: Недозвон | D72: Кр-99031840-1 | E72: UKTAMOV KOMILJON G’ULOMJON O’G’LI | F72: 998947060276 SMS O’ZI, 998996837171 SMS Uzi, 998883472121 SMS AKASI, 998941621146 SMS ONASI, | G72: JIZZAX VILOYATI SH.RASHIDOV TUMANI BUSTON MFY YOSHLIK KUCHASI 3-UY | H72: 3 | I72: 3851979.2 | K72: Telefon ko'tarmadi | tel qiliw kerak
A73: ЖИЗЗАХ ВИЛОЯТИ | C73: Недозвон | D73: Кр-99003082-6 | E73: TO’XTAYEV RASHID RAXMONQULOVICH | F73: 998881535010 SMS O’ZI, 998912352020 SMS BEGONA, 998979809700 SMS UKASI, 998915964295 SMS ozi shunga qilinsin , | G73: JIZZAX VILOYATI SHAROF RASHIDOV TUMANI ZIYOKOR MFY ZIYOKOR KO'CHASI 96-UY | H73: 3 | I73: 3507616 | K73: Telefon ko'tarmadi
... A79: ЖИЗЗАХ ВИЛОЯТИ | C79: Объезд | D79: Кр-99039896-1 | E79: UMMATOV JAVLON MAVLONOVICH | F79: 998959172024 SMS OZI, 998957701676 SMS UKASI, 998957741676 SMS SINGLIASI, 998911956219 SMS DADASI, 998995247977 sms uzi mew, 998995247977 sms uzi new, | G79: JIZZAX VILOYATI SH.RASHIDOV TUMANI UCH TEPA MFY GUNCHA KUCHASI 97-UY | H79: 10 | I79: 2824533.3 | K79: Uyiga borildi - va'da berdi
A80: ЖИЗЗАХ ВИЛОЯТИ | C80: Объезд | D80: Кр-99041710-1 | E80: MAMARAJABOVA ZULOYXA ABDUMALIK QIZI | F80: 998339269697 SMS, 998931049616 SMS, | G80: JIZZAX VILOYATI BAXMAL TUMANI TONGOTAR MFY QUSHTEPA QISHLOGI 65-UY | H80: 10 | I80: 2497483.1 | J80: 2497483.1 | K80: Uyiga borildi - to'ladi | qisman tolov qildi
A81: ЖИЗЗАХ ВИЛОЯТИ | C81: Недозвон | D81: Кр-99011601-5 | E81: JO’RAQULOV JAVLONJON QAHRAMON O’G’LI | F81: 88-126-00-25 SMS UZI, 97-482-53-53 SMS AYOLI, 88-437-53-53 SMS OTASI, 97-127-53-53 SMS AYOLI, 998776406865 SMS Ukasi tolovchi, | G81: JIZZAX VILOYATI JIZZAX TUMANI OLMACHI MAHALLASI OLMACHI KUCHASI 9/9 UY | H81: 10 | I81: 2129082.4
A82: ЖИЗЗАХ ВИЛОЯТИ | C82: Объезд | D82: Кр-99060382-1 | E82: XONIMKULOV XURSHID UMARKUL O’G’LI | F82: 998991027333 узи, 998915900150 аели, 998911968898 шериги, | G82: JIZZAX VILOYATI JIZZAX TUMANI BUNYODKOR MFY LOLAZOR KUCHASI 1A-UY | H82: 13 | I82: 1908130.3 | K82: Uyiga borildi - va'da berdi
A83: ЖИЗЗАХ ВИЛОЯТИ | C83: Недозвон | D83: Кр-99038736-1 | E83: ARZIKULOV SOBIRJON BAXTIYOR O’G’LI | F83: 998940337077 SMS OZI, 998332952405 SMS DADASI, 998904951880 SMS ONASI, 998772679767 SMS UKASI, | G83: JIZZAX VILOYATI JIZZAX SHAHAR NAVRUZ MFY UZBEKISTAN KUCHASI 38-UY | H83: 9 | I83: 1752175 | K83: Telefon ko'tarmadi
A84: ЖИЗЗАХ ВИЛОЯТИ | C84: Недозвон | D84: Кр-99063112-1 | E84: USANOVA FOTIMA ABDURASHIDOVNA | F84: +998915026065 SMS OZI, 998700113077 KATTA O’G’LI, 998881459555 O’RTANCHA O’G’LI, | G84: BAXMAL TUMANI | I84: 1648406.6 | K84: Telefon ko'tarmadi
A85: ЖИЗЗАХ ВИЛОЯТИ | C85: Объезд | D85: Кр-99026372-3 | E85: ARIPOV FAXRIDDIN JO’MANOVICH | F85: 94-138-50-20 SMS UZI , 91-209-90-77 SMS UZI, 94-001-51-35 SMS UY, 91-028-70-28 SMS AYOLI, | G85: JIZZAX VILOYATI MARJONBULOQ SHMB LALMIKOR MFY NAVRO’Z MAHALLASI 60-UY | H85: 10 | I85: 1508602.4 | J85: 1508602.4 | K85: Uyiga borildi - to'ladi
A86: ЖИЗЗАХ ВИЛОЯТИ | C86: Недозвон | D86: Кр-99052917-1 | E86: ABDUALIMOV OZODJON ABDURAXIM O’G’LI | F86: 998911972123 SMS OZI, 998915681200 SMS AYOLI, 999156813002 SMS OZI 2, | G86: JIZZAX VILOYATI JIZZAX SHAHRI OQQURG'ONLIK MAHALLASI YU SALIMOV KUCHASI 70-UY | H86: 10 | I86: 1478019.6 | K86: Telefon ko'tarmadi
A87: ЖИЗЗАХ ВИЛОЯТИ | C87: Недозвон | D87: Кр-99018090-4 | E87: JONIQULOV YOLQIN BAXODIR O’G’LI | F87: 97-326-55-99- SMS UZI , 33-326-55-99 SMS UZI 2, 99-447-40-40 SMS AKASI, 93-290-03-30 SMS AKASI2, | G87: JIZZAX VILOYATI DASHTOBOD SHAHARCHASI XAMZA MAHALLASI | H87: 1 | I87: 1376220.8 | K87: Telefon ko'tarmadi
A88: ЖИЗЗАХ ВИЛОЯТИ | C88: Объезд | D88: Кр-99030311-2 | E88: SHERANOV SHERZOD ZULFAROVICH | F88: 94-922-86-60 SMS O'ZI, 91-943-85-05 SMS O’ZI 2, 94-922-86-60 SMS UY, 93-304-52-56 SMS OTASI, | G88: JIZZAX VILOYATI ZARBDOR TUMANI DO’STLIK SHAXARCHASI SHODLIK MFY ISTIQBOL KUCHASI 43-UY | H88: 15 | I88: 1356589.8 | K88: Uyiga borildi - va'da berdi | yorqin tema
A89: ЖИЗЗАХ ВИЛОЯТИ | C89: Недозвон | D89: Кр-99041781-2 | E89: NORYIGITOV SAMANDAR O’TKIR O’G’LI | F89: +998997654666 SMS, 998973271427 SMS, 998990654666 SMS, | G89: JIZZAX VILOYATI YANGIOBOD TUMANI BALANDCHAQIR MFY MUSTAQILLIK SHOX KUCHASI 159-UY | H89: 10 | I89: 1343049.2 | K89: Telefon ko'tarmadi
A90: ЖИЗЗАХ ВИЛОЯТИ | C90: Объезд | D90: Кр-99018232-3 | E90: ELIMBAYEVA MAVLYUDA KOLDASHOVNA | F90: 97-647-48-78 SMS ERI, 97-522-05-30 SMS O'G'LI, 97-800-12-81 SMS QIZI, 93-553-18-82 SMS UKASI, | G90: JIZZAX VILOYATI ZAFAROBOD TUMANI YORQIN MAHALLASI CHEVARLAR KUCHASI 15-UY | H90: 2 | I90: 1296595.8 | K90: Uyiga borildi - va'da berdi
A91: ЖИЗЗАХ ВИЛОЯТИ | C91: Недозвон | D91: Кр-99063395-2 | E91: SOXIBOV DILSHOD YUSUPALIYEVICH | F91: 998501038581 SMS QIZI, 998882488581 SMS AYOLI, 998990661191 SMS OZI, | G91: DEXQONOBOD 2 UY 7 XONADON | H91: 10 | I91: 1119914.1 | K91: Telefon ko'tarmadi
A92: ЖИЗЗАХ ВИЛОЯТИ | C92: Недозвон | D92: Кр-99048922-1 | E92: XOLMURODOV SHERBEK MARDON O‘G‘LI | F92: +998770010109 SMS OZI, 998944841200 SMS UYI, 998973311213 SMS OPASI, 998976410109 SMS OZI 2, 998770010109 Primary phone from road24, | G92: БАХМАЛ КФЙ, БАХМАЛ КФЙ, ЛОЙИХАДАГИ, uy:Р.С | H92: 3 | I92: 1020888 | K92: Telefon ko'tarmadi | tel qiliw kerak
A93: ЖИЗЗАХ ВИЛОЯТИ | C93: Недозвон | D93: Кр-99063038-1 | E93: SALIMOV MANSUR AZIMOVICH | F93: 998771120702 AYOLI, 998904927979 UY, | G93: ТОКЧИЛИҚ МАХАЛЛАСИ, ЛОЙИХАДАГИ КЎЧА, uy:Р.С | H93: 10 | I93: 817862.12 | K93: Telefon ko'tarmadi
A94: ЖИЗЗАХ ВИЛОЯТИ | C94: Недозвон | D94: Кр-99044129-3 | E94: ANORBOYEV RABBIM QURBONOVICH | F94: +998911993133 SMS, 998915963134 SMS, 998918038686 SMS, | G94: JIZZAX VILOYATI JIZZAX SHAHRI ITTIFOQ MFY ITTIFOQ KUCHASI 36/30 - UY | H94: 13 | I94: 258025.14 | K94: Telefon ko'tarmadi | tel qiliw kerak
A95: ЖИЗЗАХ ВИЛОЯТИ | C95: Недозвон | D95: Кр-99044722-1 | E95: BERDIYEVA GULNORA KENJAYEVNA | F95: +998931257179 SMS, 998932347179 SMS, 998946894222 SMS Nomer xato, | G95: JIZZAX VILOYATI ARNASOY TUMANI G’OFUR G’ULOM MFY G’OFUR G’ULOM KUCHASI 15/1-UY | H95: 10 | I95: 202730.52 | K95: Telefon ko'tarmadi | mahallaga qiliw kerak
A96: ЖИЗЗАХ ВИЛОЯТИ | C96: Недозвон | D96: Кр-99040853-1 | E96: USMANOV AZIZBEK MIRZABEK O’G’LI | F96: +998885222554 SMS OZI, 998880940530 SMS AYOLI, 998936250078 SMS tulovchi, | G96: Шодлик МФЙ, Кудук қишлоғи, 17/А-уй | H96: 10 | I96: 180746.17 | K96: Telefon ko'tarmadi
A97: ЖИЗЗАХ ВИЛОЯТИ | C97: Объезд | D97: Кр-99034201-1 | E97: OCHILOV TO’LQIN ABDUALIMOVICH | F97: 998902294031 SMS OZI, 998915676560 SMS AYOLI, 998912080702 SMS KELINI, 998915960702 SMS SINGLI, | G97: JIZZAX VILOYATI JIZZAX TUMANI QULAMA QFY A.NAVOIY KUCHASI 27-UY | I97: 6266.97 | J97: 6266.97 | K97: Uyiga borildi - to'ladi
A98: КАШКАДАРЁ ВИЛОЯТИ | C98: Недозвон | D98: Кр-99040472-1 | E98: SHAXAROVA SHAXRIZODA FARXOD QIZI | F98: 998886727122 SMS OZI BEGONA, 998970809786 SMS AKASI, 998995850151 SMS OZI , 998945228482 SMS ZALOGADATEL , 998912120151 SMS NEW UZI , | G98: ЧУМИЧЛИ МФЙ, ЧУМИЧЛИ КИШЛОГИ, uy:Р/С | H98: 183 | I98: 42537374
A99: КАШКАДАРЁ ВИЛОЯТИ | C99: Объезд | D99: Кр-99063133-1 | E99: TO’XTAYEV BOBUR ALISHER O’G’LI | F99: 998908992275 SMS OZI, 998993458899 SMS TO'LOVCHI, 998906097727 SMS OTASI, 998919611171 SMS AKASI, | G99: QASHQADARYO VILOYATI QARSHI TUMANI BOG’OBOD MFY TUQMANG’IT QISHLOG’I 260-UY | H99: 43 | I99: 22609689 | K99: Uyiga borildi - va'da berdi
A100: КАШКАДАРЁ ВИЛОЯТИ | C100: Объезд | D100: Кр-99060317-1 | E100: NAFASOV ASADBEK VALIJON O’G’LI | F100: 998973852277 SMS OZI, 998886191100 SMS AYOLI, 998770994440 SMS DADASI, 998886195000 SMS ONASI, | G100: QASHQADARYO VILOYATI YAKKABOG’ TUMANI ISTIQLOL MFY OLAQARG’A QISHLOG’I | H100: 13 | I100: 11614788 | K100: Uyiga borildi - va'da berdi | qisnab to'lov qildi
A101: КАШКАДАРЁ ВИЛОЯТИ | C101: Недозвон | D101: Кр-99062893-1 | E101: MUXAMMADIYEVA ZARIFA LUTFULLAYEVNA | F101: 998900705555 OZI, 998936965555 UKASI, 998973115555 AKASI TO'LOVCHI , 998772352727 ONASI BEGONA , | G101: QASHQADARYO VILOYATI QARSHI SHAHRI MUSTAQILLIK MFY ISLOM KARIMOV KUCHASI 218A-UY 1-XONADON | H101: 43 | I101: 10488757
A102: КАШКАДАРЁ ВИЛОЯТИ | C102: Недозвон | D102: Кр-99040100-1 | E102: KUDRATOV SANJAR DJURAYEVICH | F102: 998880634212 SMS OZI, 998970700407 SMS OILASI (BEGONA), 998972000300 SMS UKASI, 998996750200 SMS AKASI, 998972000300 uzi, | G102: QASHQADARYO VILOYATI QARSHI TUMANI TINCHLIK MFY, PARMITON QISHLOG’I 33-UY | H102: 13 | I102: 10116647
A103: КАШКАДАРЁ ВИЛОЯТИ | C103: Недозвон | D103: Кр-99063705-1 | E103: ABADOV DOSTON RUSTAM O’G’LI | F103: +998701208881 SMS O'ZI, 998702198484 SMS , 998918127626 SMS, | G103: КАШКАДАРЁ ВИЛОЯТИ КАРШИ ТУМАНИ УЗУМЗОР МФЙ ЛАГАНДИ КИШЛОГИ 2/18 УЙ | H103: 10 | I103: 9375831.7
A104: КАШКАДАРЁ ВИЛОЯТИ | C104: Недозвон | D104: Кр-99062042-1 | E104: ESHQOBILOV O’LMAS LATIFOVICH | F104: 998970981213 SMS OZI, 998947014020 SMS AYOLI, 998886641702 SMS DADASI, 998772001213 SMS ONASI, | G104: QASHQADATRYO VILOYATI KITOB TUMANI BOG’BON MFY YANGI QISHLOG’I KUCHASI 197-UY | H104: 13 | I104: 7616262
A105: КАШКАДАРЁ ВИЛОЯТИ | C105: Недозвон | D105: Кр-99039828-1 | E105: BEGIMOV OBIDJON O’DILOVICH | F105: 998946151222 SMS OZI, 998887592404 SMS TOLOVCHI, 998959612802 SMS DADASI, 998977552404 SMS ONASI, | G105: QASHQADARYO VILOYATI QARSHI TUMANI KAT MFY CHORGUMBAZ QISHLOG’I YOSHLAR KUCHASI 19-UY | H105: 10 | I105: 6990704.7
A106: КАШКАДАРЁ ВИЛОЯТИ | C106: Недозвон | D106: Кр-99062658-1 | E106: AVAZOV SHOXRUX ASADULLOYEVICH | F106: 998918871711 OZI QAYNI UKASI, 998945240302 ONASI, 998507181711 UKASI, 998942911001 O'ZI TO'LOVCHI, | G106: QASHQADARYO VILOYATI KASBI TUMANI XO’JAKASBI MFY 3-G’ALLAKORLAR KO’CHASI 2-UY | H106: 10 | I106: 5862590.5
A107: КАШКАДАРЁ ВИЛОЯТИ | C107: Недозвон | D107: Кр-99040420-1 | E107: ESHBO’RIYEV BOYMIRZA FARMON O’G’LI | F107: 998972221232 SMS OZI, 998990218033 SMS AKASI UZIIII, 998972966323 SMS OSHNASI, | G107: QASHQADARYO VILOYATI QARSHI TUMANI MUSTAQILLIK MFY KAMOLOT KO’CHASI 34-UY | H107: 10 | I107: 5124415.5
A108: КАШКАДАРЁ ВИЛОЯТИ | C108: Недозвон | D108: Кр-99039701-1 | E108: AXMADOV RAXMATJON ISKANDAR O’G’LI | F108: 999886758088 SMS OZI, 998973140057 SMS AKASI, 998973160057 SMS AKASI 2, 998886788088 SMS UZI NEW TO'LOVCHI , 998992130365 SMS AKASI Shahriyor, | G108: QASHQADARYO VILOYATI MIRISHKOR TUMANI GULISTON MFY XAMZA KUCHASI 34-UY | H108: 10 | I108: 5099586.6
...

Sheet Объезд
A1: ← Вернуться в отчёт
A2: Область | B2: Филиал | C2: Группа | D2: Код клиента | E2: Клиент | F2: Номер телефона | G2: Адрес | H2: Кол-во просроченных дней | I2: Итого просрочка | J2: Оплата | K2: Izoh
A3: АНДИЖОН ВИЛОЯТИ | C3: Объезд | D3: Кр-99038794-1 | E3: TOSHXO’JAYEV FAZLIDDIN ZOKIRJON O’G’LI | F3: 998903807010 SMS OZI, 998916197010 SMS AYOLI, 998954779770 SMS ONASI ОГАЙНИСИНИ НОМЕРИ , 998505114440 SMS AKASI бегона , | G3: ANDIJON VILOYATI ANDIJON SHAXAR ISLOMOBOD MFY, MIRPO’STIN KO’CHASI 40 B-UY 31-XONADON | H3: 59 | I3: 21106705 | K3: Uyiga borildi - va'da berdi | 16164383.561643835 | 4942321.34
A4: АНДИЖОН ВИЛОЯТИ | C4: Объезд | D4: Кр-99057085-1 | E4: YULDASHEVA NILUFAR KAMILOVNA | F4: 998872557757 SMS OZI, 998982700122 SMS OGLI, 998772581112 SMS QIZI, 998882331807 SMS JIYANI, | G4: ANDIJON VILOYATI ANDIJON TUMANI ZANGIBOBO MFY PORLOQ KO’CHASI 306-UY | H4: 13 | I4: 15030583 | J4: 5342465 | K4: Uyiga borildi - to'ladi | 5342465.7534246575 | 9688117.5
A5: АНДИЖОН ВИЛОЯТИ | C5: Объезд | D5: Кр-99063020-2 | E5: XALIMOV ILXOMJON DJALILOVICH | F5: 998979950022 OZI, 998941030105 ONASI, 998945616463 JIYANI, 998993478909 KELINI, | G5: ANDIJON VILOYATI ASAKA TUMANI BOBUR MFY KARVONSAROY KO’CHASI 135 UY | H5: 13 | I5: 11945563 | K5: Uyiga borildi - va'da berdi | 4273972.602739726 | 7671589.99
A6: АНДИЖОН ВИЛОЯТИ | C6: Объезд | D6: Кр-99061813-1 | E6: AXMEDOVA LOLAXON XASANOVNA | F6: 998939680860 узи, 998948093111 угли, 998772093139 угли, 998990300805 угли, | G6: ANDIJON VILOYATI IZBOSKAN TUMANI CHEKYO MFY ABU ALI IBN SINO KO’CHASI 27-UY | H6: 10 | I6: 8193435.2 | K6: Uyiga borildi - va'da berdi | 2465753.4246575343 | 5727681.79
A7: АНДИЖОН ВИЛОЯТИ | C7: Объезд | D7: Кр-99063311-2 | E7: MAHKAMOVA MAVLUDA QORATOYEVNA | F7: +998907574245 SMS O’ZI, 998931041313 SMS JIYANI, 998937834245 SMS O’ZI2, 998949998375 SMS OPASI, | G7: ANDIJON VILOYATI IZBOSKAN TUMANI YUQORI MFY DAMBA KO’CHASI 10-UY | H7: 10 | I7: 7235757.5 | K7: Uyiga borildi - va'da berdi | 2191780.821917808 | 5043976.65
A8: АНДИЖОН ВИЛОЯТИ | C8: Объезд | D8: Кр-99029207-1 | E8: SOBIROVA SADOQATOY RAXIMJON QIZI | F8: 94-542-12-54 SMS TOLOVCHI, 93-849-22-52 SMS TOLOVCHI XOJAYINI tanmiman ddi , 94-282-31-32 TOLOVCHI ukasi , 95-022-11-55 TOLOVCHIS OGLI, | G8: ANDIJON VILOYATI PAXTAOBOD TUMANI AXILLIK MFY AXILLIK KO’CHASI 4-UY | H8: 10 | I8: 5333808.6 | K8: Uyiga borildi - va'da berdi | 1917808.219178082 | 3416000.38
A9: АНДИЖОН ВИЛОЯТИ | C9: Объезд | D9: Кр-99041539-1 | E9: SHERALIYEV SARDORBEK SODIQJON O’G’LI | F9: 998914845776 SMS OZI, 998996325251 SMS AYOLI, 998992425251 SMS ONASI, +998914845776 Primary phone from road24, 998948642717 SMS O’ZI2, | G9: Андижон вилояти Андижон шахар Бунёдкор (9-сон) МФЙ, Қўш ариқ дахаси, 46-уй, 15-хонадон | H9: 10 | I9: 2922859.2 | K9: Uyiga borildi - va'da berdi | 547945.205479452 | 2374914
A10: АНДИЖОН ВИЛОЯТИ | C10: Объезд | D10: Кр-99037425-1 | E10: SHUKUROV QUVONCHBEK XABIBILLAYEVICH | F10: 998905271070 SMS OZI, 998901707424 SMS OGLI, 998914865970 SMS AYOLI, 998953475970 SMS QIZI, | G10: ANDIJON VILOYATI ANDIJON TUMANI YUKSALISH MFY YUKSALISH KO’CHASI 19-UY | H10: 2 | I10: 2889861.2 | J10: 273972 | K10: Uyiga borildi - to'ladi | 273972.602739726 | 2615888.63
A11: АНДИЖОН ВИЛОЯТИ | C11: Объезд | D11: Кр-99044378-2 | E11: SHOKIROV NURULLO AXMADULLAYEVICH | F11: +998914912216 SMS O’ZI, 998770387887 SMS QIZI tel qilinmasin, 998779630238 SMS AYOLI , 998931144480 SMS O’G’LI, | G11: АНДИЖОН ВИЛОЯТИ АНДИЖОН ШАХРИ МАДАНИЯТ МФЙ, Т.КЕЛДИЕВ, uy:102 | H11: 10 | I11: 2714002.7 | K11: Uyiga borildi - va'da berdi | 821917.8082191781 | 1892084.88
A12: АНДИЖОН ВИЛОЯТИ | C12: Объезд | D12: Кр-99063106-1 | E12: SOTVOLDIYEVA MAXMUDAXON QOSIMOVNA | F12: 998770492346 OZI, 998931092588 OGLI, 998937212671 OPASI, 998942592770 DUGONASI, | G12: ANDIJON VILOYATI QO’RG’ONTEPA TUMANI UCHQUN MFY ISTIQBOL KO’CHASI 16 UY | H12: 10 | I12: 2695142.3 | J12: 821917 | K12: Uyiga borildi - to'ladi | 821917.8082191781 | 1873224.48
A13: АНДИЖОН ВИЛОЯТИ | C13: Объезд | D13: Кр-99063748-2 | E13: XURBOYEV MURODILJON MURODJON O’G’LI | F13: +998931757095 SMS O’ZI, 998505454475 SMS DADASI, 998938701978 SMS ONASI, 998971622313 SMS SINGLISI, | G13: ANDIJON VILOYATI IZBOSKAN TUMANI A. JOMIY MFY TASHABBUS MARKAZI KO’CHASI 15-UY | H13: 13 | I13: 2457473.8 | K13: Uyiga borildi - va'da berdi | 890410.9589041095 | 1567062.79
A14: АНДИЖОН ВИЛОЯТИ | C14: Объезд | D14: Кр-99044378-1 | E14: SHOKIROV NURULLO AXMADULLAYEVICH | F14: +998914912216 SMS O’ZI, 998770387887 SMS QIZI tel qilinmasin, 998779630238 SMS AYOLI , 998931144480 SMS O’G’LI, | G14: АНДИЖОН ВИЛОЯТИ АНДИЖОН ШАХРИ МАДАНИЯТ МФЙ, Т.КЕЛДИЕВ, uy:102 | I14: 1400789.4 | K14: Uyiga borildi - va'da berdi | 0 | 1400789.42
A15: АНДИЖОН ВИЛОЯТИ | C15: Объезд | D15: Кр-99041539-2 | E15: SHERALIYEV SARDORBEK SODIQJON O’G’LI | F15: 998914845776 SMS OZI, 998996325251 SMS AYOLI, 998992425251 SMS ONASI, +998914845776 Primary phone from road24, 998948642717 SMS O’ZI2, | G15: Андижон вилояти Андижон шахар Бунёдкор (9-сон) МФЙ, Қўш ариқ дахаси, 46-уй, 15-хонадон | H15: 10 | I15: 931523.62 | K15: Uyiga borildi - va'da berdi | 178082.19178082192 | 753441.43
A16: БУХОРО ВИЛОЯТИ | B16: SUPER BRANCH | C16: Объезд | D16: Кр-99019690-5 | E16: HAYDAROV FURQAT RAXMATILLOYEVICH | F16: 97-488-07-66 SMS O'ZI, 88-301-90-93 SMS AKASI, 97-296-06-93 SMS UY, 93-841-53-50 SMS AYOLI, 998505999203 SMS O'ZI2, | G16: BUXORO VILOYAT BUXORO SHAHRI BESHKAPPA KO'CHASI 106 UY | H16: 7 | I16: 2199808.5 | J16: 2484160 | K16: Uyiga borildi - to'ladi | 2 | 2484160.2179178083
A17: БУХОРО ВИЛОЯТИ | B17: SUPER BRANCH | C17: Объезд | D17: Кр-99019690-6 | E17: HAYDAROV FURQAT RAXMATILLOYEVICH | F17: 97-488-07-66 SMS O'ZI, 88-301-90-93 SMS AKASI, 97-296-06-93 SMS UY, 93-841-53-50 SMS AYOLI, 998505999203 SMS O'ZI2, | G17: BUXORO VILOYAT BUXORO SHAHRI BESHKAPPA KO'CHASI 106 UY | H17: 7 | I17: 1144641.8 | J17: 1277949 | K17: Uyiga borildi - to'ladi | 3 | 1277949.4817260276
A18: БУХОРО ВИЛОЯТИ | B18: Бухоро филиали | C18: Объезд | D18: Кр-99032591-1 | E18: BOZOROV DILSHOD OLIM O’G’LI | F18: 998995853782 SMS O’G’LI, 998940186667 SMS AYOLI(BEGONA), 998938997077 SMS ONASI, 998930831515 SMS HAMKASBI бегона , | G18: BUXORO VILOYATI ROMITAN TUMANI O'TABEK MFY, PITMON q-q, 6-uy | H18: 0 | I18: 1298935.7 | K18: Uyiga borildi - va'da berdi | 9 | 1298935.71
A19: ЖИЗЗАХ ВИЛОЯТИ | C19: Объезд | D19: Кр-99038833-1 | E19: XOSILBEKOV SHUXRAT SAFAROVICH | F19: 998941957573 SMS O’ZI, 998935570175 SMS AYOLI, 998945160190 SMS UKASI, 998947277308 SMS SINGLISI, | G19: ZOMIN TUMANI | H19: 1 | I19: 7710284 | J19: 7710284 | K19: Uyiga borildi - to'ladi
A20: ЖИЗЗАХ ВИЛОЯТИ | C20: Объезд | D20: Кр-99036552-1 | E20: ALBEKOVA MUXABAT SAYLIYEVNA | F20: 998906437402 SMS TULOVCHI, 998884374488 SMS KUYOVI TOLOVCHI, 998905163139 SMS QIZI, 998915650972 SMS UZI, | G20: JIZZAX VILOYATI JIZZAX SHAHRI XAMID OLIMJON MFY QANGLI KUCHASI 18-UY | H20: 8 | I20: 7549466.1 | K20: Uyiga borildi - va'da berdi | yorqin tema
A21: ЖИЗЗАХ ВИЛОЯТИ | C21: Объезд | D21: Кр-99063392-1 | E21: BERDIYAROV TO’RAMUROD XUDOYKULOVICH | F21: 998501568064 UZI, 998939931883 AYOLI, 998943438583 ONAS, | G21: БОГИШАМОЛ КФЙ, БОГИШАМОЛ КФЙ, МУГОЛ КИШЛОГИ, uy:РАКАМСИЗ | H21: 10 | I21: 6308129.3 | K21: Uyiga borildi - va'da berdi
A22: ЖИЗЗАХ ВИЛОЯТИ | C22: Объезд | D22: Кр-99030311-1 | E22: SHERANOV SHERZOD ZULFAROVICH | F22: 94-922-86-60 SMS O'ZI, 91-943-85-05 SMS O’ZI 2, 94-922-86-60 SMS UY, 93-304-52-56 SMS OTASI, | G22: JIZZAX VILOYATI ZARBDOR TUMANI DO’STLIK SHAXARCHASI SHODLIK MFY ISTIQBOL KUCHASI 43-UY | H22: 164 | I22: 5460425.9 | K22: Uyiga borildi - va'da berdi | yorqin tema
A23: ЖИЗЗАХ ВИЛОЯТИ | C23: Объезд | D23: Кр-99021925-1 | E23: ISMOILOVA NARGIZA ABDUSALIYEVNA | F23: 998938567000 SMS O’ZI, 998501040408 SMS ERI, 998943437777 SMS ERI , 998905160057 SMS ERINI UKASI, 998931070408 tolovchi eri , 998971299092 sms tulovchi, 998508043200 FARUX TULOVCHISI, | G23: JIZZAX VILOYATI SHAROF RASHIDOV TUMANI QANG'LI QFY ARISHLI MAHALLASI ZIYOKOR KUCHASI 4-UY | H23: 3 | I23: 5112052.5 | K23: Uyiga borildi - va'da berdi
A24: ЖИЗЗАХ ВИЛОЯТИ | C24: Объезд | D24: Кр-99042640-1 | E24: XO’JAQULOV FURQAT JAYNAROVICH | F24: +998771070575 SMS, 998932920870 SMS, 998990343029 SMS, | G24: JIZZAX VILOYATI ZAFAROBOD TUMANI BIRLIK QFY RUDAKIY KUCHASI 4-A UY | H24: 10 | I24: 4645444 | K24: Uyiga borildi - va'da berdi
A25: ЖИЗЗАХ ВИЛОЯТИ | C25: Объезд | D25: Кр-99063375-1 | E25: AG’LAMOV AZIMXON AKRAM O’G’LI | F25: 998881511212 AKASI, 998915981212 AKASI, 998970105070 UZI, | G25: УЧАРИК МФЙ, ХАМЗАОБОД, ФИРДАВСИЙ, uy:9 | H25: 10 | I25: 3915897.3 | K25: Uyiga borildi - va'da berdi
A26: ЖИЗЗАХ ВИЛОЯТИ | C26: Объезд | D26: Кр-99040996-1 | E26: BOBAQULOV JASUR INOMOVICH | F26: 998959118222 SMS OZI, 998888481114 SMS AYOLI, 998956311666 SMS UY, 998915935501 SMS SINGLISI, | G26: JIZZAX VILOYATI SH.RASHIDOV TUMANI UCHTEPA MFY BESHQAYRAGOCH KUCHASI 168-UY | H26: 10 | I26: 3196871.9 | K26: Uyiga borildi - va'da berdi
A27: ЖИЗЗАХ ВИЛОЯТИ | C27: Объезд | D27: Кр-99039896-1 | E27: UMMATOV JAVLON MAVLONOVICH | F27: 998959172024 SMS OZI, 998957701676 SMS UKASI, 998957741676 SMS SINGLIASI, 998911956219 SMS DADASI, 998995247977 sms uzi mew, 998995247977 sms uzi new, | G27: JIZZAX VILOYATI SH.RASHIDOV TUMANI UCH TEPA MFY GUNCHA KUCHASI 97-UY | H27: 10 | I27: 2824533.3 | K27: Uyiga borildi - va'da berdi
A28: ЖИЗЗАХ ВИЛОЯТИ | C28: Объезд | D28: Кр-99041710-1 | E28: MAMARAJABOVA ZULOYXA ABDUMALIK QIZI | F28: 998339269697 SMS, 998931049616 SMS, | G28: JIZZAX VILOYATI BAXMAL TUMANI TONGOTAR MFY QUSHTEPA QISHLOGI 65-UY | H28: 10 | I28: 2497483.1 | J28: 2497483.1 | K28: Uyiga borildi - to'ladi | qisman tolov qildi
A29: ЖИЗЗАХ ВИЛОЯТИ | C29: Объезд | D29: Кр-99060382-1 | E29: XONIMKULOV XURSHID UMARKUL O’G’LI | F29: 998991027333 узи, 998915900150 аели, 998911968898 шериги, | G29: JIZZAX VILOYATI JIZZAX TUMANI BUNYODKOR MFY LOLAZOR KUCHASI 1A-UY | H29: 13 | I29: 1908130.3 | K29: Uyiga borildi - va'da berdi
A30: ЖИЗЗАХ ВИЛОЯТИ | C30: Объезд | D30: Кр-99026372-3 | E30: ARIPOV FAXRIDDIN JO’MANOVICH | F30: 94-138-50-20 SMS UZI , 91-209-90-77 SMS UZI, 94-001-51-35 SMS UY, 91-028-70-28 SMS AYOLI, | G30: JIZZAX VILOYATI MARJONBULOQ SHMB LALMIKOR MFY NAVRO’Z MAHALLASI 60-UY | H30: 10 | I30: 1508602.4 | J30: 1508602.4 | K30: Uyiga borildi - to'ladi
A31: ЖИЗЗАХ ВИЛОЯТИ | C31: Объезд | D31: Кр-99030311-2 | E31: SHERANOV SHERZOD ZULFAROVICH | F31: 94-922-86-60 SMS O'ZI, 91-943-85-05 SMS O’ZI 2, 94-922-86-60 SMS UY, 93-304-52-56 SMS OTASI, | G31: JIZZAX VILOYATI ZARBDOR TUMANI DO’STLIK SHAXARCHASI SHODLIK MFY ISTIQBOL KUCHASI 43-UY | H31: 15 | I31: 1356589.8 | K31: Uyiga borildi - va'da berdi | yorqin tema
A32: ЖИЗЗАХ ВИЛОЯТИ | C32: Объезд | D32: Кр-99018232-3 | E32: ELIMBAYEVA MAVLYUDA KOLDASHOVNA | F32: 97-647-48-78 SMS ERI, 97-522-05-30 SMS O'G'LI, 97-800-12-81 SMS QIZI, 93-553-18-82 SMS UKASI, | G32: JIZZAX VILOYATI ZAFAROBOD TUMANI YORQIN MAHALLASI CHEVARLAR KUCHASI 15-UY | H32: 2 | I32: 1296595.8 | K32: Uyiga borildi - va'da berdi
A33: ЖИЗЗАХ ВИЛОЯТИ | C33: Объезд | D33: Кр-99034201-1 | E33: OCHILOV TO’LQIN ABDUALIMOVICH | F33: 998902294031 SMS OZI, 998915676560 SMS AYOLI, 998912080702 SMS KELINI, 998915960702 SMS SINGLI, | G33: JIZZAX VILOYATI JIZZAX TUMANI QULAMA QFY A.NAVOIY KUCHASI 27-UY | I33: 6266.97 | J33: 6266.97 | K33: Uyiga borildi - to'ladi
A34: КАШКАДАРЁ ВИЛОЯТИ | C34: Объезд | D34: Кр-99063133-1 | E34: TO’XTAYEV BOBUR ALISHER O’G’LI | F34: 998908992275 SMS OZI, 998993458899 SMS TO'LOVCHI, 998906097727 SMS OTASI, 998919611171 SMS AKASI, | G34: QASHQADARYO VILOYATI QARSHI TUMANI BOG’OBOD MFY TUQMANG’IT QISHLOG’I 260-UY | H34: 43 | I34: 22609689 | K34: Uyiga borildi - va'da berdi
A35: КАШКАДАРЁ ВИЛОЯТИ | C35: Объезд | D35: Кр-99060317-1 | E35: NAFASOV ASADBEK VALIJON O’G’LI | F35: 998973852277 SMS OZI, 998886191100 SMS AYOLI, 998770994440 SMS DADASI, 998886195000 SMS ONASI, | G35: QASHQADARYO VILOYATI YAKKABOG’ TUMANI ISTIQLOL MFY OLAQARG’A QISHLOG’I | H35: 13 | I35: 11614788 | K35: Uyiga borildi - va'da berdi | qisnab to'lov qildi
A36: КАШКАДАРЁ ВИЛОЯТИ | C36: Объезд | D36: Кр-99063959-1 | E36: IBROGIMOV RASHID ISMOIL UG’LI | F36: 998887737107 SMS AKASI, 998953307107 SMS AKASI, 998992719999 SMS UYI, | G36: QASHQADARYO VILOYATI SHAXRISABZ TUMANI YANGIOBOD MFY ZAMONDOSH 67 - UY | H36: 10 | I36: 4235038.1 | K36: Uyiga borildi - va'da berdi
A37: КАШКАДАРЁ ВИЛОЯТИ | C37: Объезд | D37: Кр-99037441-4 | E37: KOSIMOV ABROR ABDISALOMOVICH | F37: 998887417117 SMS OZI, 998905175558 SMS AKASI BEGONA, 998941729897 SMS JURASI, | G37: QASHQADARYO VILOYATI G’UZOR TUMANI TINCHLIK MFY YANGI TONG KO’CHASI 765-UY | H37: 10 | I37: 3313868 | K37: Uyiga borildi - va'da berdi
A38: КАШКАДАРЁ ВИЛОЯТИ | C38: Объезд | D38: Кр-99040694-2 | E38: TOSHPULATOV SHAHRIYOR XOLMUROD O’G’LI | F38: 998932061021 AKASI, 998952622787 UKASI, | G38: ОЛМАЗОР МФЙ, УЧТУТ, uy:Р/С | H38: 10 | I38: 2788081.5 | K38: Uyiga borildi - va'da berdi
A39: КАШКАДАРЁ ВИЛОЯТИ | C39: Объезд | D39: Кр-99059908-1 | E39: TO’LAYEV MIRJALOL MUZAFFARJON O’G’LI | F39: +998883110080 SMS, 998771727141 SMS, 998889518080 SMS, | G39: КАШКАДАРЁ ВИЛОЯТИ ГУЗОР ТУМАНИ ШЕРАЛИ МФЙ ХАЛКАБОД КИШЛОГИ | H39: 10 | I39: 2353346.3 | K39: Uyiga borildi - va'da berdi
A40: КАШКАДАРЁ ВИЛОЯТИ | C40: Объезд | D40: Кр-99037085-2 | E40: XAMRAYEVA GULNORA XURRAMOVNA | F40: 998979549700 SMS OZI (OG'LI) XUSAN, 998881941597 SMS O’G’LI, 998884287278 SMS UKASI (UZI), 998886757572 SMS AKASI, | G40: QASHQADARYO VILOYATI QARSHI TUMANI MEVAZOR MFY NAVRUZ QURG’ONI SHAHARCHASI 67/1 UY | H40: 10 | I40: 1951671.2 | J40: 1951671.2 | K40: Uyiga borildi - to'ladi
A41: КАШКАДАРЁ ВИЛОЯТИ | C41: Объезд | D41: Кр-99038805-1 | E41: ESHQULOV ABROR AZAMATOVICH | F41: 998976776676 SMS O’ZI, 998990647161 SMS AYOLI, 998972560232 SMS AKASI , 998947061030 SMS ONASI, | G41: QARSHI TUMANI | H41: 6 | I41: 1414554.5 | J41: 1414554.5 | K41: Uyiga borildi - to'ladi
A42: КАШКАДАРЁ ВИЛОЯТИ | C42: Объезд | D42: Кр-99035313-4 | E42: OMONOV RO’YIDDIN ADASH O’G’LI | F42: 998906167214 SMS OILASI, 998913830559 SMS AKASI UZIII TO'LOVCHI, 998993830559 SMS OILASI, 998914682525 SMS UKASI (POCHCHASI), | G42: QASHQADARYO VILOYATI QARSHI TUMANI TINCHLIK MFY PARMITON QISHLOG’I 13-UY | H42: 10 | I42: 1341477.2 | J42: 1341477.2 | K42: Uyiga borildi - to'ladi
A43: КАШКАДАРЁ ВИЛОЯТИ | C43: Объезд | D43: Кр-99035313-2 | E43: OMONOV RO’YIDDIN ADASH O’G’LI | F43: 998906167214 SMS OILASI, 998913830559 SMS AKASI UZIII TO'LOVCHI, 998993830559 SMS OILASI, 998914682525 SMS UKASI (POCHCHASI), | G43: QASHQADARYO VILOYATI QARSHI TUMANI TINCHLIK MFY PARMITON QISHLOG’I 13-UY | H43: 3 | I43: 999946.2 | J43: 999946.2 | K43: Uyiga borildi - to'ladi
A44: КАШКАДАРЁ ВИЛОЯТИ | C44: Объезд | D44: Кр-99038004-1 | E44: RAXMONOVA NILUFAR RAXMIDDIN QIZI | F44: 998889543030 SMS OZI, 998882070694 SMS OILASI, 998979537171 SMS AKASI, 998991689400 SMS AKASI, 998974380089 SMS TO'LOVCHI, | G44: КАШКАДАРЁ ВИЛОЯТИ КОСОН ТУМАНИ Эсабой МФЙ Эсабой кучаси 31-уй | H44: 10 | I44: 779178.8 | J44: 779178.8 | K44: Uyiga borildi - to'ladi
A45: КАШКАДАРЁ ВИЛОЯТИ | C45: Объезд | D45: Кр-99040703-2 | E45: SHOMURODOV BEKMUROD SHERQULOVICH | F45: +998934213611 sms uzi , 998333993611 sms ogli, 998773004642 sms ayoli , 998996862082 sms uzi2, | G45: КАЗОКЛИ МФЙ, КАЗОКЛИ, uy:Р/С | I45: 466210.86 | J45: 466210.86 | K45: Uyiga borildi - to'ladi
A46: КОРАКАЛПОГИСТОН РЕСПУБЛИКАСИ | C46: Объезд | D46: Кр-99062698-1 | E46: ABDUALIYEV ABDIBAY ABDIRXANOVICH | F46: 998997887003 SSM OZI, 998973546546 SMS AYOLI, 998991807003 SMS OGLI, 999877880239 SMS OGLI 2, | G46: QORAQALPOGISTON RES NUKUS SHAHAR AMUDARYO MFY SARI KOL KUSHASI 30 UY | H46: 15 | I46: 9839953.6 | K46: Uyiga borildi - va'da berdi | KO'TARMADI | 1424
A47: КОРАКАЛПОГИСТОН РЕСПУБЛИКАСИ | C47: Объезд | D47: Кр-99046605-1 | E47: BALTAYEV SADULLA MAKSUDOVICH | F47: 998907147737 SMS UZI, 998947020528 SMS UGLI, 998945640304 SMS QIZI BEGONA , 998997147737 o'zi newww, | G47: QORAQALPOGISTON RES XOJAYLI TUMANI TUTZAR MFY XALKABAD KUSHASI 8 UY | H47: 13 | I47: 6971404.1 | K47: Uyiga borildi - va'da berdi | BUGUNGA VADA BERDILA OYLIGIM TUSHDI TASHEMAN DEDILA | 1120
A48: КОРАКАЛПОГИСТОН РЕСПУБЛИКАСИ | C48: Объезд | D48: Кр-99056113-1 | E48: TAJIMURATOVA NASIBA JUMAMBETOVNA | F48: 998959469019 SMS OZI , 998880042678 SMS OZI 2 AKASI TO'LOVCHI , 998902625683 SMS OZI 3, | G48: QARAQALPOGISTON RES NUKUS SHAHAR DOSLIQ GUZARI MFY A.DOSNAZAROV KUSHASI 131 UY 28 KVARTIRA | H48: 10 | I48: 5927006 | K48: Uyiga borildi - va'da berdi | 1250
A49: КОРАКАЛПОГИСТОН РЕСПУБЛИКАСИ | C49: Объезд | D49: Кр-99052708-1 | E49: ABDIRAMANOV ZAKIR ABDIRIYEMOVICH | F49: 998930009217 SMS OZI, 998913897229 SMS AKASI, 998904238131 SMS QIZI, 998904230693 SMS OGLI, 998907357534 ozi newww, | G49: QARAQALPOGISTON RES XOJAYLI TUMANI SABIK MFY SAXRA KUSHASI 7 UY | H49: 10 | I49: 4723738 | K49: Uyiga borildi - va'da berdi | QIZI BN GAPLASHDIM AYTIB QO'YAMAN AKAM TO'LAYDI DEDI 20KUNI OYLIGI TUSHADI EKAN | 1202
A50: КОРАКАЛПОГИСТОН РЕСПУБЛИКАСИ | C50: Объезд | D50: Кр-99057077-1 | E50: SERIKBAYEV MARAT ALDANAZAROVICH | F50: 998946831315 SMS UZI, 998905906668 SMS QIZI, 998933083023 SMS UKASI, 998938743798 SMS KELINI, | G50: QARAQALPOGISTON RES NUKUS SHAHAR SHIGIS MFY MATEKE JUMANAZAROV KUSHASI 18 UY | H50: 10 | I50: 2558543.1 | K50: Uyiga borildi - va'da berdi | 20KUNI TO'LOV QILADI | 1261
A51: КОРАКАЛПОГИСТОН РЕСПУБЛИКАСИ | C51: Объезд | D51: Кр-99041431-1 | E51: BAYNAZAROVA AMANGUL KALIBAYEVNA | F51: 998906536610 SMS OZI, 998919359599 SMS QIZI, 998913918821 SMS OGLI, 998913810499 SMS KELINI, 998933029514 SMS UKASI WU RAQAM ISHLAYDI, | G51: QARAQALPOGISTON RES NUKUS SHAHAR XAUA JOLI MFY DAWLET BAQSI KUSHASI 21 UY | H51: 10 | I51: 2047607.4 | K51: Uyiga borildi - va'da berdi | UKASI BN GAPLASHDIM OY OXIRIDA OPAM OYLIK OLADILA VA FILIALGA TASHAB BERADILA DEDILA QOZOQDALA | 999
A52: КОРАКАЛПОГИСТОН РЕСПУБЛИКАСИ | C52: Объезд | D52: Кр-99047374-1 | E52: SHARAPOV BAXIT URAZBAYEVICH | F52: 998880716102 OGLI, 998907077908 OZI, 998994507986 OYALI, | G52: Qaraqalpogiston Respublikasi nukus shahar Nurli bostan MFY Askerler joli kushasi 215 uy | H52: 10 | I52: 1770339.7 | K52: Uyiga borildi - va'da berdi | UYIGA FILIAL BORISHDI QOZOQDA ISHLAYDI 3KUNDA OYLIGINI OLIB FILIALGA TASHAB BERAMAN DEBDILA | 1130
A53: КОРАКАЛПОГИСТОН РЕСПУБЛИКАСИ | C53: Объезд | D53: Кр-99063402-1 | E53: JAMGIRBAYEV SHOXZOD XALMURAT ULI | F53: 998906527006 OZI, 998913931005 AKASI, 998951773003 AKASI 2, | G53: QARAQALPOGISTON RES NUKUS SHAHAR NAUBAXAR MFY ELI AZAT KUSHASI 15 UY | H53: 10 | I53: 1767587.4 | J53: 1767587.4 | K53: Uyiga borildi - to'ladi | 1552
A54: НАВОИЙ ВИЛОЯТИ | C54: Объезд | D54: Кр-99040670-1 | E54: SATTOROV ZAFAR FATTOHOVICH | F54: 998997540001 SMS OZI oqtuvchi , 998912512244 SMS ERI, 998913086648 SMS ONASI, 998930590059 SMS JIYANI, | G54: NAVOIY VILOYATI, QIZILTEPA TUMANI, GULZOR MFY, GULZOR KO'CHASI, 561-UY | H54: 10 | I54: 4302470.6 | K54: Uyiga borildi | uyiga boramiz dip etti
A55: НАМАНГАН ВИЛОЯТИ | C55: Объезд | D55: Кр-99063350-2 | E55: HASANOV NASRIDDIN FAZLIDDINOVICH | F55: +998947058118 SMS O’ZI, 998932726162 SMS QIZI, 998947322062 SMS AYOLI, | G55: НАМАНГАН ВИЛОЯТИ УЙЧИ ТУМАНИ НАВОИЙ МФЙ БОҒИ ЭРАМ КЎЧАСИ 1 УЙ | H55: 10 | I55: 6845285.9 | K55: Uyiga borildi | qisman tolov qilb berdi | Стандартрый
A56: НАМАНГАН ВИЛОЯТИ | C56: Объезд | D56: Кр-99063450-2 | E56: MUYDINOVA GULJAXON YUSUPOVNA | F56: +998942830389 SMS O’ZI, 998508877719 SMS UY, 998932916566 SMS SINGLISI, | G56: НАМАНГАН ВИЛОЯТИ ЯНГИ НАМАНГАН ТУМАНИ КЕЛАЖАК ТОНГИ МФЙ ХАСАНОБОД КЎЧАСИ 28А-УЙ | H56: 10 | I56: 3616653.2 | K56: Uyiga borildi | uyida xch kim yogakan | Стандартрый
A57: НАМАНГАН ВИЛОЯТИ | C57: Объезд | D57: Кр-99034285-1 | E57: NURIDDINOV MURODJON ABDULVOXIT O’G’LI | F57: 998990903636 SMS O’ZI, 998945087459 SMS DADASI, 998956751004 SMS AYOLI, 998933554343 SMS UKASI, | G57: NAMANGAN VILOYATI UYCHI TUMANI YORQO’RG’ON QFY OQTOSH MFY TARAQQIYOT KO’CHA 22 UY | H57: 10 | I57: 2820987.5 | K57: Uyiga borildi | bittasini yopib berdi qolgani erta indin qisman tolab berdi bunga | Стандартрый
A58: НАМАНГАН ВИЛОЯТИ | C58: Объезд | D58: Кр-99050372-2 | E58: MAMANAZAROV NODIRBEK ISROIL O’G’LI | F58: +998932534343 SMS O’ZI, 998993790909 SMS O’ZI 2 begona, 998995410505 SMS AYOLI BEGONA, | G58: NAMANGAN VILOYATI NAMANGAN SHAHAR SHODLIK MFY TO’RAQO’RG’ON KO’CHASI 12 UY | H58: 10 | I58: 1336418.1 | K58: Uyiga borildi | yopildi | Стандартрый
A59: НАМАНГАН ВИЛОЯТИ | C59: Объезд | D59: Кр-99034285-2 | E59: NURIDDINOV MURODJON ABDULVOXIT O’G’LI | F59: 998990903636 SMS O’ZI, 998945087459 SMS DADASI, 998956751004 SMS AYOLI, 998933554343 SMS UKASI, | G59: NAMANGAN VILOYATI UYCHI TUMANI YORQO’RG’ON QFY OQTOSH MFY TARAQQIYOT KO’CHA 22 UY | H59: 10 | I59: 902766.97 | K59: Uyiga borildi | yopildi | Стандартрый
A60: САМАРКАНД ВИЛОЯТИ | C60: Объезд | D60: Кр-99045220-1 | E60: ABDIYEV FAXRIDDIN ASKAROVICH | F60: +998935157020 SMS OZI 2, 998937772322 SMS AYOLI, 998940994040 SMS OZI, 998953307020 SMS UYI, | G60: SAMARQAND VILOYATI PAYARIQ TUMANI ILG’OR MFY QOZI QISHLOG’I | H60: 73 | I60: 19138778 | K60: Uyiga borildi - va'da berdi | sudda ishi
A61: САМАРКАНД ВИЛОЯТИ | C61: Объезд | D61: Кр-99034543-2 | E61: KULIYEV XURSHID ISMAILOVICH | F61: 998912975577 SMS O’ZI, 998913140077 SMS ERI, 998915494303 SMS , +998913140077 SMS OZI, | G61: SAMARQAND VILOYATI PASTDARG’OM TUMANI TURON MFY | H61: 10 | I61: 14530822 | K61: Uyiga borildi - va'da berdi | ishxonasiga borildi
A62: САМАРКАНД ВИЛОЯТИ | C62: Объезд | D62: Кр-99045550-1 | E62: YO’LYAXSHIYEV MOHIR MANSUR O’G’LI | F62: +998952306777 SMS OZI, 998507068065 SMS AYASI, 998507757594 SMS AYOLI, 998940947545 SMS UKASI, | G62: SAMARQAND VILOYATI URGUT TUMANI YUQORI TEGANA MFY X.BAYQORO KUCHASI 24-UY | H62: 43 | I62: 9416166.3 | K62: Uyiga borildi - va'da berdi
A63: САМАРКАНД ВИЛОЯТИ | C63: Объезд | D63: Кр-99057329-1 | E63: SODIQOV ANVARJON VORISJONOVICH | F63: 998953976067 SMS UZI, 998500579222 SMS TULOVCHI, 998997798472 SMS TULOVCHI ZALOGATEL , 998910320010 SMS UY, | G63: SAMARQAND TUMANI | H63: 10 | I63: 3639543.1 | K63: Uyiga borildi - va'da berdi | uyiga borildi
A64: САМАРКАНД ВИЛОЯТИ | C64: Объезд | D64: Кр-99059521-1 | E64: NEMATOVA LOLAXON FARXODJON QIZI | F64: +998944600370 SMS OZI, 998500105600 SMS UKASI, 998949230370 SMS ERI, 998979290370 SMS UYI, | G64: SAMARQAND VILOYATI PAYARIQ TUMANI ERNAZARQURG’ON MFY YANGI ZAMON KUCHASI 54-UY | H64: 10 | I64: 3587565.2 | K64: Uyiga borildi - va'da berdi | uyiga borishdi
A65: САМАРКАНД ВИЛОЯТИ | C65: Объезд | D65: Кр-99062920-1 | E65: BOBOYEV SHERXON RUZIMURODOVICH | F65: +998992957374 SMS OZI, 998904757374 SMS OZI 2, 998956738444 SMS UKASI, | G65: SAMARQAND VILOYATI NUROBOD TUMANI OQSOY MFY | H65: 10 | I65: 3443274.9 | J65: 3443274.9 | K65: Uyiga borildi - to'ladi | yopildi
A66: САМАРКАНД ВИЛОЯТИ | C66: Объезд | D66: Кр-99057430-1 | E66: TOSHMURODOV JAVLONBEK ULUG’BEKOVICH | F66: 998942894664 SMS UZI, 998918460505 SMS AKASI TULOVCHI, 998942870050 SMS AKASI, 998942131877 SMS AYASI, | G66: SAMARQAND VILOYATI PAXTACHI TUMANI MIRZO NODIM MFY REGISTON KUCHASI 97-UY | H66: 10 | I66: 3387227.9 | J66: 3387227.9 | K66: Uyiga borildi - to'ladi | yopildi
A67: САМАРКАНД ВИЛОЯТИ | C67: Объезд | D67: Кр-99008241-5 | E67: KOMILOV SHERZOD NAJIMOVICH | F67: 99-593-55-60 SMS, 94-002-49-62 SMS OGLI бегона, 93-295-08-33 SMS KUYOVI, 99-224-49-92 SMS KUYOVI, 998950205560 Yangi raqami Tolovchi, 932950833 SMS KUYOVI, 940024962 SMS OGLI бегона, 992244992 SMS KUYOVI, 995935560 SMS, | G67: SAMARQAND VILOYATI KATTAQO’RG’ON TUMANI MULLAKICHKINA | H67: 3 | I67: 2920966.9 | K67: Uyiga borildi - va'da berdi
A68: САМАРКАНД ВИЛОЯТИ | C68: Объезд | D68: Кр-99062811-2 | E68: SHOKIROV SAVRIDDIN SALOHIDDIN O’G’LI | F68: +998931430020 SMS OZI, 998505711620 SMS OPASI, 998937243255 SMS UKASI, | G68: SAMARQAND VILOYATI TAYLOQ TUMANI YANGI XAYOT MFY CHOVONDOZ KUCHASI | H68: 10 | I68: 2882928 | J68: 2882928 | K68: Uyiga borildi - to'ladi | yopildi
A69: САМАРКАНД ВИЛОЯТИ | C69: Объезд | D69: Кр-99037081-1 | E69: QUZIYEV SHERZOD HAMDAMKULOVICH | F69: 998944771277 SMS OZI, 998940090440 SMS AYOLI, 998990215277 SMS OGLI, 998930388336 SMS QIZI, 998700444786 SMS UZI NEW, 998700111786 SMS XOTINI NEW, 998990215277 SMS UY, | G69: SAMARQAND VILOYATI TAYLOQ TUMANI NAYMAN MFY JASORAT KUCHASI 1-UY | H69: 15 | I69: 2231295.5 | K69: Uyiga borildi - va'da berdi
A70: САМАРКАНД ВИЛОЯТИ | C70: Объезд | D70: Кр-99050656-2 | E70: BERDIMURODOV NUMONJON KOMILJONOVICH | F70: +998939705584 SMS OZI, 998770530720 SMS UYI, 998933599647 SMS AYOLI, 998997189688 SMS ZALOGADATEL, | G70: SAMARQAND VILOYATI PAYARIQ TUMANI ZARAFSHON MFY KASHFIYOT 49-UY | I70: 1852074.8 | K70: Uyiga borildi - va'da berdi | uyida doston aka
A71: САМАРКАНД ВИЛОЯТИ | C71: Объезд | D71: Кр-99007936-14 | E71: MAMASHARIPOV UTKIR MAMARZAYEVICH | F71: 99-344-03-45 SMS, 99-459-49-27 SMS AYOLI, 99-250-69-06 SMS ozi , 99-161-65-45 SMS UYI , 99-150-69-06 SMS ayoli , 77-080-89-01 SMS FARANGIZ SHU TOLOVCHI, +998957710587 SMS OZI, 998991198901 SMS UKASI, 998995398901 SMS UYI, 998990827644 tulovchi, 998500281120 SMS UYI, 998959584111 SMS AKASI, | G71: SAMARQAND VILOYATI OQDARYO TUMANI A.TEMUR MFY KALLAR QISHLOG’I | H71: 10 | I71: 1779309.2 | K71: Uyiga borildi - va'da berdi
A72: САМАРКАНД ВИЛОЯТИ | C72: Объезд | D72: Кр-99040926-1 | E72: ABDIVALIYEVA IRODA URAQOVNA | F72: +998993827337 SMS OZI, 998701085409 SMS OPASI, 998945378668 SMS UZI 2, 998993837337 SMS ERI, | G72: А.НАВОИЙ ҚФЙ, ЯНГИОБОД МФЙ, МУЗОН ҚИШЛОҒИ, uy:Р/С | H72: 15 | I72: 1681946.4 | K72: Uyiga borildi - va'da berdi
A73: САМАРКАНД ВИЛОЯТИ | C73: Объезд | D73: Кр-99007936-12 | E73: MAMASHARIPOV UTKIR MAMARZAYEVICH | F73: 99-344-03-45 SMS, 99-459-49-27 SMS AYOLI, 99-250-69-06 SMS ozi , 99-161-65-45 SMS UYI , 99-150-69-06 SMS ayoli , 77-080-89-01 SMS FARANGIZ SHU TOLOVCHI, +998957710587 SMS OZI, 998991198901 SMS UKASI, 998995398901 SMS UYI, 998990827644 tulovchi, 998500281120 SMS UYI, 998959584111 SMS AKASI, | G73: SAMARQAND VILOYATI OQDARYO TUMANI A.TEMUR MFY KALLAR QISHLOG’I | H73: 10 | I73: 1197934.8 | K73: Uyiga borildi - va'da berdi
A74: САМАРКАНД ВИЛОЯТИ | C74: Объезд | D74: Кр-99007936-11 | E74: MAMASHARIPOV UTKIR MAMARZAYEVICH | F74: 99-344-03-45 SMS, 99-459-49-27 SMS AYOLI, 99-250-69-06 SMS ozi , 99-161-65-45 SMS UYI , 99-150-69-06 SMS ayoli , 77-080-89-01 SMS FARANGIZ SHU TOLOVCHI, +998957710587 SMS OZI, 998991198901 SMS UKASI, 998995398901 SMS UYI, 998990827644 tulovchi, 998500281120 SMS UYI, 998959584111 SMS AKASI, | G74: SAMARQAND VILOYATI OQDARYO TUMANI A.TEMUR MFY KALLAR QISHLOG’I | H74: 3 | I74: 1176359 | K74: Uyiga borildi - va'da berdi
A75: САМАРКАНД ВИЛОЯТИ | C75: Объезд | D75: Кр-99008241-6 | E75: KOMILOV SHERZOD NAJIMOVICH | F75: 99-593-55-60 SMS, 94-002-49-62 SMS OGLI бегона, 93-295-08-33 SMS KUYOVI, 99-224-49-92 SMS KUYOVI, 998950205560 Yangi raqami Tolovchi, 932950833 SMS KUYOVI, 940024962 SMS OGLI бегона, 992244992 SMS KUYOVI, 995935560 SMS, | G75: SAMARQAND VILOYATI KATTAQO’RG’ON TUMANI MULLAKICHKINA | H75: 2 | I75: 921961.21 | J75: 921961.21 | K75: Uyiga borildi - to'ladi | yopildi
A76: САМАРКАНД ВИЛОЯТИ | C76: Объезд | D76: Кр-99034419-1 | E76: ABDULLAYEVA SOADAT ALLAMURADOVNA | F76: 998991332753 SMS O’ZI, 998942561450 SMS O’G’LI, 998992742115 SMS NABIRASI, | G76: SAMARQAND VILOYATI PAXTACHI TUMANI ZARAFSHON MFY ORZU KUCHASI 34-UY | I76: 777575.78 | J76: 777575.78 | K76: Uyiga borildi - to'ladi | yopildi
A77: САМАРКАНД ВИЛОЯТИ | C77: Объезд | D77: Кр-99037081-3 | E77: QUZIYEV SHERZOD HAMDAMKULOVICH | F77: 998944771277 SMS OZI, 998940090440 SMS AYOLI, 998990215277 SMS OGLI, 998930388336 SMS QIZI, 998700444786 SMS UZI NEW, 998700111786 SMS XOTINI NEW, 998990215277 SMS UY, | G77: SAMARQAND VILOYATI TAYLOQ TUMANI NAYMAN MFY JASORAT KUCHASI 1-UY | H77: 10 | I77: 687256.27 | K77: Uyiga borildi - va'da berdi
A78: СУРХОНДАРЁ ВИЛОЯТИ | C78: Объезд | D78: Кр-99039320-1 | E78: KURBANOV FAZLIDDIN ABDUKAXOROVICH | F78: 998991354667 SMS OZI, 998991205994 SMS AYOLI, 998994513084 SMS AKASI, 998745116760 SMS UY, | G78: SURXONDARYO VILOYATI DENOV TUMANI OYBARAK MFY CHINORSOY KO’CHASI 42-UY | H78: 167 | I78: 20832795 | K78: Uyiga borildi - va'da berdi | 21sanaga tolov | 771
A79: СУРХОНДАРЁ ВИЛОЯТИ | C79: Объезд | D79: Кр-99041110-1 | E79: KASIMOV NODIRBEK BAYKABILOVICH | F79: +998998830188 SMS O’ZI, 998770043004 SMS KELINI, 998958449474 SMS AYOLI, 998991090189 SMS DO’STDI, 998998830188 Primary phone from road24, | G79: ЖОНЧЕККА ҚФЙ, ДЕХКОН МФЙ, ЖОНЧЕККА ҚФЙ, ДЕХКОН МФЙ, ДЕХКОН, uy:. | H79: 10 | I79: 4357378.6 | K79: Uyiga borildi - va'da berdi | oy oxrga | 960
A80: СУРХОНДАРЁ ВИЛОЯТИ | C80: Объезд | D80: Кр-99035964-1 | E80: SULOYMONOV ERKIN NOZIMOVICH | F80: 998770300464 SMS O’ZI, 998881538883 SMS AYOLI, 998770320564 SMS O’G’LI, 998936034414 SMS OSHNASI, | G80: SURXONDARYO VILOYATI DENOV TUMANI O’RTAQISHLOQ MFY TAVAKULL K’OCHASI 21-UY | H80: 3 | I80: 2520864 | K80: Uyiga borildi - va'da berdi | wu hafta yopad | 543
A81: СУРХОНДАРЁ ВИЛОЯТИ | C81: Объезд | D81: Кр-99035996-1 | E81: ALMARDONOV BOBOMUROD BOBORAXMATOVICH | F81: 998995444686 SMS OZI, 998883176868 SMS SHERIGI, 998978967555 SMS UY, 998975502586 SMS, | G81: SURXONDARYO VILOYATI DENOV TUMANI FAYZLI MFY BUYUK IPAKYULI KO'CHASI 1-UY | H81: 3 | I81: 2248695.2 | J81: 2248695.2 | K81: Uyiga borildi - to'ladi | toladi | 544
A82: СУРХОНДАРЁ ВИЛОЯТИ | C82: Объезд | D82: Кр-99039591-1 | E82: YO’LDOSHEV BAHODIR HAZRATQULOVICH | F82: 998975339787 SMS OZI, 998971231999 SMS UY, 998884207571 SMS ONASI, | G82: SURXONDARYO VILOYATI DENOV TUMANI MUQUMIY MFY TARAQQIYOT 6-UY | H82: 3 | I82: 2242889 | K82: Uyiga borildi - va'da berdi | bugun erte tolo qlad | 806
A83: СУРХОНДАРЁ ВИЛОЯТИ | C83: Объезд | D83: Кр-99038010-1 | E83: ABDURAXIMOVA MUNAVVAR XO’SHBOQ QIZI | F83: 998942004892 SMS OZI, 998958987789 SMS UYI , 998958110962 SMS SINGLISi, 998945300101 SMS UYI 2 , | G83: SURXONDARYO VILOYATI DENOV TUMANI ELOBOD MFY NURLISAODAT 19-UY | H83: 9 | I83: 1890410 | J83: 1890410 | K83: Uyiga borildi - to'ladi | oylik tolovi yopild | 671
A84: СУРХОНДАРЁ ВИЛОЯТИ | C84: Объезд | D84: Кр-99011383-5 | E84: BURONOV ESHMAMAT KENJAYEVICH | F84: 99-179-87-70 SMS OZI FERMER , 33-707-44-94 SMS O’G’LI FAXRIDDIN, 91-517-57-59 SMS SO’G’LI BAXROM, 90-378-57-59 SMS ZALOGADATEL, 998953169515 SMS ugli QUVONCHBEK TOSHDA YURIDIKDA UQIDI , 998955545759 OGLI BAXROM, 998952380056 SMS O'ZI, 998883510272 MAHALLA RAISI, 998994551664 RUSTAM AKA QOSHNISI , | G84: SURXONDARYO VILOYATI DENOV TUMANI BINOKOR QFY OZOD MFY TERAKZOR KO’CHASI 89-UY | H84: 10 | I84: 1150057 | K84: Uyiga borildi - va'da berdi | 20 cilarida tolo qlad | 34
A85: СУРХОНДАРЁ ВИЛОЯТИ | C85: Объезд | D85: Кр-99031360-1 | E85: AZIMOVA IRODA ISMATULLAYEVNA | F85: 99-425-57-94 SMS OZi, 99-204-57-94 SMS UY, 93-634-35-69 SMS DADASI, 99-209-57-94 SMS OZI, | G85: SURXONDARYO VILOYATI SARIOSIYO TUMANI BOGI-IRAM QFY SHAXRIOBOD MFY SAXI KO’CHASI 69-UY | I85: 883090.92 | K85: Uyiga borildi - va'da berdi | wahnoz ogan | 311
A86: ТОШКЕНТ ШАХРИ | C86: Объезд | D86: Кр-99063240-1 | E86: BOZOROV FAZLIDDIN JUMAYEVICH | F86: 998777923003 SMS DADASI (ISHXONASI), 998908073003 SMS ISHXONMASI, 998936998569 SMS ONASI, 998999162111 SMS OZI, | G86: TOSHKENT SHAHAR YANGIHAYOT TUMANI BINOKOR MFY SANGZOR KOCHASI 24-UY 19-XONADON | H86: 15 | I86: 11101366 | K86: Uyiga borildi - va'da berdi | 3-4kunda to'\
A87: ТОШКЕНТ ШАХРИ | C87: Объезд | D87: Кр-99042127-1 | E87: ABDULLAYEVA SHAXLO SHARIFJONOVNA | F87: 998953205678 SMS OZI begona , 998909813239 SMS ozi , 998946449886 SMS ogli , 998917829977 SMS eri , | G87: TOSHKENT SHAHAR YUNUSOBOD TUMANI TIKLANISH MFY TIKLANISH PROEZD 6 KOCHASI 2-UY | H87: 10 | I87: 7578561.1 | K87: Uyiga borildi - va'da berdi | bugun sud
A88: ТОШКЕНТ ШАХРИ | C88: Объезд | D88: Кр-99036167-2 | E88: AXMEDOV BOTIR YULDASHEVICH | F88: 998998200012 SMS O’ZI , 998710500122 SMS O’ZI 2, 998903165191 SMS AYOLI , 998990952222 SMS O’G’LI , | G88: TOSHKENT SHAHAR SIRG’ALI TUMANI YANGI TURMUSH 5-TOR KO’CHASI 25-UY | H88: 77 | I88: 7168753.4 | K88: Uyiga borildi - va'da berdi
A89: ТОШКЕНТ ШАХРИ | C89: Объезд | D89: Кр-99039892-1 | E89: ATABEKOVA DILNOZA MUROD QIZI | F89: +998770054745 SMS, | G89: г. Ташкент, Янгихаётский район, 8-строительная территория, Орият МСГ, 49- Дом, 35- Квартира | H89: 10 | I89: 6281395.6 | K89: Uyiga borildi - va'da berdi | dushanbi to'lidi
A90: ТОШКЕНТ ШАХРИ | C90: Объезд | D90: Кр-99036291-3 | E90: ABDUG‘AFOROV ABRORJON ABDURASUL O‘G‘LI | F90: 998998849202 SMS OZI, 998997710748 SMS ISHCHISI , 998932790919 SMS DOSTI, +998998849202 Primary phone from road24, | G90: БОБОДЕҲҚОН МФЙ, БОБОДЕҲҚОН КЎЧАСИ, uy:45А | H90: 15 | I90: 4891662.9 | K90: Uyiga borildi - va'da berdi
A91: ТОШКЕНТ ШАХРИ | C91: Объезд | D91: Кр-99036018-1 | E91: ARIPOVA SANOBAR NARIMANOVNA | F91: 998910141058 SMS OZI, 998900073026 SMS KELINI, 998935287242 SMS OGLI, 998358306912 SMS KELINI, | G91: TOSHKENT SHAHAR YUNUSOBOD TUMANI 10-MAVZE 7- UY 37- KVARTIRA | H91: 3 | I91: 3763996.3 | K91: Uyiga borildi - va'da berdi
A92: ТОШКЕНТ ШАХРИ | C92: Объезд | D92: Кр-99035003-2 | E92: ABDULAZIZOV AKBARJON ABDUSALOM O‘G‘LI | F92: 998998865038 SMS O’ZI, 998811103432 SMS O’ZI 2, 998994092541 SMS DO’STI, 998998865038 SMS O’ZI 3, +998998865038 Primary phone from road24, | G92: УСТА ШИРИН МФЙ, КЎРГАЗМА КЎЧАСИ, uy:57 | H92: 10 | I92: 3520552.5 | K92: Uyiga borildi - va'da berdi
A93: ТОШКЕНТ ШАХРИ | C93: Объезд | D93: Кр-99039378-1 | E93: TOXIROVA SHAXZODAXON TOXIR QIZI | F93: +998946494367 SMS O’ZI, 998909833055 SMS AYOLI 2, 998933498843 SMS AYOLI, | G93: кв. Сергели 1, дом 10, кв. 20 | H93: 10 | I93: 2210694.1 | K93: Uyiga borildi - va'da berdi
A94: ТОШКЕНТ ШАХРИ | C94: Объезд | D94: Кр-99041059-1 | E94: ABBOSOV NOZIMJON XOJIAKBAR O’G’LI | F94: +998774889944 SMS O’ZI, 998950227769 SMS ONASI, 998991445334 SMS ADASI, | G94: YANGIHAYOT TUMANI YANGI SERGELI 2-UY | H94: 13 | I94: 1936901.8 | K94: Uyiga borildi - va'da berdi
A95: ФАРГОНА ВИЛОЯТИ | C95: Объезд | D95: Кр-99036825-1 | E95: RAXMANKULOVA RANO EMINOVNA | F95: 998916619568 SMS OZI, 998916667777 SMS OGLI BEGONA, 998992041119 SMS OGLI 2, 998902741221 SMS UYI BEGONA, 998972711111 SMS , | G95: FARG’ONA VILOYATI FARG’ONA SHAHAR OQARIQ MFY OQARIQ KO’CHASI 350-A UY | H95: 122 | I95: 53771510 | K95: Uyiga borildi - va'da berdi | 20648677.87
A96: ФАРГОНА ВИЛОЯТИ | C96: Объезд | D96: Кр-99044960-2 | E96: ABDULLAYEV BEGALI MIRZAJONOVICH | F96: +998508786500 SMS O’ZI Ишсиз тел қилинмасин, 998908562142 AYOLI Боғчада зам директор тел қилинмасин, 998911448272 O’G’LI 2 тел қилинмасин, 998993646566 O’G’LI тел қилинмасин, | G96: FARG’ONA VILOYATI BESHARIQ TUMANI SHOBERDI MFY GULYOR KO’CHASI 40-UY | H96: 135 | I96: 46884562 | K96: Uyiga borildi - va'da berdi | 11979165
A97: ФАРГОНА ВИЛОЯТИ | C97: Объезд | D97: Кр-99060331-1 | E97: UMAROVA EXTIBOR SOTVOLDIYEVNA | F97: 998905331878 узи, 998932974444 невара, 998982775557 уй, 998943313223 эри, | G97: FARG’ONA VILOYATI, FARG’ONA SHAHRI, FARG’ONA MFY, FITRAT KO’CHASI, 27-UY | H97: 43 | I97: 32543292 | K97: Uyiga borildi - va'da berdi | TOLOVCHINI AYOLI BILAN GAPLASHILDI AYTAMAN TOLASHADI DEDI | 9776256.28
... A100: ФАРГОНА ВИЛОЯТИ | C100: Объезд | D100: Кр-99059331-3 | E100: YUSUPOV AXATJON MARUFOVICH | F100: +998944490113 SMS, 998941575202 SMS QARINDASH, 998948220113 SMS AYOLI, 998930617923 ORTOGI , | G100: FARG’ONA VILOYATI FURQAT TUMANI XALQABOD MFY XALQABOD QISHLOGI 26-UY | H100: 43 | I100: 12771913 | K100: Uyiga borildi - va'da berdi | BIROVGA OLIB BERGAN AYTAMAN TOLAYDI DEYABDI ISHI KASHA | 7411175.03
A101: ФАРГОНА ВИЛОЯТИ | C101: Объезд | D101: Кр-99041275-1 | E101: JUMAMATOVA ZULXUMOR ISAKOVNA | F101: +998907788327 O’ZI, 998947215300 UY, 998982787707 ERI, 998987781111 O’G’LI TOLOVCHI, | G101: 13-СИМТЕПА (Х.ИБРАГИМОВА) МФЙ, ОБИХАЁТ (ШОКИРОВА) КЎЧАСИ, uy:32А | H101: 73 | I101: 10626970 | J101: 2964372 | K101: Uyiga borildi - to'ladi | 2964372.32
A102: ФАРГОНА ВИЛОЯТИ | C102: Объезд | D102: Кр-99061811-1 | E102: RASULOVA ODINA ABDURAXMONOVNA | F102: 998905355332 OZI , 998772567505 QIZI , 998882066464 OGLI , 998958680024 UY , | G102: FARG’ONA VILOYATI FARG’ONA SHAHAR TEMIRYOL 60-UY | H102: 13 | I102: 7550412.8 | K102: Uyiga borildi - va'da berdi | BUGUN 2500QILADI EKAN QOLGANINIYAM BIR IKKUNDA QILIB BERADI EKAN | 2708333
...

Sheet Оплатили без разговора
A1: ← Вернуться в отчёт
A2: Область | B2: Филиал | C2: Группа | D2: Код клиента | E2: Клиент | F2: Номер телефона | G2: Адрес | H2: Кол-во просроченных дней | I2: Итого просрочка | J2: Оплата | K2: Izoh
